Workbook

Sheet Summary
A1: Summary by quarter
A2: Every number is a formula over the Events sheet. 'Rule pass' = front expiry within 14 sessions of the last close before results (the playbook's run-up rule).
A3: Quarter | B3: Period | C3: Results events | D3: After close | E3: During market | F3: Weekend / holiday | G3: Avg three-day sum % | H3: % three-day positive | I3: Avg excess vs Nifty % | J3: Avg size of reaction move % | K3: % sales up YoY | L3: % profit up YoY | M3: Avg EBITDA margin chg YoY (pts) | N3: Avg expected move % (options) | O3: Avg actual / expected move (x) | P3: Avg IV drop % | Q3: Run-up trades (rule pass) | R3: Run-up avg return % (rule pass) | S3: Run-up win rate (rule pass)
A4: Q3 FY23 | B4: Oct-Dec 2022 | C4: =COUNTIFS(Events!$A$6:$A$3108,$A4) -> 199 | D4: =COUNTIFS(Events!$A$6:$A$3108,$A4,Events!$K$6:$K$3108,"After close") -> 124 | E4: =COUNTIFS(Events!$A$6:$A$3108,$A4,Events!$K$6:$K$3108,"During market") -> 63 | F4: =COUNTIFS(Events!$A$6:$A$3108,$A4,Events!$K$6:$K$3108,"Non-trading day") -> 11 | G4: =IFERROR(AVERAGEIFS(Events!$T$6:$T$3108,Events!$A$6:$A$3108,$A4),"") -> -0.00078411029 | H4: =IFERROR(COUNTIFS(Events!$A$6:$A$3108,$A4,Events!$T$6:$T$3108,">0")/COUNTIFS(Events!$A$6:$A$3108,$A4,Events!$T$6:$T$3108,"<>"),"") -> 0.46031746 | I4: =IFERROR(AVERAGEIFS(Events!$W$6:$W$3108,Events!$A$6:$A$3108,$A4),"") -> -0.00035966502 | J4: =IFERROR(AVERAGEIFS(Events!$AC$6:$AC$3108,Events!$A$6:$A$3108,$A4),"") -> 0.027299043 | K4: =IFERROR(COUNTIFS(Events!$A$6:$A$3108,$A4,Events!$AU$6:$AU$3108,">0")/COUNTIFS(Events!$A$6:$A$3108,$A4,Events!$AU$6:$AU$3108,"<>"),"") -> 0.85795455 | L4: =IFERROR(COUNTIFS(Events!$A$6:$A$3108,$A4,Events!$BA$6:$BA$3108,">0")/COUNTIFS(Events!$A$6:$A$3108,$A4,Events!$BA$6:$BA$3108,"<>"),"") -> 0.64189189 | M4: =IFERROR(AVERAGEIFS(Events!$AY$6:$AY$3108,Events!$A$6:$A$3108,$A4),"") -> -0.062371061 | N4: =IFERROR(AVERAGEIFS(Events!$CJ$6:$CJ$3108,Events!$A$6:$A$3108,$A4),"") -> 0.063015114 | O4: =IFERROR(AVERAGEIFS(Events!$CK$6:$CK$3108,Events!$A$6:$A$3108,$A4),"") -> 0.45236005 | P4: =IFERROR(AVERAGEIFS(Events!$CI$6:$CI$3108,Events!$A$6:$A$3108,$A4),"") -> -0.098235077 | Q4: =COUNTIFS(Events!$A$6:$A$3108,$A4,Events!$CM$6:$CM$3108,"Yes",Events!$CL$6:$CL$3108,"<>") -> 65 | R4: =IFERROR(AVERAGEIFS(Events!$CL$6:$CL$3108,Events!$A$6:$A$3108,$A4,Events!$CM$6:$CM$3108,"Yes"),"") -> -0.080738606 | S4: =IFERROR(COUNTIFS(Events!$A$6:$A$3108,$A4,Events!$CL$6:$CL$3108,">0",Events!$CM$6:$CM$3108,"Yes")/COUNTIFS(Events!$A$6:$A$3108,$A4,Events!$CL$6:$CL$3108,"<>",Events!$CM$6:$CM$3108,"Yes"),"") -> 0.29230769
A5: Q4 FY23 | B5: Jan-Mar 2023 | C5: =COUNTIFS(Events!$A$6:$A$3108,$A5) -> 200 | D5: =COUNTIFS(Events!$A$6:$A$3108,$A5,Events!$K$6:$K$3108,"After close") -> 120 | E5: =COUNTIFS(Events!$A$6:$A$3108,$A5,Events!$K$6:$K$3108,"During market") -> 57 | F5: =COUNTIFS(Events!$A$6:$A$3108,$A5,Events!$K$6:$K$3108,"Non-trading day") -> 21 | G5: =IFERROR(AVERAGEIFS(Events!$T$6:$T$3108,Events!$A$6:$A$3108,$A5),"") -> 0.0073437312 | H5: =IFERROR(COUNTIFS(Events!$A$6:$A$3108,$A5,Events!$T$6:$T$3108,">0")/COUNTIFS(Events!$A$6:$A$3108,$A5,Events!$T$6:$T$3108,"<>"),"") -> 0.54450262 | I5: =IFERROR(AVERAGEIFS(Events!$W$6:$W$3108,Events!$A$6:$A$3108,$A5),"") -> 0.0014996983 | J5: =IFERROR(AVERAGEIFS(Events!$AC$6:$AC$3108,Events!$A$6:$A$3108,$A5),"") -> 0.028292562 | K5: =IFERROR(COUNTIFS(Events!$A$6:$A$3108,$A5,Events!$AU$6:$AU$3108,">0")/COUNTIFS(Events!$A$6:$A$3108,$A5,Events!$AU$6:$AU$3108,"<>"),"") -> 0.86170213 | L5: =IFERROR(COUNTIFS(Events!$A$6:$A$3108,$A5,Events!$BA$6:$BA$3108,">0")/COUNTIFS(Events!$A$6:$A$3108,$A5,Events!$BA$6:$BA$3108,"<>"),"") -> 0.63975155 | M5: =IFERROR(AVERAGEIFS(Events!$AY$6:$AY$3108,Events!$A$6:$A$3108,$A5),"") -> 0.010637263 | N5: =IFERROR(AVERAGEIFS(Events!$CJ$6:$CJ$3108,Events!$A$6:$A$3108,$A5),"") -> 0.057414456 | O5: =IFERROR(AVERAGEIFS(Events!$CK$6:$CK$3108,Events!$A$6:$A$3108,$A5),"") -> 0.47796664 | P5: =IFERROR(AVERAGEIFS(Events!$CI$6:$CI$3108,Events!$A$6:$A$3108,$A5),"") -> -0.16351047 | Q5: =COUNTIFS(Events!$A$6:$A$3108,$A5,Events!$CM$6:$CM$3108,"Yes",Events!$CL$6:$CL$3108,"<>") -> 61 | R5: =IFERROR(AVERAGEIFS(Events!$CL$6:$CL$3108,Events!$A$6:$A$3108,$A5,Events!$CM$6:$CM$3108,"Yes"),"") -> 0.045490892 | S5: =IFERROR(COUNTIFS(Events!$A$6:$A$3108,$A5,Events!$CL$6:$CL$3108,">0",Events!$CM$6:$CM$3108,"Yes")/COUNTIFS(Events!$A$6:$A$3108,$A5,Events!$CL$6:$CL$3108,"<>",Events!$CM$6:$CM$3108,"Yes"),"") -> 0.52459016
A6: Q1 FY24 | B6: Apr-Jun 2023 | C6: =COUNTIFS(Events!$A$6:$A$3108,$A6) -> 200 | D6: =COUNTIFS(Events!$A$6:$A$3108,$A6,Events!$K$6:$K$3108,"After close") -> 112 | E6: =COUNTIFS(Events!$A$6:$A$3108,$A6,Events!$K$6:$K$3108,"During market") -> 72 | F6: =COUNTIFS(Events!$A$6:$A$3108,$A6,Events!$K$6:$K$3108,"Non-trading day") -> 15 | G6: =IFERROR(AVERAGEIFS(Events!$T$6:$T$3108,Events!$A$6:$A$3108,$A6),"") -> -0.00067566989 | H6: =IFERROR(COUNTIFS(Events!$A$6:$A$3108,$A6,Events!$T$6:$T$3108,">0")/COUNTIFS(Events!$A$6:$A$3108,$A6,Events!$T$6:$T$3108,"<>"),"") -> 0.47894737 | I6: =IFERROR(AVERAGEIFS(Events!$W$6:$W$3108,Events!$A$6:$A$3108,$A6),"") -> 0.0019276615 | J6: =IFERROR(AVERAGEIFS(Events!$AC$6:$AC$3108,Events!$A$6:$A$3108,$A6),"") -> 0.025350293 | K6: =IFERROR(COUNTIFS(Events!$A$6:$A$3108,$A6,Events!$AU$6:$AU$3108,">0")/COUNTIFS(Events!$A$6:$A$3108,$A6,Events!$AU$6:$AU$3108,"<>"),"") -> 0.81456954 | L6: =IFERROR(COUNTIFS(Events!$A$6:$A$3108,$A6,Events!$BA$6:$BA$3108,">0")/COUNTIFS(Events!$A$6:$A$3108,$A6,Events!$BA$6:$BA$3108,"<>"),"") -> 0.72519084 | M6: =IFERROR(AVERAGEIFS(Events!$AY$6:$AY$3108,Events!$A$6:$A$3108,$A6),"") -> 0.025583819 | N6: =IFERROR(AVERAGEIFS(Events!$CJ$6:$CJ$3108,Events!$A$6:$A$3108,$A6),"") -> 0.063118768 | O6: =IFERROR(AVERAGEIFS(Events!$CK$6:$CK$3108,Events!$A$6:$A$3108,$A6),"") -> 0.39623744 | P6: =IFERROR(AVERAGEIFS(Events!$CI$6:$CI$3108,Events!$A$6:$A$3108,$A6),"") -> -0.12198804 | Q6: =COUNTIFS(Events!$A$6:$A$3108,$A6,Events!$CM$6:$CM$3108,"Yes",Events!$CL$6:$CL$3108,"<>") -> 53 | R6: =IFERROR(AVERAGEIFS(Events!$CL$6:$CL$3108,Events!$A$6:$A$3108,$A6,Events!$CM$6:$CM$3108,"Yes"),"") -> 0.070544851 | S6: =IFERROR(COUNTIFS(Events!$A$6:$A$3108,$A6,Events!$CL$6:$CL$3108,">0",Events!$CM$6:$CM$3108,"Yes")/COUNTIFS(Events!$A$6:$A$3108,$A6,Events!$CL$6:$CL$3108,"<>",Events!$CM$6:$CM$3108,"Yes"),"") -> 0.30188679
A7: Q2 FY24 | B7: Jul-Sep 2023 | C7: =COUNTIFS(Events!$A$6:$A$3108,$A7) -> 202 | D7: =COUNTIFS(Events!$A$6:$A$3108,$A7,Events!$K$6:$K$3108,"After close") -> 109 | E7: =COUNTIFS(Events!$A$6:$A$3108,$A7,Events!$K$6:$K$3108,"During market") -> 71 | F7: =COUNTIFS(Events!$A$6:$A$3108,$A7,Events!$K$6:$K$3108,"Non-trading day") -> 20 | G7: =IFERROR(AVERAGEIFS(Events!$T$6:$T$3108,Events!$A$6:$A$3108,$A7),"") -> 0.0075002949 | H7: =IFERROR(COUNTIFS(Events!$A$6:$A$3108,$A7,Events!$T$6:$T$3108,">0")/COUNTIFS(Events!$A$6:$A$3108,$A7,Events!$T$6:$T$3108,"<>"),"") -> 0.54123711 | I7: =IFERROR(AVERAGEIFS(Events!$W$6:$W$3108,Events!$A$6:$A$3108,$A7),"") -> 0.0068971445 | J7: =IFERROR(AVERAGEIFS(Events!$AC$6:$AC$3108,Events!$A$6:$A$3108,$A7),"") -> 0.024232827 | K7: =IFERROR(COUNTIFS(Events!$A$6:$A$3108,$A7,Events!$AU$6:$AU$3108,">0")/COUNTIFS(Events!$A$6:$A$3108,$A7,Events!$AU$6:$AU$3108,"<>"),"") -> 0.81967213 | L7: =IFERROR(COUNTIFS(Events!$A$6:$A$3108,$A7,Events!$BA$6:$BA$3108,">0")/COUNTIFS(Events!$A$6:$A$3108,$A7,Events!$BA$6:$BA$3108,"<>"),"") -> 0.78064516 | M7: =IFERROR(AVERAGEIFS(Events!$AY$6:$AY$3108,Events!$A$6:$A$3108,$A7),"") -> 0.036674867 | N7: =IFERROR(AVERAGEIFS(Events!$CJ$6:$CJ$3108,Events!$A$6:$A$3108,$A7),"") -> 0.054308871 | O7: =IFERROR(AVERAGEIFS(Events!$CK$6:$CK$3108,Events!$A$6:$A$3108,$A7),"") -> 0.45796686 | P7: =IFERROR(AVERAGEIFS(Events!$CI$6:$CI$3108,Events!$A$6:$A$3108,$A7),"") -> -0.099620677 | Q7: =COUNTIFS(Events!$A$6:$A$3108,$A7,Events!$CM$6:$CM$3108,"Yes",Events!$CL$6:$CL$3108,"<>") -> 54 | R7: =IFERROR(AVERAGEIFS(Events!$CL$6:$CL$3108,Events!$A$6:$A$3108,$A7,Events!$CM$6:$CM$3108,"Yes"),"") -> 0.051597608 | S7: =IFERROR(COUNTIFS(Events!$A$6:$A$3108,$A7,Events!$CL$6:$CL$3108,">0",Events!$CM$6:$CM$3108,"Yes")/COUNTIFS(Events!$A$6:$A$3108,$A7,Events!$CL$6:$CL$3108,"<>",Events!$CM$6:$CM$3108,"Yes"),"") -> 0.48148148
A8: Q3 FY24 | B8: Oct-Dec 2023 | C8: =COUNTIFS(Events!$A$6:$A$3108,$A8) -> 203 | D8: =COUNTIFS(Events!$A$6:$A$3108,$A8,Events!$K$6:$K$3108,"After close") -> 112 | E8: =COUNTIFS(Events!$A$6:$A$3108,$A8,Events!$K$6:$K$3108,"During market") -> 71 | F8: =COUNTIFS(Events!$A$6:$A$3108,$A8,Events!$K$6:$K$3108,"Non-trading day") -> 20 | G8: =IFERROR(AVERAGEIFS(Events!$T$6:$T$3108,Events!$A$6:$A$3108,$A8),"") -> 0.00071947546 | H8: =IFERROR(COUNTIFS(Events!$A$6:$A$3108,$A8,Events!$T$6:$T$3108,">0")/COUNTIFS(Events!$A$6:$A$3108,$A8,Events!$T$6:$T$3108,"<>"),"") -> 0.5025641 | I8: =IFERROR(AVERAGEIFS(Events!$W$6:$W$3108,Events!$A$6:$A$3108,$A8),"") -> -0.00096846979 | J8: =IFERROR(AVERAGEIFS(Events!$AC$6:$AC$3108,Events!$A$6:$A$3108,$A8),"") -> 0.037795429 | K8: =IFERROR(COUNTIFS(Events!$A$6:$A$3108,$A8,Events!$AU$6:$AU$3108,">0")/COUNTIFS(Events!$A$6:$A$3108,$A8,Events!$AU$6:$AU$3108,"<>"),"") -> 0.84375 | L8: =IFERROR(COUNTIFS(Events!$A$6:$A$3108,$A8,Events!$BA$6:$BA$3108,">0")/COUNTIFS(Events!$A$6:$A$3108,$A8,Events!$BA$6:$BA$3108,"<>"),"") -> 0.77108434 | M8: =IFERROR(AVERAGEIFS(Events!$AY$6:$AY$3108,Events!$A$6:$A$3108,$A8),"") -> 0.028679025 | N8: =IFERROR(AVERAGEIFS(Events!$CJ$6:$CJ$3108,Events!$A$6:$A$3108,$A8),"") -> 0.0790595 | O8: =IFERROR(AVERAGEIFS(Events!$CK$6:$CK$3108,Events!$A$6:$A$3108,$A8),"") -> 0.48901211 | P8: =IFERROR(AVERAGEIFS(Events!$CI$6:$CI$3108,Events!$A$6:$A$3108,$A8),"") -> -0.089277249 | Q8: =COUNTIFS(Events!$A$6:$A$3108,$A8,Events!$CM$6:$CM$3108,"Yes",Events!$CL$6:$CL$3108,"<>") -> 41 | R8: =IFERROR(AVERAGEIFS(Events!$CL$6:$CL$3108,Events!$A$6:$A$3108,$A8,Events!$CM$6:$CM$3108,"Yes"),"") -> 0.19111234 | S8: =IFERROR(COUNTIFS(Events!$A$6:$A$3108,$A8,Events!$CL$6:$CL$3108,">0",Events!$CM$6:$CM$3108,"Yes")/COUNTIFS(Events!$A$6:$A$3108,$A8,Events!$CL$6:$CL$3108,"<>",Events!$CM$6:$CM$3108,"Yes"),"") -> 0.75609756
A9: Q4 FY24 | B9: Jan-Mar 2024 | C9: =COUNTIFS(Events!$A$6:$A$3108,$A9) -> 204 | D9: =COUNTIFS(Events!$A$6:$A$3108,$A9,Events!$K$6:$K$3108,"After close") -> 113 | E9: =COUNTIFS(Events!$A$6:$A$3108,$A9,Events!$K$6:$K$3108,"During market") -> 64 | F9: =COUNTIFS(Events!$A$6:$A$3108,$A9,Events!$K$6:$K$3108,"Non-trading day") -> 26 | G9: =IFERROR(AVERAGEIFS(Events!$T$6:$T$3108,Events!$A$6:$A$3108,$A9),"") -> 0.012048187 | H9: =IFERROR(COUNTIFS(Events!$A$6:$A$3108,$A9,Events!$T$6:$T$3108,">0")/COUNTIFS(Events!$A$6:$A$3108,$A9,Events!$T$6:$T$3108,"<>"),"") -> 0.56852792 | I9: =IFERROR(AVERAGEIFS(Events!$W$6:$W$3108,Events!$A$6:$A$3108,$A9),"") -> 0.0092775438 | J9: =IFERROR(AVERAGEIFS(Events!$AC$6:$AC$3108,Events!$A$6:$A$3108,$A9),"") -> 0.033517389 | K9: =IFERROR(COUNTIFS(Events!$A$6:$A$3108,$A9,Events!$AU$6:$AU$3108,">0")/COUNTIFS(Events!$A$6:$A$3108,$A9,Events!$AU$6:$AU$3108,"<>"),"") -> 0.85492228 | L9: =IFERROR(COUNTIFS(Events!$A$6:$A$3108,$A9,Events!$BA$6:$BA$3108,">0")/COUNTIFS(Events!$A$6:$A$3108,$A9,Events!$BA$6:$BA$3108,"<>"),"") -> 0.68047337 | M9: =IFERROR(AVERAGEIFS(Events!$AY$6:$AY$3108,Events!$A$6:$A$3108,$A9),"") -> 0.01608179 | N9: =IFERROR(AVERAGEIFS(Events!$CJ$6:$CJ$3108,Events!$A$6:$A$3108,$A9),"") -> 0.072850131 | O9: =IFERROR(AVERAGEIFS(Events!$CK$6:$CK$3108,Events!$A$6:$A$3108,$A9),"") -> 0.45750506 | P9: =IFERROR(AVERAGEIFS(Events!$CI$6:$CI$3108,Events!$A$6:$A$3108,$A9),"") -> -0.12888722 | Q9: =COUNTIFS(Events!$A$6:$A$3108,$A9,Events!$CM$6:$CM$3108,"Yes",Events!$CL$6:$CL$3108,"<>") -> 61 | R9: =IFERROR(AVERAGEIFS(Events!$CL$6:$CL$3108,Events!$A$6:$A$3108,$A9,Events!$CM$6:$CM$3108,"Yes"),"") -> 0.054352723 | S9: =IFERROR(COUNTIFS(Events!$A$6:$A$3108,$A9,Events!$CL$6:$CL$3108,">0",Events!$CM$6:$CM$3108,"Yes")/COUNTIFS(Events!$A$6:$A$3108,$A9,Events!$CL$6:$CL$3108,"<>",Events!$CM$6:$CM$3108,"Yes"),"") -> 0.57377049
A10: Q1 FY25 | B10: Apr-Jun 2024 | C10: =COUNTIFS(Events!$A$6:$A$3108,$A10) -> 204 | D10: =COUNTIFS(Events!$A$6:$A$3108,$A10,Events!$K$6:$K$3108,"After close") -> 110 | E10: =COUNTIFS(Events!$A$6:$A$3108,$A10,Events!$K$6:$K$3108,"During market") -> 74 | F10: =COUNTIFS(Events!$A$6:$A$3108,$A10,Events!$K$6:$K$3108,"Non-trading day") -> 19 | G10: =IFERROR(AVERAGEIFS(Events!$T$6:$T$3108,Events!$A$6:$A$3108,$A10),"") -> 0.0077113233 | H10: =IFERROR(COUNTIFS(Events!$A$6:$A$3108,$A10,Events!$T$6:$T$3108,">0")/COUNTIFS(Events!$A$6:$A$3108,$A10,Events!$T$6:$T$3108,"<>"),"") -> 0.53266332 | I10: =IFERROR(AVERAGEIFS(Events!$W$6:$W$3108,Events!$A$6:$A$3108,$A10),"") -> 0.007911735 | J10: =IFERROR(AVERAGEIFS(Events!$AC$6:$AC$3108,Events!$A$6:$A$3108,$A10),"") -> 0.02777609 | K10: =IFERROR(COUNTIFS(Events!$A$6:$A$3108,$A10,Events!$AU$6:$AU$3108,">0")/COUNTIFS(Events!$A$6:$A$3108,$A10,Events!$AU$6:$AU$3108,"<>"),"") -> 0.89005236 | L10: =IFERROR(COUNTIFS(Events!$A$6:$A$3108,$A10,Events!$BA$6:$BA$3108,">0")/COUNTIFS(Events!$A$6:$A$3108,$A10,Events!$BA$6:$BA$3108,"<>"),"") -> 0.77058824 | M10: =IFERROR(AVERAGEIFS(Events!$AY$6:$AY$3108,Events!$A$6:$A$3108,$A10),"") -> -0.0021506247 | N10: =IFERROR(AVERAGEIFS(Events!$CJ$6:$CJ$3108,Events!$A$6:$A$3108,$A10),"") -> 0.068774092 | O10: =IFERROR(AVERAGEIFS(Events!$CK$6:$CK$3108,Events!$A$6:$A$3108,$A10),"") -> 0.40736744 | P10: =IFERROR(AVERAGEIFS(Events!$CI$6:$CI$3108,Events!$A$6:$A$3108,$A10),"") -> -0.12603567 | Q10: =COUNTIFS(Events!$A$6:$A$3108,$A10,Events!$CM$6:$CM$3108,"Yes",Events!$CL$6:$CL$3108,"<>") -> 49 | R10: =IFERROR(AVERAGEIFS(Events!$CL$6:$CL$3108,Events!$A$6:$A$3108,$A10,Events!$CM$6:$CM$3108,"Yes"),"") -> 0.0081885479 | S10: =IFERROR(COUNTIFS(Events!$A$6:$A$3108,$A10,Events!$CL$6:$CL$3108,">0",Events!$CM$6:$CM$3108,"Yes")/COUNTIFS(Events!$A$6:$A$3108,$A10,Events!$CL$6:$CL$3108,"<>",Events!$CM$6:$CM$3108,"Yes"),"") -> 0.3877551
A11: Q2 FY25 | B11: Jul-Sep 2024 | C11: =COUNTIFS(Events!$A$6:$A$3108,$A11) -> 209 | D11: =COUNTIFS(Events!$A$6:$A$3108,$A11,Events!$K$6:$K$3108,"After close") -> 126 | E11: =COUNTIFS(Events!$A$6:$A$3108,$A11,Events!$K$6:$K$3108,"During market") -> 69 | F11: =COUNTIFS(Events!$A$6:$A$3108,$A11,Events!$K$6:$K$3108,"Non-trading day") -> 13 | G11: =IFERROR(AVERAGEIFS(Events!$T$6:$T$3108,Events!$A$6:$A$3108,$A11),"") -> -0.0061816112 | H11: =IFERROR(COUNTIFS(Events!$A$6:$A$3108,$A11,Events!$T$6:$T$3108,">0")/COUNTIFS(Events!$A$6:$A$3108,$A11,Events!$T$6:$T$3108,"<>"),"") -> 0.42857143 | I11: =IFERROR(AVERAGEIFS(Events!$W$6:$W$3108,Events!$A$6:$A$3108,$A11),"") -> 0.00070968564 | J11: =IFERROR(AVERAGEIFS(Events!$AC$6:$AC$3108,Events!$A$6:$A$3108,$A11),"") -> 0.037371603 | K11: =IFERROR(COUNTIFS(Events!$A$6:$A$3108,$A11,Events!$AU$6:$AU$3108,">0")/COUNTIFS(Events!$A$6:$A$3108,$A11,Events!$AU$6:$AU$3108,"<>"),"") -> 0.87309645 | L11: =IFERROR(COUNTIFS(Events!$A$6:$A$3108,$A11,Events!$BA$6:$BA$3108,">0")/COUNTIFS(Events!$A$6:$A$3108,$A11,Events!$BA$6:$BA$3108,"<>"),"") -> 0.69822485 | M11: =IFERROR(AVERAGEIFS(Events!$AY$6:$AY$3108,Events!$A$6:$A$3108,$A11),"") -> 0.015624645 | N11: =IFERROR(AVERAGEIFS(Events!$CJ$6:$CJ$3108,Events!$A$6:$A$3108,$A11),"") -> 0.058222861 | O11: =IFERROR(AVERAGEIFS(Events!$CK$6:$CK$3108,Events!$A$6:$A$3108,$A11),"") -> 0.65267496 | P11: =IFERROR(AVERAGEIFS(Events!$CI$6:$CI$3108,Events!$A$6:$A$3108,$A11),"") -> -0.16461315 | Q11: =COUNTIFS(Events!$A$6:$A$3108,$A11,Events!$CM$6:$CM$3108,"Yes",Events!$CL$6:$CL$3108,"<>") -> 109 | R11: =IFERROR(AVERAGEIFS(Events!$CL$6:$CL$3108,Events!$A$6:$A$3108,$A11,Events!$CM$6:$CM$3108,"Yes"),"") -> 0.19278184 | S11: =IFERROR(COUNTIFS(Events!$A$6:$A$3108,$A11,Events!$CL$6:$CL$3108,">0",Events!$CM$6:$CM$3108,"Yes")/COUNTIFS(Events!$A$6:$A$3108,$A11,Events!$CL$6:$CL$3108,"<>",Events!$CM$6:$CM$3108,"Yes"),"") -> 0.56880734
A12: Q3 FY25 | B12: Oct-Dec 2024 | C12: =COUNTIFS(Events!$A$6:$A$3108,$A12) -> 210 | D12: =COUNTIFS(Events!$A$6:$A$3108,$A12,Events!$K$6:$K$3108,"After close") -> 129 | E12: =COUNTIFS(Events!$A$6:$A$3108,$A12,Events!$K$6:$K$3108,"During market") -> 70 | F12: =COUNTIFS(Events!$A$6:$A$3108,$A12,Events!$K$6:$K$3108,"Non-trading day") -> 9 | G12: =IFERROR(AVERAGEIFS(Events!$T$6:$T$3108,Events!$A$6:$A$3108,$A12),"") -> -0.0053164652 | H12: =IFERROR(COUNTIFS(Events!$A$6:$A$3108,$A12,Events!$T$6:$T$3108,">0")/COUNTIFS(Events!$A$6:$A$3108,$A12,Events!$T$6:$T$3108,"<>"),"") -> 0.46601942 | I12: =IFERROR(AVERAGEIFS(Events!$W$6:$W$3108,Events!$A$6:$A$3108,$A12),"") -> -0.0054772659 | J12: =IFERROR(AVERAGEIFS(Events!$AC$6:$AC$3108,Events!$A$6:$A$3108,$A12),"") -> 0.03529863 | K12: =IFERROR(COUNTIFS(Events!$A$6:$A$3108,$A12,Events!$AU$6:$AU$3108,">0")/COUNTIFS(Events!$A$6:$A$3108,$A12,Events!$AU$6:$AU$3108,"<>"),"") -> 0.88383838 | L12: =IFERROR(COUNTIFS(Events!$A$6:$A$3108,$A12,Events!$BA$6:$BA$3108,">0")/COUNTIFS(Events!$A$6:$A$3108,$A12,Events!$BA$6:$BA$3108,"<>"),"") -> 0.64772727 | M12: =IFERROR(AVERAGEIFS(Events!$AY$6:$AY$3108,Events!$A$6:$A$3108,$A12),"") -> 0.011927833 | N12: =IFERROR(AVERAGEIFS(Events!$CJ$6:$CJ$3108,Events!$A$6:$A$3108,$A12),"") -> 0.074843855 | O12: =IFERROR(AVERAGEIFS(Events!$CK$6:$CK$3108,Events!$A$6:$A$3108,$A12),"") -> 0.48273734 | P12: =IFERROR(AVERAGEIFS(Events!$CI$6:$CI$3108,Events!$A$6:$A$3108,$A12),"") -> -0.16406961 | Q12: =COUNTIFS(Events!$A$6:$A$3108,$A12,Events!$CM$6:$CM$3108,"Yes",Events!$CL$6:$CL$3108,"<>") -> 97 | R12: =IFERROR(AVERAGEIFS(Events!$CL$6:$CL$3108,Events!$A$6:$A$3108,$A12,Events!$CM$6:$CM$3108,"Yes"),"") -> 0.010531451 | S12: =IFERROR(COUNTIFS(Events!$A$6:$A$3108,$A12,Events!$CL$6:$CL$3108,">0",Events!$CM$6:$CM$3108,"Yes")/COUNTIFS(Events!$A$6:$A$3108,$A12,Events!$CL$6:$CL$3108,"<>",Events!$CM$6:$CM$3108,"Yes"),"") -> 0.4742268
A13: Q4 FY25 | B13: Jan-Mar 2025 | C13: =COUNTIFS(Events!$A$6:$A$3108,$A13) -> 212 | D13: =COUNTIFS(Events!$A$6:$A$3108,$A13,Events!$K$6:$K$3108,"After close") -> 160 | E13: =COUNTIFS(Events!$A$6:$A$3108,$A13,Events!$K$6:$K$3108,"During market") -> 31 | F13: =COUNTIFS(Events!$A$6:$A$3108,$A13,Events!$K$6:$K$3108,"Non-trading day") -> 17 | G13: =IFERROR(AVERAGEIFS(Events!$T$6:$T$3108,Events!$A$6:$A$3108,$A13),"") -> 0.010293256 | H13: =IFERROR(COUNTIFS(Events!$A$6:$A$3108,$A13,Events!$T$6:$T$3108,">0")/COUNTIFS(Events!$A$6:$A$3108,$A13,Events!$T$6:$T$3108,"<>"),"") -> 0.52380952 | I13: =IFERROR(AVERAGEIFS(Events!$W$6:$W$3108,Events!$A$6:$A$3108,$A13),"") -> 0.0059475698 | J13: =IFERROR(AVERAGEIFS(Events!$AC$6:$AC$3108,Events!$A$6:$A$3108,$A13),"") -> 0.027829355 | K13: =IFERROR(COUNTIFS(Events!$A$6:$A$3108,$A13,Events!$AU$6:$AU$3108,">0")/COUNTIFS(Events!$A$6:$A$3108,$A13,Events!$AU$6:$AU$3108,"<>"),"") -> 0.85427136 | L13: =IFERROR(COUNTIFS(Events!$A$6:$A$3108,$A13,Events!$BA$6:$BA$3108,">0")/COUNTIFS(Events!$A$6:$A$3108,$A13,Events!$BA$6:$BA$3108,"<>"),"") -> 0.66666667 | M13: =IFERROR(AVERAGEIFS(Events!$AY$6:$AY$3108,Events!$A$6:$A$3108,$A13),"") -> 0.006597987 | N13: =IFERROR(AVERAGEIFS(Events!$CJ$6:$CJ$3108,Events!$A$6:$A$3108,$A13),"") -> 0.072933463 | O13: =IFERROR(AVERAGEIFS(Events!$CK$6:$CK$3108,Events!$A$6:$A$3108,$A13),"") -> 0.36940703 | P13: =IFERROR(AVERAGEIFS(Events!$CI$6:$CI$3108,Events!$A$6:$A$3108,$A13),"") -> -0.11633419 | Q13: =COUNTIFS(Events!$A$6:$A$3108,$A13,Events!$CM$6:$CM$3108,"Yes",Events!$CL$6:$CL$3108,"<>") -> 74 | R13: =IFERROR(AVERAGEIFS(Events!$CL$6:$CL$3108,Events!$A$6:$A$3108,$A13,Events!$CM$6:$CM$3108,"Yes"),"") -> -0.038828429 | S13: =IFERROR(COUNTIFS(Events!$A$6:$A$3108,$A13,Events!$CL$6:$CL$3108,">0",Events!$CM$6:$CM$3108,"Yes")/COUNTIFS(Events!$A$6:$A$3108,$A13,Events!$CL$6:$CL$3108,"<>",Events!$CM$6:$CM$3108,"Yes"),"") -> 0.32432432
A14: Q1 FY26 | B14: Apr-Jun 2025 | C14: =COUNTIFS(Events!$A$6:$A$3108,$A14) -> 212 | D14: =COUNTIFS(Events!$A$6:$A$3108,$A14,Events!$K$6:$K$3108,"After close") -> 128 | E14: =COUNTIFS(Events!$A$6:$A$3108,$A14,Events!$K$6:$K$3108,"During market") -> 70 | F14: =COUNTIFS(Events!$A$6:$A$3108,$A14,Events!$K$6:$K$3108,"Non-trading day") -> 13 | G14: =IFERROR(AVERAGEIFS(Events!$T$6:$T$3108,Events!$A$6:$A$3108,$A14),"") -> -0.0024914309 | H14: =IFERROR(COUNTIFS(Events!$A$6:$A$3108,$A14,Events!$T$6:$T$3108,">0")/COUNTIFS(Events!$A$6:$A$3108,$A14,Events!$T$6:$T$3108,"<>"),"") -> 0.47142857 | I14: =IFERROR(AVERAGEIFS(Events!$W$6:$W$3108,Events!$A$6:$A$3108,$A14),"") -> 0.0010809227 | J14: =IFERROR(AVERAGEIFS(Events!$AC$6:$AC$3108,Events!$A$6:$A$3108,$A14),"") -> 0.027183741 | K14: =IFERROR(COUNTIFS(Events!$A$6:$A$3108,$A14,Events!$AU$6:$AU$3108,">0")/COUNTIFS(Events!$A$6:$A$3108,$A14,Events!$AU$6:$AU$3108,"<>"),"") -> 0.8241206 | L14: =IFERROR(COUNTIFS(Events!$A$6:$A$3108,$A14,Events!$BA$6:$BA$3108,">0")/COUNTIFS(Events!$A$6:$A$3108,$A14,Events!$BA$6:$BA$3108,"<>"),"") -> 0.68333333 | M14: =IFERROR(AVERAGEIFS(Events!$AY$6:$AY$3108,Events!$A$6:$A$3108,$A14),"") -> 0.0033443195 | N14: =IFERROR(AVERAGEIFS(Events!$CJ$6:$CJ$3108,Events!$A$6:$A$3108,$A14),"") -> 0.057104604 | O14: =IFERROR(AVERAGEIFS(Events!$CK$6:$CK$3108,Events!$A$6:$A$3108,$A14),"") -> 0.45429194 | P14: =IFERROR(AVERAGEIFS(Events!$CI$6:$CI$3108,Events!$A$6:$A$3108,$A14),"") -> -0.11774236 | Q14: =COUNTIFS(Events!$A$6:$A$3108,$A14,Events!$CM$6:$CM$3108,"Yes",Events!$CL$6:$CL$3108,"<>") -> 122 | R14: =IFERROR(AVERAGEIFS(Events!$CL$6:$CL$3108,Events!$A$6:$A$3108,$A14,Events!$CM$6:$CM$3108,"Yes"),"") -> 0.0092613044 | S14: =IFERROR(COUNTIFS(Events!$A$6:$A$3108,$A14,Events!$CL$6:$CL$3108,">0",Events!$CM$6:$CM$3108,"Yes")/COUNTIFS(Events!$A$6:$A$3108,$A14,Events!$CL$6:$CL$3108,"<>",Events!$CM$6:$CM$3108,"Yes"),"") -> 0.28688525
A15: Q2 FY26 | B15: Jul-Sep 2025 | C15: =COUNTIFS(Events!$A$6:$A$3108,$A15) -> 212 | D15: =COUNTIFS(Events!$A$6:$A$3108,$A15,Events!$K$6:$K$3108,"After close") -> 131 | E15: =COUNTIFS(Events!$A$6:$A$3108,$A15,Events!$K$6:$K$3108,"During market") -> 60 | F15: =COUNTIFS(Events!$A$6:$A$3108,$A15,Events!$K$6:$K$3108,"Non-trading day") -> 20 | G15: =IFERROR(AVERAGEIFS(Events!$T$6:$T$3108,Events!$A$6:$A$3108,$A15),"") -> 0.0066284719 | H15: =IFERROR(COUNTIFS(Events!$A$6:$A$3108,$A15,Events!$T$6:$T$3108,">0")/COUNTIFS(Events!$A$6:$A$3108,$A15,Events!$T$6:$T$3108,"<>"),"") -> 0.53554502 | I15: =IFERROR(AVERAGEIFS(Events!$W$6:$W$3108,Events!$A$6:$A$3108,$A15),"") -> 0.0044425224 | J15: =IFERROR(AVERAGEIFS(Events!$AC$6:$AC$3108,Events!$A$6:$A$3108,$A15),"") -> 0.02942194 | K15: =IFERROR(COUNTIFS(Events!$A$6:$A$3108,$A15,Events!$AU$6:$AU$3108,">0")/COUNTIFS(Events!$A$6:$A$3108,$A15,Events!$AU$6:$AU$3108,"<>"),"") -> 0.8627451 | L15: =IFERROR(COUNTIFS(Events!$A$6:$A$3108,$A15,Events!$BA$6:$BA$3108,">0")/COUNTIFS(Events!$A$6:$A$3108,$A15,Events!$BA$6:$BA$3108,"<>"),"") -> 0.67955801 | M15: =IFERROR(AVERAGEIFS(Events!$AY$6:$AY$3108,Events!$A$6:$A$3108,$A15),"") -> -0.0033096847 | N15: =IFERROR(AVERAGEIFS(Events!$CJ$6:$CJ$3108,Events!$A$6:$A$3108,$A15),"") -> 0.055983082 | O15: =IFERROR(AVERAGEIFS(Events!$CK$6:$CK$3108,Events!$A$6:$A$3108,$A15),"") -> 0.53291966 | P15: =IFERROR(AVERAGEIFS(Events!$CI$6:$CI$3108,Events!$A$6:$A$3108,$A15),"") -> -0.13620364 | Q15: =COUNTIFS(Events!$A$6:$A$3108,$A15,Events!$CM$6:$CM$3108,"Yes",Events!$CL$6:$CL$3108,"<>") -> 122 | R15: =IFERROR(AVERAGEIFS(Events!$CL$6:$CL$3108,Events!$A$6:$A$3108,$A15,Events!$CM$6:$CM$3108,"Yes"),"") -> -0.015100843 | S15: =IFERROR(COUNTIFS(Events!$A$6:$A$3108,$A15,Events!$CL$6:$CL$3108,">0",Events!$CM$6:$CM$3108,"Yes")/COUNTIFS(Events!$A$6:$A$3108,$A15,Events!$CL$6:$CL$3108,"<>",Events!$CM$6:$CM$3108,"Yes"),"") -> 0.37704918
... A18: Q1 FY27 | B18: Apr-Jun 2026 | C18: =COUNTIFS(Events!$A$6:$A$3108,$A18) -> 212 | D18: =COUNTIFS(Events!$A$6:$A$3108,$A18,Events!$K$6:$K$3108,"After close") -> 114 | E18: =COUNTIFS(Events!$A$6:$A$3108,$A18,Events!$K$6:$K$3108,"During market") -> 80 | F18: =COUNTIFS(Events!$A$6:$A$3108,$A18,Events!$K$6:$K$3108,"Non-trading day") -> 16 | G18: =IFERROR(AVERAGEIFS(Events!$T$6:$T$3108,Events!$A$6:$A$3108,$A18),"") -> 0.0035881287 | H18: =IFERROR(COUNTIFS(Events!$A$6:$A$3108,$A18,Events!$T$6:$T$3108,">0")/COUNTIFS(Events!$A$6:$A$3108,$A18,Events!$T$6:$T$3108,"<>"),"") -> 0.51415094 | I18: =IFERROR(AVERAGEIFS(Events!$W$6:$W$3108,Events!$A$6:$A$3108,$A18),"") -> 0.0011012401 | J18: =IFERROR(AVERAGEIFS(Events!$AC$6:$AC$3108,Events!$A$6:$A$3108,$A18),"") -> 0.030007701 | K18: =IFERROR(COUNTIFS(Events!$A$6:$A$3108,$A18,Events!$AU$6:$AU$3108,">0")/COUNTIFS(Events!$A$6:$A$3108,$A18,Events!$AU$6:$AU$3108,"<>"),"") -> 0.92270531 | L18: =IFERROR(COUNTIFS(Events!$A$6:$A$3108,$A18,Events!$BA$6:$BA$3108,">0")/COUNTIFS(Events!$A$6:$A$3108,$A18,Events!$BA$6:$BA$3108,"<>"),"") -> 0.75647668 | M18: =IFERROR(AVERAGEIFS(Events!$AY$6:$AY$3108,Events!$A$6:$A$3108,$A18),"") -> 0.0044008573 | N18: =IFERROR(AVERAGEIFS(Events!$CJ$6:$CJ$3108,Events!$A$6:$A$3108,$A18),"") -> 0.064907961 | O18: =IFERROR(AVERAGEIFS(Events!$CK$6:$CK$3108,Events!$A$6:$A$3108,$A18),"") -> 0.46502498 | P18: =IFERROR(AVERAGEIFS(Events!$CI$6:$CI$3108,Events!$A$6:$A$3108,$A18),"") -> -0.14724885 | Q18: =COUNTIFS(Events!$A$6:$A$3108,$A18,Events!$CM$6:$CM$3108,"Yes",Events!$CL$6:$CL$3108,"<>") -> 111 | R18: =IFERROR(AVERAGEIFS(Events!$CL$6:$CL$3108,Events!$A$6:$A$3108,$A18,Events!$CM$6:$CM$3108,"Yes"),"") -> -0.0061018844 | S18: =IFERROR(COUNTIFS(Events!$A$6:$A$3108,$A18,Events!$CL$6:$CL$3108,">0",Events!$CM$6:$CM$3108,"Yes")/COUNTIFS(Events!$A$6:$A$3108,$A18,Events!$CL$6:$CL$3108,"<>",Events!$CM$6:$CM$3108,"Yes"),"") -> 0.33333333
A19: All quarters | C19: =COUNTIFS(Events!$A$6:$A$3108,"<>") -> 3103 | D19: =COUNTIFS(Events!$A$6:$A$3108,"<>",Events!$K$6:$K$3108,"After close") -> 1841 | E19: =COUNTIFS(Events!$A$6:$A$3108,"<>",Events!$K$6:$K$3108,"During market") -> 982 | F19: =COUNTIFS(Events!$A$6:$A$3108,"<>",Events!$K$6:$K$3108,"Non-trading day") -> 260 | G19: =IFERROR(AVERAGEIFS(Events!$T$6:$T$3108,Events!$A$6:$A$3108,"<>"),"") -> 0.0032559418 | H19: =IFERROR(COUNTIFS(Events!$A$6:$A$3108,"<>",Events!$T$6:$T$3108,">0")/COUNTIFS(Events!$A$6:$A$3108,"<>",Events!$T$6:$T$3108,"<>"),"") -> 0.50445692 | I19: =IFERROR(AVERAGEIFS(Events!$W$6:$W$3108,Events!$A$6:$A$3108,"<>"),"") -> 0.0029667542 | J19: =IFERROR(AVERAGEIFS(Events!$AC$6:$AC$3108,Events!$A$6:$A$3108,"<>"),"") -> 0.030677338 | K19: =IFERROR(COUNTIFS(Events!$A$6:$A$3108,"<>",Events!$AU$6:$AU$3108,">0")/COUNTIFS(Events!$A$6:$A$3108,"<>",Events!$AU$6:$AU$3108,"<>"),"") -> 0.86401384 | L19: =IFERROR(COUNTIFS(Events!$A$6:$A$3108,"<>",Events!$BA$6:$BA$3108,">0")/COUNTIFS(Events!$A$6:$A$3108,"<>",Events!$BA$6:$BA$3108,"<>"),"") -> 0.70227808 | M19: =IFERROR(AVERAGEIFS(Events!$AY$6:$AY$3108,Events!$A$6:$A$3108,"<>"),"") -> 0.0075195822 | N19: =IFERROR(AVERAGEIFS(Events!$CJ$6:$CJ$3108,Events!$A$6:$A$3108,"<>"),"") -> 0.065824381 | O19: =IFERROR(AVERAGEIFS(Events!$CK$6:$CK$3108,Events!$A$6:$A$3108,"<>"),"") -> 0.47374933 | P19: =IFERROR(AVERAGEIFS(Events!$CI$6:$CI$3108,Events!$A$6:$A$3108,"<>"),"") -> -0.12756074 | Q19: =COUNTIFS(Events!$A$6:$A$3108,"<>",Events!$CM$6:$CM$3108,"Yes",Events!$CL$6:$CL$3108,"<>") -> 1220 | R19: =IFERROR(AVERAGEIFS(Events!$CL$6:$CL$3108,Events!$A$6:$A$3108,"<>",Events!$CM$6:$CM$3108,"Yes"),"") -> 0.038055532 | S19: =IFERROR(COUNTIFS(Events!$A$6:$A$3108,"<>",Events!$CL$6:$CL$3108,">0",Events!$CM$6:$CM$3108,"Yes")/COUNTIFS(Events!$A$6:$A$3108,"<>",Events!$CL$6:$CL$3108,"<>",Events!$CM$6:$CM$3108,"Yes"),"") -> 0.43360656

Sheet By industry
A1: By industry (NSE industry classification)
A2: Formulas over the Events sheet, all 15 quarters.
A3: Industry | B3: Results events | C3: After close | D3: During market | E3: Weekend / holiday | F3: Avg three-day sum % | G3: % three-day positive | H3: Avg excess vs Nifty % | I3: Avg size of reaction move % | J3: % sales up YoY | K3: % profit up YoY | L3: Avg EBITDA margin chg YoY (pts) | M3: Avg expected move % (options) | N3: Avg actual / expected move (x) | O3: Avg IV drop % | P3: Run-up trades (rule pass) | Q3: Run-up avg return % (rule pass) | R3: Run-up win rate (rule pass)
A4: Banks | B4: =COUNTIFS(Events!$F$6:$F$3108,$A4) -> 225 | C4: =COUNTIFS(Events!$F$6:$F$3108,$A4,Events!$K$6:$K$3108,"After close") -> 60 | D4: =COUNTIFS(Events!$F$6:$F$3108,$A4,Events!$K$6:$K$3108,"During market") -> 88 | E4: =COUNTIFS(Events!$F$6:$F$3108,$A4,Events!$K$6:$K$3108,"Non-trading day") -> 77 | F4: =IFERROR(AVERAGEIFS(Events!$T$6:$T$3108,Events!$F$6:$F$3108,$A4),"") -> 0.0010748307 | G4: =IFERROR(COUNTIFS(Events!$F$6:$F$3108,$A4,Events!$T$6:$T$3108,">0")/COUNTIFS(Events!$F$6:$F$3108,$A4,Events!$T$6:$T$3108,"<>"),"") -> 0.54222222 | H4: =IFERROR(AVERAGEIFS(Events!$W$6:$W$3108,Events!$F$6:$F$3108,$A4),"") -> 0.0022603272 | I4: =IFERROR(AVERAGEIFS(Events!$AC$6:$AC$3108,Events!$F$6:$F$3108,$A4),"") -> 0.030514663 | J4: =IFERROR(COUNTIFS(Events!$F$6:$F$3108,$A4,Events!$AU$6:$AU$3108,">0")/COUNTIFS(Events!$F$6:$F$3108,$A4,Events!$AU$6:$AU$3108,"<>"),"") -> 0.93809524 | K4: =IFERROR(COUNTIFS(Events!$F$6:$F$3108,$A4,Events!$BA$6:$BA$3108,">0")/COUNTIFS(Events!$F$6:$F$3108,$A4,Events!$BA$6:$BA$3108,"<>"),"") -> 0.85576923 | L4: =IFERROR(AVERAGEIFS(Events!$AY$6:$AY$3108,Events!$F$6:$F$3108,$A4),"") | M4: =IFERROR(AVERAGEIFS(Events!$CJ$6:$CJ$3108,Events!$F$6:$F$3108,$A4),"") -> 0.060028872 | N4: =IFERROR(AVERAGEIFS(Events!$CK$6:$CK$3108,Events!$F$6:$F$3108,$A4),"") -> 0.54404705 | O4: =IFERROR(AVERAGEIFS(Events!$CI$6:$CI$3108,Events!$F$6:$F$3108,$A4),"") -> -0.16681027 | P4: =COUNTIFS(Events!$F$6:$F$3108,$A4,Events!$CM$6:$CM$3108,"Yes",Events!$CL$6:$CL$3108,"<>") -> 92 | Q4: =IFERROR(AVERAGEIFS(Events!$CL$6:$CL$3108,Events!$F$6:$F$3108,$A4,Events!$CM$6:$CM$3108,"Yes"),"") -> 0.046335422 | R4: =IFERROR(COUNTIFS(Events!$F$6:$F$3108,$A4,Events!$CL$6:$CL$3108,">0",Events!$CM$6:$CM$3108,"Yes")/COUNTIFS(Events!$F$6:$F$3108,$A4,Events!$CL$6:$CL$3108,"<>",Events!$CM$6:$CM$3108,"Yes"),"") -> 0.40217391
A5: Computers - Software | B5: =COUNTIFS(Events!$F$6:$F$3108,$A5) -> 150 | C5: =COUNTIFS(Events!$F$6:$F$3108,$A5,Events!$K$6:$K$3108,"After close") -> 125 | D5: =COUNTIFS(Events!$F$6:$F$3108,$A5,Events!$K$6:$K$3108,"During market") -> 16 | E5: =COUNTIFS(Events!$F$6:$F$3108,$A5,Events!$K$6:$K$3108,"Non-trading day") -> 4 | F5: =IFERROR(AVERAGEIFS(Events!$T$6:$T$3108,Events!$F$6:$F$3108,$A5),"") -> 5.821061e-05 | G5: =IFERROR(COUNTIFS(Events!$F$6:$F$3108,$A5,Events!$T$6:$T$3108,">0")/COUNTIFS(Events!$F$6:$F$3108,$A5,Events!$T$6:$T$3108,"<>"),"") -> 0.48 | H5: =IFERROR(AVERAGEIFS(Events!$W$6:$W$3108,Events!$F$6:$F$3108,$A5),"") -> -0.0012781954 | I5: =IFERROR(AVERAGEIFS(Events!$AC$6:$AC$3108,Events!$F$6:$F$3108,$A5),"") -> 0.035128955 | J5: =IFERROR(COUNTIFS(Events!$F$6:$F$3108,$A5,Events!$AU$6:$AU$3108,">0")/COUNTIFS(Events!$F$6:$F$3108,$A5,Events!$AU$6:$AU$3108,"<>"),"") -> 0.90344828 | K5: =IFERROR(COUNTIFS(Events!$F$6:$F$3108,$A5,Events!$BA$6:$BA$3108,">0")/COUNTIFS(Events!$F$6:$F$3108,$A5,Events!$BA$6:$BA$3108,"<>"),"") -> 0.69503546 | L5: =IFERROR(AVERAGEIFS(Events!$AY$6:$AY$3108,Events!$F$6:$F$3108,$A5),"") -> -0.041522736 | M5: =IFERROR(AVERAGEIFS(Events!$CJ$6:$CJ$3108,Events!$F$6:$F$3108,$A5),"") -> 0.062748578 | N5: =IFERROR(AVERAGEIFS(Events!$CK$6:$CK$3108,Events!$F$6:$F$3108,$A5),"") -> 0.61009208 | O5: =IFERROR(AVERAGEIFS(Events!$CI$6:$CI$3108,Events!$F$6:$F$3108,$A5),"") -> -0.22089315 | P5: =COUNTIFS(Events!$F$6:$F$3108,$A5,Events!$CM$6:$CM$3108,"Yes",Events!$CL$6:$CL$3108,"<>") -> 98 | Q5: =IFERROR(AVERAGEIFS(Events!$CL$6:$CL$3108,Events!$F$6:$F$3108,$A5,Events!$CM$6:$CM$3108,"Yes"),"") -> 0.07663019 | R5: =IFERROR(COUNTIFS(Events!$F$6:$F$3108,$A5,Events!$CL$6:$CL$3108,">0",Events!$CM$6:$CM$3108,"Yes")/COUNTIFS(Events!$F$6:$F$3108,$A5,Events!$CL$6:$CL$3108,"<>",Events!$CM$6:$CM$3108,"Yes"),"") -> 0.5
A6: Pharmaceuticals | B6: =COUNTIFS(Events!$F$6:$F$3108,$A6) -> 135 | C6: =COUNTIFS(Events!$F$6:$F$3108,$A6,Events!$K$6:$K$3108,"After close") -> 81 | D6: =COUNTIFS(Events!$F$6:$F$3108,$A6,Events!$K$6:$K$3108,"During market") -> 34 | E6: =COUNTIFS(Events!$F$6:$F$3108,$A6,Events!$K$6:$K$3108,"Non-trading day") -> 19 | F6: =IFERROR(AVERAGEIFS(Events!$T$6:$T$3108,Events!$F$6:$F$3108,$A6),"") -> 0.0039927517 | G6: =IFERROR(COUNTIFS(Events!$F$6:$F$3108,$A6,Events!$T$6:$T$3108,">0")/COUNTIFS(Events!$F$6:$F$3108,$A6,Events!$T$6:$T$3108,"<>"),"") -> 0.52592593 | H6: =IFERROR(AVERAGEIFS(Events!$W$6:$W$3108,Events!$F$6:$F$3108,$A6),"") -> 0.0043645434 | I6: =IFERROR(AVERAGEIFS(Events!$AC$6:$AC$3108,Events!$F$6:$F$3108,$A6),"") -> 0.025530363 | J6: =IFERROR(COUNTIFS(Events!$F$6:$F$3108,$A6,Events!$AU$6:$AU$3108,">0")/COUNTIFS(Events!$F$6:$F$3108,$A6,Events!$AU$6:$AU$3108,"<>"),"") -> 0.91791045 | K6: =IFERROR(COUNTIFS(Events!$F$6:$F$3108,$A6,Events!$BA$6:$BA$3108,">0")/COUNTIFS(Events!$F$6:$F$3108,$A6,Events!$BA$6:$BA$3108,"<>"),"") -> 0.68965517 | L6: =IFERROR(AVERAGEIFS(Events!$AY$6:$AY$3108,Events!$F$6:$F$3108,$A6),"") -> 0.0095460651 | M6: =IFERROR(AVERAGEIFS(Events!$CJ$6:$CJ$3108,Events!$F$6:$F$3108,$A6),"") -> 0.061953526 | N6: =IFERROR(AVERAGEIFS(Events!$CK$6:$CK$3108,Events!$F$6:$F$3108,$A6),"") -> 0.4347267 | O6: =IFERROR(AVERAGEIFS(Events!$CI$6:$CI$3108,Events!$F$6:$F$3108,$A6),"") -> -0.15108079 | P6: =COUNTIFS(Events!$F$6:$F$3108,$A6,Events!$CM$6:$CM$3108,"Yes",Events!$CL$6:$CL$3108,"<>") -> 73 | Q6: =IFERROR(AVERAGEIFS(Events!$CL$6:$CL$3108,Events!$F$6:$F$3108,$A6,Events!$CM$6:$CM$3108,"Yes"),"") -> 0.010807613 | R6: =IFERROR(COUNTIFS(Events!$F$6:$F$3108,$A6,Events!$CL$6:$CL$3108,">0",Events!$CM$6:$CM$3108,"Yes")/COUNTIFS(Events!$F$6:$F$3108,$A6,Events!$CL$6:$CL$3108,"<>",Events!$CM$6:$CM$3108,"Yes"),"") -> 0.38356164
A7: Finance | B7: =COUNTIFS(Events!$F$6:$F$3108,$A7) -> 105 | C7: =COUNTIFS(Events!$F$6:$F$3108,$A7,Events!$K$6:$K$3108,"After close") -> 67 | D7: =COUNTIFS(Events!$F$6:$F$3108,$A7,Events!$K$6:$K$3108,"During market") -> 34 | E7: =COUNTIFS(Events!$F$6:$F$3108,$A7,Events!$K$6:$K$3108,"Non-trading day") -> 3 | F7: =IFERROR(AVERAGEIFS(Events!$T$6:$T$3108,Events!$F$6:$F$3108,$A7),"") -> -0.00018276707 | G7: =IFERROR(COUNTIFS(Events!$F$6:$F$3108,$A7,Events!$T$6:$T$3108,">0")/COUNTIFS(Events!$F$6:$F$3108,$A7,Events!$T$6:$T$3108,"<>"),"") -> 0.45714286 | H7: =IFERROR(AVERAGEIFS(Events!$W$6:$W$3108,Events!$F$6:$F$3108,$A7),"") -> -0.0026512148 | I7: =IFERROR(AVERAGEIFS(Events!$AC$6:$AC$3108,Events!$F$6:$F$3108,$A7),"") -> 0.030784593 | J7: =IFERROR(COUNTIFS(Events!$F$6:$F$3108,$A7,Events!$AU$6:$AU$3108,">0")/COUNTIFS(Events!$F$6:$F$3108,$A7,Events!$AU$6:$AU$3108,"<>"),"") -> 0.8952381 | K7: =IFERROR(COUNTIFS(Events!$F$6:$F$3108,$A7,Events!$BA$6:$BA$3108,">0")/COUNTIFS(Events!$F$6:$F$3108,$A7,Events!$BA$6:$BA$3108,"<>"),"") -> 0.81818182 | L7: =IFERROR(AVERAGEIFS(Events!$AY$6:$AY$3108,Events!$F$6:$F$3108,$A7),"") -> -0.0072170239 | M7: =IFERROR(AVERAGEIFS(Events!$CJ$6:$CJ$3108,Events!$F$6:$F$3108,$A7),"") -> 0.069483033 | N7: =IFERROR(AVERAGEIFS(Events!$CK$6:$CK$3108,Events!$F$6:$F$3108,$A7),"") -> 0.49405314 | O7: =IFERROR(AVERAGEIFS(Events!$CI$6:$CI$3108,Events!$F$6:$F$3108,$A7),"") -> -0.10161122 | P7: =COUNTIFS(Events!$F$6:$F$3108,$A7,Events!$CM$6:$CM$3108,"Yes",Events!$CL$6:$CL$3108,"<>") -> 33 | Q7: =IFERROR(AVERAGEIFS(Events!$CL$6:$CL$3108,Events!$F$6:$F$3108,$A7,Events!$CM$6:$CM$3108,"Yes"),"") -> 0.021363641 | R7: =IFERROR(COUNTIFS(Events!$F$6:$F$3108,$A7,Events!$CL$6:$CL$3108,">0",Events!$CM$6:$CM$3108,"Yes")/COUNTIFS(Events!$F$6:$F$3108,$A7,Events!$CL$6:$CL$3108,"<>",Events!$CM$6:$CM$3108,"Yes"),"") -> 0.48484848
A8: Power | B8: =COUNTIFS(Events!$F$6:$F$3108,$A8) -> 90 | C8: =COUNTIFS(Events!$F$6:$F$3108,$A8,Events!$K$6:$K$3108,"After close") -> 69 | D8: =COUNTIFS(Events!$F$6:$F$3108,$A8,Events!$K$6:$K$3108,"During market") -> 12 | E8: =COUNTIFS(Events!$F$6:$F$3108,$A8,Events!$K$6:$K$3108,"Non-trading day") -> 9 | F8: =IFERROR(AVERAGEIFS(Events!$T$6:$T$3108,Events!$F$6:$F$3108,$A8),"") -> -0.0098163744 | G8: =IFERROR(COUNTIFS(Events!$F$6:$F$3108,$A8,Events!$T$6:$T$3108,">0")/COUNTIFS(Events!$F$6:$F$3108,$A8,Events!$T$6:$T$3108,"<>"),"") -> 0.43820225 | H8: =IFERROR(AVERAGEIFS(Events!$W$6:$W$3108,Events!$F$6:$F$3108,$A8),"") -> -0.010493536 | I8: =IFERROR(AVERAGEIFS(Events!$AC$6:$AC$3108,Events!$F$6:$F$3108,$A8),"") -> 0.023062848 | J8: =IFERROR(COUNTIFS(Events!$F$6:$F$3108,$A8,Events!$AU$6:$AU$3108,">0")/COUNTIFS(Events!$F$6:$F$3108,$A8,Events!$AU$6:$AU$3108,"<>"),"") -> 0.69318182 | K8: =IFERROR(COUNTIFS(Events!$F$6:$F$3108,$A8,Events!$BA$6:$BA$3108,">0")/COUNTIFS(Events!$F$6:$F$3108,$A8,Events!$BA$6:$BA$3108,"<>"),"") -> 0.59090909 | L8: =IFERROR(AVERAGEIFS(Events!$AY$6:$AY$3108,Events!$F$6:$F$3108,$A8),"") -> 0.0027631351 | M8: =IFERROR(AVERAGEIFS(Events!$CJ$6:$CJ$3108,Events!$F$6:$F$3108,$A8),"") -> 0.057949907 | N8: =IFERROR(AVERAGEIFS(Events!$CK$6:$CK$3108,Events!$F$6:$F$3108,$A8),"") -> 0.37433348 | O8: =IFERROR(AVERAGEIFS(Events!$CI$6:$CI$3108,Events!$F$6:$F$3108,$A8),"") -> -0.12626492 | P8: =COUNTIFS(Events!$F$6:$F$3108,$A8,Events!$CM$6:$CM$3108,"Yes",Events!$CL$6:$CL$3108,"<>") -> 29 | Q8: =IFERROR(AVERAGEIFS(Events!$CL$6:$CL$3108,Events!$F$6:$F$3108,$A8,Events!$CM$6:$CM$3108,"Yes"),"") -> -0.03199456 | R8: =IFERROR(COUNTIFS(Events!$F$6:$F$3108,$A8,Events!$CL$6:$CL$3108,">0",Events!$CM$6:$CM$3108,"Yes")/COUNTIFS(Events!$F$6:$F$3108,$A8,Events!$CL$6:$CL$3108,"<>",Events!$CM$6:$CM$3108,"Yes"),"") -> 0.44827586
A9: Construction | B9: =COUNTIFS(Events!$F$6:$F$3108,$A9) -> 90 | C9: =COUNTIFS(Events!$F$6:$F$3108,$A9,Events!$K$6:$K$3108,"After close") -> 70 | D9: =COUNTIFS(Events!$F$6:$F$3108,$A9,Events!$K$6:$K$3108,"During market") -> 19 | E9: =COUNTIFS(Events!$F$6:$F$3108,$A9,Events!$K$6:$K$3108,"Non-trading day") -> 1 | F9: =IFERROR(AVERAGEIFS(Events!$T$6:$T$3108,Events!$F$6:$F$3108,$A9),"") -> -0.0083017495 | G9: =IFERROR(COUNTIFS(Events!$F$6:$F$3108,$A9,Events!$T$6:$T$3108,">0")/COUNTIFS(Events!$F$6:$F$3108,$A9,Events!$T$6:$T$3108,"<>"),"") -> 0.38888889 | H9: =IFERROR(AVERAGEIFS(Events!$W$6:$W$3108,Events!$F$6:$F$3108,$A9),"") -> -0.0084033433 | I9: =IFERROR(AVERAGEIFS(Events!$AC$6:$AC$3108,Events!$F$6:$F$3108,$A9),"") -> 0.026495641 | J9: =IFERROR(COUNTIFS(Events!$F$6:$F$3108,$A9,Events!$AU$6:$AU$3108,">0")/COUNTIFS(Events!$F$6:$F$3108,$A9,Events!$AU$6:$AU$3108,"<>"),"") -> 0.71590909 | K9: =IFERROR(COUNTIFS(Events!$F$6:$F$3108,$A9,Events!$BA$6:$BA$3108,">0")/COUNTIFS(Events!$F$6:$F$3108,$A9,Events!$BA$6:$BA$3108,"<>"),"") -> 0.73255814 | L9: =IFERROR(AVERAGEIFS(Events!$AY$6:$AY$3108,Events!$F$6:$F$3108,$A9),"") -> -0.02148609 | M9: =IFERROR(AVERAGEIFS(Events!$CJ$6:$CJ$3108,Events!$F$6:$F$3108,$A9),"") -> 0.072964196 | N9: =IFERROR(AVERAGEIFS(Events!$CK$6:$CK$3108,Events!$F$6:$F$3108,$A9),"") -> 0.41901313 | O9: =IFERROR(AVERAGEIFS(Events!$CI$6:$CI$3108,Events!$F$6:$F$3108,$A9),"") -> -0.11828236 | P9: =COUNTIFS(Events!$F$6:$F$3108,$A9,Events!$CM$6:$CM$3108,"Yes",Events!$CL$6:$CL$3108,"<>") -> 28 | Q9: =IFERROR(AVERAGEIFS(Events!$CL$6:$CL$3108,Events!$F$6:$F$3108,$A9,Events!$CM$6:$CM$3108,"Yes"),"") -> 0.089089993 | R9: =IFERROR(COUNTIFS(Events!$F$6:$F$3108,$A9,Events!$CL$6:$CL$3108,">0",Events!$CM$6:$CM$3108,"Yes")/COUNTIFS(Events!$F$6:$F$3108,$A9,Events!$CL$6:$CL$3108,"<>",Events!$CM$6:$CM$3108,"Yes"),"") -> 0.39285714
A10: Electrical Equipment | B10: =COUNTIFS(Events!$F$6:$F$3108,$A10) -> 75 | C10: =COUNTIFS(Events!$F$6:$F$3108,$A10,Events!$K$6:$K$3108,"After close") -> 48 | D10: =COUNTIFS(Events!$F$6:$F$3108,$A10,Events!$K$6:$K$3108,"During market") -> 26 | E10: =COUNTIFS(Events!$F$6:$F$3108,$A10,Events!$K$6:$K$3108,"Non-trading day") -> 1 | F10: =IFERROR(AVERAGEIFS(Events!$T$6:$T$3108,Events!$F$6:$F$3108,$A10),"") -> 0.0041226543 | G10: =IFERROR(COUNTIFS(Events!$F$6:$F$3108,$A10,Events!$T$6:$T$3108,">0")/COUNTIFS(Events!$F$6:$F$3108,$A10,Events!$T$6:$T$3108,"<>"),"") -> 0.54794521 | H10: =IFERROR(AVERAGEIFS(Events!$W$6:$W$3108,Events!$F$6:$F$3108,$A10),"") -> 0.0021143318 | I10: =IFERROR(AVERAGEIFS(Events!$AC$6:$AC$3108,Events!$F$6:$F$3108,$A10),"") -> 0.03518668 | J10: =IFERROR(COUNTIFS(Events!$F$6:$F$3108,$A10,Events!$AU$6:$AU$3108,">0")/COUNTIFS(Events!$F$6:$F$3108,$A10,Events!$AU$6:$AU$3108,"<>"),"") -> 0.8630137 | K10: =IFERROR(COUNTIFS(Events!$F$6:$F$3108,$A10,Events!$BA$6:$BA$3108,">0")/COUNTIFS(Events!$F$6:$F$3108,$A10,Events!$BA$6:$BA$3108,"<>"),"") -> 0.6557377 | L10: =IFERROR(AVERAGEIFS(Events!$AY$6:$AY$3108,Events!$F$6:$F$3108,$A10),"") -> -0.01799247 | M10: =IFERROR(AVERAGEIFS(Events!$CJ$6:$CJ$3108,Events!$F$6:$F$3108,$A10),"") -> 0.071717235 | N10: =IFERROR(AVERAGEIFS(Events!$CK$6:$CK$3108,Events!$F$6:$F$3108,$A10),"") -> 0.4875787 | O10: =IFERROR(AVERAGEIFS(Events!$CI$6:$CI$3108,Events!$F$6:$F$3108,$A10),"") -> -0.13895853 | P10: =COUNTIFS(Events!$F$6:$F$3108,$A10,Events!$CM$6:$CM$3108,"Yes",Events!$CL$6:$CL$3108,"<>") -> 43 | Q10: =IFERROR(AVERAGEIFS(Events!$CL$6:$CL$3108,Events!$F$6:$F$3108,$A10,Events!$CM$6:$CM$3108,"Yes"),"") -> 0.077711918 | R10: =IFERROR(COUNTIFS(Events!$F$6:$F$3108,$A10,Events!$CL$6:$CL$3108,">0",Events!$CM$6:$CM$3108,"Yes")/COUNTIFS(Events!$F$6:$F$3108,$A10,Events!$CL$6:$CL$3108,"<>",Events!$CM$6:$CM$3108,"Yes"),"") -> 0.46511628
A11: Steel And Steel Products | B11: =COUNTIFS(Events!$F$6:$F$3108,$A11) -> 75 | C11: =COUNTIFS(Events!$F$6:$F$3108,$A11,Events!$K$6:$K$3108,"After close") -> 53 | D11: =COUNTIFS(Events!$F$6:$F$3108,$A11,Events!$K$6:$K$3108,"During market") -> 14 | E11: =COUNTIFS(Events!$F$6:$F$3108,$A11,Events!$K$6:$K$3108,"Non-trading day") -> 8 | F11: =IFERROR(AVERAGEIFS(Events!$T$6:$T$3108,Events!$F$6:$F$3108,$A11),"") -> -0.0029565431 | G11: =IFERROR(COUNTIFS(Events!$F$6:$F$3108,$A11,Events!$T$6:$T$3108,">0")/COUNTIFS(Events!$F$6:$F$3108,$A11,Events!$T$6:$T$3108,"<>"),"") -> 0.52 | H11: =IFERROR(AVERAGEIFS(Events!$W$6:$W$3108,Events!$F$6:$F$3108,$A11),"") -> -0.0043688085 | I11: =IFERROR(AVERAGEIFS(Events!$AC$6:$AC$3108,Events!$F$6:$F$3108,$A11),"") -> 0.02344528 | J11: =IFERROR(COUNTIFS(Events!$F$6:$F$3108,$A11,Events!$AU$6:$AU$3108,">0")/COUNTIFS(Events!$F$6:$F$3108,$A11,Events!$AU$6:$AU$3108,"<>"),"") -> 0.61643836 | K11: =IFERROR(COUNTIFS(Events!$F$6:$F$3108,$A11,Events!$BA$6:$BA$3108,">0")/COUNTIFS(Events!$F$6:$F$3108,$A11,Events!$BA$6:$BA$3108,"<>"),"") -> 0.48148148 | L11: =IFERROR(AVERAGEIFS(Events!$AY$6:$AY$3108,Events!$F$6:$F$3108,$A11),"") -> 0.0023587355 | M11: =IFERROR(AVERAGEIFS(Events!$CJ$6:$CJ$3108,Events!$F$6:$F$3108,$A11),"") -> 0.063199981 | N11: =IFERROR(AVERAGEIFS(Events!$CK$6:$CK$3108,Events!$F$6:$F$3108,$A11),"") -> 0.37954278 | O11: =IFERROR(AVERAGEIFS(Events!$CI$6:$CI$3108,Events!$F$6:$F$3108,$A11),"") -> -0.09757952 | P11: =COUNTIFS(Events!$F$6:$F$3108,$A11,Events!$CM$6:$CM$3108,"Yes",Events!$CL$6:$CL$3108,"<>") -> 35 | Q11: =IFERROR(AVERAGEIFS(Events!$CL$6:$CL$3108,Events!$F$6:$F$3108,$A11,Events!$CM$6:$CM$3108,"Yes"),"") -> -0.0114517 | R11: =IFERROR(COUNTIFS(Events!$F$6:$F$3108,$A11,Events!$CL$6:$CL$3108,">0",Events!$CM$6:$CM$3108,"Yes")/COUNTIFS(Events!$F$6:$F$3108,$A11,Events!$CL$6:$CL$3108,"<>",Events!$CM$6:$CM$3108,"Yes"),"") -> 0.4
A12: Refineries | B12: =COUNTIFS(Events!$F$6:$F$3108,$A12) -> 60 | C12: =COUNTIFS(Events!$F$6:$F$3108,$A12,Events!$K$6:$K$3108,"After close") -> 40 | D12: =COUNTIFS(Events!$F$6:$F$3108,$A12,Events!$K$6:$K$3108,"During market") -> 20 | E12: =COUNTIFS(Events!$F$6:$F$3108,$A12,Events!$K$6:$K$3108,"Non-trading day") -> 0 | F12: =IFERROR(AVERAGEIFS(Events!$T$6:$T$3108,Events!$F$6:$F$3108,$A12),"") -> 0.003830512 | G12: =IFERROR(COUNTIFS(Events!$F$6:$F$3108,$A12,Events!$T$6:$T$3108,">0")/COUNTIFS(Events!$F$6:$F$3108,$A12,Events!$T$6:$T$3108,"<>"),"") -> 0.54237288 | H12: =IFERROR(AVERAGEIFS(Events!$W$6:$W$3108,Events!$F$6:$F$3108,$A12),"") -> 0.0039693205 | I12: =IFERROR(AVERAGEIFS(Events!$AC$6:$AC$3108,Events!$F$6:$F$3108,$A12),"") -> 0.0251297 | J12: =IFERROR(COUNTIFS(Events!$F$6:$F$3108,$A12,Events!$AU$6:$AU$3108,">0")/COUNTIFS(Events!$F$6:$F$3108,$A12,Events!$AU$6:$AU$3108,"<>"),"") -> 0.68965517 | K12: =IFERROR(COUNTIFS(Events!$F$6:$F$3108,$A12,Events!$BA$6:$BA$3108,">0")/COUNTIFS(Events!$F$6:$F$3108,$A12,Events!$BA$6:$BA$3108,"<>"),"") -> 0.5 | L12: =IFERROR(AVERAGEIFS(Events!$AY$6:$AY$3108,Events!$F$6:$F$3108,$A12),"") -> 0.0048226473 | M12: =IFERROR(AVERAGEIFS(Events!$CJ$6:$CJ$3108,Events!$F$6:$F$3108,$A12),"") -> 0.05645762 | N12: =IFERROR(AVERAGEIFS(Events!$CK$6:$CK$3108,Events!$F$6:$F$3108,$A12),"") -> 0.48543483 | O12: =IFERROR(AVERAGEIFS(Events!$CI$6:$CI$3108,Events!$F$6:$F$3108,$A12),"") -> -0.087111459 | P12: =COUNTIFS(Events!$F$6:$F$3108,$A12,Events!$CM$6:$CM$3108,"Yes",Events!$CL$6:$CL$3108,"<>") -> 29 | Q12: =IFERROR(AVERAGEIFS(Events!$CL$6:$CL$3108,Events!$F$6:$F$3108,$A12,Events!$CM$6:$CM$3108,"Yes"),"") -> 0.11897505 | R12: =IFERROR(COUNTIFS(Events!$F$6:$F$3108,$A12,Events!$CL$6:$CL$3108,">0",Events!$CM$6:$CM$3108,"Yes")/COUNTIFS(Events!$F$6:$F$3108,$A12,Events!$CL$6:$CL$3108,"<>",Events!$CM$6:$CM$3108,"Yes"),"") -> 0.4137931
A13: Cement And Cement Products | B13: =COUNTIFS(Events!$F$6:$F$3108,$A13) -> 60 | C13: =COUNTIFS(Events!$F$6:$F$3108,$A13,Events!$K$6:$K$3108,"After close") -> 20 | D13: =COUNTIFS(Events!$F$6:$F$3108,$A13,Events!$K$6:$K$3108,"During market") -> 34 | E13: =COUNTIFS(Events!$F$6:$F$3108,$A13,Events!$K$6:$K$3108,"Non-trading day") -> 5 | F13: =IFERROR(AVERAGEIFS(Events!$T$6:$T$3108,Events!$F$6:$F$3108,$A13),"") -> 0.001099614 | G13: =IFERROR(COUNTIFS(Events!$F$6:$F$3108,$A13,Events!$T$6:$T$3108,">0")/COUNTIFS(Events!$F$6:$F$3108,$A13,Events!$T$6:$T$3108,"<>"),"") -> 0.45 | H13: =IFERROR(AVERAGEIFS(Events!$W$6:$W$3108,Events!$F$6:$F$3108,$A13),"") -> -0.0003175078 | I13: =IFERROR(AVERAGEIFS(Events!$AC$6:$AC$3108,Events!$F$6:$F$3108,$A13),"") -> 0.018975664 | J13: =IFERROR(COUNTIFS(Events!$F$6:$F$3108,$A13,Events!$AU$6:$AU$3108,">0")/COUNTIFS(Events!$F$6:$F$3108,$A13,Events!$AU$6:$AU$3108,"<>"),"") -> 0.9137931 | K13: =IFERROR(COUNTIFS(Events!$F$6:$F$3108,$A13,Events!$BA$6:$BA$3108,">0")/COUNTIFS(Events!$F$6:$F$3108,$A13,Events!$BA$6:$BA$3108,"<>"),"") -> 0.5862069 | L13: =IFERROR(AVERAGEIFS(Events!$AY$6:$AY$3108,Events!$F$6:$F$3108,$A13),"") -> 0.0020745859 | M13: =IFERROR(AVERAGEIFS(Events!$CJ$6:$CJ$3108,Events!$F$6:$F$3108,$A13),"") -> 0.056537442 | N13: =IFERROR(AVERAGEIFS(Events!$CK$6:$CK$3108,Events!$F$6:$F$3108,$A13),"") -> 0.36405658 | O13: =IFERROR(AVERAGEIFS(Events!$CI$6:$CI$3108,Events!$F$6:$F$3108,$A13),"") -> -0.088350378 | P13: =COUNTIFS(Events!$F$6:$F$3108,$A13,Events!$CM$6:$CM$3108,"Yes",Events!$CL$6:$CL$3108,"<>") -> 29 | Q13: =IFERROR(AVERAGEIFS(Events!$CL$6:$CL$3108,Events!$F$6:$F$3108,$A13,Events!$CM$6:$CM$3108,"Yes"),"") -> -0.015352254 | R13: =IFERROR(COUNTIFS(Events!$F$6:$F$3108,$A13,Events!$CL$6:$CL$3108,">0",Events!$CM$6:$CM$3108,"Yes")/COUNTIFS(Events!$F$6:$F$3108,$A13,Events!$CL$6:$CL$3108,"<>",Events!$CM$6:$CM$3108,"Yes"),"") -> 0.34482759
A14: Miscellaneous | B14: =COUNTIFS(Events!$F$6:$F$3108,$A14) -> 60 | C14: =COUNTIFS(Events!$F$6:$F$3108,$A14,Events!$K$6:$K$3108,"After close") -> 48 | D14: =COUNTIFS(Events!$F$6:$F$3108,$A14,Events!$K$6:$K$3108,"During market") -> 12 | E14: =COUNTIFS(Events!$F$6:$F$3108,$A14,Events!$K$6:$K$3108,"Non-trading day") -> 0 | F14: =IFERROR(AVERAGEIFS(Events!$T$6:$T$3108,Events!$F$6:$F$3108,$A14),"") -> 0.011690731 | G14: =IFERROR(COUNTIFS(Events!$F$6:$F$3108,$A14,Events!$T$6:$T$3108,">0")/COUNTIFS(Events!$F$6:$F$3108,$A14,Events!$T$6:$T$3108,"<>"),"") -> 0.55 | H14: =IFERROR(AVERAGEIFS(Events!$W$6:$W$3108,Events!$F$6:$F$3108,$A14),"") -> 0.011323143 | I14: =IFERROR(AVERAGEIFS(Events!$AC$6:$AC$3108,Events!$F$6:$F$3108,$A14),"") -> 0.036730765 | J14: =IFERROR(COUNTIFS(Events!$F$6:$F$3108,$A14,Events!$AU$6:$AU$3108,">0")/COUNTIFS(Events!$F$6:$F$3108,$A14,Events!$AU$6:$AU$3108,"<>"),"") -> 1 | K14: =IFERROR(COUNTIFS(Events!$F$6:$F$3108,$A14,Events!$BA$6:$BA$3108,">0")/COUNTIFS(Events!$F$6:$F$3108,$A14,Events!$BA$6:$BA$3108,"<>"),"") -> 0.88135593 | L14: =IFERROR(AVERAGEIFS(Events!$AY$6:$AY$3108,Events!$F$6:$F$3108,$A14),"") -> 0.0068212859 | M14: =IFERROR(AVERAGEIFS(Events!$CJ$6:$CJ$3108,Events!$F$6:$F$3108,$A14),"") -> 0.068390157 | N14: =IFERROR(AVERAGEIFS(Events!$CK$6:$CK$3108,Events!$F$6:$F$3108,$A14),"") -> 0.59067721 | O14: =IFERROR(AVERAGEIFS(Events!$CI$6:$CI$3108,Events!$F$6:$F$3108,$A14),"") -> -0.15156753 | P14: =COUNTIFS(Events!$F$6:$F$3108,$A14,Events!$CM$6:$CM$3108,"Yes",Events!$CL$6:$CL$3108,"<>") -> 26 | Q14: =IFERROR(AVERAGEIFS(Events!$CL$6:$CL$3108,Events!$F$6:$F$3108,$A14,Events!$CM$6:$CM$3108,"Yes"),"") -> 0.013619865 | R14: =IFERROR(COUNTIFS(Events!$F$6:$F$3108,$A14,Events!$CL$6:$CL$3108,">0",Events!$CM$6:$CM$3108,"Yes")/COUNTIFS(Events!$F$6:$F$3108,$A14,Events!$CL$6:$CL$3108,"<>",Events!$CM$6:$CM$3108,"Yes"),"") -> 0.42307692
A15: Personal Care | B15: =COUNTIFS(Events!$F$6:$F$3108,$A15) -> 60 | C15: =COUNTIFS(Events!$F$6:$F$3108,$A15,Events!$K$6:$K$3108,"After close") -> 37 | D15: =COUNTIFS(Events!$F$6:$F$3108,$A15,Events!$K$6:$K$3108,"During market") -> 22 | E15: =COUNTIFS(Events!$F$6:$F$3108,$A15,Events!$K$6:$K$3108,"Non-trading day") -> 1 | F15: =IFERROR(AVERAGEIFS(Events!$T$6:$T$3108,Events!$F$6:$F$3108,$A15),"") -> 0.0019405102 | G15: =IFERROR(COUNTIFS(Events!$F$6:$F$3108,$A15,Events!$T$6:$T$3108,">0")/COUNTIFS(Events!$F$6:$F$3108,$A15,Events!$T$6:$T$3108,"<>"),"") -> 0.43333333 | H15: =IFERROR(AVERAGEIFS(Events!$W$6:$W$3108,Events!$F$6:$F$3108,$A15),"") -> 0.001629057 | I15: =IFERROR(AVERAGEIFS(Events!$AC$6:$AC$3108,Events!$F$6:$F$3108,$A15),"") -> 0.026487864 | J15: =IFERROR(COUNTIFS(Events!$F$6:$F$3108,$A15,Events!$AU$6:$AU$3108,">0")/COUNTIFS(Events!$F$6:$F$3108,$A15,Events!$AU$6:$AU$3108,"<>"),"") -> 0.86666667 | K15: =IFERROR(COUNTIFS(Events!$F$6:$F$3108,$A15,Events!$BA$6:$BA$3108,">0")/COUNTIFS(Events!$F$6:$F$3108,$A15,Events!$BA$6:$BA$3108,"<>"),"") -> 0.76271186 | L15: =IFERROR(AVERAGEIFS(Events!$AY$6:$AY$3108,Events!$F$6:$F$3108,$A15),"") -> -0.00012932181 | M15: =IFERROR(AVERAGEIFS(Events!$CJ$6:$CJ$3108,Events!$F$6:$F$3108,$A15),"") -> 0.057657326 | N15: =IFERROR(AVERAGEIFS(Events!$CK$6:$CK$3108,Events!$F$6:$F$3108,$A15),"") -> 0.47447817 | O15: =IFERROR(AVERAGEIFS(Events!$CI$6:$CI$3108,Events!$F$6:$F$3108,$A15),"") -> -0.13283822 | P15: =COUNTIFS(Events!$F$6:$F$3108,$A15,Events!$CM$6:$CM$3108,"Yes",Events!$CL$6:$CL$3108,"<>") -> 15 | Q15: =IFERROR(AVERAGEIFS(Events!$CL$6:$CL$3108,Events!$F$6:$F$3108,$A15,Events!$CM$6:$CM$3108,"Yes"),"") -> 0.036853097 | R15: =IFERROR(COUNTIFS(Events!$F$6:$F$3108,$A15,Events!$CL$6:$CL$3108,">0",Events!$CM$6:$CM$3108,"Yes")/COUNTIFS(Events!$F$6:$F$3108,$A15,Events!$CL$6:$CL$3108,"<>",Events!$CM$6:$CM$3108,"Yes"),"") -> 0.4
... A47: Brew/Distilleries | B47: =COUNTIFS(Events!$F$6:$F$3108,$A47) -> 15 | C47: =COUNTIFS(Events!$F$6:$F$3108,$A47,Events!$K$6:$K$3108,"After close") -> 9 | D47: =COUNTIFS(Events!$F$6:$F$3108,$A47,Events!$K$6:$K$3108,"During market") -> 6 | E47: =COUNTIFS(Events!$F$6:$F$3108,$A47,Events!$K$6:$K$3108,"Non-trading day") -> 0 | F47: =IFERROR(AVERAGEIFS(Events!$T$6:$T$3108,Events!$F$6:$F$3108,$A47),"") -> 0.020078375 | G47: =IFERROR(COUNTIFS(Events!$F$6:$F$3108,$A47,Events!$T$6:$T$3108,">0")/COUNTIFS(Events!$F$6:$F$3108,$A47,Events!$T$6:$T$3108,"<>"),"") -> 0.73333333 | H47: =IFERROR(AVERAGEIFS(Events!$W$6:$W$3108,Events!$F$6:$F$3108,$A47),"") -> 0.016717512 | I47: =IFERROR(AVERAGEIFS(Events!$AC$6:$AC$3108,Events!$F$6:$F$3108,$A47),"") -> 0.021710635 | J47: =IFERROR(COUNTIFS(Events!$F$6:$F$3108,$A47,Events!$AU$6:$AU$3108,">0")/COUNTIFS(Events!$F$6:$F$3108,$A47,Events!$AU$6:$AU$3108,"<>"),"") -> 0.93333333 | K47: =IFERROR(COUNTIFS(Events!$F$6:$F$3108,$A47,Events!$BA$6:$BA$3108,">0")/COUNTIFS(Events!$F$6:$F$3108,$A47,Events!$BA$6:$BA$3108,"<>"),"") -> 0.71428571 | L47: =IFERROR(AVERAGEIFS(Events!$AY$6:$AY$3108,Events!$F$6:$F$3108,$A47),"") -> 0.0057940756 | M47: =IFERROR(AVERAGEIFS(Events!$CJ$6:$CJ$3108,Events!$F$6:$F$3108,$A47),"") -> 0.080913363 | N47: =IFERROR(AVERAGEIFS(Events!$CK$6:$CK$3108,Events!$F$6:$F$3108,$A47),"") -> 0.4175726 | O47: =IFERROR(AVERAGEIFS(Events!$CI$6:$CI$3108,Events!$F$6:$F$3108,$A47),"") -> 0.081386043 | P47: =COUNTIFS(Events!$F$6:$F$3108,$A47,Events!$CM$6:$CM$3108,"Yes",Events!$CL$6:$CL$3108,"<>") -> 0 | Q47: =IFERROR(AVERAGEIFS(Events!$CL$6:$CL$3108,Events!$F$6:$F$3108,$A47,Events!$CM$6:$CM$3108,"Yes"),"") | R47: =IFERROR(COUNTIFS(Events!$F$6:$F$3108,$A47,Events!$CL$6:$CL$3108,">0",Events!$CM$6:$CM$3108,"Yes")/COUNTIFS(Events!$F$6:$F$3108,$A47,Events!$CL$6:$CL$3108,"<>",Events!$CM$6:$CM$3108,"Yes"),"")
A48: All industries | B48: =COUNTIFS(Events!$F$6:$F$3108,"<>") -> 1917 | C48: =COUNTIFS(Events!$F$6:$F$3108,"<>",Events!$K$6:$K$3108,"After close") -> 1147 | D48: =COUNTIFS(Events!$F$6:$F$3108,"<>",Events!$K$6:$K$3108,"During market") -> 607 | E48: =COUNTIFS(Events!$F$6:$F$3108,"<>",Events!$K$6:$K$3108,"Non-trading day") -> 154 | F48: =IFERROR(AVERAGEIFS(Events!$T$6:$T$3108,Events!$F$6:$F$3108,"<>"),"") -> 0.0019821077 | G48: =IFERROR(COUNTIFS(Events!$F$6:$F$3108,"<>",Events!$T$6:$T$3108,">0")/COUNTIFS(Events!$F$6:$F$3108,"<>",Events!$T$6:$T$3108,"<>"),"") -> 0.50653424 | H48: =IFERROR(AVERAGEIFS(Events!$W$6:$W$3108,Events!$F$6:$F$3108,"<>"),"") -> 0.0018268191 | I48: =IFERROR(AVERAGEIFS(Events!$AC$6:$AC$3108,Events!$F$6:$F$3108,"<>"),"") -> 0.028900134 | J48: =IFERROR(COUNTIFS(Events!$F$6:$F$3108,"<>",Events!$AU$6:$AU$3108,">0")/COUNTIFS(Events!$F$6:$F$3108,"<>",Events!$AU$6:$AU$3108,"<>"),"") -> 0.84734869 | K48: =IFERROR(COUNTIFS(Events!$F$6:$F$3108,"<>",Events!$BA$6:$BA$3108,">0")/COUNTIFS(Events!$F$6:$F$3108,"<>",Events!$BA$6:$BA$3108,"<>"),"") -> 0.71156138 | L48: =IFERROR(AVERAGEIFS(Events!$AY$6:$AY$3108,Events!$F$6:$F$3108,"<>"),"") -> 0.0016517823 | M48: =IFERROR(AVERAGEIFS(Events!$CJ$6:$CJ$3108,Events!$F$6:$F$3108,"<>"),"") -> 0.063233345 | N48: =IFERROR(AVERAGEIFS(Events!$CK$6:$CK$3108,Events!$F$6:$F$3108,"<>"),"") -> 0.47873148 | O48: =IFERROR(AVERAGEIFS(Events!$CI$6:$CI$3108,Events!$F$6:$F$3108,"<>"),"") -> -0.13143158 | P48: =COUNTIFS(Events!$F$6:$F$3108,"<>",Events!$CM$6:$CM$3108,"Yes",Events!$CL$6:$CL$3108,"<>") -> 847 | Q48: =IFERROR(AVERAGEIFS(Events!$CL$6:$CL$3108,Events!$F$6:$F$3108,"<>",Events!$CM$6:$CM$3108,"Yes"),"") -> 0.030142693 | R48: =IFERROR(COUNTIFS(Events!$F$6:$F$3108,"<>",Events!$CL$6:$CL$3108,">0",Events!$CM$6:$CM$3108,"Yes")/COUNTIFS(Events!$F$6:$F$3108,"<>",Events!$CL$6:$CL$3108,"<>",Events!$CM$6:$CM$3108,"Yes"),"") -> 0.42502952

Sheet By stock
A1: By stock
A2: Formulas over the Events sheet, all 15 quarters.
A3: Symbol | B3: Company | C3: Industry | D3: Results events | E3: After close | F3: Avg three-day sum % | G3: % three-day positive | H3: Avg excess vs Nifty % | I3: Avg size of reaction move % | J3: % sales up YoY | K3: % profit up YoY | L3: Avg EBITDA margin chg YoY (pts) | M3: Avg expected move % (options) | N3: Avg actual / expected move (x) | O3: Avg IV drop % | P3: Run-up trades (rule pass) | Q3: Run-up avg return % (rule pass) | R3: Run-up win rate (rule pass)
A4: 360ONE | B4: =INDEX(Events!$E$6:$E$3108,MATCH($A4,Events!$D$6:$D$3108,0)) -> 360 ONE WAM LIMITED | C4: =INDEX(Events!$F$6:$F$3108,MATCH($A4,Events!$D$6:$D$3108,0)) -> 0 | D4: =COUNTIFS(Events!$D$6:$D$3108,$A4) -> 15 | E4: =COUNTIFS(Events!$D$6:$D$3108,$A4,Events!$K$6:$K$3108,"After close") -> 12 | F4: =IFERROR(AVERAGEIFS(Events!$T$6:$T$3108,Events!$D$6:$D$3108,$A4),"") -> 0.00059493517 | G4: =IFERROR(COUNTIFS(Events!$D$6:$D$3108,$A4,Events!$T$6:$T$3108,">0")/COUNTIFS(Events!$D$6:$D$3108,$A4,Events!$T$6:$T$3108,"<>"),"") -> 0.64285714 | H4: =IFERROR(AVERAGEIFS(Events!$W$6:$W$3108,Events!$D$6:$D$3108,$A4),"") -> 8.5437957e-05 | I4: =IFERROR(AVERAGEIFS(Events!$AC$6:$AC$3108,Events!$D$6:$D$3108,$A4),"") -> 0.032123706 | J4: =IFERROR(COUNTIFS(Events!$D$6:$D$3108,$A4,Events!$AU$6:$AU$3108,">0")/COUNTIFS(Events!$D$6:$D$3108,$A4,Events!$AU$6:$AU$3108,"<>"),"") -> 0.92857143 | K4: =IFERROR(COUNTIFS(Events!$D$6:$D$3108,$A4,Events!$BA$6:$BA$3108,">0")/COUNTIFS(Events!$D$6:$D$3108,$A4,Events!$BA$6:$BA$3108,"<>"),"") -> 1 | L4: =IFERROR(AVERAGEIFS(Events!$AY$6:$AY$3108,Events!$D$6:$D$3108,$A4),"") | M4: =IFERROR(AVERAGEIFS(Events!$CJ$6:$CJ$3108,Events!$D$6:$D$3108,$A4),"") -> 0.058463763 | N4: =IFERROR(AVERAGEIFS(Events!$CK$6:$CK$3108,Events!$D$6:$D$3108,$A4),"") -> 0.44387782 | O4: =IFERROR(AVERAGEIFS(Events!$CI$6:$CI$3108,Events!$D$6:$D$3108,$A4),"") -> -0.15649243 | P4: =COUNTIFS(Events!$D$6:$D$3108,$A4,Events!$CM$6:$CM$3108,"Yes",Events!$CL$6:$CL$3108,"<>") -> 5 | Q4: =IFERROR(AVERAGEIFS(Events!$CL$6:$CL$3108,Events!$D$6:$D$3108,$A4,Events!$CM$6:$CM$3108,"Yes"),"") -> 0.069709918 | R4: =IFERROR(COUNTIFS(Events!$D$6:$D$3108,$A4,Events!$CL$6:$CL$3108,">0",Events!$CM$6:$CM$3108,"Yes")/COUNTIFS(Events!$D$6:$D$3108,$A4,Events!$CL$6:$CL$3108,"<>",Events!$CM$6:$CM$3108,"Yes"),"") -> 0.4
A5: ABB | B5: =INDEX(Events!$E$6:$E$3108,MATCH($A5,Events!$D$6:$D$3108,0)) -> ABB India Limited | C5: =INDEX(Events!$F$6:$F$3108,MATCH($A5,Events!$D$6:$D$3108,0)) -> Electrical Equipment | D5: =COUNTIFS(Events!$D$6:$D$3108,$A5) -> 15 | E5: =COUNTIFS(Events!$D$6:$D$3108,$A5,Events!$K$6:$K$3108,"After close") -> 13 | F5: =IFERROR(AVERAGEIFS(Events!$T$6:$T$3108,Events!$D$6:$D$3108,$A5),"") -> 0.0058053874 | G5: =IFERROR(COUNTIFS(Events!$D$6:$D$3108,$A5,Events!$T$6:$T$3108,">0")/COUNTIFS(Events!$D$6:$D$3108,$A5,Events!$T$6:$T$3108,"<>"),"") -> 0.6 | H5: =IFERROR(AVERAGEIFS(Events!$W$6:$W$3108,Events!$D$6:$D$3108,$A5),"") -> 0.0057663658 | I5: =IFERROR(AVERAGEIFS(Events!$AC$6:$AC$3108,Events!$D$6:$D$3108,$A5),"") -> 0.046552597 | J5: =IFERROR(COUNTIFS(Events!$D$6:$D$3108,$A5,Events!$AU$6:$AU$3108,">0")/COUNTIFS(Events!$D$6:$D$3108,$A5,Events!$AU$6:$AU$3108,"<>"),"") -> 1 | K5: =IFERROR(COUNTIFS(Events!$D$6:$D$3108,$A5,Events!$BA$6:$BA$3108,">0")/COUNTIFS(Events!$D$6:$D$3108,$A5,Events!$BA$6:$BA$3108,"<>"),"") -> 0.76923077 | L5: =IFERROR(AVERAGEIFS(Events!$AY$6:$AY$3108,Events!$D$6:$D$3108,$A5),"") -> 0.0089011877 | M5: =IFERROR(AVERAGEIFS(Events!$CJ$6:$CJ$3108,Events!$D$6:$D$3108,$A5),"") -> 0.073012832 | N5: =IFERROR(AVERAGEIFS(Events!$CK$6:$CK$3108,Events!$D$6:$D$3108,$A5),"") -> 0.6361731 | O5: =IFERROR(AVERAGEIFS(Events!$CI$6:$CI$3108,Events!$D$6:$D$3108,$A5),"") -> -0.13998456 | P5: =COUNTIFS(Events!$D$6:$D$3108,$A5,Events!$CM$6:$CM$3108,"Yes",Events!$CL$6:$CL$3108,"<>") -> 10 | Q5: =IFERROR(AVERAGEIFS(Events!$CL$6:$CL$3108,Events!$D$6:$D$3108,$A5,Events!$CM$6:$CM$3108,"Yes"),"") -> 0.12724421 | R5: =IFERROR(COUNTIFS(Events!$D$6:$D$3108,$A5,Events!$CL$6:$CL$3108,">0",Events!$CM$6:$CM$3108,"Yes")/COUNTIFS(Events!$D$6:$D$3108,$A5,Events!$CL$6:$CL$3108,"<>",Events!$CM$6:$CM$3108,"Yes"),"") -> 0.7
A6: ABCAPITAL | B6: =INDEX(Events!$E$6:$E$3108,MATCH($A6,Events!$D$6:$D$3108,0)) -> Aditya Birla Capital Limited | C6: =INDEX(Events!$F$6:$F$3108,MATCH($A6,Events!$D$6:$D$3108,0)) -> 0 | D6: =COUNTIFS(Events!$D$6:$D$3108,$A6) -> 15 | E6: =COUNTIFS(Events!$D$6:$D$3108,$A6,Events!$K$6:$K$3108,"After close") -> 3 | F6: =IFERROR(AVERAGEIFS(Events!$T$6:$T$3108,Events!$D$6:$D$3108,$A6),"") -> 0.027439865 | G6: =IFERROR(COUNTIFS(Events!$D$6:$D$3108,$A6,Events!$T$6:$T$3108,">0")/COUNTIFS(Events!$D$6:$D$3108,$A6,Events!$T$6:$T$3108,"<>"),"") -> 0.73333333 | H6: =IFERROR(AVERAGEIFS(Events!$W$6:$W$3108,Events!$D$6:$D$3108,$A6),"") -> 0.020257381 | I6: =IFERROR(AVERAGEIFS(Events!$AC$6:$AC$3108,Events!$D$6:$D$3108,$A6),"") -> 0.0278737 | J6: =IFERROR(COUNTIFS(Events!$D$6:$D$3108,$A6,Events!$AU$6:$AU$3108,">0")/COUNTIFS(Events!$D$6:$D$3108,$A6,Events!$AU$6:$AU$3108,"<>"),"") -> 1 | K6: =IFERROR(COUNTIFS(Events!$D$6:$D$3108,$A6,Events!$BA$6:$BA$3108,">0")/COUNTIFS(Events!$D$6:$D$3108,$A6,Events!$BA$6:$BA$3108,"<>"),"") -> 0.71428571 | L6: =IFERROR(AVERAGEIFS(Events!$AY$6:$AY$3108,Events!$D$6:$D$3108,$A6),"") | M6: =IFERROR(AVERAGEIFS(Events!$CJ$6:$CJ$3108,Events!$D$6:$D$3108,$A6),"") -> 0.075392046 | N6: =IFERROR(AVERAGEIFS(Events!$CK$6:$CK$3108,Events!$D$6:$D$3108,$A6),"") -> 0.37906816 | O6: =IFERROR(AVERAGEIFS(Events!$CI$6:$CI$3108,Events!$D$6:$D$3108,$A6),"") -> -0.076674509 | P6: =COUNTIFS(Events!$D$6:$D$3108,$A6,Events!$CM$6:$CM$3108,"Yes",Events!$CL$6:$CL$3108,"<>") -> 3 | Q6: =IFERROR(AVERAGEIFS(Events!$CL$6:$CL$3108,Events!$D$6:$D$3108,$A6,Events!$CM$6:$CM$3108,"Yes"),"") -> 0.080976809 | R6: =IFERROR(COUNTIFS(Events!$D$6:$D$3108,$A6,Events!$CL$6:$CL$3108,">0",Events!$CM$6:$CM$3108,"Yes")/COUNTIFS(Events!$D$6:$D$3108,$A6,Events!$CL$6:$CL$3108,"<>",Events!$CM$6:$CM$3108,"Yes"),"") -> 0.66666667
A7: ADANIENSOL | B7: =INDEX(Events!$E$6:$E$3108,MATCH($A7,Events!$D$6:$D$3108,0)) -> Adani Energy Solutions Limited | C7: =INDEX(Events!$F$6:$F$3108,MATCH($A7,Events!$D$6:$D$3108,0)) -> 0 | D7: =COUNTIFS(Events!$D$6:$D$3108,$A7) -> 15 | E7: =COUNTIFS(Events!$D$6:$D$3108,$A7,Events!$K$6:$K$3108,"After close") -> 7 | F7: =IFERROR(AVERAGEIFS(Events!$T$6:$T$3108,Events!$D$6:$D$3108,$A7),"") -> -0.0094875771 | G7: =IFERROR(COUNTIFS(Events!$D$6:$D$3108,$A7,Events!$T$6:$T$3108,">0")/COUNTIFS(Events!$D$6:$D$3108,$A7,Events!$T$6:$T$3108,"<>"),"") -> 0.41666667 | H7: =IFERROR(AVERAGEIFS(Events!$W$6:$W$3108,Events!$D$6:$D$3108,$A7),"") -> -0.0074094146 | I7: =IFERROR(AVERAGEIFS(Events!$AC$6:$AC$3108,Events!$D$6:$D$3108,$A7),"") -> 0.018536169 | J7: =IFERROR(COUNTIFS(Events!$D$6:$D$3108,$A7,Events!$AU$6:$AU$3108,">0")/COUNTIFS(Events!$D$6:$D$3108,$A7,Events!$AU$6:$AU$3108,"<>"),"") -> 1 | K7: =IFERROR(COUNTIFS(Events!$D$6:$D$3108,$A7,Events!$BA$6:$BA$3108,">0")/COUNTIFS(Events!$D$6:$D$3108,$A7,Events!$BA$6:$BA$3108,"<>"),"") -> 0.61538462 | L7: =IFERROR(AVERAGEIFS(Events!$AY$6:$AY$3108,Events!$D$6:$D$3108,$A7),"") -> 0.02184263 | M7: =IFERROR(AVERAGEIFS(Events!$CJ$6:$CJ$3108,Events!$D$6:$D$3108,$A7),"") -> 0.080326302 | N7: =IFERROR(AVERAGEIFS(Events!$CK$6:$CK$3108,Events!$D$6:$D$3108,$A7),"") -> 0.26987123 | O7: =IFERROR(AVERAGEIFS(Events!$CI$6:$CI$3108,Events!$D$6:$D$3108,$A7),"") -> -0.026718888 | P7: =COUNTIFS(Events!$D$6:$D$3108,$A7,Events!$CM$6:$CM$3108,"Yes",Events!$CL$6:$CL$3108,"<>") -> 3 | Q7: =IFERROR(AVERAGEIFS(Events!$CL$6:$CL$3108,Events!$D$6:$D$3108,$A7,Events!$CM$6:$CM$3108,"Yes"),"") -> -0.15664483 | R7: =IFERROR(COUNTIFS(Events!$D$6:$D$3108,$A7,Events!$CL$6:$CL$3108,">0",Events!$CM$6:$CM$3108,"Yes")/COUNTIFS(Events!$D$6:$D$3108,$A7,Events!$CL$6:$CL$3108,"<>",Events!$CM$6:$CM$3108,"Yes"),"") -> 0
A8: ADANIENT | B8: =INDEX(Events!$E$6:$E$3108,MATCH($A8,Events!$D$6:$D$3108,0)) -> Adani Enterprises Limited | C8: =INDEX(Events!$F$6:$F$3108,MATCH($A8,Events!$D$6:$D$3108,0)) -> Trading | D8: =COUNTIFS(Events!$D$6:$D$3108,$A8) -> 15 | E8: =COUNTIFS(Events!$D$6:$D$3108,$A8,Events!$K$6:$K$3108,"After close") -> 1 | F8: =IFERROR(AVERAGEIFS(Events!$T$6:$T$3108,Events!$D$6:$D$3108,$A8),"") -> 0.010138633 | G8: =IFERROR(COUNTIFS(Events!$D$6:$D$3108,$A8,Events!$T$6:$T$3108,">0")/COUNTIFS(Events!$D$6:$D$3108,$A8,Events!$T$6:$T$3108,"<>"),"") -> 0.66666667 | H8: =IFERROR(AVERAGEIFS(Events!$W$6:$W$3108,Events!$D$6:$D$3108,$A8),"") -> 0.0062769014 | I8: =IFERROR(AVERAGEIFS(Events!$AC$6:$AC$3108,Events!$D$6:$D$3108,$A8),"") -> 0.023908767 | J8: =IFERROR(COUNTIFS(Events!$D$6:$D$3108,$A8,Events!$AU$6:$AU$3108,">0")/COUNTIFS(Events!$D$6:$D$3108,$A8,Events!$AU$6:$AU$3108,"<>"),"") -> 0.6 | K8: =IFERROR(COUNTIFS(Events!$D$6:$D$3108,$A8,Events!$BA$6:$BA$3108,">0")/COUNTIFS(Events!$D$6:$D$3108,$A8,Events!$BA$6:$BA$3108,"<>"),"") -> 0.57142857 | L8: =IFERROR(AVERAGEIFS(Events!$AY$6:$AY$3108,Events!$D$6:$D$3108,$A8),"") -> 0.047767843 | M8: =IFERROR(AVERAGEIFS(Events!$CJ$6:$CJ$3108,Events!$D$6:$D$3108,$A8),"") -> 0.097450899 | N8: =IFERROR(AVERAGEIFS(Events!$CK$6:$CK$3108,Events!$D$6:$D$3108,$A8),"") -> 0.28131601 | O8: =IFERROR(AVERAGEIFS(Events!$CI$6:$CI$3108,Events!$D$6:$D$3108,$A8),"") -> -0.032941297 | P8: =COUNTIFS(Events!$D$6:$D$3108,$A8,Events!$CM$6:$CM$3108,"Yes",Events!$CL$6:$CL$3108,"<>") -> 1 | Q8: =IFERROR(AVERAGEIFS(Events!$CL$6:$CL$3108,Events!$D$6:$D$3108,$A8,Events!$CM$6:$CM$3108,"Yes"),"") -> -0.18961845 | R8: =IFERROR(COUNTIFS(Events!$D$6:$D$3108,$A8,Events!$CL$6:$CL$3108,">0",Events!$CM$6:$CM$3108,"Yes")/COUNTIFS(Events!$D$6:$D$3108,$A8,Events!$CL$6:$CL$3108,"<>",Events!$CM$6:$CM$3108,"Yes"),"") -> 0
A9: ADANIGREEN | B9: =INDEX(Events!$E$6:$E$3108,MATCH($A9,Events!$D$6:$D$3108,0)) -> Adani Green Energy Limited | C9: =INDEX(Events!$F$6:$F$3108,MATCH($A9,Events!$D$6:$D$3108,0)) -> 0 | D9: =COUNTIFS(Events!$D$6:$D$3108,$A9) -> 15 | E9: =COUNTIFS(Events!$D$6:$D$3108,$A9,Events!$K$6:$K$3108,"After close") -> 4 | F9: =IFERROR(AVERAGEIFS(Events!$T$6:$T$3108,Events!$D$6:$D$3108,$A9),"") -> -0.013210983 | G9: =IFERROR(COUNTIFS(Events!$D$6:$D$3108,$A9,Events!$T$6:$T$3108,">0")/COUNTIFS(Events!$D$6:$D$3108,$A9,Events!$T$6:$T$3108,"<>"),"") -> 0.4 | H9: =IFERROR(AVERAGEIFS(Events!$W$6:$W$3108,Events!$D$6:$D$3108,$A9),"") -> -0.013296254 | I9: =IFERROR(AVERAGEIFS(Events!$AC$6:$AC$3108,Events!$D$6:$D$3108,$A9),"") -> 0.041194221 | J9: =IFERROR(COUNTIFS(Events!$D$6:$D$3108,$A9,Events!$AU$6:$AU$3108,">0")/COUNTIFS(Events!$D$6:$D$3108,$A9,Events!$AU$6:$AU$3108,"<>"),"") -> 0.93333333 | K9: =IFERROR(COUNTIFS(Events!$D$6:$D$3108,$A9,Events!$BA$6:$BA$3108,">0")/COUNTIFS(Events!$D$6:$D$3108,$A9,Events!$BA$6:$BA$3108,"<>"),"") -> 0.71428571 | L9: =IFERROR(AVERAGEIFS(Events!$AY$6:$AY$3108,Events!$D$6:$D$3108,$A9),"") -> 0.055427741 | M9: =IFERROR(AVERAGEIFS(Events!$CJ$6:$CJ$3108,Events!$D$6:$D$3108,$A9),"") -> 0.087514166 | N9: =IFERROR(AVERAGEIFS(Events!$CK$6:$CK$3108,Events!$D$6:$D$3108,$A9),"") -> 0.68843693 | O9: =IFERROR(AVERAGEIFS(Events!$CI$6:$CI$3108,Events!$D$6:$D$3108,$A9),"") -> 0.053409079 | P9: =COUNTIFS(Events!$D$6:$D$3108,$A9,Events!$CM$6:$CM$3108,"Yes",Events!$CL$6:$CL$3108,"<>") -> 3 | Q9: =IFERROR(AVERAGEIFS(Events!$CL$6:$CL$3108,Events!$D$6:$D$3108,$A9,Events!$CM$6:$CM$3108,"Yes"),"") -> 0.0031240639 | R9: =IFERROR(COUNTIFS(Events!$D$6:$D$3108,$A9,Events!$CL$6:$CL$3108,">0",Events!$CM$6:$CM$3108,"Yes")/COUNTIFS(Events!$D$6:$D$3108,$A9,Events!$CL$6:$CL$3108,"<>",Events!$CM$6:$CM$3108,"Yes"),"") -> 0.33333333
A10: ADANIPORTS | B10: =INDEX(Events!$E$6:$E$3108,MATCH($A10,Events!$D$6:$D$3108,0)) -> Adani Ports and Special Economic Zone Limited | C10: =INDEX(Events!$F$6:$F$3108,MATCH($A10,Events!$D$6:$D$3108,0)) -> Shipping | D10: =COUNTIFS(Events!$D$6:$D$3108,$A10) -> 15 | E10: =COUNTIFS(Events!$D$6:$D$3108,$A10,Events!$K$6:$K$3108,"After close") -> 1 | F10: =IFERROR(AVERAGEIFS(Events!$T$6:$T$3108,Events!$D$6:$D$3108,$A10),"") -> 0.045291731 | G10: =IFERROR(COUNTIFS(Events!$D$6:$D$3108,$A10,Events!$T$6:$T$3108,">0")/COUNTIFS(Events!$D$6:$D$3108,$A10,Events!$T$6:$T$3108,"<>"),"") -> 0.86666667 | H10: =IFERROR(AVERAGEIFS(Events!$W$6:$W$3108,Events!$D$6:$D$3108,$A10),"") -> 0.040173972 | I10: =IFERROR(AVERAGEIFS(Events!$AC$6:$AC$3108,Events!$D$6:$D$3108,$A10),"") -> 0.019950513 | J10: =IFERROR(COUNTIFS(Events!$D$6:$D$3108,$A10,Events!$AU$6:$AU$3108,">0")/COUNTIFS(Events!$D$6:$D$3108,$A10,Events!$AU$6:$AU$3108,"<>"),"") -> 1 | K10: =IFERROR(COUNTIFS(Events!$D$6:$D$3108,$A10,Events!$BA$6:$BA$3108,">0")/COUNTIFS(Events!$D$6:$D$3108,$A10,Events!$BA$6:$BA$3108,"<>"),"") -> 0.8 | L10: =IFERROR(AVERAGEIFS(Events!$AY$6:$AY$3108,Events!$D$6:$D$3108,$A10),"") -> 0.018798473 | M10: =IFERROR(AVERAGEIFS(Events!$CJ$6:$CJ$3108,Events!$D$6:$D$3108,$A10),"") -> 0.076729256 | N10: =IFERROR(AVERAGEIFS(Events!$CK$6:$CK$3108,Events!$D$6:$D$3108,$A10),"") -> 0.29413 | O10: =IFERROR(AVERAGEIFS(Events!$CI$6:$CI$3108,Events!$D$6:$D$3108,$A10),"") -> -0.063901339 | P10: =COUNTIFS(Events!$D$6:$D$3108,$A10,Events!$CM$6:$CM$3108,"Yes",Events!$CL$6:$CL$3108,"<>") -> 2 | Q10: =IFERROR(AVERAGEIFS(Events!$CL$6:$CL$3108,Events!$D$6:$D$3108,$A10,Events!$CM$6:$CM$3108,"Yes"),"") -> -0.01442862 | R10: =IFERROR(COUNTIFS(Events!$D$6:$D$3108,$A10,Events!$CL$6:$CL$3108,">0",Events!$CM$6:$CM$3108,"Yes")/COUNTIFS(Events!$D$6:$D$3108,$A10,Events!$CL$6:$CL$3108,"<>",Events!$CM$6:$CM$3108,"Yes"),"") -> 0.5
A11: ADANIPOWER | B11: =INDEX(Events!$E$6:$E$3108,MATCH($A11,Events!$D$6:$D$3108,0)) -> Adani Power Limited | C11: =INDEX(Events!$F$6:$F$3108,MATCH($A11,Events!$D$6:$D$3108,0)) -> Power | D11: =COUNTIFS(Events!$D$6:$D$3108,$A11) -> 15 | E11: =COUNTIFS(Events!$D$6:$D$3108,$A11,Events!$K$6:$K$3108,"After close") -> 5 | F11: =IFERROR(AVERAGEIFS(Events!$T$6:$T$3108,Events!$D$6:$D$3108,$A11),"") -> -0.00078938538 | G11: =IFERROR(COUNTIFS(Events!$D$6:$D$3108,$A11,Events!$T$6:$T$3108,">0")/COUNTIFS(Events!$D$6:$D$3108,$A11,Events!$T$6:$T$3108,"<>"),"") -> 0.57142857 | H11: =IFERROR(AVERAGEIFS(Events!$W$6:$W$3108,Events!$D$6:$D$3108,$A11),"") -> -0.00075753236 | I11: =IFERROR(AVERAGEIFS(Events!$AC$6:$AC$3108,Events!$D$6:$D$3108,$A11),"") -> 0.018811674 | J11: =IFERROR(COUNTIFS(Events!$D$6:$D$3108,$A11,Events!$AU$6:$AU$3108,">0")/COUNTIFS(Events!$D$6:$D$3108,$A11,Events!$AU$6:$AU$3108,"<>"),"") -> 0.66666667 | K11: =IFERROR(COUNTIFS(Events!$D$6:$D$3108,$A11,Events!$BA$6:$BA$3108,">0")/COUNTIFS(Events!$D$6:$D$3108,$A11,Events!$BA$6:$BA$3108,"<>"),"") -> 0.46666667 | L11: =IFERROR(AVERAGEIFS(Events!$AY$6:$AY$3108,Events!$D$6:$D$3108,$A11),"") -> 0.0067324819 | M11: =IFERROR(AVERAGEIFS(Events!$CJ$6:$CJ$3108,Events!$D$6:$D$3108,$A11),"") -> 0.089872865 | N11: =IFERROR(AVERAGEIFS(Events!$CK$6:$CK$3108,Events!$D$6:$D$3108,$A11),"") -> 0.19520299 | O11: =IFERROR(AVERAGEIFS(Events!$CI$6:$CI$3108,Events!$D$6:$D$3108,$A11),"") -> -0.055152584 | P11: =COUNTIFS(Events!$D$6:$D$3108,$A11,Events!$CM$6:$CM$3108,"Yes",Events!$CL$6:$CL$3108,"<>") -> 1 | Q11: =IFERROR(AVERAGEIFS(Events!$CL$6:$CL$3108,Events!$D$6:$D$3108,$A11,Events!$CM$6:$CM$3108,"Yes"),"") -> -0.32681942 | R11: =IFERROR(COUNTIFS(Events!$D$6:$D$3108,$A11,Events!$CL$6:$CL$3108,">0",Events!$CM$6:$CM$3108,"Yes")/COUNTIFS(Events!$D$6:$D$3108,$A11,Events!$CL$6:$CL$3108,"<>",Events!$CM$6:$CM$3108,"Yes"),"") -> 0
A12: ALKEM | B12: =INDEX(Events!$E$6:$E$3108,MATCH($A12,Events!$D$6:$D$3108,0)) -> Alkem Laboratories Limited | C12: =INDEX(Events!$F$6:$F$3108,MATCH($A12,Events!$D$6:$D$3108,0)) -> 0 | D12: =COUNTIFS(Events!$D$6:$D$3108,$A12) -> 15 | E12: =COUNTIFS(Events!$D$6:$D$3108,$A12,Events!$K$6:$K$3108,"After close") -> 1 | F12: =IFERROR(AVERAGEIFS(Events!$T$6:$T$3108,Events!$D$6:$D$3108,$A12),"") -> -0.0059495114 | G12: =IFERROR(COUNTIFS(Events!$D$6:$D$3108,$A12,Events!$T$6:$T$3108,">0")/COUNTIFS(Events!$D$6:$D$3108,$A12,Events!$T$6:$T$3108,"<>"),"") -> 0.4 | H12: =IFERROR(AVERAGEIFS(Events!$W$6:$W$3108,Events!$D$6:$D$3108,$A12),"") -> -8.9579711e-05 | I12: =IFERROR(AVERAGEIFS(Events!$AC$6:$AC$3108,Events!$D$6:$D$3108,$A12),"") -> 0.021947485 | J12: =IFERROR(COUNTIFS(Events!$D$6:$D$3108,$A12,Events!$AU$6:$AU$3108,">0")/COUNTIFS(Events!$D$6:$D$3108,$A12,Events!$AU$6:$AU$3108,"<>"),"") -> 0.93333333 | K12: =IFERROR(COUNTIFS(Events!$D$6:$D$3108,$A12,Events!$BA$6:$BA$3108,">0")/COUNTIFS(Events!$D$6:$D$3108,$A12,Events!$BA$6:$BA$3108,"<>"),"") -> 0.73333333 | L12: =IFERROR(AVERAGEIFS(Events!$AY$6:$AY$3108,Events!$D$6:$D$3108,$A12),"") -> 0.012800559 | M12: =IFERROR(AVERAGEIFS(Events!$CJ$6:$CJ$3108,Events!$D$6:$D$3108,$A12),"") -> 0.06610512 | N12: =IFERROR(AVERAGEIFS(Events!$CK$6:$CK$3108,Events!$D$6:$D$3108,$A12),"") -> 0.36307746 | O12: =IFERROR(AVERAGEIFS(Events!$CI$6:$CI$3108,Events!$D$6:$D$3108,$A12),"") -> -0.093803828 | P12: =COUNTIFS(Events!$D$6:$D$3108,$A12,Events!$CM$6:$CM$3108,"Yes",Events!$CL$6:$CL$3108,"<>") -> 8 | Q12: =IFERROR(AVERAGEIFS(Events!$CL$6:$CL$3108,Events!$D$6:$D$3108,$A12,Events!$CM$6:$CM$3108,"Yes"),"") -> 0.025592794 | R12: =IFERROR(COUNTIFS(Events!$D$6:$D$3108,$A12,Events!$CL$6:$CL$3108,">0",Events!$CM$6:$CM$3108,"Yes")/COUNTIFS(Events!$D$6:$D$3108,$A12,Events!$CL$6:$CL$3108,"<>",Events!$CM$6:$CM$3108,"Yes"),"") -> 0.375
A13: AMBER | B13: =INDEX(Events!$E$6:$E$3108,MATCH($A13,Events!$D$6:$D$3108,0)) -> Amber Enterprises India Limited | C13: =INDEX(Events!$F$6:$F$3108,MATCH($A13,Events!$D$6:$D$3108,0)) -> 0 | D13: =COUNTIFS(Events!$D$6:$D$3108,$A13) -> 15 | E13: =COUNTIFS(Events!$D$6:$D$3108,$A13,Events!$K$6:$K$3108,"After close") -> 7 | F13: =IFERROR(AVERAGEIFS(Events!$T$6:$T$3108,Events!$D$6:$D$3108,$A13),"") -> 0.039708557 | G13: =IFERROR(COUNTIFS(Events!$D$6:$D$3108,$A13,Events!$T$6:$T$3108,">0")/COUNTIFS(Events!$D$6:$D$3108,$A13,Events!$T$6:$T$3108,"<>"),"") -> 0.8 | H13: =IFERROR(AVERAGEIFS(Events!$W$6:$W$3108,Events!$D$6:$D$3108,$A13),"") -> 0.042472738 | I13: =IFERROR(AVERAGEIFS(Events!$AC$6:$AC$3108,Events!$D$6:$D$3108,$A13),"") -> 0.066968742 | J13: =IFERROR(COUNTIFS(Events!$D$6:$D$3108,$A13,Events!$AU$6:$AU$3108,">0")/COUNTIFS(Events!$D$6:$D$3108,$A13,Events!$AU$6:$AU$3108,"<>"),"") -> 0.73333333 | K13: =IFERROR(COUNTIFS(Events!$D$6:$D$3108,$A13,Events!$BA$6:$BA$3108,">0")/COUNTIFS(Events!$D$6:$D$3108,$A13,Events!$BA$6:$BA$3108,"<>"),"") -> 0.45454545 | L13: =IFERROR(AVERAGEIFS(Events!$AY$6:$AY$3108,Events!$D$6:$D$3108,$A13),"") -> 0.00073802578 | M13: =IFERROR(AVERAGEIFS(Events!$CJ$6:$CJ$3108,Events!$D$6:$D$3108,$A13),"") -> 0.076591925 | N13: =IFERROR(AVERAGEIFS(Events!$CK$6:$CK$3108,Events!$D$6:$D$3108,$A13),"") -> 0.82599615 | O13: =IFERROR(AVERAGEIFS(Events!$CI$6:$CI$3108,Events!$D$6:$D$3108,$A13),"") -> -0.17243851 | P13: =COUNTIFS(Events!$D$6:$D$3108,$A13,Events!$CM$6:$CM$3108,"Yes",Events!$CL$6:$CL$3108,"<>") -> 4 | Q13: =IFERROR(AVERAGEIFS(Events!$CL$6:$CL$3108,Events!$D$6:$D$3108,$A13,Events!$CM$6:$CM$3108,"Yes"),"") -> 0.30297012 | R13: =IFERROR(COUNTIFS(Events!$D$6:$D$3108,$A13,Events!$CL$6:$CL$3108,">0",Events!$CM$6:$CM$3108,"Yes")/COUNTIFS(Events!$D$6:$D$3108,$A13,Events!$CL$6:$CL$3108,"<>",Events!$CM$6:$CM$3108,"Yes"),"") -> 0.5
A14: AMBUJACEM | B14: =INDEX(Events!$E$6:$E$3108,MATCH($A14,Events!$D$6:$D$3108,0)) -> Ambuja Cements Limited | C14: =INDEX(Events!$F$6:$F$3108,MATCH($A14,Events!$D$6:$D$3108,0)) -> Cement And Cement Products | D14: =COUNTIFS(Events!$D$6:$D$3108,$A14) -> 15 | E14: =COUNTIFS(Events!$D$6:$D$3108,$A14,Events!$K$6:$K$3108,"After close") -> 2 | F14: =IFERROR(AVERAGEIFS(Events!$T$6:$T$3108,Events!$D$6:$D$3108,$A14),"") -> -0.0061354146 | G14: =IFERROR(COUNTIFS(Events!$D$6:$D$3108,$A14,Events!$T$6:$T$3108,">0")/COUNTIFS(Events!$D$6:$D$3108,$A14,Events!$T$6:$T$3108,"<>"),"") -> 0.26666667 | H14: =IFERROR(AVERAGEIFS(Events!$W$6:$W$3108,Events!$D$6:$D$3108,$A14),"") -> -0.0065252688 | I14: =IFERROR(AVERAGEIFS(Events!$AC$6:$AC$3108,Events!$D$6:$D$3108,$A14),"") -> 0.021434098 | J14: =IFERROR(COUNTIFS(Events!$D$6:$D$3108,$A14,Events!$AU$6:$AU$3108,">0")/COUNTIFS(Events!$D$6:$D$3108,$A14,Events!$AU$6:$AU$3108,"<>"),"") -> 0.85714286 | K14: =IFERROR(COUNTIFS(Events!$D$6:$D$3108,$A14,Events!$BA$6:$BA$3108,">0")/COUNTIFS(Events!$D$6:$D$3108,$A14,Events!$BA$6:$BA$3108,"<>"),"") -> 0.57142857 | L14: =IFERROR(AVERAGEIFS(Events!$AY$6:$AY$3108,Events!$D$6:$D$3108,$A14),"") -> 0.0029351285 | M14: =IFERROR(AVERAGEIFS(Events!$CJ$6:$CJ$3108,Events!$D$6:$D$3108,$A14),"") -> 0.074632943 | N14: =IFERROR(AVERAGEIFS(Events!$CK$6:$CK$3108,Events!$D$6:$D$3108,$A14),"") -> 0.33711677 | O14: =IFERROR(AVERAGEIFS(Events!$CI$6:$CI$3108,Events!$D$6:$D$3108,$A14),"") -> -0.052694556 | P14: =COUNTIFS(Events!$D$6:$D$3108,$A14,Events!$CM$6:$CM$3108,"Yes",Events!$CL$6:$CL$3108,"<>") -> 2 | Q14: =IFERROR(AVERAGEIFS(Events!$CL$6:$CL$3108,Events!$D$6:$D$3108,$A14,Events!$CM$6:$CM$3108,"Yes"),"") -> -0.0031969064 | R14: =IFERROR(COUNTIFS(Events!$D$6:$D$3108,$A14,Events!$CL$6:$CL$3108,">0",Events!$CM$6:$CM$3108,"Yes")/COUNTIFS(Events!$D$6:$D$3108,$A14,Events!$CL$6:$CL$3108,"<>",Events!$CM$6:$CM$3108,"Yes"),"") -> 0
A15: ANANDRATHI | B15: =INDEX(Events!$E$6:$E$3108,MATCH($A15,Events!$D$6:$D$3108,0)) -> Anand Rathi Wealth Limited | C15: =INDEX(Events!$F$6:$F$3108,MATCH($A15,Events!$D$6:$D$3108,0)) -> 0 | D15: =COUNTIFS(Events!$D$6:$D$3108,$A15) -> 15 | E15: =COUNTIFS(Events!$D$6:$D$3108,$A15,Events!$K$6:$K$3108,"After close") -> 13 | F15: =IFERROR(AVERAGEIFS(Events!$T$6:$T$3108,Events!$D$6:$D$3108,$A15),"") -> 0.027115871 | G15: =IFERROR(COUNTIFS(Events!$D$6:$D$3108,$A15,Events!$T$6:$T$3108,">0")/COUNTIFS(Events!$D$6:$D$3108,$A15,Events!$T$6:$T$3108,"<>"),"") -> 0.73333333 | H15: =IFERROR(AVERAGEIFS(Events!$W$6:$W$3108,Events!$D$6:$D$3108,$A15),"") -> 0.023277736 | I15: =IFERROR(AVERAGEIFS(Events!$AC$6:$AC$3108,Events!$D$6:$D$3108,$A15),"") -> 0.03293475 | J15: =IFERROR(COUNTIFS(Events!$D$6:$D$3108,$A15,Events!$AU$6:$AU$3108,">0")/COUNTIFS(Events!$D$6:$D$3108,$A15,Events!$AU$6:$AU$3108,"<>"),"") -> 1 | K15: =IFERROR(COUNTIFS(Events!$D$6:$D$3108,$A15,Events!$BA$6:$BA$3108,">0")/COUNTIFS(Events!$D$6:$D$3108,$A15,Events!$BA$6:$BA$3108,"<>"),"") -> 1 | L15: =IFERROR(AVERAGEIFS(Events!$AY$6:$AY$3108,Events!$D$6:$D$3108,$A15),"") -> -0.010104669 | M15: =IFERROR(AVERAGEIFS(Events!$CJ$6:$CJ$3108,Events!$D$6:$D$3108,$A15),"") | N15: =IFERROR(AVERAGEIFS(Events!$CK$6:$CK$3108,Events!$D$6:$D$3108,$A15),"") | O15: =IFERROR(AVERAGEIFS(Events!$CI$6:$CI$3108,Events!$D$6:$D$3108,$A15),"") | P15: =COUNTIFS(Events!$D$6:$D$3108,$A15,Events!$CM$6:$CM$3108,"Yes",Events!$CL$6:$CL$3108,"<>") -> 0 | Q15: =IFERROR(AVERAGEIFS(Events!$CL$6:$CL$3108,Events!$D$6:$D$3108,$A15,Events!$CM$6:$CM$3108,"Yes"),"") | R15: =IFERROR(COUNTIFS(Events!$D$6:$D$3108,$A15,Events!$CL$6:$CL$3108,">0",Events!$CM$6:$CM$3108,"Yes")/COUNTIFS(Events!$D$6:$D$3108,$A15,Events!$CL$6:$CL$3108,"<>",Events!$CM$6:$CM$3108,"Yes"),"")
... A215: ZYDUSLIFE | B215: =INDEX(Events!$E$6:$E$3108,MATCH($A215,Events!$D$6:$D$3108,0)) -> Zydus Lifesciences Limited | C215: =INDEX(Events!$F$6:$F$3108,MATCH($A215,Events!$D$6:$D$3108,0)) -> 0 | D215: =COUNTIFS(Events!$D$6:$D$3108,$A215) -> 15 | E215: =COUNTIFS(Events!$D$6:$D$3108,$A215,Events!$K$6:$K$3108,"After close") -> 1 | F215: =IFERROR(AVERAGEIFS(Events!$T$6:$T$3108,Events!$D$6:$D$3108,$A215),"") -> 0.021016404 | G215: =IFERROR(COUNTIFS(Events!$D$6:$D$3108,$A215,Events!$T$6:$T$3108,">0")/COUNTIFS(Events!$D$6:$D$3108,$A215,Events!$T$6:$T$3108,"<>"),"") -> 0.53333333 | H215: =IFERROR(AVERAGEIFS(Events!$W$6:$W$3108,Events!$D$6:$D$3108,$A215),"") -> 0.021575663 | I215: =IFERROR(AVERAGEIFS(Events!$AC$6:$AC$3108,Events!$D$6:$D$3108,$A215),"") -> 0.020796418 | J215: =IFERROR(COUNTIFS(Events!$D$6:$D$3108,$A215,Events!$AU$6:$AU$3108,">0")/COUNTIFS(Events!$D$6:$D$3108,$A215,Events!$AU$6:$AU$3108,"<>"),"") -> 1 | K215: =IFERROR(COUNTIFS(Events!$D$6:$D$3108,$A215,Events!$BA$6:$BA$3108,">0")/COUNTIFS(Events!$D$6:$D$3108,$A215,Events!$BA$6:$BA$3108,"<>"),"") -> 0.8 | L215: =IFERROR(AVERAGEIFS(Events!$AY$6:$AY$3108,Events!$D$6:$D$3108,$A215),"") -> 0.02039375 | M215: =IFERROR(AVERAGEIFS(Events!$CJ$6:$CJ$3108,Events!$D$6:$D$3108,$A215),"") -> 0.057336408 | N215: =IFERROR(AVERAGEIFS(Events!$CK$6:$CK$3108,Events!$D$6:$D$3108,$A215),"") -> 0.3923906 | O215: =IFERROR(AVERAGEIFS(Events!$CI$6:$CI$3108,Events!$D$6:$D$3108,$A215),"") -> -0.094410737 | P215: =COUNTIFS(Events!$D$6:$D$3108,$A215,Events!$CM$6:$CM$3108,"Yes",Events!$CL$6:$CL$3108,"<>") -> 11 | Q215: =IFERROR(AVERAGEIFS(Events!$CL$6:$CL$3108,Events!$D$6:$D$3108,$A215,Events!$CM$6:$CM$3108,"Yes"),"") -> -0.035028799 | R215: =IFERROR(COUNTIFS(Events!$D$6:$D$3108,$A215,Events!$CL$6:$CL$3108,">0",Events!$CM$6:$CM$3108,"Yes")/COUNTIFS(Events!$D$6:$D$3108,$A215,Events!$CL$6:$CL$3108,"<>",Events!$CM$6:$CM$3108,"Yes"),"") -> 0.27272727

Sheet Events
A1: F&O stocks - results report, last 15 quarters (no conditions applied)
A2: 3103 results events, 212 stocks. All data from NSE: results date/time (NSE filings), prices (equity bhavcopy), indices, financials (results XBRL), options (F&O bhavcopy). See Notes.
A4: Stock & quarter | I4: Results timing | Q4: 3-day window (Day -1, Result day, Day +1) | AA4: Reaction day | AG4: Before results (2 sessions before result day) | AO4: After results | AR4: Results: this quarter (Rs crore) | BE4: Banks only | BL4: Valuation & ratios (before results) | BT4: Cash flow (latest half-year or year) | BY4: Peers (same NSE industry, same quarter) | CE4: Options (NSE F&O) | CN4: Notes
A5: Quarter | B5: Quarter period | C5: Quarter end | D5: Symbol | E5: Company | F5: Industry (NSE) | G5: Sector index | H5: Lot size | I5: Results date | J5: Results time (IST) | K5: Timing | L5: Time source | M5: Day -1 | N5: Result day | O5: Day +1 | P5: Reaction day | Q5: Day -1 % | R5: Result day % | S5: Day +1 % | T5: Three-day sum % | U5: Nifty 50 3-day % | V5: Sector 3-day % | W5: Excess vs Nifty % | X5: Excess vs sector % | Y5: Peer median 3-day % | Z5: Vs peers 3-day % | AA5: Gap at open % | AB5: Close move % | AC5: Size of move % | AD5: High-low range % | AE5: Close in range (0 low-1 high) | AF5: Volume vs 20D avg (x) | AG5: Price (Rs) | AH5: 1W % | AI5: 1M % | AJ5: 3M % | AK5: 6M % | AL5: 1Y % | AM5: Sector 1M % | AN5: 1M vs sector % | AO5: Next 5 sessions % | AP5: Next 20 sessions % | AQ5: Next 20 vs Nifty % | AR5: Basis | AS5: Type | AT5: Sales / Interest earned | AU5: Sales YoY % | AV5: Sales QoQ % | AW5: EBITDA | AX5: EBITDA margin % | AY5: EBITDA margin chg YoY (pts) | AZ5: Net profit | BA5: Net profit YoY % | BB5: Net profit QoQ % | BC5: Net margin % | BD5: EPS (Rs) | BE5: Net interest income | BF5: NII YoY % | BG5: Pre-provision profit YoY % | BH5: Provisions YoY % | BI5: Gross NPA % | BJ5: Net NPA % | BK5: ROA % (quarter) | BL5: Market cap (Rs cr) | BM5: TTM net profit | BN5: P/E | BO5: P/B | BP5: ROE % | BQ5: Debt / equity | BR5: Sector index P/E | BS5: Sector index P/B | BT5: Cash-flow period | BU5: Operating cash flow | BV5: Capex | BW5: Free cash flow | BX5: CFO / net profit (x) | BY5: Peers (n) | BZ5: Peer median sales YoY % | CA5: Peer median profit YoY % | CB5: Profit growth rank | CC5: Peer median P/E | CD5: P/E vs peers % | CE5: Expiry used | CF5: IV 5 sessions before | CG5: IV before results | CH5: IV after results | CI5: IV drop % | CJ5: Expected move % (straddle) | CK5: Actual / expected move (x) | CL5: Run-up straddle return % | CM5: Run-up rule pass | CN5: Data notes
A6: Q3 FY23 | B6: Oct-Dec 2022 | C6: 44926 | D6: TCS | E6: Tata Consultancy Services Limited | F6: Computers - Software | G6: Nifty IT | H6: 225 | I6: 44935 | J6: 17:14 | K6: After close | L6: NSE announcement | M6: 44932 | N6: 44935 | O6: 44936 | P6: 44936 | Q6: -0.030065537 | R6: 0.033753172 | S6: -0.010105574 | T6: -0.0064179389 | U6: -0.0041727567 | V6: -0.00024500939 | W6: -0.0022451822 | X6: -0.0061729295 | Y6: 0.0015252858 | Z6: -0.0079432247 | AA6: -0.010527267 | AB6: -0.010105574 | AC6: 0.010105574 | AD6: 0.020452115 | AE6: 0.82916053 | AF6: 2.5987544 | AG6: 3311.1 | AH6: 0.012956023 | AI6: -0.020558481 | AJ6: 0.067425329 | AK6: 0.029474862 | AL6: -0.14766716 | AM6: -0.054967279 | AN6: 0.034408798 | AO6: 0.027994158 | AP6: 0.071111246 | AQ6: 0.073480882 | AR6: Consolidated | AS6: Company | AT6: 58229 | AU6: 0.19114248 | AV6: 0.052794301 | AW6: 15553 | AX6: 0.26710059 | AY6: -0.0076871816 | AZ6: 10846 | BA6: 0.1102467 | BB6: 0.039785255 | BC6: 0.18626458 | BD6: 29.64 | BL6: 1211862.6 | BM6: 39604 | BN6: 30.5995 | BO6: 12.435227 | BP6: 0.4063866 | BQ6: 0 | BR6: 26.2 | BS6: 8.03 | BT6: H1 FY23 | BU6: 20458 | BV6: 1324 | BW6: 19134 | BX6: 1.0275755 | BY6: 9 | BZ6: 0.19944373 | CA6: 0.13375796 | CB6: 6 of 10 | CC6: 25.58673 | CD6: 0.1959129 | CE6: 44951 | CF6: 0.21500196 | CG6: 0.23677704 | CH6: 0.19078529 | CI6: -0.19424074 | CJ6: 0.041218476 | CK6: 0.24517097 | CL6: -0.034719751 | CM6: Yes
A7: Q3 FY23 | B7: Oct-Dec 2022 | C7: 44926 | D7: ANANDRATHI | E7: Anand Rathi Wealth Limited | G7: Nifty 500 | H7: 250 | I7: 44938 | J7: 17:35 | K7: After close | L7: NSE announcement | M7: 44937 | N7: 44938 | O7: 44939 | P7: 44939 | Q7: -0.0065009048 | R7: 0.018011333 | S7: 0.024120337 | T7: 0.035630765 | U7: 0.0023846862 | V7: 0.0013712472 | W7: 0.033246079 | X7: 0.034259518 | AA7: 0.00059638195 | AB7: 0.024120337 | AC7: 0.024120337 | AD7: 0.058246637 | AE7: 0.83503982 | AF7: 5.0001362 | AG7: 746.05 | AH7: 0.059203521 | AI7: 0.076939733 | AJ7: 0.13037879 | AK7: 0.1512229 | AL7: 0.20437485 | AM7: -0.031763331 | AN7: 0.10870306 | AO7: 0.092267874 | AP7: 0.034940149 | AQ7: 0.04528175 | AR7: Consolidated | AS7: Company | AT7: 138.0015 | AU7: 0.30567879 | AV7: 0.014246331 | AW7: 61.717 | AX7: 0.44721978 | AY7: 0.026480714 | AZ7: 43.1658 | BA7: 0.3474112 | BB7: 0.0056308694 | BC7: 0.31279225 | BD7: 10.38 | BL7: 3110.1482 | BM7: 149.0309 | BN7: 20.86915 | BO7: 7.7478829 | BP7: 0.37126011 | BQ7: 0.051678906 | BR7: 22.67 | BS7: 4.05 | BT7: H1 FY23 | BU7: 167.1598 | BV7: 0 | BW7: 167.1598 | BX7: 2.0230602 | BY7: 0 | CN7: no option prices for this event
A8: Q3 FY23 | B8: Oct-Dec 2022 | C8: 44926 | D8: HCLTECH | E8: HCL Technologies Limited | F8: Computers - Software | G8: Nifty IT | H8: 400 | I8: 44938 | J8: 17:27 | K8: After close | L8: NSE announcement | M8: 44937 | N8: 44938 | O8: 44939 | P8: 44939 | Q8: -0.0085068384 | R8: 0.015974592 | S8: 0.005738814 | T8: 0.013206568 | U8: 0.0023846862 | V8: 0.015052148 | W8: 0.010821882 | X8: -0.0018455804 | Y8: 0.00047142478 | Z8: 0.012735143 | AA8: -0.025894648 | AB8: 0.005738814 | AC8: 0.005738814 | AD8: 0.040125041 | AE8: 0.85581395 | AF8: 3.3444656 | AG8: 1063.85 | AH8: 0.021606568 | AI8: 0.034471023 | AJ8: 0.13344343 | AK8: 0.081643028 | AL8: -0.17566154 | AM8: -0.018856818 | AN8: 0.053327841 | AO8: 0.027834478 | AP8: 0.03265912 | AQ8: 0.043000722 | AR8: Consolidated | AS8: Company | AT8: 26700 | AU8: 0.19564731 | AV8: 0.081584704 | AW8: 6365 | AX8: 0.23838951 | AY8: -0.0031133305 | AZ8: 4096 | BA8: 0.19000581 | BB8: 0.17397535 | BC8: 0.15340824 | BD8: 15.13 | BR8: 26.18 | BS8: 8.02 | BT8: H1 FY23 | BU8: 5697 | BV8: 925 | BW8: 4772 | BX8: 0.84125812 | BY8: 9 | BZ8: 0.19944373 | CA8: 0.1102467 | CB8: 3 of 10 | CC8: 26.279137 | CE8: 44951 | CF8: 0.25244965 | CG8: 0.29391493 | CH8: 0.19738593 | CI8: -0.32842494 | CJ8: 0.044331974 | CK8: 0.1294509 | CL8: 0.025450861 | CM8: Yes
A9: Q3 FY23 | B9: Oct-Dec 2022 | C9: 44926 | D9: INFY | E9: Infosys Limited | F9: Computers - Software | G9: Nifty IT | H9: 400 | I9: 44938 | J9: 15:38 | K9: After close | L9: NSE announcement | M9: 44937 | N9: 44938 | O9: 44939 | P9: 44939 | Q9: 0.0010205817 | R9: 0.0063551402 | S9: 0.015568013 | T9: 0.022943735 | U9: 0.0023846862 | V9: 0.015052148 | W9: 0.020559049 | X9: 0.0078915866 | Y9: 0.00047142478 | Z9: 0.02247231 | AA9: 0.0019586654 | AB9: 0.015568013 | AC9: 0.015568013 | AD9: 0.034715656 | AE9: 0.69357977 | AF9: 1.8013402 | AG9: 1469.75 | AH9: -0.034678664 | AI9: -0.05005817 | AJ9: 0.032272791 | AK9: -0.029515666 | AL9: -0.18990795 | AM9: -0.018856818 | AN9: -0.031201351 | AO9: 0.01456456 | AP9: 0.042430087 | AQ9: 0.052771688 | AR9: Consolidated | AS9: Company | AT9: 38318 | AU9: 0.20243512 | AV9: 0.048716405 | AW9: 9367 | AX9: 0.2444543 | AY9: -0.018607798 | AZ9: 6586 | BA9: 0.13375796 | BB9: 0.093838233 | BC9: 0.17187745 | BD9: 15.72 | BL9: 617001.05 | BM9: 22876 | BN9: 26.971544 | BO9: 7.7143453 | BP9: 0.28601793 | BQ9: 0 | BR9: 26.18 | BS9: 8.02 | BT9: H1 FY23 | BU9: 10760 | BV9: 1234 | BW9: 9526 | BX9: 0.94543537 | BY9: 9 | BZ9: 0.19564731 | CA9: 0.1102467 | CB9: 5 of 10 | CC9: 25.58673 | CD9: 0.054122382 | CE9: 44951 | CF9: 0.27999053 | CG9: 0.29159444 | CH9: 0.20525391 | CI9: -0.29609802 | CJ9: 0.044129024 | CK9: 0.35278399 | CL9: -0.19993602 | CM9: Yes
A10: Q3 FY23 | B10: Oct-Dec 2022 | C10: 44926 | D10: LTF | E10: L&T Finance Limited | G10: Nifty 500 | H10: 2250 | I10: 44939 | J10: 18:56 | K10: After close | L10: NSE announcement | M10: 44938 | N10: 44939 | O10: 44942 | P10: 44942 | AM10: -0.037923229 | AR10: Consolidated | AS10: NBFC / financial | AT10: 3432.49 | AU10: 210.10025 | AV10: 29.889939 | AZ10: 453.64 | BB10: 0.39076583 | BC10: 0.13216062 | BD10: 1.83 | BR10: 22.62 | BS10: 4.04 | BT10: H1 FY23 | BU10: -104.88 | BV10: 0 | BW10: -104.88 | BX10: -0.31570392 | BY10: 0 | CN10: no option prices for this event
A11: Q3 FY23 | B11: Oct-Dec 2022 | C11: 44926 | D11: WIPRO | E11: Wipro Limited | F11: Computers - Software | G11: Nifty IT | H11: 3000 | I11: 44939 | J11: 15:39 | K11: After close | L11: NSE announcement | M11: 44938 | N11: 44939 | O11: 44942 | P11: 44942 | Q11: 0.0016503745 | R11: -0.0015209125 | S11: 0.011931962 | T11: 0.012061424 | U11: -2.4248644e-05 | V11: 0.023202966 | W11: 0.012085673 | X11: -0.011141542 | Y11: 0.00047142478 | Z11: 0.01159 | AA11: -0.0099009901 | AB11: 0.011931962 | AC11: 0.011931962 | AD11: 0.030464585 | AE11: 0.8 | AF11: 2.7439939 | AG11: 393.85 | AH11: 0.010649217 | AI11: -0.009805154 | AJ11: -0.034563059 | AK11: -0.04219358 | AL11: -0.43208363 | AM11: -0.026558599 | AN11: 0.016753445 | AO11: 0.021073758 | AP11: 0.016307075 | AQ11: 0.014351205 | AR11: Consolidated | AS11: Company | AT11: 23229 | AU11: 0.14351961 | AV11: 0.030581596 | AW11: 4547.4 | AX11: 0.19576392 | AY11: -0.0099750965 | AZ11: 3052.9 | BA11: 0.028258673 | BB11: 0.1481384 | BC11: 0.13142623 | BD11: 5.57 | BR11: 26.1 | BS11: 8.05 | BT11: H1 FY23 | BU11: 4979.3 | BV11: 873.7 | BW11: 4105.6 | BX11: 0.95341401 | BY11: 9 | BZ11: 0.19944373 | CA11: 0.13375796 | CB11: 7 of 10 | CC11: 26.279137 | CE11: 44951 | CF11: 0.28406839 | CG11: 0.29988508 | CH11: 0.2174905 | CI11: -0.27475383 | CJ11: 0.042661249 | CK11: 0.27969088 | CL11: -0.014059072 | CM11: Yes
A12: Q3 FY23 | B12: Oct-Dec 2022 | C12: 44926 | D12: DMART | E12: Avenue Supermarts Limited | G12: Nifty 500 | H12: 150 | I12: 44940 | J12: 14:20 | K12: Non-trading day | L12: NSE announcement | M12: 44939 | N12: 44942 | O12: 44943 | P12: 44942 | Q12: -0.01229613 | R12: -0.047972151 | S12: 0.0031128087 | T12: -0.057155472 | U12: 0.01092573 | V12: 0.0076293204 | W12: -0.068081202 | X12: -0.064784792 | AA12: -0.044956907 | AB12: -0.047972151 | AC12: 0.047972151 | AD12: 0.026606621 | AE12: 0.32247082 | AF12: 6.2722016 | AG12: 3911.8 | AH12: 0.013997615 | AI12: -0.068862917 | AJ12: -0.092379262 | AK12: 0.0086117987 | AL12: -0.13165664 | AM12: -0.04285947 | AN12: -0.026003447 | AO12: -0.047780367 | AP12: -0.039080709 | AQ12: -0.037006296 | AR12: Consolidated | AS12: Company | AT12: 11569.05 | AU12: 0.25508258 | AV12: 0.087487416 | AW12: 965.26 | AX12: 0.083434681 | AY12: -0.010564295 | AZ12: 589.68 | BA12: 0.067178225 | BB12: -0.14011987 | BC12: 0.050970477 | BD12: 9.1 | BL12: 253396.62 | BM12: 2308.09 | BN12: 109.78628 | BO12: 16.887119 | BP12: 0.15381811 | BQ12: 0.047371865 | BR12: 22.59 | BS12: 4.03 | BT12: H1 FY23 | BU12: 834.56 | BV12: 968.52 | BW12: -133.96 | BX12: 0.62810266 | BY12: 0 | CN12: no option prices for this event
A13: Q3 FY23 | B13: Oct-Dec 2022 | C13: 44926 | D13: HDFCBANK | E13: HDFC Bank Limited | F13: Banks | G13: Nifty Bank | H13: 650 | I13: 44940 | J13: 13:02 | K13: Non-trading day | L13: NSE announcement | M13: 44939 | N13: 44942 | O13: 44943 | P13: 44942 | Q13: 0.00078154308 | R13: -0.0095898541 | S13: 0.014886772 | T13: 0.0060784612 | U13: 0.01092573 | V13: 0.0036607554 | W13: -0.0048472685 | X13: 0.0024177058 | Y13: 0.00018514364 | Z13: 0.0058933175 | AA13: 0.0089651079 | AB13: -0.0095898541 | AC13: 0.0095898541 | AD13: 0.025614594 | AE13: 0.12195122 | AF13: 1.5119535 | AG13: 1599.4 | AH13: -0.00018753516 | AI13: -0.037810197 | AJ13: 0.14767509 | AK13: 0.14915936 | AL13: 0.021393448 | AM13: -0.04465131 | AN13: 0.0068411125 | AO13: 0.053825595 | AP13: 0.03816272 | AQ13: 0.040237133 | AR13: Standalone | AS13: Bank | AT13: 42707.77 | AU13: 0.31537835 | AV13: 0.10680945 | AZ13: 12259.49 | BA13: 0.18538512 | BB13: 0.15592535 | BC13: 0.28705526 | BD13: 21.99 | BE13: 22987.83 | BF13: 0.24639331 | BG13: 0.13400851 | BH13: -0.062639029 | BI13: 0.0123 | BJ13: 0.0033 | BK13: 0.0056 | BL13: 890865.8 | BM13: 40199.15 | BN13: 22.161309 | BO13: 3.5058084 | BP13: 0.158195 | BR13: 17.7 | BS13: 2.77 | BY13: 14 | BZ13: 0.27291649 | CA13: 0.61249873 | CB13: 10 of 13 | CC13: 25.154937 | CD13: -0.11900756 | CE13: 44951 | CF13: 0.19091905 | CG13: 0.19786148 | CH13: 0.1946783 | CI13: -0.016087913 | CJ13: 0.02812607 | CK13: 0.34095963 | CL13: -0.21927872 | CM13: Yes
A14: Q3 FY23 | B14: Oct-Dec 2022 | C14: 44926 | D14: ANGELONE | E14: Angel One Limited | G14: Nifty 500 | H14: 2500 | I14: 44942 | J14: 19:27 | K14: After close | L14: NSE announcement | M14: 44939 | N14: 44942 | O14: 44943 | P14: 44943 | Q14: 0.017423504 | R14: 0.0083518504 | S14: -0.017553191 | T14: 0.0082221631 | U14: 0.01092573 | V14: 0.0076293204 | W14: -0.0027035665 | X14: 0.00059284275 | AA14: 0.0068389058 | AB14: -0.017553191 | AC14: 0.017553191 | AD14: 0.034080547 | AE14: 0.17502787 | AF14: 1.8130377 | AG14: 1282.75 | AH14: -0.021921464 | AI14: -0.15954136 | AJ14: -0.19240092 | AK14: -0.031777182 | AL14: 0.019755147 | AM14: -0.04285947 | AN14: -0.11668189 | AO14: -0.015314409 | AP14: -0.12878026 | AQ14: -0.12670585 | AR14: Consolidated | AS14: NBFC / financial | AT14: 718.479 | AU14: 0.20283969 | AV14: 0.0024388508 | AZ14: 227.982 | BB14: 0.067556367 | BC14: 0.31731199 | BD14: 27.35 | BL14: 10687.36 | BM14: 418.249 | BN14: 25.552625 | BO14: 5.6639359 | BP14: 0.22165769 | BQ14: 1.5727368 | BR14: 22.59 | BS14: 4.03 | BT14: H1 FY23 | BU14: -1805.773 | BV14: 54.407 | BW14: -1860.18 | BX14: -4.5708829 | BY14: 0 | CN14: no option prices for this event
A15: Q3 FY23 | B15: Oct-Dec 2022 | C15: 44926 | D15: FEDERALBNK | E15: The Federal Bank Limited | F15: Banks | G15: Nifty Bank | H15: 2500 | I15: 44942 | J15: 12:28 | K15: During market | L15: NSE announcement | M15: 44939 | N15: 44942 | O15: 44943 | P15: 44942 | Q15: 0.025175861 | R15: 0.013362225 | S15: -0.016393443 | T15: 0.022144643 | U15: 0.01092573 | V15: 0.0036607554 | W15: 0.011218913 | X15: 0.018483887 | Y15: 0.00018514364 | Z15: 0.021959499 | AA15: 0.0057782593 | AB15: 0.013362225 | AC15: 0.013362225 | AD15: 0.045142651 | AE15: 0.504 | AF15: 4.1239436 | AG15: 135.05 | AH15: -0.012070227 | AI15: -0.012431444 | AJ15: 0.081265012 | AK15: 0.37176232 | AL15: 0.40020736 | AM15: -0.04465131 | AN15: 0.032219865 | AO15: -0.02173913 | AP15: -0.060507246 | AQ15: -0.058432833 | AR15: Standalone | AS15: Bank | AT15: 4433.25 | AU15: 0.28777712 | AZ15: 803.61 | BA15: 0.54027945 | BC15: 0.18126882 | BD15: 3.8 | BE15: 1956.53 | BF15: 0.27138216 | BG15: 0.39366065 | BH15: -0.071455276 | BI15: 0.0243 | BJ15: 0.0073 | BK15: 0.0033 | BR15: 17.7 | BS15: 2.77 | BY15: 14 | BZ15: 0.27445986 | CA15: 0.51333938 | CB15: 7 of 13 | CC15: 22.161309 | CE15: 44951 | CF15: 0.39262612 | CG15: 0.40221983 | CH15: 0.33113574 | CI15: -0.17672946 | CJ15: 0.057132591 | CK15: 0.23388095 | CL15: -0.15052083 | CM15: Yes
A16: Q3 FY23 | B16: Oct-Dec 2022 | C16: 44926 | D16: MAHABANK | E16: Bank of Maharashtra | F16: Banks | G16: Nifty Bank | H16: 6500 | I16: 44942 | J16: 12:58 | K16: During market | L16: NSE announcement | M16: 44939 | N16: 44942 | O16: 44943 | P16: 44942 | Q16: 0.012779553 | R16: 0.042586751 | S16: -0.031770045 | T16: 0.023596258 | U16: 0.01092573 | V16: 0.0036607554 | W16: 0.012670528 | X16: 0.019935503 | Y16: 0.00018514364 | Z16: 0.023411114 | AA16: 0.0078864353 | AB16: 0.042586751 | AC16: 0.042586751 | AD16: 0.08044164 | AE16: 0.45098039 | AF16: 2.131593 | AG16: 31.3 | AH16: 0.0064308682 | AI16: -0.082111437 | AJ16: 0.7535014 | AK16: 0.92615385 | AL16: 0.53431373 | AM16: -0.04465131 | AN16: -0.037460127 | AO16: -0.0734375 | AP16: -0.1484375 | AQ16: -0.14636309 | AR16: Standalone | AS16: Bank | AT16: 4129.04 | AU16: 0.25805587 | AV16: 0.082300147 | AZ16: 775.03 | BA16: 1.3874257 | BB16: 0.44849176 | BC16: 0.18770223 | BD16: 1.15 | BE16: 1979.62 | BF16: 0.29650466 | BG16: 0.35942433 | BH16: -0.22652595 | BI16: 0.0294 | BJ16: 0.0047 | BK16: 0.013 | BR16: 17.7 | BS16: 2.77 | BY16: 14 | BZ16: 0.28932048 | CA16: 0.44112011 | CB16: 1 of 13 | CC16: 22.161309 | CN16: no option prices for this event
A17: Q3 FY23 | B17: Oct-Dec 2022 | C17: 44926 | D17: BANKINDIA | E17: Bank of India | F17: Banks | G17: Nifty Bank | H17: 5200 | I17: 44943 | J17: 12:24 | K17: During market | L17: NSE announcement | M17: 44942 | N17: 44943 | O17: 44944 | P17: 44943 | Q17: 0.015041494 | R17: -0.045477772 | S17: -0.043361884 | T17: -0.073798163 | U17: 0.011622277 | V17: 0.0020720428 | W17: -0.08542044 | X17: -0.075870206 | Y17: 0.0016680946 | Z17: -0.075466257 | AA17: 0.01073071 | AB17: -0.045477772 | AC17: 0.045477772 | AD17: 0.10577414 | AE17: 0.36231884 | AF17: 2.7211993 | AG17: 96.4 | AH17: 0.031567683 | AI17: 0.020645844 | AJ17: 1.0686695 | AK17: 1.0888407 | AL17: 0.76395242 | AM17: -0.025907969 | AN17: 0.046553813 | AO17: -0.076105204 | AP17: -0.13094572 | AQ17: -0.12381676 | AR17: Standalone | AS17: Bank | AT17: 12727.75 | AU17: 0.35749345 | AV17: 0.10701115 | AZ17: 1151.01 | BA17: 0.12025889 | BB17: 0.19896875 | BC17: 0.090433109 | BD17: 2.8 | BE17: 5595.03 | BF17: 0.64178233 | BG17: 0.74254917 | BH17: 4.6100678 | BI17: 0.0766 | BJ17: 0.0161 | BK17: 0.0055 | BR17: 17.82 | BS17: 2.79 | BY17: 14 | BZ17: 0.27291649 | CA17: 0.61249873 | CB17: 11 of 13 | CC17: 22.161309 | CN17: no option prices for this event
A18: Q3 FY23 | B18: Oct-Dec 2022 | C18: 44926 | D18: ICICIGI | E18: ICICI Lombard General Insurance Company Limited | G18: Nifty 500 | H18: 325 | I18: 44943 | J18: 17:29 | K18: After close | L18: NSE announcement (no filing record) | M18: 44942 | N18: 44943 | O18: 44944 | P18: 44944 | Q18: -0.004501454 | R18: -0.00016006403 | S18: -0.039342032 | T18: -0.04400355 | U18: 0.011622277 | V18: 0.0078366937 | W18: -0.055625827 | X18: -0.051840243 | AA18: -0.012246858 | AB18: -0.039342032 | AC18: 0.039342032 | AD18: 0.047626671 | AE18: 0.43109244 | AF18: 6.8660375 | AG18: 1255.15 | AH18: -0.013014076 | AI18: 0.016974558 | AJ18: 0.11405494 | AK18: 0.018831933 | AL18: -0.1204891 | AM18: -0.027730965 | AN18: 0.044705523 | AO18: -0.052660084 | AP18: -0.068116485 | AQ18: -0.060987528 | BR18: 22.65 | BS18: 4.05 | BY18: 0 | CE18: 44951 | CF18: 0.30873248 | CG18: 0.2971507 | CH18: 0.24804834 | CI18: -0.16524396 | CJ18: 0.036704926 | CK18: 1.0718461 | CL18: -0.28141214 | CM18: Yes | CN18: no NSE XBRL results for this quarter
A19: Q3 FY23 | B19: Oct-Dec 2022 | C19: 44926 | D19: ICICIPRULI | E19: ICICI Prudential Life Insurance Company Limited | G19: Nifty 500 | H19: 925 | I19: 44943 | J19: 20:12 | K19: After close | L19: NSE announcement (no filing record) | M19: 44942 | N19: 44943 | O19: 44944 | P19: 44944 | Q19: 0.017037589 | R19: 0.015181656 | S19: 0.005259901 | T19: 0.037479147 | U19: 0.011622277 | V19: 0.0078366937 | W19: 0.025856869 | X19: 0.029642453 | AA19: 0.0010313531 | AB19: 0.005259901 | AC19: 0.005259901 | AD19: 0.028362211 | AE19: 0.89818182 | AF19: 2.9874558 | AG19: 469.55 | AH19: -0.0072938689 | AI19: 0.036534216 | AJ19: -0.085321905 | AK19: -0.10536344 | AL19: -0.20178496 | AM19: -0.027730965 | AN19: 0.064265181 | AO19: -0.047604391 | AP19: -0.1207551 | AQ19: -0.11362615 | BR19: 22.65 | BS19: 4.05 | BY19: 0 | CE19: 44951 | CF19: 0.27287621 | CG19: 0.3068296 | CH19: 0.22529944 | CI19: -0.26571803 | CJ19: 0.037784413 | CK19: 0.13920822 | CL19: 0.15283752 | CM19: Yes | CN19: no NSE XBRL results for this quarter
A20: Q3 FY23 | B20: Oct-Dec 2022 | C20: 44926 | D20: INDUSINDBK | E20: IndusInd Bank Limited | F20: Banks | G20: Nifty Bank | H20: 700 | I20: 44944 | J20: 16:06 | K20: After close | L20: NSE announcement | M20: 44943 | N20: 44944 | O20: 44945 | P20: 44945 | Q20: -0.0071817632 | R20: -0.0059739099 | S20: -0.0183565 | T20: -0.031512173 | U20: 0.011895757 | V20: 0.0038377184 | W20: -0.043407931 | X20: -0.035349892 | Y20: 0.0016680946 | Z20: -0.033180268 | AA20: -0.0065412919 | AB20: -0.0183565 | AC20: 0.0183565 | AD20: 0.050490597 | AE20: 0.28016194 | AF20: 3.7063721 | AG20: 1239.25 | AH20: 0.016903951 | AI20: 0.0078890651 | AJ20: 0.033009628 | AK20: 0.50962358 | AL20: 0.33669507 | AM20: -0.024339708 | AN20: 0.032228773 | AO20: -0.070092874 | AP20: -0.071508892 | AQ20: -0.062471375 | BR20: 17.53 | BS20: 2.78 | BY20: 14 | BZ20: 0.28777712 | CA20: 0.54027945 | CC20: 22.161309 | CE20: 44951 | CF20: 0.33465792 | CG20: 0.39022878 | CH20: 0.31331977 | CI20: -0.19708697 | CJ20: 0.043927332 | CK20: 0.41788334 | CL20: -0.20812169 | CM20: Yes | CN20: no NSE XBRL results for this quarter
A21: Q3 FY23 | B21: Oct-Dec 2022 | C21: 44926 | D21: OFSS | E21: Oracle Financial Services Software Limited | F21: Computers - Software | G21: Nifty IT | H21: 100 | I21: 44944 | J21: 19:13 | K21: After close | L21: NSE announcement | M21: 44943 | N21: 44944 | O21: 44945 | P21: 44945 | Q21: 0.01169893 | R21: -0.005063089 | S21: -0.0061644165 | T21: 0.00047142478 | U21: 0.011895757 | V21: 0.012526335 | W21: -0.011424333 | X21: -0.01205491 | Y21: 0.0015252858 | Z21: -0.001053861 | AA21: 0.001717689 | AB21: -0.0061644165 | AC21: 0.0061644165 | AD21: 0.019681184 | AE21: 0.13621533 | AF21: 1.5870382 | AG21: 3094.3 | AH21: 0.029100705 | AI21: 0.024992961 | AJ21: 0.052393504 | AK21: -0.02431103 | AL21: -0.2553724 | AM21: 0.019596059 | AN21: 0.0053969021 | AO21: -0.014182106 | AP21: 0.044000065 | AQ21: 0.053037581 | AR21: Consolidated | AS21: Company | AT21: 1449.296 | AU21: 0.14448253 | AV21: 0.053245244 | AW21: 606.211 | AX21: 0.41827963 | AY21: -0.043512802 | AZ21: 437.33 | BA21: 0.0045642172 | BB21: 0.099498685 | BC21: 0.3017534 | BD21: 50.63 | BR21: 26.16 | BS21: 8.19 | BT21: H1 FY23 | BU21: 863.914 | BV21: 24.225 | BW21: 839.689 | BX21: 0.9712257 | BY21: 9 | BZ21: 0.19944373 | CA21: 0.13375796 | CB21: 8 of 10 | CC21: 26.279137 | CE21: 44951 | CF21: 0.2393408 | CG21: 0.30341468 | CH21: 0.21086922 | CI21: -0.30501313 | CJ21: 0.034429673 | CK21: 0.17904371 | CL21: 0.042586279 | CM21: Yes
A22: Q3 FY23 | B22: Oct-Dec 2022 | C22: 44926 | D22: PERSISTENT | E22: Persistent Systems Limited | F22: Computers - Software | G22: Nifty IT | H22: 125 | I22: 44944 | J22: 16:22 | K22: After close | L22: NSE announcement | M22: 44943 | N22: 44944 | O22: 44945 | P22: 44945 | Q22: 0.00064164664 | R22: -0.0043000478 | S22: 0.07539903 | T22: 0.071740629 | U22: 0.011895757 | V22: 0.012526335 | W22: 0.059844872 | X22: 0.059214294 | Y22: 0.00047142478 | Z22: 0.071269204 | AA22: -0.0024244873 | AB22: 0.07539903 | AC22: 0.07539903 | AD22: 0.090413173 | AE22: 0.94455307 | AF22: 7.8749926 | AG22: 3974.15 | AH22: -0.0051816714 | AI22: 0.0014615646 | AJ22: 0.095214474 | AK22: 0.25280562 | AL22: -0.1204422 | AM22: 0.019596059 | AN22: -0.018134494 | AO22: 0.074868194 | AP22: 0.15316511 | AQ22: 0.16220262 | AR22: Consolidated | AS22: Company | AT22: 2169.368 | AU22: 0.45427584 | AV22: 0.058930286 | AW22: 371.9 | AX22: 0.17143242 | AY22: 0.0031142979 | AZ22: 237.954 | BA22: 0.34898381 | BB22: 0.081540266 | BC22: 0.10968817 | BD22: 31.9 | BR22: 26.16 | BS22: 8.19 | BT22: H1 FY23 | BU22: 378.518 | BV22: 282.598 | BW22: 95.92 | BX22: 0.87695829 | BY22: 9 | BZ22: 0.19564731 | CA22: 0.1102467 | CB22: 1 of 10 | CC22: 26.279137 | CE22: 44951 | CF22: 0.34791104 | CG22: 0.42150342 | CH22: 0.33352666 | CI22: -0.20872133 | CJ22: 0.04735552 | CK22: 1.5921909 | CL22: -0.17953157 | CM22: Yes
A23: Q3 FY23 | B23: Oct-Dec 2022 | C23: 44926 | D23: 360ONE | E23: 360 ONE WAM LIMITED | G23: Nifty 500 | H23: 500 | I23: 44945 | J23: 17:44 | K23: After close | L23: NSE announcement | M23: 44944 | N23: 44945 | O23: 44946 | P23: 44946 | AM23: -0.022789301 | AO23: -0.040239303 | AP23: -0.047340356 | AQ23: -0.037186509 | AR23: Consolidated | AS23: NBFC / financial | AT23: 518.38 | AU23: -0.033293543 | AV23: 0.025966829 | AZ23: 171.54 | BC23: 0.33091554 | BD23: 19.3 | BR23: 22.64 | BS23: 4.06 | BT23: H1 FY23 | BU23: -901.38 | BV23: 20.11 | BW23: -921.49 | BY23: 0 | CN23: no option prices for this event
A24: Q3 FY23 | B24: Oct-Dec 2022 | C24: 44926 | D24: ASIANPAINT | E24: Asian Paints Limited | F24: Paints | G24: Nifty Consumer Durables | H24: 250 | I24: 44945 | J24: 13:36 | K24: During market | L24: NSE announcement | M24: 44944 | N24: 44945 | O24: 44946 | P24: 44945 | Q24: 0.001479139 | R24: -0.026856803 | S24: -0.027336322 | T24: -0.052713987 | U24: -0.0013877639 | V24: -0.011954491 | W24: -0.051326223 | X24: -0.040759495 | AA24: 0.0032764621 | AB24: -0.026856803 | AC24: 0.026856803 | AD24: 0.044138868 | AE24: 0.17346154 | AF24: 2.5980824 | AG24: 2940.9 | AH24: -0.0065701691 | AI24: -0.045456758 | AJ24: -0.088333308 | AK24: -0.012507765 | AL24: -0.12587683 | AM24: -0.037333495 | AN24: -0.0081232637 | AO24: -0.0077480451 | AP24: 0.013541144 | AQ24: 0.023694991 | AR24: Consolidated | AS24: Company | AT24: 8636.74 | AU24: 0.012841201 | AV24: 0.021184572 | AW24: 1611.43 | AX24: 0.1865785 | AY24: 0.0057098961 | AZ24: 1072.67 | BA24: 0.056099794 | BB24: 0.37045649 | BC24: 0.12419848 | BD24: 11.19 | BL24: 282091.13 | BM24: 3665.75 | BN24: 76.953182 | BO24: 20.002633 | BP24: 0.2599325 | BQ24: 0.070609883 | BR24: 55.05 | BS24: 10.59 | BT24: H1 FY23 | BU24: 1336.18 | BV24: 447.12 | BW24: 889.06 | BX24: 0.74247072 | BY24: 0 | CE24: 44951 | CF24: 0.23856615 | CG24: 0.26563672 | CH24: 0.23917486 | CI24: -0.09961671 | CJ24: 0.029898477 | CK24: 0.8982666 | CL24: -0.2470772 | CM24: Yes
A25: Q3 FY23 | B25: Oct-Dec 2022 | C25: 44926 | D25: AUBANK | E25: AU Small Finance Bank Limited | G25: Nifty 500 | H25: 1000 | I25: 44945 | J25: 16:08 | K25: After close | L25: NSE announcement | M25: 44944 | N25: 44945 | O25: 44946 | P25: 44946 | Q25: 0.002388535 | R25: -0.013105639 | S25: -0.0078873239 | T25: -0.018604428 | U25: -0.0013877639 | V25: -0.0031130252 | W25: -0.017216664 | X25: -0.015491403 | AA25: 0.010623742 | AB25: -0.0078873239 | AC25: 0.0078873239 | AD25: 0.024547284 | AE25: 0.16065574 | AF25: 1.3273023 | AG25: 628 | AH25: 0.0044785669 | AI25: -0.063525201 | AJ25: 0.0038363171 | AK25: 0.14150686 | AL25: -0.0050697085 | AM25: -0.022789301 | AN25: -0.0407359 | AO25: -0.016386793 | AP25: -0.021578648 | AQ25: -0.011424801 | AR25: Standalone | AS25: Bank | AT25: 2118.0716 | AZ25: 392.8282 | BC25: 0.18546502 | BD25: 5.9 | BE25: 1152.7333 | BI25: 0.0181 | BJ25: 0.0051 | BK25: 0.005 | BR25: 22.64 | BS25: 4.06 | BY25: 0 | CE25: 44951 | CF25: 0.32195224 | CG25: 0.34595676 | CH25: 0.30318576 | CI25: -0.12363106 | CJ25: 0.034766476 | CK25: 0.22686579 | CL25: -0.27236066 | CM25: Yes
A26: Q3 FY23 | B26: Oct-Dec 2022 | C26: 44926 | D26: HAVELLS | E26: Havells India Limited | F26: Electrical Equipment | G26: Nifty India Manufacturing | H26: 500 | I26: 44945 | J26: 14:24 | K26: During market | L26: NSE announcement | M26: 44944 | N26: 44945 | O26: 44946 | P26: 44945 | Q26: 0.020965962 | R26: 0.0022031926 | S26: -0.043012983 | T26: -0.019843828 | U26: -0.0013877639 | V26: -0.0029526161 | W26: -0.018456064 | X26: -0.016891212 | Y26: 0.011508905 | Z26: -0.031352733 | AA26: -0.0023279016 | AB26: 0.0022031926 | AC26: 0.0022031926 | AD26: 0.029514466 | AE26: 0.48028169 | AF26: 2.1410048 | AG26: 1178.1 | AH26: -0.0029620853 | AI26: 0.013419355 | AJ26: -0.062805775 | AK26: -0.061723479 | AL26: -0.12399152 | AM26: -0.0081360287 | AN26: 0.021555384 | AO26: 0.019894244 | AP26: 0.053831484 | AQ26: 0.063985331 | AR26: Consolidated | AS26: Company | AT26: 4127.57 | AU26: 0.12645563 | AV26: 0.12177775 | AW26: 423.61 | AX26: 0.10262939 | AY26: -0.017508373 | AZ26: 0 | BA26: -1 | BB26: -1 | BC26: 0 | BD26: 4.53 | BR26: 22.01 | BS26: 3.95 | BT26: H1 FY23 | BU26: -110.35 | BV26: 166.58 | BW26: -276.93 | BX26: -0.25652649 | BY26: 4 | BZ26: 0.077854008 | CA26: 0.73390685 | CB26: 5 of 5 | CC26: 34.878248 | CE26: 44951 | CF26: 0.26757755 | CG26: 0.31755624 | CH26: 0.28634382 | CI26: -0.098289422 | CJ26: 0.035684544 | CK26: 0.061740808 | CL26: -0.19132411 | CM26: Yes
A27: Q3 FY23 | B27: Oct-Dec 2022 | C27: 44926 | D27: HINDUNILVR | E27: Hindustan Unilever Limited | F27: Diversified | G27: Nifty 500 | H27: 300 | I27: 44945 | J27: 16:16 | K27: After close | L27: NSE announcement | M27: 44944 | N27: 44945 | O27: 44946 | P27: 44946 | Q27: 0.0069914341 | R27: -0.013569354 | S27: -0.038116803 | T27: -0.044694724 | U27: -0.0013877639 | V27: -0.0031130252 | W27: -0.04330696 | X27: -0.041581699 | AA27: -0.037645061 | AB27: -0.038116803 | AC27: 0.038116803 | AD27: 0.026021323 | AE27: 0.18419144 | AF27: 3.594989 | AG27: 2667.55 | AH27: 0.0089641999 | AI27: -0.01859755 | AJ27: 0.025093669 | AK27: 0.038563364 | AL27: 0.12854846 | AM27: -0.022789301 | AN27: 0.0041917516 | AO27: 0.0076115743 | AP27: -0.014634625 | AQ27: -0.0044807778 | AR27: Consolidated | AS27: Company | AT27: 15597 | AU27: 0.16057742 | AV27: 0.029912837 | AW27: 3591 | AX27: 0.23023658 | AY27: -0.018442633 | AZ27: 2474 | BA27: 0.077057031 | BB27: -0.071669794 | BC27: 0.15862025 | BD27: 10.53 | BL27: 626874.25 | BM27: 9647 | BN27: 64.981264 | BO27: 12.638849 | BP27: 0.19449989 | BQ27: 0.0021169782 | BR27: 22.64 | BS27: 4.06 | BT27: H1 FY23 | BU27: 5099.99 | BV27: 521 | BW27: 4578.99 | BX27: 1.0106996 | BY27: 0 | CE27: 44951 | CF27: 0.18382636 | CG27: 0.20148266 | CH27: 0.19076828 | CI27: -0.053177642 | CJ27: 0.020515627 | CK27: 1.8579399 | CL27: -0.091235851 | CM27: Yes
A28: Q3 FY23 | B28: Oct-Dec 2022 | C28: 44926 | D28: HINDZINC | E28: Hindustan Zinc Limited | F28: Metals | G28: Nifty Metal | H28: 1225 | I28: 44945 | J28: 17:54 | K28: After close | L28: NSE announcement | M28: 44944 | N28: 44945 | O28: 44946 | P28: 44946 | Q28: 0.039706517 | R28: 0.04483188 | S28: -0.0650245 | T28: 0.019513897 | U28: -0.0013877639 | V28: 0.0019199088 | W28: 0.020901661 | X28: 0.017593989 | AA28: -0.086213747 | AB28: -0.0650245 | AC28: 0.0650245 | AD28: 0.043967686 | AE28: 0.77108434 | AF28: 7.1796592 | AG28: 347.55 | AH28: 0.011201629 | AI28: 0.072685185 | AJ28: 0.23881661 | AK28: 0.21797792 | AL28: 0.053181818 | AM28: 0.0075714317 | AN28: 0.065113753 | AO28: -0.065155807 | AP28: -0.090084986 | AQ28: -0.079931139 | AR28: Consolidated | AS28: Company | AT28: 7628 | AU28: -0.045306633 | AV28: -0.061400271 | AW28: 3469 | AX28: 0.45477189 | AY28: -0.092161774 | AZ28: 0 | BC28: 0 | BD28: 5.1 | BL28: 146839.88 | BM28: 2928 | BN28: 50.150231 | BO28: 4.6949698 | BP28: 0.09361811 | BQ28: 0.068007418 | BR28: 10.47 | BS28: 2.21 | BT28: H1 FY23 | BU28: 8464 | BV28: 2040 | BW28: 6424 | BY28: 0 | CN28: no option prices for this event
A29: Q3 FY23 | B29: Oct-Dec 2022 | C29: 44926 | D29: MPHASIS | E29: MphasiS Limited | F29: Computers - Software | G29: Nifty IT | H29: 275 | I29: 44945 | J29: 22:35 | K29: After close | L29: NSE announcement | M29: 44944 | N29: 44945 | O29: 44946 | P29: 44946 | Q29: 0.0027185893 | R29: 0.0099167094 | S29: -0.020654461 | T29: -0.0080191623 | U29: -0.0013877639 | V29: 0.0010867441 | W29: -0.0066313985 | X29: -0.0091059065 | Y29: 0.0015252858 | Z29: -0.0095444482 | AA29: -0.013689022 | AB29: -0.020654461 | AC29: 0.020654461 | AD29: 0.042784241 | AE29: 0.73148672 | AF29: 3.2797991 | AG29: 2041.5 | AH29: 0.026524199 | AI29: 0.061594862 | AJ29: -0.034751773 | AK29: -0.046718498 | AL29: -0.37448295 | AM29: 0.032971535 | AN29: 0.028623327 | AO29: 0.045538735 | AP29: 0.10789519 | AQ29: 0.11804904 | AR29: Consolidated | AS29: Company | AT29: 3506.213 | AU29: 0.12244863 | AV29: -0.0038658227 | AW29: 617.504 | AX29: 0.17611708 | AY29: -0.00095652137 | AZ29: 412.272 | BA29: 0.15263127 | BB29: -0.014796972 | BC29: 0.11758327 | BD29: 21.9 | BL29: 38410.21 | BM29: 1501.177 | BN29: 25.58673 | BO29: 5.505174 | BP29: 0.21515739 | BQ29: 0.048151305 | BR29: 26.37 | BS29: 8.25 | BT29: H1 FY23 | BU29: 828.527 | BV29: 54.452 | BW29: 774.075 | BX29: 1.0099763 | BY29: 9 | BZ29: 0.19944373 | CA29: 0.1102467 | CB29: 4 of 10 | CC29: 26.971544 | CD29: -0.051343547 | CE29: 44951 | CF29: 0.3240547 | CG29: 0.34419707 | CH29: 0.27187396 | CI29: -0.21012122 | CJ29: 0.034706266 | CK29: 0.59512195 | CL29: -0.21594243 | CM29: Yes
A30: Q3 FY23 | B30: Oct-Dec 2022 | C30: 44926 | D30: POLYCAB | E30: Polycab India Limited | G30: Nifty 500 | H30: 125 | I30: 44945 | J30: 14:57 | K30: During market | L30: NSE announcement | M30: 44944 | N30: 44945 | O30: 44946 | P30: 44945 | Q30: 0.013340203 | R30: 0.027237071 | S30: -0.023828042 | T30: 0.016749232 | U30: -0.0013877639 | V30: -0.0031130252 | W30: 0.018136996 | X30: 0.019862257 | AA30: -0.0049208309 | AB30: 0.027237071 | AC30: 0.027237071 | AD30: 0.043942475 | AE30: 0.87396694 | AF30: 2.845592 | AG30: 2717.35 | AH30: 0.01363399 | AI30: -0.0046336996 | AJ30: -0.011531256 | AK30: 0.26004498 | AL30: 0.0087048517 | AM30: -0.022789301 | AN30: 0.018155602 | AO30: 0.02100536 | AP30: 0.087443865 | AQ30: 0.097597712 | AR30: Consolidated | AS30: Company | AT30: 3715.182 | AU30: 0.10177533 | AV30: 0.11488081 | AW30: 503.839 | AX30: 0.13561624 | AY30: 0.028352171 | AZ30: 357.647 | BA30: 0.13123585 | BB30: 0.33552032 | BC30: 0.096266347 | BD30: 23.9 | BL30: 40665.414 | BM30: 1129.046 | BN30: 36.0175 | BO30: 6.9713997 | BP30: 0.1935559 | BQ30: 0.017679042 | BR30: 22.64 | BS30: 4.06 | BT30: H1 FY23 | BU30: 957.5718 | BV30: 200.515 | BW30: 757.0568 | BX30: 1.9640363 | BY30: 0 | CE30: 44951 | CF30: 0.31059632 | CG30: 0.32559468 | CH30: 0.33506984 | CI30: 0.029101092 | CJ30: 0.03659136 | CK30: 0.744358 | CL30: -0.25273 | CM30: Yes
A31: Q3 FY23 | B31: Oct-Dec 2022 | C31: 44926 | D31: COFORGE | E31: Coforge Limited | G31: Nifty 500 | H31: 475 | I31: 44946 | J31: 07:34 | K31: Before open | L31: NSE announcement | M31: 44945 | N31: 44946 | O31: 44949 | P31: 44946 | Q31: 0.01038005 | R31: 0.034148063 | S31: 0.062627986 | T31: 0.1071561 | U31: -0.0025521308 | V31: -0.0040695079 | W31: 0.10970823 | X31: 0.11122561 | AA31: 0.01876946 | AB31: 0.034148063 | AC31: 0.034148063 | AD31: 0.052690625 | AE31: 0.29186603 | AF31: 8.4818498 | AG31: 3925.8 | AH31: -0.0026168034 | AI31: 0.0076618026 | AJ31: 0.029758548 | AK31: 0.1406738 | AL31: -0.30245203 | AM31: -0.016523381 | AN31: 0.024185184 | AO31: 0.0045883136 | AP31: -0.0043474271 | AQ31: 0.011760374 | AR31: Consolidated | AS31: Company | AT31: 2055.8 | AU31: 0.23985284 | AV31: 0.049198734 | AW31: 359.5 | AX31: 0.1748711 | AY31: -0.0080491135 | AZ31: 295.2 | BA31: 0.60696788 | BB31: 0.4679264 | BC31: 0.14359373 | BD31: 37.41 | BL31: 23947.38 | BM31: 742.2 | BN31: 32.2654 | BO31: 8.4682556 | BP31: 0.26245624 | BQ31: 0.20651367 | BR31: 22.75 | BS31: 4.08 | BT31: H1 FY23 | BU31: 108.8 | BV31: 89.2 | BW31: 19.6 | BX31: 0.31014823 | BY31: 0 | CE31: 44951 | CF31: 0.35643615 | CG31: 0.38273936 | CH31: 0.3041312 | CI31: -0.20538301 | CJ31: 0.038459591 | CK31: 0.88789459 | CL31: -0.29746674 | CM31: Yes
A32: Q3 FY23 | B32: Oct-Dec 2022 | C32: 44926 | D32: HDFCLIFE | E32: HDFC Life Insurance Company Limited | G32: Nifty 500 | H32: 1100 | I32: 44946 | J32: 13:48 | K32: During market | L32: NSE announcement (no filing record) | M32: 44945 | N32: 44946 | O32: 44949 | P32: 44946 | Q32: 0.0069877714 | R32: -0.024287485 | S32: -0.0022860046 | T32: -0.019585718 | U32: -0.0025521308 | V32: -0.0040695079 | W32: -0.017033587 | X32: -0.01551621 | AA32: 0.004543577 | AB32: -0.024287485 | AC32: 0.024287485 | AD32: 0.033292028 | AE32: 0.11414392 | AF32: 1.1959071 | AG32: 601.05 | AH32: 0.0020005001 | AI32: 0.036650569 | AJ32: 0.13074969 | AK32: 0.10741594 | AL32: -0.10843284 | AM32: -0.016523381 | AN32: 0.053173951 | AO32: -0.017566191 | AP32: -0.14960964 | AQ32: -0.13350184 | BR32: 22.75 | BS32: 4.08 | BY32: 0 | CE32: 44951 | CF32: 0.24245867 | CG32: 0.28502131 | CH32: 0.25383684 | CI32: -0.10941101 | CJ32: 0.028703398 | CK32: 0.84615363 | CL32: -0.21035124 | CM32: Yes | CN32: no NSE XBRL results for this quarter
A33: Q3 FY23 | B33: Oct-Dec 2022 | C33: 44926 | D33: IEX | E33: Indian Energy Exchange Limited | G33: Nifty 500 | H33: 4350 | I33: 44946 | J33: 18:42 | K33: After close | L33: NSE announcement | M33: 44945 | N33: 44946 | O33: 44949 | P33: 44949 | Q33: -0.0071684588 | R33: -0.020216606 | S33: 0.02210759 | T33: -0.005277475 | U33: -0.0025521308 | V33: -0.0040695079 | W33: -0.0027253442 | X33: -0.0012079671 | AA33: -0.0066322771 | AB33: 0.02210759 | AC33: 0.02210759 | AD33: 0.038688283 | AE33: 0.86666667 | AF33: 1.4163858 | AG33: 139.5 | AH33: -0.016566796 | AI33: -0.030576789 | AJ33: -0.010287336 | AK33: -0.16241369 | AL33: -0.47566247 | AM33: -0.016523381 | AN33: -0.014053408 | AO33: -0.00072098053 | AP33: 0.038572459 | AQ33: 0.05468026 | AR33: Consolidated | AS33: Company | AT33: 100.2751 | AU33: -0.14690128 | AV33: 0.05332647 | AW33: 83.2838 | AX33: 0.83055315 | AY33: -0.010165334 | AZ33: 77.2161 | BA33: -0.039091608 | BB33: 0.084430294 | BC33: 0.77004261 | BD33: 0.86 | BL33: 12524.98 | BM33: 309.0454 | BN33: 40.52796 | BO33: 16.582362 | BP33: 0.40915856 | BQ33: 0 | BR33: 22.75 | BS33: 4.08 | BT33: H1 FY23 | BU33: -358.5194 | BV33: 0 | BW33: -358.5194 | BX33: -2.554778 | BY33: 0 | CE33: 44980 | CF33: 0.33132892 | CG33: 0.32539963 | CH33: 0.29116738 | CI33: -0.10520063 | CJ33: 0.078618663 | CK33: 0.28120028 | CL33: -0.14947959 | CM33: No
A34: Q3 FY23 | B34: Oct-Dec 2022 | C34: 44926 | D34: JSWENERGY | E34: JSW Energy Limited | F34: Power | G34: Nifty Energy | H34: 1075 | I34: 44946 | J34: 18:27 | K34: After close | L34: NSE announcement | M34: 44945 | N34: 44946 | O34: 44949 | P34: 44949 | Q34: 0.0033981499 | R34: -0.012793979 | S34: -0.05908138 | T34: -0.068477209 | U34: -0.0025521308 | V34: -0.0051462232 | W34: -0.065925078 | X34: -0.063330986 | Y34: -0.011555459 | Z34: -0.056921751 | AA34: -0.028016009 | AB34: -0.05908138 | AC34: 0.05908138 | AD34: 0.034877073 | AE34: 0.10928962 | AF34: 2.4789302 | AG34: 264.85 | AH34: -0.051906211 | AI34: -0.049865471 | AJ34: -0.16857636 | AK34: 0.13159581 | AM34: -0.013033678 | AN34: -0.036831793 | AO34: -0.034433867 | AP34: -0.094389305 | AQ34: -0.078281504 | AR34: Consolidated | AS34: Company | AT34: 2248.09 | AU34: 0.18724189 | AV34: -0.058383735 | AW34: 624.93 | AX34: 0.27798264 | AY34: -0.13986963 | AZ34: 179.61 | BA34: -0.44552835 | BB34: -0.61429768 | BC34: 0.079894488 | BD34: 1.09 | BR34: 14.86 | BS34: 2.28 | BT34: H1 FY23 | BU34: 1799.82 | BV34: 2063.87 | BW34: -264.05 | BX34: 1.7540396 | BY34: 5 | BZ34: 0.29468879 | CA34: 0.061803947 | CB34: 5 of 6 | CC34: 9.8684585 | CN34: no option prices for this event
A35: Q3 FY23 | B35: Oct-Dec 2022 | C35: 44926 | D35: JSWSTEEL | E35: JSW Steel Limited | F35: Steel And Steel Products | G35: Nifty Metal | H35: 675 | I35: 44946 | J35: 15:31 | K35: After close | L35: NSE announcement | M35: 44945 | N35: 44946 | O35: 44949 | P35: 44949 | Q35: -0.0092550349 | R35: -0.024472074 | S35: -0.010115315 | T35: -0.043842424 | U35: -0.0025521308 | V35: -0.018636902 | W35: -0.041290293 | X35: -0.025205522 | Y35: 0.0063601599 | Z35: -0.050202584 | AA35: -0.0052599636 | AB35: -0.010115315 | AC35: 0.010115315 | AD35: 0.028525187 | AE35: 0.37588652 | AF35: 1.4090062 | AG35: 767.15 | AH35: 0.017170512 | AI35: 0.028626978 | AJ35: 0.22567503 | AK35: 0.3092414 | AL35: 0.096868745 | AM35: 0.023036013 | AN35: 0.0055909645 | AO35: -0.023843586 | AP35: -0.018870495 | AQ35: -0.0027626941 | AR35: Consolidated | AS35: Company | AT35: 39134 | AU35: 0.027921515 | AV35: -0.063286897 | AW35: 4547 | AX35: 0.11619052 | AY35: -0.12367709 | AZ35: 490 | BA35: -0.8875373 | BC35: 0.012521081 | BD35: 2.04 | BL35: 184116 | BM35: 7699 | BN35: 23.914275 | BO35: 2.9692777 | BP35: 0.1241634 | BQ35: 1.218556 | BR35: 10.64 | BS35: 2.25 | BT35: H1 FY23 | BU35: 6122 | BV35: 5634 | BW35: 488 | BY35: 4 | BZ35: -0.0057821006 | CA35: -1 | CB35: 2 of 4 | CC35: 43.80089 | CD35: -0.45402309 | CE35: 44980 | CF35: 0.27957641 | CG35: 0.2745963 | CH35: 0.24558113 | CI35: -0.10566484 | CJ35: 0.066258164 | CK35: 0.15266518 | CL35: -0.18447264 | CM35: No
A36: Q3 FY23 | B36: Oct-Dec 2022 | C36: 44926 | D36: LTM | E36: LTM Limited | G36: Nifty 500 | H36: 150 | I36: 44946 | J36: 16:55 | K36: After close | L36: NSE announcement | M36: 44945 | N36: 44946 | O36: 44949 | P36: 44949 | AM36: -0.016523381 | AR36: Consolidated | AS36: Company | AT36: 8620 | AU36: 1.0833333 | AV36: 0.78220688 | AW36: 1374.8 | AX36: 0.15948956 | AY36: -0.041375677 | AZ36: 1000.5 | BA36: 0.63480392 | BB36: 0.47283969 | BC36: 0.11606729 | BD36: 33.83 | BR36: 22.75 | BS36: 4.08 | BT36: H1 FY23 | BU36: 586.3 | BV36: 398.5 | BW36: 187.8 | BX36: 0.44660268 | BY36: 0 | CN36: no option prices for this event
A37: Q3 FY23 | B37: Oct-Dec 2022 | C37: 44926 | D37: PETRONET | E37: Petronet LNG Limited | F37: Gas | G37: Nifty Oil & Gas | H37: 1900 | I37: 44946 | J37: 17:42 | K37: After close | L37: NSE announcement | M37: 44945 | N37: 44946 | O37: 44949 | P37: 44949 | Q37: 0.0042792793 | R37: 0 | S37: 0.016371384 | T37: 0.020650663 | U37: -0.0025521308 | V37: 0.010202136 | W37: 0.023202794 | X37: 0.010448527 | AA37: 0.0044853106 | AB37: 0.016371384 | AC37: 0.016371384 | AD37: 0.033415564 | AE37: 0.91946309 | AF37: 2.0089495 | AG37: 222 | AH37: 0.0068027211 | AI37: 0.042008918 | AJ37: 0.099826604 | AK37: -0.017699115 | AL37: -0.0053763441 | AM37: -0.0024165305 | AN37: 0.044425449 | AO37: -0.041262136 | AP37: -0.058031774 | AQ37: -0.041923973 | AR37: Consolidated | AS37: Company | AT37: 15775.87 | AV37: -0.013127958 | AW37: 1674.9 | AX37: 0.10616847 | AZ37: 0 | BC37: 0 | BD37: 7.98 | BR37: 15.4 | BS37: 2.09 | BT37: H1 FY23 | BU37: 712.73 | BV37: 324.99 | BW37: 387.74 | BY37: 1 | CE37: 44980 | CG37: 0.27741495 | CH37: 0.23472059 | CI37: -0.15390073 | CJ37: 0.068085106 | CK37: 0.2404547
A38: Q3 FY23 | B38: Oct-Dec 2022 | C38: 44926 | D38: RBLBANK | E38: RBL Bank Limited | G38: Nifty 500 | H38: 3175 | I38: 44946 | J38: 15:47 | K38: After close | L38: NSE announcement | M38: 44945 | N38: 44946 | O38: 44949 | P38: 44949 | Q38: -0.029863729 | R38: 0.014943216 | S38: -0.014134276 | T38: -0.029054788 | U38: -0.0025521308 | V38: -0.0040695079 | W38: -0.026502658 | X38: -0.024985281 | AA38: 0.018551237 | AB38: -0.014134276 | AC38: 0.014134276 | AD38: 0.050353357 | AE38: 0.22222222 | AF38: 1.5487821 | AG38: 172.45 | AH38: -0.047237569 | AI38: 0.01740413 | AJ38: 0.33941748 | AK38: 1.0075669 | AL38: 0.11114691 | AM38: -0.016523381 | AN38: 0.033927511 | AO38: -0.069593787 | AP38: -0.051075269 | AQ38: -0.034967468 | AR38: Standalone | AS38: Bank | AT38: 2368.64 | AV38: 0.088699521 | AZ38: 208.97 | BB38: 0.036814686 | BC38: 0.088223622 | BD38: 3.49 | BE38: 1148.15 | BI38: 0.0361 | BJ38: 0.0118 | BK38: 0.0078 | BR38: 22.75 | BS38: 4.08 | BY38: 0 | CE38: 44980 | CF38: 0.4428547 | CG38: 0.42759088 | CH38: 0.39089401 | CI38: -0.085822383 | CJ38: 0.10279001 | CK38: 0.13750631 | CL38: -0.11586652 | CM38: No
A39: Q3 FY23 | B39: Oct-Dec 2022 | C39: 44926 | D39: RELIANCE | E39: Reliance Industries Limited | F39: Refineries | G39: Nifty Oil & Gas | H39: 500 | I39: 44946 | J39: 19:07 | K39: After close | L39: NSE announcement | M39: 44945 | N39: 44946 | O39: 44949 | P39: 44949 | Q39: -0.0010708369 | R39: -0.011892963 | S39: -0.0050559843 | T39: -0.018019784 | U39: -0.0025521308 | V39: 0.010202136 | W39: -0.015467654 | X39: -0.028221921 | Y39: -0.0094033313 | Z39: -0.0086164532 | AA39: 0.0025996356 | AB39: -0.0050559843 | AC39: 0.0050559843 | AD39: 0.016866927 | AE39: 0.12864078 | AF39: 1.048542 | AG39: 2474.7 | AH39: -0.020366962 | AI39: -0.056106492 | AJ39: -0.007698785 | AK39: 0.021653421 | AL39: -0.030384954 | AM39: -0.0024165305 | AN39: -0.053689961 | AO39: -0.031457022 | AP39: 0.001563593 | AQ39: 0.017671394 | AR39: Consolidated | AS39: Company | AT39: 220592 | AU39: 0.15329559 | AV39: -0.052696221 | AW39: 35247 | AX39: 0.15978367 | AY39: -0.010351894 | AZ39: 15792 | BA39: -0.14863335 | BB39: 0.15641476 | BC39: 0.071589178 | BD39: 23.34 | BL39: 1674382 | BM39: 61254 | BN39: 27.335064 | BO39: 2.1193395 | BP39: 0.0775319 | BQ39: 0.37321609 | BR39: 15.4 | BS39: 2.09 | BT39: H1 FY23 | BU39: 30050 | BV39: 68204 | BW39: -38154 | BX39: 0.95061846 | BY39: 3 | BZ39: 0.13291908 | CA39: -0.62566497 | CB39: 1 of 3 | CE39: 44980 | CF39: 0.23454126 | CG39: 0.23897413 | CH39: 0.22549292 | CI39: -0.056412848 | CJ39: 0.057750449 | CK39: 0.08754883 | CL39: -0.1218564 | CM39: No
A40: Q3 FY23 | B40: Oct-Dec 2022 | C40: 44926 | D40: UNIONBANK | E40: Union Bank of India | F40: Banks | G40: Nifty Bank | H40: 4425 | I40: 44946 | J40: 13:21 | K40: During market | L40: NSE announcement | M40: 44945 | N40: 44946 | O40: 44949 | P40: 44946 | Q40: 0.0043076923 | R40: -0.0042892157 | S40: 0.0030769231 | T40: 0.0030953997 | U40: -0.0025521308 | V40: 0.0085597989 | W40: 0.0056475305 | X40: -0.0054643992 | Y40: 0.00018514364 | Z40: 0.0029102561 | AA40: 0.0042892157 | AB40: -0.0042892157 | AC40: 0.0042892157 | AD40: 0.034926471 | AE40: 0.21052632 | AF40: 0.85224598 | AG40: 81.25 | AH40: 0.035691523 | AI40: -0.031007752 | AJ40: 0.75865801 | AK40: 1.1870794 | AL40: 0.77984666 | AM40: -0.020791291 | AN40: -0.010216461 | AO40: -0.036809816 | AP40: -0.14662577 | AQ40: -0.13051797 | AR40: Standalone | AS40: Bank | AT40: 20882.86 | AU40: 0.23350808 | AV40: 0.055853471 | AZ40: 2244.8 | BA40: 1.0681776 | BB40: 0.21136246 | BC40: 0.10749485 | BD40: 3.28 | BE40: 8628.08 | BF40: 0.2026221 | BG40: 0.29833333 | BH40: 0.19074906 | BI40: 0.0793 | BJ40: 0.0214 | BK40: 0.0073 | BL40: 55532.344 | BM40: 5936.58 | BN40: 9.3542652 | BO40: 0.74524764 | BP40: 0.079669287 | BR40: 17.58 | BS40: 2.8 | BY40: 14 | BZ40: 0.28932048 | CA40: 0.44112011 | CB40: 2 of 13 | CC40: 25.51604 | CD40: -0.63339667 | CN40: no option prices for this event
A41: Q3 FY23 | B41: Oct-Dec 2022 | C41: 44926 | D41: ICICIBANK | E41: ICICI Bank Limited | F41: Banks | G41: Nifty Bank | H41: 700 | I41: 44947 | J41: 15:58 | K41: Non-trading day | L41: NSE announcement | M41: 44946 | N41: 44949 | O41: 44950 | P41: 44949 | Q41: 0.0048490446 | R41: 0.0015511001 | S41: -0.0010898245 | T41: 0.0053103203 | U41: 0.00059943817 | V41: 0.0095512446 | W41: 0.0047108821 | X41: -0.0042409243 | Y41: 0.00018514364 | Z41: 0.0051251766 | AA41: 0.01338542 | AB41: 0.0015511001 | AC41: 0.0015511001 | AD41: 0.021485609 | AE41: 0.37967914 | AF41: 1.5533153 | AG41: 866.15 | AH41: 0.0063905188 | AI41: -0.029251891 | AJ41: -0.025319305 | AK41: 0.10952411 | AL41: 0.052302272 | AM41: -0.0067835267 | AN41: -0.022468365 | AO41: -0.026184324 | AP41: -0.036175711 | AQ41: -0.0050469623 | AR41: Standalone | AS41: Bank | AT41: 28505.63 | AU41: 0.29086385 | AV41: 0.094978919 | AZ41: 8311.85 | BA41: 0.34196076 | BB41: 0.099765277 | BC41: 0.29158626 | BD41: 11.92 | BE41: 16464.98 | BF41: 0.34561345 | BG41: 0.30773483 | BH41: 0.12461515 | BI41: 0.0313 | BJ41: 0.0058 | BK41: 0.022 | BL41: 603615.6 | BM41: 28154.89 | BN41: 21.439104 | BO41: 3.3073575 | BP41: 0.15426753 | BR41: 17.37 | BS41: 2.79 | BY41: 14 | BZ41: 0.27291649 | CA41: 0.61249873 | CB41: 8 of 13 | CC41: 25.51604 | CD41: -0.15977935 | CE41: 44980 | CF41: 0.23564965 | CG41: 0.23655293 | CH41: 0.2291494 | CI41: -0.031297567 | CJ41: 0.057116642 | CK41: 0.027156711 | CL41: -0.14749837 | CM41: No
A42: Q3 FY23 | B42: Oct-Dec 2022 | C42: 44926 | D42: IDFCFIRSTB | E42: IDFC First Bank Limited | G42: Nifty 500 | H42: 9275 | I42: 44947 | J42: 16:07 | K42: Non-trading day | L42: NSE announcement | M42: 44946 | N42: 44949 | O42: 44950 | P42: 44949 | Q42: -0.00084175084 | R42: -0.00084245998 | S42: -0.0084317032 | T42: -0.010115914 | U42: 0.00059943817 | V42: -0.0020043834 | W42: -0.010715352 | X42: -0.0081115306 | AA42: 0.036225779 | AB42: -0.00084245998 | AC42: 0.00084245998 | AD42: 0.048020219 | AE42: 0.10526316 | AF42: 1.9273131 | AG42: 59.4 | AH42: -0.0033557047 | AI42: 0.0076335878 | AJ42: 0.045774648 | AK42: 0.68510638 | AL42: 0.24397906 | AM42: -0.0069457191 | AN42: 0.014579307 | AO42: -0.039115646 | AP42: -0.091836735 | AQ42: -0.060707986 | AR42: Standalone | AS42: Bank | AT42: 5911.82 | AU42: 0.3347497 | AV42: 0.080832735 | AZ42: 604.61 | BA42: 1.1511777 | BB42: 0.088269705 | BC42: 0.10227138 | BD42: 0.97 | BE42: 3285.3 | BF42: 0.27339184 | BG42: 0.63793798 | BH42: 0.14898558 | BI42: 0.0296 | BJ42: 0.0103 | BK42: 0.0111 | BL42: 36954.76 | BM42: 1653.69 | BN42: 22.346848 | BO42: 1.6758099 | BP42: 0.074990885 | BR42: 22.66 | BS42: 4.07 | BY42: 0 | CE42: 44980 | CF42: 0.39304801 | CG42: 0.40130979 | CH42: 0.3751549 | CI42: -0.065173813 | CJ42: 0.096638655 | CK42: 0.0087176294 | CL42: -0.13470243 | CM42: No
A43: Q3 FY23 | B43: Oct-Dec 2022 | C43: 44926 | D43: KOTAKBANK | E43: Kotak Mahindra Bank Limited | F43: Banks | G43: Nifty Bank | H43: 2000 | I43: 44947 | J43: 13:08 | K43: Non-trading day | L43: NSE announcement | M43: 44946 | N43: 44949 | O43: 44950 | P43: 44949 | Q43: -0.0024896735 | R43: 0.011827103 | S43: -0.013174492 | T43: -0.0038370624 | U43: 0.00059943817 | V43: 0.0095512446 | W43: -0.0044365006 | X43: -0.013388307 | Y43: 0.0016680946 | Z43: -0.0055051569 | AA43: 0.015372398 | AB43: 0.011827103 | AC43: 0.011827103 | AD43: 0.016818878 | AE43: 0.46374368 | AF43: 2.9394473 | AG43: 1767.3 | AH43: -0.0068558584 | AI43: -0.026066351 | AJ43: -0.051648735 | AK43: -0.03686749 | AL43: -0.090029091 | AM43: -0.0067835267 | AN43: -0.019282824 | AO43: -0.0088339724 | AP43: -0.033915637 | AQ43: -0.0027868887 | AR43: Standalone | AS43: Bank | AT43: 8998.61 | AU43: 0.3047477 | AV43: 0.11192651 | AZ43: 2791.88 | BA43: 0.30990541 | BB43: 0.081838895 | BC43: 0.31025681 | BD43: 14.06 | BE43: 5652.92 | BF43: 0.30422906 | BG43: 0.42533876 | BI43: 0.019 | BJ43: 0.0043 | BK43: 0.0062 | BL43: 350939.83 | BM43: 9550.59 | BN43: 36.745356 | BO43: 4.5531726 | BP43: 0.12391151 | BR43: 17.37 | BS43: 2.79 | BY43: 14 | BZ43: 0.27291649 | CA43: 0.61249873 | CB43: 9 of 13 | CC43: 21.800207 | CD43: 0.68555083 | CE43: 44980 | CF43: 0.22458221 | CG43: 0.22322794 | CH43: 0.20327754 | CI43: -0.089372335 | CJ43: 0.054021915 | CK43: 0.21893158 | CL43: -0.15421933 | CM43: No
A44: Q3 FY23 | B44: Oct-Dec 2022 | C44: 44926 | D44: SBILIFE | E44: SBI Life Insurance Company Limited | G44: Nifty 500 | H44: 375 | I44: 44947 | J44: 17:32 | K44: Non-trading day | L44: NSE announcement (no filing record) | M44: 44946 | N44: 44949 | O44: 44950 | P44: 44949 | Q44: -0.020406621 | R44: -0.00054008178 | S44: -0.017098966 | T44: -0.038045668 | U44: 0.00059943817 | V44: -0.0020043834 | W44: -0.038645106 | X44: -0.036041285 | AA44: -0.008564154 | AB44: -0.00054008178 | AC44: 0.00054008178 | AD44: 0.029434457 | AE44: 0.40366972 | AF44: 1.3840967 | AG44: 1323.1 | AH44: 0.0056243825 | AI44: 0.07190019 | AJ44: 0.081892146 | AK44: 0.13090303 | AL44: 0.045185244 | AM44: -0.0069457191 | AN44: 0.078845909 | AO44: -0.12868643 | AP44: -0.11160416 | AQ44: -0.080475414 | BR44: 22.66 | BS44: 4.07 | BY44: 0 | CE44: 44980 | CG44: 0.25212914 | CH44: 0.23469053 | CI44: -0.06916539 | CJ44: 0.060766642 | CK44: 0.0088878004 | CN44: no NSE XBRL results for this quarter
A45: Q3 FY23 | B45: Oct-Dec 2022 | C45: 44926 | D45: ULTRACEMCO | E45: UltraTech Cement Limited | F45: Cement And Cement Products | G45: Nifty Commodities | H45: 50 | I45: 44947 | J45: 13:25 | K45: Non-trading day | L45: NSE announcement | M45: 44946 | N45: 44949 | O45: 44950 | P45: 44949 | Q45: -0.0048805174 | R45: -0.045616993 | S45: -0.0058469287 | T45: -0.056344439 | U45: 0.00059943817 | V45: -0.024991061 | W45: -0.056943877 | X45: -0.031353378 | Y45: -0.0054314221 | Z45: -0.050913017 | AA45: -0.0072661154 | AB45: -0.045616993 | AC45: 0.045616993 | AD45: 0.049455564 | AE45: 0.05564164 | AF45: 3.0211073 | AG45: 7212.35 | AH45: 0.0082478839 | AI45: 0.037643691 | AJ45: 0.14439966 | AK45: 0.18510151 | AL45: -0.04546778 | AM45: 0.014892258 | AN45: 0.022751433 | AO45: 0.048709928 | AP45: 0.058159684 | AQ45: 0.089288432 | AR45: Consolidated | AS45: Company | AT45: 15520.93 | AU45: 0.19530332 | AV45: 0.1172012 | AW45: 2335.85 | AX45: 0.15049678 | AY45: -0.035825363 | AZ45: 1058.2 | BA45: -0.38122025 | BB45: 0.40023553 | BC45: 0.068178904 | BD45: 36.7 | BR45: 13.14 | BS45: 2.33 | BT45: H1 FY23 | BU45: 829.37 | BV45: 3123.37 | BW45: -2294 | BX45: 0.3544604 | BY45: 3 | BZ45: 0.17357505 | CA45: 0.44076649 | CB45: 3 of 4 | CC45: 34.372694 | CE45: 44980 | CF45: 0.24659582 | CG45: 0.24466467 | CH45: 0.23096621 | CI45: -0.0559887 | CJ45: 0.058925042 | CK45: 0.77415291 | CL45: -0.15942952 | CM45: No
A46: Q3 FY23 | B46: Oct-Dec 2022 | C46: 44926 | D46: YESBANK | E46: Yes Bank Limited | F46: Banks | G46: Nifty Bank | H46: 31100 | I46: 44947 | J46: 14:23 | K46: Non-trading day | L46: NSE announcement | M46: 44946 | N46: 44949 | O46: 44950 | P46: 44949 | Q46: -0.019851117 | R46: -0.081012658 | S46: 0.0027548209 | T46: -0.098108954 | U46: 0.00059943817 | V46: 0.0095512446 | W46: -0.098708392 | X46: -0.1076602 | Y46: 0.0016680946 | Z46: -0.099777048 | AA46: -0.10126582 | AB46: -0.081012658 | AC46: 0.081012658 | AD46: 0.058227848 | AE46: 0.60869565 | AF46: 1.7923429 | AG46: 20.15 | AH46: 0.012562814 | AI46: 0.01511335 | AJ46: 0.26332288 | AK46: 0.49259259 | AL46: 0.46014493 | AM46: -0.0067835267 | AN46: 0.021896877 | AO46: -0.071428571 | AP46: -0.1043956 | AQ46: -0.073266856 | AR46: Standalone | AS46: Bank | AT46: 5871.97 | AU46: 0.19877488 | AV46: 0.072627403 | AZ46: 51.52 | BA46: -0.806627 | BB46: -0.66287135 | BC46: 0.0087738868 | BD46: 0.02 | BE46: 1970.62 | BF46: 0.11714267 | BG46: 0.250388 | BH46: 1.2548175 | BI46: 0.0002 | BJ46: 0.0001 | BK46: 0 | BL46: 50487.538 | BM46: 1100.8505 | BN46: 45.862302 | BO46: 1.4665104 | BP46: 0.03197638 | BR46: 17.37 | BS46: 2.79 | BY46: 14 | BZ46: 0.28932048 | CA46: 0.61249873 | CB46: 13 of 13 | CC46: 21.800207 | CD46: 1.1037554 | CN46: no option prices for this event
A47: Q3 FY23 | B47: Oct-Dec 2022 | C47: 44926 | D47: AMBER | E47: Amber Enterprises India Limited | G47: Nifty 500 | H47: 100 | I47: 44949 | J47: 18:15 | K47: After close | L47: NSE announcement | M47: 44946 | N47: 44949 | O47: 44950 | P47: 44950 | Q47: 0.026179971 | R47: 0.023713973 | S47: 0.04014357 | T47: 0.090037513 | U47: 0.00059943817 | V47: -0.0020043834 | W47: 0.089438075 | X47: 0.092041897 | AA47: -0.0020109968 | AB47: 0.04014357 | AC47: 0.04014357 | AD47: 0.07524692 | AE47: 0.8514885 | AF47: 7.1466225 | AG47: 1869.75 | AH47: -0.0028265913 | AI47: -0.035316273 | AJ47: -0.14974648 | AK47: -0.24987964 | AL47: -0.47268599 | AM47: -0.0069457191 | AN47: -0.028370554 | AO47: -0.080198722 | AP47: -0.072587553 | AQ47: -0.041458805 | AR47: Consolidated | AS47: Company | AT47: 1348.3059 | AU47: 0.3838846 | AV47: 0.79667589 | AW47: 78.5117 | AX47: 0.058229887 | AY47: -0.017335753 | AZ47: 14.1509 | BA47: -0.55940357 | BC47: 0.010495319 | BD47: 4.2 | BL47: 6299.8796 | BM47: 128.4031 | BN47: 49.063298 | BO47: 3.5209095 | BP47: 0.071762593 | BQ47: 0.73284505 | BR47: 22.66 | BS47: 4.07 | BT47: H1 FY23 | BU47: -19.70179 | BV47: 275.3906 | BW47: -295.09239 | BX47: -0.50428578 | BY47: 0 | CN47: no option prices for this event
A48: Q3 FY23 | B48: Oct-Dec 2022 | C48: 44926 | D48: AXISBANK | E48: Axis Bank Limited | F48: Banks | G48: Nifty Bank | H48: 625 | I48: 44949 | J48: 15:48 | K48: After close | L48: NSE announcement | M48: 44946 | N48: 44949 | O48: 44950 | P48: 44950 | Q48: 0.0019920319 | R48: 0.0023104616 | S48: -0.024123512 | T48: -0.019821019 | U48: 0.00059943817 | V48: 0.0095512446 | W48: -0.020420457 | X48: -0.029372264 | Y48: 0.0016680946 | Z48: -0.021489114 | AA48: 0.002465959 | AB48: -0.024123512 | AC48: 0.024123512 | AD48: 0.033504878 | AE48: 0.2064 | AF48: 2.7125653 | AG48: 928.7 | AH48: -0.0073218962 | AI48: -0.003861418 | AJ48: 0.12453835 | AK48: 0.32557808 | AL48: 0.28061224 | AM48: -0.0067835267 | AN48: 0.0029221087 | AO48: -0.058174028 | AP48: -0.084431993 | AQ48: -0.053303245 | AR48: Consolidated | AS48: Bank | AT48: 22842.58 | AU48: 0.32335445 | AV48: 0.099109841 | AZ48: 6187.38 | BA48: 0.71194497 | BB48: 0.1024619 | BC48: 0.27087045 | BD48: 20.13 | BE48: 11748.59 | BF48: 0.35782135 | BG48: 0.58478495 | BH48: 0.083006825 | BI48: 0.0238 | BJ48: 0.0047 | BK48: 0.0192 | BL48: 285324.5 | BM48: 17469.6 | BN48: 16.332629 | BO48: 2.2252723 | BP48: 0.13624703 | BR48: 17.37 | BS48: 2.79 | BY48: 14 | BZ48: 0.27291649 | CA48: 0.44112011 | CB48: 5 of 13 | CC48: 25.51604 | CD48: -0.35990736 | CE48: 44980 | CF48: 0.24028508 | CG48: 0.24602091 | CH48: 0.23245121 | CI48: -0.055156672 | CJ48: 0.058139535 | CK48: 0.41492441 | CL48: -0.080573913 | CM48: No
A49: Q3 FY23 | B49: Oct-Dec 2022 | C49: 44926 | D49: CANBK | E49: Canara Bank | F49: Banks | G49: Nifty Bank | H49: 6750 | I49: 44949 | J49: 12:10 | K49: During market | L49: NSE announcement | M49: 44946 | N49: 44949 | O49: 44950 | P49: 44949 | Q49: -0.003748243 | R49: 0.012854679 | S49: -0.0089769386 | T49: 0.00012949785 | U49: 0.00059943817 | V49: 0.0095512446 | W49: -0.00046994032 | X49: -0.0094217467 | Y49: 0.0016680946 | Z49: -0.0015385967 | AA49: 0.0083085123 | AB49: 0.012854679 | AC49: 0.012854679 | AD49: 0.022103778 | AE49: 0.5035461 | AF49: 1.3363146 | AG49: 320.15 | AH49: 0.0094592464 | AI49: 0.017641449 | AJ49: 0.23657783 | AK49: 0.43468519 | AL49: 0.43500672 | AM49: -0.0067835267 | AN49: 0.024424976 | AO49: -0.11151023 | AP49: -0.14368265 | AQ49: -0.1125539 | AR49: Standalone | AS49: Bank | AT49: 22231.42 | AV49: 0.08539401 | AZ49: 2881.52 | BB49: 0.06504038 | BC49: 0.12961475 | BD49: 15.88 | BE49: 8599.95 | BI49: 0.0589 | BJ49: 0.0196 | BK49: 0.0088 | BR49: 17.37 | BS49: 2.79 | BY49: 14 | BZ49: 0.28777712 | CA49: 0.54027945 | CC49: 22.161309 | CE49: 44980 | CF49: 0.35293965 | CG49: 0.35756839 | CH49: 0.31812008 | CI49: -0.11032383 | CJ49: 0.086031597 | CK49: 0.14941812 | CL49: -0.10901798 | CM49: No
A50: Q3 FY23 | B50: Oct-Dec 2022 | C50: 44926 | D50: CONCOR | E50: Container Corporation of India Limited | F50: Travel And Transport | G50: Nifty Services Sector | H50: 1250 | I50: 44949 | J50: 17:55 | K50: After close | L50: NSE announcement | M50: 44946 | N50: 44949 | O50: 44950 | P50: 44950 | Q50: -0.0082917574 | R50: -0.0067313824 | S50: -0.029319446 | T50: -0.044342586 | U50: 0.00059943817 | V50: 0.0084675473 | W50: -0.044942024 | X50: -0.052810134 | AA50: -0.014695392 | AB50: -0.029319446 | AC50: 0.029319446 | AD50: 0.019403624 | AE50: 0.24632353 | AF50: 2.9119315 | AG50: 711.55 | AH50: -0.014610165 | AI50: -0.047711456 | AJ50: -0.04374412 | AK50: 0.056260669 | AL50: 0.045013952 | AM50: -0.0019681514 | AN50: -0.045743305 | AO50: -0.10141839 | AP50: -0.13735577 | AQ50: -0.10622702 | AR50: Consolidated | AS50: Company | AT50: 2004.46 | AU50: 0.034277075 | AV50: 0.0091223053 | AW50: 430.16 | AX50: 0.21460144 | AY50: -0.023465051 | AZ50: 294.2 | BA50: 0.033695232 | BB50: -0.030546677 | BC50: 0.1467727 | BD50: 4.82 | BL50: 43354.741 | BM50: 1142.72 | BN50: 37.939952 | BO50: 3.9232362 | BP50: 0.10340646 | BQ50: 0.0053082322 | BR50: 21.57 | BS50: 4.39 | BT50: H1 FY23 | BU50: 685.97 | BV50: 116.73 | BW50: 569.24 | BX50: 1.1422363 | BY50: 0 | CE50: 44980 | CG50: 0.28644757 | CH50: 0.28661301 | CI50: 0.00057754664 | CJ50: 0.067535798 | CK50: 0.43413193
A51: Q3 FY23 | B51: Oct-Dec 2022 | C51: 44926 | D51: KEI | E51: KEI Industries Limited | F51: Miscellaneous | G51: Nifty 500 | H51: 175 | I51: 44949 | J51: 17:40 | K51: After close | L51: NSE announcement | M51: 44946 | N51: 44949 | O51: 44950 | P51: 44950 | Q51: -0.014677707 | R51: 0.0091619154 | S51: -0.011070834 | T51: -0.016586626 | U51: 0.00059943817 | V51: -0.0020043834 | W51: -0.017186064 | X51: -0.014582242 | Y51: 0.017668136 | Z51: -0.034254762 | AA51: 0.012377127 | AB51: -0.011070834 | AC51: 0.011070834 | AD51: 0.04372816 | AE51: 0.16579537 | AF51: 1.5592178 | AG51: 1539.75 | AH51: 0.071689577 | AI51: 0.042343623 | AJ51: 0.028969527 | AK51: 0.2828043 | AL51: 0.31176521 | AM51: -0.0069457191 | AN51: 0.049289342 | AO51: 0.096955287 | AP51: 0.092629285 | AQ51: 0.12375803 | AR51: Consolidated | AS51: Company | AT51: 1784.315 | AU51: 0.14097872 | AV51: 0.10959826 | AW51: 182.176 | AX51: 0.10209856 | AY51: 0.0018259033 | AZ51: 128.603 | BA51: 0.27042913 | BB51: 0.20319034 | BC51: 0.072074157 | BD51: 14.26 | BL51: 13887.005 | BM51: 427.855 | BN51: 32.45727 | BO51: 5.9247658 | BP51: 0.18254049 | BQ51: 0.067946419 | BR51: 22.66 | BS51: 4.07 | BT51: H1 FY23 | BU51: 263.944 | BV51: 26.489 | BW51: 237.455 | BX51: 1.2530276 | BY51: 3 | BZ51: 0.1716576 | CA51: -0.32802032 | CB51: 1 of 4 | CC51: 75.626592 | CD51: -0.57082199 | CN51: no option prices for this event
A52: Q3 FY23 | B52: Oct-Dec 2022 | C52: 44926 | D52: CGPOWER | E52: CG Power and Industrial Solutions Limited | G52: Nifty 500 | H52: 850 | I52: 44950 | J52: 13:05 | K52: During market | L52: NSE announcement | M52: 44949 | N52: 44950 | O52: 44951 | P52: 44950 | Q52: -0.029416467 | R52: -0.013836271 | S52: 0.0035075998 | T52: -0.039745138 | U52: -0.0074644374 | V52: -0.011423402 | W52: -0.0322807 | X52: -0.028321735 | AA52: 0.0042826552 | AB52: -0.013836271 | AC52: 0.013836271 | AD52: 0.047109208 | AE52: 0.37412587 | AF52: 0.86750932 | AG52: 312.75 | AH52: 0.013612056 | AI52: 0.2204878 | AJ52: 0.22863877 | AK52: 0.53836695 | AL52: 0.73172757 | AM52: -0.0054174902 | AN52: 0.2259053 | AO52: 0.0189747 | AP52: 0.045938748 | AQ52: 0.067216474 | AR52: Consolidated | AS52: Company | AT52: 1775.44 | AU52: 0.14469926 | AV52: 0.046672994 | AW52: 306.54 | AX52: 0.17265579 | AY52: -0.22947572 | AZ52: 227.86 | BA52: -0.58195428 | BC52: 0.12834002 | BD52: 1.49 | BL52: 47760.052 | BM52: 545.06 | BN52: 87.623477 | BO52: 35.359482 | BP52: 0.40353891 | BQ52: 0.1564226 | BR52: 22.54 | BS52: 4.05 | BT52: H1 FY23 | BU52: 409.55 | BV52: 26.66 | BW52: 382.89 | BY52: 0 | CN52: no option prices for this event
A53: Q3 FY23 | B53: Oct-Dec 2022 | C53: 44926 | D53: COLPAL | E53: Colgate Palmolive (India) Limited | F53: Personal Care | G53: Nifty FMCG | H53: 275 | I53: 44950 | J53: 13:53 | K53: During market | L53: NSE announcement | M53: 44949 | N53: 44950 | O53: 44951 | P53: 44950 | Q53: -0.0062331256 | R53: -0.021097471 | S53: -0.0055165325 | T53: -0.032847129 | U53: -0.0074644374 | V53: 0.0087568919 | W53: -0.025382692 | X53: -0.041604021 | Y53: -0.00092055957 | Z53: -0.031926569 | AA53: 0.00103978 | AB53: -0.021097471 | AC53: 0.021097471 | AD53: 0.027034279 | AE53: 0.09057072 | AF53: 2.3590703 | AG53: 1500.05 | AH53: 0.010611062 | AI53: -0.054252569 | AJ53: -0.054699562 | AK53: -0.046800534 | AL53: 0.03633977 | AM53: -0.026304437 | AN53: -0.027948132 | AO53: 0.0070631202 | AP53: 0.001963892 | AQ53: 0.023241617 | AR53: Standalone | AS53: Company | AT53: 1291.27 | AU53: 0.0087101209 | AV53: -0.06934154 | AW53: 361.45 | AX53: 0.27991822 | AY53: -0.017358598 | AZ53: 243.24 | BA53: -0.036024254 | BB53: -0.12509891 | BC53: 0.18837269 | BD53: 8.94 | BL53: 40801.36 | BM53: 1063.59 | BN53: 38.361925 | BO53: 24.709527 | BP53: 0.64411594 | BQ53: 0 | BR53: 40.15 | BS53: 10.66 | BT53: H1 FY23 | BU53: 700.29 | BV53: 36.39 | BW53: 663.9 | BX53: 1.4359327 | BY53: 3 | BZ53: 0.034476077 | CA53: 0.058064516 | CB53: 4 of 4 | CC53: 59.111823 | CD53: -0.35102788 | CE53: 44980 | CG53: 0.17964837 | CH53: 0.16690723 | CI53: -0.070922664 | CJ53: 0.043155811 | CK53: 0.48886745
A54: Q3 FY23 | B54: Oct-Dec 2022 | C54: 44926 | D54: HDFCAMC | E54: HDFC Asset Management Company Limited | G54: Nifty 500 | H54: 300 | I54: 44950 | J54: 14:49 | K54: During market | L54: NSE announcement | M54: 44949 | N54: 44950 | O54: 44951 | P54: 44950 | Q54: -0.010558069 | R54: -0.018542583 | S54: -0.015099048 | T54: -0.0441997 | U54: -0.0074644374 | V54: -0.011423402 | W54: -0.036735263 | X54: -0.032776298 | AA54: 0.0031487405 | AB54: -0.018542583 | AC54: 0.018542583 | AD54: 0.026489404 | AE54: 0.12641509 | AF54: 1.3357091 | AG54: 2022.15 | AH54: -0.060622953 | AI54: -0.073725436 | AJ54: -0.02290353 | AK54: 0.052271426 | AL54: -0.15539637 | AM54: -0.0054174902 | AN54: -0.068307946 | AO54: -0.04451798 | AP54: -0.079858328 | AQ54: -0.058580603 | AR54: Consolidated | AS54: NBFC / financial | AT54: 559.56 | AU54: 0.017992614 | AZ54: 369.16 | BA54: 0.026157054 | BC54: 0.65973265 | BD54: 17.31 | BR54: 22.54 | BS54: 4.05 | BY54: 0 | CE54: 44980 | CG54: 0.25050809 | CH54: 0.25845695 | CI54: 0.031730973 | CJ54: 0.05907763 | CK54: 0.31386809
A55: Q3 FY23 | B55: Oct-Dec 2022 | C55: 44926 | D55: INDUSTOWER | E55: Indus Towers Limited | G55: Nifty 500 | H55: 1700 | I55: 44950 | J55: 19:38 | K55: After close | L55: NSE announcement | M55: 44949 | N55: 44950 | O55: 44951 | P55: 44951 | Q55: 0.0084572762 | R55: -0.01417004 | S55: -0.07362863 | T55: -0.079341394 | U55: -0.0074644374 | V55: -0.011423402 | W55: -0.071876957 | X55: -0.067917992 | AA55: -0.036667644 | AB55: -0.07362863 | AC55: 0.07362863 | AD55: 0.093282488 | AE55: 0.1509434 | AF55: 7.3660345 | AG55: 171.45 | AH55: -0.071235103 | AI55: -0.1074961 | AJ55: -0.11828233 | AK55: -0.2278766 | AL55: -0.36664204 | AM55: -0.0054174902 | AN55: -0.10207861 | AO55: -0.096580114 | AP55: 0.095630146 | AQ55: 0.11690787 | AR55: Consolidated | AS55: Company | AT55: 6765 | AU55: -0.023443139 | AV55: -0.15082971 | AW55: 669.8 | AX55: 0.099009608 | AY55: -0.43491365 | AZ55: 0 | BA55: -1 | BB55: -1 | BC55: 0 | BD55: -2.63 | BL55: 46204.06 | BM55: 2919.9 | BN55: 15.82385 | BO55: 2.2566196 | BP55: 0.14260876 | BQ55: 0.29504906 | BR55: 22.54 | BS55: 4.05 | BT55: H1 FY23 | BU55: 2989.8 | BV55: 1484.4 | BW55: 1505.4 | BX55: 2.2161441 | BY55: 0 | CE55: 44980 | CF55: 0.299492 | CG55: 0.36449235 | CH55: 0.34414994 | CI55: -0.055810269 | CJ55: 0.083798883 | CK55: 0.87863499 | CL55: 0.10169935 | CM55: No
A56: Q3 FY23 | B56: Oct-Dec 2022 | C56: 44926 | D56: LODHA | E56: Lodha Developers Limited | G56: Nifty 500 | H56: 625 | I56: 44950 | J56: 19:08 | K56: After close | L56: NSE announcement | M56: 44949 | N56: 44950 | O56: 44951 | P56: 44951 | Q56: -0.024421766 | R56: -0.015348773 | S56: -0.010160056 | T56: -0.049930595 | U56: -0.0074644374 | V56: -0.011423402 | W56: -0.042466157 | X56: -0.038507192 | AA56: -0.010252842 | AB56: -0.010160056 | AC56: 0.010160056 | AD56: 0.022686152 | AE56: 0.37014315 | AF56: 0.54077754 | AG56: 1121.95 | AH56: 0.10005883 | AI56: 0.092506938 | AJ56: 0.11586852 | AK56: -0.0089656391 | AL56: -0.094069199 | AM56: -0.0054174902 | AN56: 0.097924428 | AO56: -0.0486033 | AP56: -0.24461005 | AQ56: -0.22333232 | AR56: Consolidated | AS56: Company | AT56: 1773.8 | AU56: -0.1386979 | AV56: 0.0047410546 | AW56: 403.75 | AX56: 0.22761867 | AY56: -0.0082609848 | AZ56: 404.54 | BA56: 0.41650618 | BC56: 0.22806404 | BD56: 8.4 | BL56: 54035.356 | BM56: 26.67 | BN56: 2026.0726 | BO56: 4.7116365 | BP56: 0.0023255023 | BQ56: 0.91100485 | BR56: 22.54 | BS56: 4.05 | BT56: H1 FY23 | BU56: 1082.79 | BV56: 47.38 | BW56: 1035.41 | BY56: 0 | CN56: no option prices for this event
A57: Q3 FY23 | B57: Oct-Dec 2022 | C57: 44926 | D57: MARUTI | E57: Maruti Suzuki India Limited | F57: Automobiles - 4 Wheelers | G57: Nifty Auto | H57: 50 | I57: 44950 | J57: 12:56 | K57: During market | L57: NSE announcement | M57: 44949 | N57: 44950 | O57: 44951 | P57: 44950 | Q57: -0.0026896372 | R57: 0.033467584 | S57: 0.0098059502 | T57: 0.040583897 | U57: -0.0074644374 | V57: 0.02081505 | W57: 0.048048334 | X57: 0.019768847 | Y57: 0.031539714 | Z57: 0.0090441833 | AA57: 0.0039087097 | AB57: 0.033467584 | AC57: 0.033467584 | AD57: 0.035760535 | AE57: 0.93621262 | AF57: 2.3704432 | AG57: 8439.8 | AH57: -0.0016088201 | AI57: 0.012652456 | AJ57: -0.030275872 | AK57: -0.035346695 | AL57: 0.052908667 | AM57: 0.010912248 | AN57: 0.0017402084 | AO57: 0.0097961089 | AP57: -0.010001025 | AQ57: 0.011276701 | AR57: Consolidated | AS57: Company | AT57: 29057.5 | AU57: 0.24960758 | AV57: -0.02955665 | AW57: 2837 | AX57: 0.097634002 | AY57: 0.030452139 | AZ57: 2391.5 | BA57: 1.2955462 | BB57: 10.254118 | BC57: 0.082302332 | BD57: 79.17 | BL57: 254881.96 | BM57: 4166.3 | BN57: 61.177054 | BO57: 4.4574667 | BP57: 0.072861742 | BQ57: 0.010284903 | BR57: 38.54 | BS57: 4.92 | BT57: H1 FY23 | BU57: 5084.1 | BV57: 3740.4 | BW57: 1343.7 | BX57: 1.6146664 | BY57: 3 | BZ57: 0.42664354 | CA57: 0.62418609 | CC57: 37.645963 | CD57: 0.62506279 | CE57: 44980 | CF57: 0.21493436 | CG57: 0.21030463 | CH57: 0.21710983 | CI57: 0.032358801 | CJ57: 0.049787507 | CK57: 0.67220847 | CL57: -0.16175335 | CM57: No
A58: Q3 FY23 | B58: Oct-Dec 2022 | C58: 44926 | D58: MOTILALOFS | E58: Motilal Oswal Financial Services Limited | F58: Finance | G58: Nifty Financial Services | H58: 775 | I58: 44950 | J58: 17:26 | K58: After close | L58: NSE announcement | M58: 44949 | N58: 44950 | O58: 44951 | P58: 44951 | Q58: 0.0033877212 | R58: -0.00041342245 | S58: -0.045357414 | T58: -0.042383115 | U58: -0.0074644374 | V58: -0.014988281 | W58: -0.034918677 | X58: -0.027394834 | Y58: 0.023318667 | Z58: -0.065701781 | AA58: -0.027986489 | AB58: -0.045357414 | AC58: 0.045357414 | AD58: 0.03446612 | AE58: 0.378 | AF58: 1.4109599 | AG58: 723.2 | AH58: -0.026321104 | AI58: 0.027856737 | AJ58: 0.040201366 | AK58: -0.096056496 | AL58: -0.25041459 | AM58: -0.0045708589 | AN58: 0.032427596 | AO58: 0.0007220738 | AP58: -0.09921294 | AQ58: -0.077935214 | AR58: Consolidated | AS58: Company | AT58: 1072.08 | AU58: 0.045972526 | AV58: -0.18770126 | AW58: 486.65 | AX58: 0.45393068 | AY58: 0.016547755 | AZ58: 226.45 | BA58: -0.049647474 | BB58: -0.55534392 | BC58: 0.21122491 | BD58: 15.45 | BL58: 10674.432 | BM58: 1078.37 | BN58: 9.898673 | BO58: 1.7874432 | BP58: 0.18057402 | BQ58: 1.3018671 | BR58: 18.68 | BS58: 3.63 | BT58: H1 FY23 | BU58: -1545.6135 | BV58: 71.22005 | BW58: -1616.8335 | BX58: -2.8594407 | BY58: 6 | BZ58: 0.19586864 | CA58: 0.23601177 | CB58: 5 of 6 | CC58: 23.736365 | CD58: -0.58297436 | CN58: no option prices for this event
A59: Q3 FY23 | B59: Oct-Dec 2022 | C59: 44926 | D59: PIDILITIND | E59: Pidilite Industries Limited | F59: Chemicals - Speciality | G59: Nifty Commodities | H59: 500 | I59: 44950 | J59: 17:04 | K59: After close | L59: NSE announcement | M59: 44949 | N59: 44950 | O59: 44951 | P59: 44951 | Q59: 0.0029135104 | R59: -0.011308931 | S59: -0.028144479 | T59: -0.0365399 | U59: -0.0074644374 | V59: -0.029672043 | W59: -0.029075462 | X59: -0.0068678563 | AA59: -0.021554348 | AB59: -0.028144479 | AC59: 0.028144479 | AD59: 0.022246941 | AE59: 0.30754717 | AF59: 2.9860004 | AG59: 2402.6 | AH59: -0.040935673 | AI59: -0.058450083 | AJ59: -0.089130682 | AK59: 0.035224164 | AL59: -0.10129423 | AM59: 0.014485151 | AN59: -0.072935234 | AO59: -0.010301041 | AP59: -0.020364532 | AQ59: 0.00091319386 | AR59: Consolidated | AS59: Company | AT59: 2997.59 | AU59: 0.051520318 | AV59: -0.0045032629 | AW59: 495.86 | AX59: 0.16541955 | AY59: -0.027173896 | AZ59: 304.17 | BA59: -0.15152445 | BB59: -0.085037902 | BC59: 0.10147152 | BD59: 5.98 | BL59: 122124.16 | BM59: 1298.89 | BN59: 94.02194 | BO59: 18.49615 | BP59: 0.19672163 | BQ59: 0.083541835 | BR59: 13.05 | BS59: 2.31 | BT59: H1 FY23 | BU59: 308.29 | BV59: 179.82 | BW59: 128.47 | BX59: 0.44936958 | BY59: 1 | CE59: 44980 | CF59: 0.24096376 | CG59: 0.25411616 | CH59: 0.21679584 | CI59: -0.14686326 | CJ59: 0.058664146 | CK59: 0.47975605 | CL59: 0.031993548 | CM59: No
A60: Q3 FY23 | B60: Oct-Dec 2022 | C60: 44926 | D60: PNBHOUSING | E60: PNB Housing Finance Limited | G60: Nifty 500 | H60: 650 | I60: 44950 | J60: 14:58 | K60: During market | L60: NSE announcement | M60: 44949 | N60: 44950 | O60: 44951 | P60: 44950 | Q60: -0.013199479 | R60: 0.048229088 | S60: -0.01186197 | T60: 0.023167639 | U60: -0.0074644374 | V60: -0.011423402 | W60: 0.030632076 | X60: 0.034591041 | AA60: 0.0011303693 | AB60: 0.048229088 | AC60: 0.048229088 | AD60: 0.067445365 | AE60: 0.81843575 | AF60: 1.131879 | AG60: 537.9 | AH60: -0.072985782 | AI60: 0.056051831 | AJ60: 0.25780428 | AK60: 0.5 | AL60: 0.11539658 | AM60: -0.0054174902 | AN60: 0.061469321 | AO60: -0.0098217534 | AP60: 0.073845035 | AQ60: 0.09512276 | AR60: Consolidated | AS60: NBFC / financial | AT60: 1796.51 | AU60: 0.20137356 | AV60: 0.066551493 | AZ60: 269.13 | BB60: 0.024749648 | BC60: 0.14980713 | BD60: 15.95 | BR60: 22.54 | BS60: 4.05 | BT60: H1 FY23 | BU60: -351.28 | BV60: 7.46 | BW60: -358.74 | BX60: -0.70596274 | BY60: 0 | CN60: no option prices for this event
A61: Q3 FY23 | B61: Oct-Dec 2022 | C61: 44926 | D61: SBICARD | E61: SBI Cards and Payment Services Limited | G61: Nifty 500 | H61: 800 | I61: 44950 | J61: 14:17 | K61: During market | L61: NSE announcement | M61: 44949 | N61: 44950 | O61: 44951 | P61: 44950 | Q61: 0.019536182 | R61: -0.028873102 | S61: -0.040134228 | T61: -0.049471148 | U61: -0.0074644374 | V61: -0.011423402 | W61: -0.042006711 | X61: -0.038047746 | AA61: -0.0014990549 | AB61: -0.028873102 | AC61: 0.028873102 | AD61: 0.044971648 | AE61: 0.37681159 | AF61: 4.2004907 | AG61: 752.45 | AH61: -0.044325903 | AI61: -0.043718625 | AJ61: -0.13056791 | AK61: -0.1419204 | AL61: -0.13546274 | AM61: -0.0054174902 | AN61: -0.038301135 | AO61: 0.031114529 | AP61: 0.03370158 | AQ61: 0.054979306 | AR61: Standalone | AS61: NBFC / financial | AT61: 3507.12 | AU61: 0.21376313 | AV61: 0.063705177 | AZ61: 509.46 | BA61: 0.32059723 | BB61: -0.030781523 | BC61: 0.14526449 | BD61: 5.39 | BL61: 70981.543 | BM61: 2119.19 | BN61: 33.494657 | BO61: 7.9584741 | BP61: 0.23760428 | BQ61: 2.0889988 | BR61: 22.54 | BS61: 4.05 | BT61: H1 FY23 | BU61: -4180.125 | BV61: 27.324 | BW61: -4207.449 | BX61: -3.6268555 | BY61: 0 | CE61: 44980 | CF61: 0.2501279 | CG61: 0.25326023 | CH61: 0.24897417 | CI61: -0.016923564 | CJ61: 0.059667427 | CK61: 0.48390056 | CL61: -0.083754647 | CM61: No
A62: Q3 FY23 | B62: Oct-Dec 2022 | C62: 44926 | D62: SONACOMS | E62: Sona BLW Precision Forgings Limited | G62: Nifty 500 | H62: 1225 | I62: 44950 | J62: 15:09 | K62: During market | L62: NSE announcement | M62: 44949 | N62: 44950 | O62: 44951 | P62: 44950 | Q62: 0.024022552 | R62: 0.035547576 | S62: 0.051779935 | T62: 0.11135006 | U62: -0.0074644374 | V62: -0.011423402 | W62: 0.1188145 | X62: 0.12277347 | AA62: 0.0051466188 | AB62: 0.035547576 | AC62: 0.035547576 | AD62: 0.046918013 | AE62: 0.82653061 | AF62: 0.97109359 | AG62: 407.95 | AH62: -0.041583461 | AI62: -0.035921068 | AJ62: -0.14547549 | AK62: -0.28767243 | AL62: -0.44823155 | AM62: -0.0054174902 | AN62: -0.030503578 | AO62: -0.0085714286 | AP62: 0.01956044 | AQ62: 0.040838165 | AR62: Consolidated | AS62: Company | AT62: 675.2644 | AU62: 0.36652258 | AV62: 0.027188386 | AW62: 176.4574 | AX62: 0.26131601 | AY62: -0.0028558556 | AZ62: 107.1013 | BB62: 0.15727638 | BC62: 0.15860647 | BD62: 1.83 | BL62: 23838.681 | BM62: 273.0454 | BN62: 87.306655 | BO62: 11.249246 | BP62: 0.12884752 | BQ62: 0.083106047 | BR62: 22.54 | BS62: 4.05 | BT62: H1 FY23 | BU62: 230.7208 | BV62: 165.819 | BW62: 64.9018 | BX62: 1.3701981 | BY62: 0 | CN62: no option prices for this event
A63: Q3 FY23 | B63: Oct-Dec 2022 | C63: 44926 | D63: SUPREMEIND | E63: Supreme Industries Limited | F63: Plastic And Plastic Products | G63: Nifty 500 | H63: 175 | I63: 44950 | J63: 13:02 | K63: During market | L63: NSE announcement | M63: 44949 | N63: 44950 | O63: 44951 | P63: 44950 | Q63: -0.0040448962 | R63: 0.019711242 | S63: 0.0066727834 | T63: 0.022339129 | U63: -0.0074644374 | V63: -0.011423402 | W63: 0.029803567 | X63: 0.033762532 | AA63: 0.0049969168 | AB63: 0.019711242 | AC63: 0.019711242 | AD63: 0.033638819 | AE63: 0.56573957 | AF63: 1.6678724 | AG63: 2361 | AH63: -0.043955376 | AI63: -0.0025137836 | AJ63: 0.12871997 | AK63: 0.24640359 | AL63: 0.04213105 | AM63: -0.0054174902 | AN63: 0.0029037066 | AO63: 0.055700555 | AP63: 0.1163311 | AQ63: 0.13760882 | AR63: Consolidated | AS63: Company | AT63: 2310.71 | AU63: 0.18795852 | AV63: 0.10740439 | AW63: 303.36 | AX63: 0.13128432 | AY63: -0.032140881 | AZ63: 210.03 | BC63: 0.090894141 | BD63: 16.53 | BR63: 22.54 | BS63: 4.05 | BT63: H1 FY23 | BU63: 369.15 | BV63: 236.85 | BW63: 132.3 | BY63: 1 | CN63: no option prices for this event
A64: Q3 FY23 | B64: Oct-Dec 2022 | C64: 44926 | D64: TVSMOTOR | E64: TVS Motor Company Limited | F64: Automobiles - 2 And 3 Wheelers | G64: Nifty Auto | H64: 175 | I64: 44950 | J64: 17:19 | K64: After close | L64: NSE announcement | M64: 44949 | N64: 44950 | O64: 44951 | P64: 44951 | Q64: 0.012166203 | R64: 0.0021900784 | S64: 0.054937236 | T64: 0.069293518 | U64: -0.0074644374 | V64: 0.02081505 | W64: 0.076757955 | X64: 0.048478467 | Y64: 0.035036937 | Z64: 0.03425658 | AA64: 0.011333028 | AB64: 0.054937236 | AC64: 0.054937236 | AD64: 0.05249784 | AE64: 0.88867377 | AF64: 3.6103792 | AG64: 969.9 | AH64: -0.032180811 | AI64: -0.066596093 | AJ64: -0.15055176 | AK64: 0.10536213 | AL64: 0.50886745 | AM64: 0.010912248 | AN64: -0.077508341 | AO64: -0.0345409 | AP64: 0.076500626 | AQ64: 0.097778352 | AR64: Consolidated | AS64: Company | AT64: 8066.13 | AU64: 0.22263181 | AV64: -0.057778749 | AW64: 1021.2 | AX64: 0.12660346 | AY64: 0.010018775 | AZ64: 300.89 | BA64: 0.21449041 | BB64: -0.22111776 | BC64: 0.037302895 | BD64: 6.33 | BL64: 46079.949 | BM64: 1216.88 | BN64: 37.867291 | BO64: 9.0889983 | BP64: 0.24002241 | BQ64: 3.5879196 | BR64: 38.54 | BS64: 4.92 | BT64: H1 FY23 | BU64: -1953.15 | BV64: 492.51 | BW64: -2445.66 | BX64: -2.8237769 | BY64: 2 | BZ64: 0.023021694 | CA64: 0.03088214 | CB64: 1 of 3 | CC64: 20.444936 | CD64: 0.85215992 | CE64: 44980 | CF64: 0.26252032 | CG64: 0.28834832 | CH64: 0.27546098 | CI64: -0.044693645 | CJ64: 0.06634591 | CK64: 0.82804254 | CL64: -0.062247648 | CM64: No
A65: Q3 FY23 | B65: Oct-Dec 2022 | C65: 44926 | D65: UNITDSPR | E65: United Spirits Limited | G65: Nifty 500 | H65: 400 | I65: 44950 | J65: 18:59 | K65: After close | L65: NSE announcement | M65: 44949 | N65: 44950 | O65: 44951 | P65: 44951 | AM65: -0.0054174902 | AR65: Consolidated | AS65: Company | AT65: 6609.8 | AU65: -0.25875835 | AV65: -0.2019752 | AW65: 223.1 | AX65: 0.033752912 | AY65: -0.024415571 | AZ65: 214.2 | BA65: -0.28504673 | BB65: -0.61272826 | BC65: 0.032406427 | BD65: 3.02 | BR65: 22.54 | BS65: 4.05 | BT65: H1 FY23 | BU65: 384.9 | BV65: 79.7 | BW65: 305.2 | BX65: 0.46979129 | BY65: 0 | CN65: no option prices for this event
A66: Q3 FY23 | B66: Oct-Dec 2022 | C66: 44926 | D66: BAJAJ-AUTO | E66: Bajaj Auto Limited | F66: Automobiles - 2 And 3 Wheelers | G66: Nifty Auto | H66: 75 | I66: 44951 | J66: 15:28 | K66: During market | L66: NSE announcement | M66: 44950 | N66: 44951 | O66: 44953 | P66: 44951 | Q66: 0.017372466 | R66: 0.0083819341 | S66: 0.059006295 | T66: 0.084760695 | U66: -0.02858096 | V66: 0.022744223 | W66: 0.11334166 | X66: 0.062016472 | Y66: 0.027303349 | Z66: 0.057457346 | AA66: 0.00067815001 | AB66: 0.0083819341 | AC66: 0.0083819341 | AD66: 0.017984538 | AE66: 0.65912519 | AF66: 1.4340376 | AG66: 3623.55 | AH66: 0.011274995 | AI66: 0.023081484 | AJ66: -0.020609222 | AK66: -0.10685104 | AL66: 0.09514167 | AM66: 0.045852403 | AN66: -0.022770919 | AO66: -0.021388201 | AP66: -0.022048644 | AQ66: -0.01417843 | AR66: Consolidated | AS66: Company | AT66: 9318.54 | AU66: 0.032908614 | AV66: -0.086660309 | AW66: 1757.29 | AX66: 0.18857997 | AY66: 0.036590035 | AZ66: 1472.7 | BA66: 0.03009065 | BB66: -0.14350021 | BC66: 0.15803978 | BD66: 52.1 | BR66: 38.86 | BS66: 4.96 | BT66: H1 FY23 | BU66: 2418.54 | BV66: 319.56 | BW66: 2098.98 | BX66: 0.83896391 | BY66: 2 | BZ66: 0.11788329 | CA66: 0.12308202 | CB66: 3 of 3 | CC66: 29.156113 | CE66: 44980 | CF66: 0.19007707 | CG66: 0.19379401 | CH66: 0.22606522 | CI66: 0.16652326 | CJ66: 0.044613194 | CK66: 0.18788016 | CL66: 0.011191953 | CM66: No
A67: Q3 FY23 | B67: Oct-Dec 2022 | C67: 44926 | D67: CIPLA | E67: Cipla Limited | F67: Pharmaceuticals | G67: Nifty Pharma | H67: 425 | I67: 44951 | J67: 14:09 | K67: During market | L67: NSE announcement | M67: 44950 | N67: 44951 | O67: 44953 | P67: 44951 | Q67: -0.00037645287 | R67: -0.02532599 | S67: 0.011591403 | T67: -0.01411104 | U67: -0.02858096 | V67: -0.016542956 | W67: 0.01446992 | X67: 0.0024319168 | Y67: -0.017369445 | Z67: 0.0032584056 | AA67: 0.0025890882 | AB67: -0.02532599 | AC67: 0.02532599 | AD67: 0.045426729 | AE67: 0.31606218 | AF67: 2.1256531 | AG67: 1062.55 | AH67: 0.0027840695 | AI67: -0.050574096 | AJ67: -0.073546081 | AK67: 0.097108931 | AL67: 0.20422735 | AM67: -0.0051625217 | AN67: -0.045411575 | AO67: -0.023824302 | AP67: -0.081594653 | AQ67: -0.073724439 | AR67: Consolidated | AS67: Company | AT67: 5810.09 | AU67: 0.060456007 | AV67: -0.0031654582 | AW67: 1407.55 | AX67: 0.24225959 | AY67: 0.017583285 | AZ67: 800.96 | BA67: 0.099313752 | BB67: 0.015287109 | BC67: 0.13785673 | BD67: 9.92 | BR67: 33.05 | BS67: 4.35 | BT67: H1 FY23 | BU67: 1133.72 | BV67: 392.38 | BW67: 741.34 | BX67: 0.76846743 | BY67: 8 | BZ67: 0.11561413 | CA67: -0.38068768 | CB67: 2 of 7 | CC67: 39.658545 | CE67: 44980 | CF67: 0.20836342 | CG67: 0.22641459 | CH67: 0.22890167 | CI67: 0.010984606 | CJ67: 0.052207511 | CK67: 0.48510242 | CL67: -0.10168025 | CM67: No
A68: Q3 FY23 | B68: Oct-Dec 2022 | C68: 44926 | D68: DIXON | E68: Dixon Technologies (India) Limited | G68: Nifty 500 | H68: 50 | I68: 44951 | J68: 16:23 | K68: After close | L68: NSE announcement | M68: 44950 | N68: 44951 | O68: 44953 | P68: 44953 | Q68: -0.0051644469 | R68: -0.032556802 | S68: -0.19085558 | T68: -0.22857683 | U68: -0.02858096 | V68: -0.034615282 | W68: -0.19999587 | X68: -0.19396155 | AA68: -0.068018313 | AB68: -0.19085558 | AC68: 0.19085558 | AD68: 0.16616624 | AE68: 0.16244745 | AF68: 34.435765 | AG68: 3495.05 | AH68: -0.014826716 | AI68: -0.059977676 | AJ68: -0.18326595 | AK68: -0.11480745 | AL68: -0.3312509 | AM68: 0.023740529 | AN68: -0.083718206 | AO68: 0.012363142 | AP68: 0.027610405 | AQ68: 0.035480619 | AR68: Consolidated | AS68: Company | AT68: 2404.72 | AU68: -0.21753193 | AW68: 111.15 | AX68: 0.046221598 | AY68: 0.012706589 | AZ68: 51.91 | BA68: 0.11923243 | BC68: 0.021586713 | BD68: 8.74 | BR68: 22.64 | BS68: 4.06 | BY68: 0 | CE68: 44980 | CF68: 0.31293631 | CG68: 0.40522156 | CH68: 0.53814867 | CI68: 0.32803562 | CJ68: 0.091478287 | CK68: 2.0863484 | CL68: 0.084660714 | CM68: No
A69: Q3 FY23 | B69: Oct-Dec 2022 | C69: 44926 | D69: DLF | E69: DLF Limited | F69: Construction | G69: Nifty Infrastructure | H69: 950 | I69: 44951 | J69: 16:42 | K69: After close | L69: NSE announcement | M69: 44950 | N69: 44951 | O69: 44953 | P69: 44953 | Q69: -0.012582871 | R69: -0.035215127 | S69: 0.011077972 | T69: -0.036720027 | U69: -0.02858096 | V69: -0.042184556 | W69: -0.0081390666 | X69: 0.0054645291 | Y69: -0.012943504 | Z69: -0.023776523 | AA69: 0.0082374663 | AB69: 0.011077972 | AC69: 0.011077972 | AD69: 0.036074421 | AE69: 0.68503937 | AF69: 1.9445245 | AG69: 369.55 | AH69: -0.011237458 | AI69: 0.035154062 | AJ69: 0.0051679587 | AK69: 0.024819745 | AL69: -0.093907074 | AM69: 0.015784371 | AN69: 0.019369691 | AO69: -0.0068829892 | AP69: -0.027812895 | AQ69: -0.019942681 | AR69: Consolidated | AS69: Company | AT69: 1494.8 | AU69: -0.035426212 | AV69: 0.14778015 | AW69: 477.2 | AX69: 0.31924003 | AY69: 0.12766102 | AZ69: 519.21 | BA69: 0.3682144 | BB69: 0.088399296 | BC69: 0.34734413 | BD69: 2.1 | BL69: 91474.712 | BM69: 1731.42 | BN69: 52.832191 | BO69: 2.5008793 | BP69: 0.047336278 | BQ69: 0.099443585 | BR69: 21.26 | BS69: 2.96 | BT69: H1 FY23 | BU69: 1027.03 | BV69: 22.09 | BW69: 1004.94 | BX69: 1.0849558 | BY69: 5 | BZ69: 0.33604918 | CA69: 0.50423072 | CB69: 4 of 5 | CC69: 30.260363 | CD69: 0.74592056 | CE69: 44980 | CF69: 0.31214748 | CG69: 0.34183189 | CH69: 0.35464108 | CI69: 0.037472169 | CJ69: 0.076802731 | CK69: 0.1442393 | CL69: -0.057713677 | CM69: No
A70: Q3 FY23 | B70: Oct-Dec 2022 | C70: 44926 | D70: DRREDDY | E70: Dr. Reddy's Laboratories Limited | F70: Pharmaceuticals | G70: Nifty Pharma | H70: 625 | I70: 44951 | J70: 16:09 | K70: After close | L70: NSE announcement | M70: 44950 | N70: 44951 | O70: 44953 | P70: 44953 | Q70: -0.019618014 | R70: -0.012180354 | S70: 0.02691058 | T70: -0.0048877877 | U70: -0.02858096 | V70: -0.016542956 | W70: 0.023693172 | X70: 0.011655169 | Y70: -0.017369445 | Z70: 0.012481658 | AA70: 0.018817172 | AB70: 0.02691058 | AC70: 0.02691058 | AD70: 0.03036218 | AE70: 0.4754998 | AF70: 4.1221585 | AG70: 4337.85 | AH70: 0.0027276615 | AI70: 0.0063566449 | AJ70: -0.0090576813 | AK70: -0.0076067809 | AL70: -0.055253673 | AM70: -0.0051625217 | AN70: 0.011519167 | AO70: 0.010280482 | AP70: 0.041052388 | AQ70: 0.048922601 | AR70: Consolidated | AS70: Company | AT70: 6789.8 | AU70: 0.27190304 | AV70: 0.072333302 | AW70: 1938.5 | AX70: 0.28550178 | AY70: 0.057770107 | AZ70: 0 | BB70: -1 | BC70: 0 | BD70: 74.91 | BL70: 72181.824 | BM70: 2400.2 | BN70: 30.073254 | BO70: 3.4744226 | BP70: 0.11553198 | BQ70: 0.083219415 | BR70: 33.05 | BS70: 4.35 | BT70: H1 FY23 | BU70: 1593.6 | BV70: 581.6 | BW70: 1012 | BX70: 0.69190691 | BY70: 8 | BZ70: 0.079492092 | CA70: -0.10116183 | CC70: 47.158089 | CD70: -0.36228854 | CE70: 44980 | CF70: 0.21624024 | CG70: 0.28376859 | CH70: 0.22486334 | CI70: -0.20758201 | CJ70: 0.063717953 | CK70: 0.42233905 | CL70: 0.22575879 | CM70: No
A71: Q3 FY23 | B71: Oct-Dec 2022 | C71: 44926 | D71: INDIANB | E71: Indian Bank | F71: Banks | G71: Nifty Bank | H71: 1000 | I71: 44951 | J71: 13:42 | K71: During market | L71: NSE announcement | M71: 44950 | N71: 44951 | O71: 44953 | P71: 44951 | Q71: 0.0078152136 | R71: 0.0068929864 | S71: -0.033544412 | T71: -0.018836212 | U71: -0.02858096 | V71: -0.058729723 | W71: 0.0097447479 | X71: 0.039893511 | Y71: 0.0016680946 | Z71: -0.020504307 | AA71: 0.0077546097 | AB71: 0.0068929864 | AC71: 0.0068929864 | AD71: 0.037566776 | AE71: 0.87614679 | AF71: 1.4237446 | AG71: 287.9 | AH71: -0.0013874436 | AI71: 0.060209906 | AJ71: 0.23113107 | AK71: 0.62931522 | AL71: 1.0288936 | AM71: 0.027675881 | AN71: 0.032534025 | AO71: 0.044094209 | AP71: -0.034708695 | AQ71: -0.026838481 | AR71: Standalone | AS71: Bank | AT71: 11834.23 | AU71: 0.19228165 | AV71: 0.10498044 | AZ71: 1395.76 | BA71: 1.0236324 | BB71: 0.13919133 | BC71: 0.11794261 | BD71: 11.21 | BE71: 5499.19 | BF71: 0.25120076 | BG71: 0.23524009 | BH71: 0.0090972905 | BI71: 0.0653 | BJ71: 0.01 | BK71: 0.008 | BR71: 17.28 | BS71: 2.82 | BY71: 14 | BZ71: 0.28932048 | CA71: 0.44112011 | CB71: 3 of 13 | CC71: 22.161309 | CN71: no option prices for this event
A72: Q3 FY23 | B72: Oct-Dec 2022 | C72: 44926 | D72: PATANJALI | E72: Patanjali Foods Limited | G72: Nifty 500 | H72: 1075 | I72: 44951 | J72: 18:21 | K72: After close | L72: NSE announcement | M72: 44950 | N72: 44951 | O72: 44953 | P72: 44953 | AM72: 0.023740529 | AR72: Standalone | AS72: Company | AT72: 7926.6402 | AU72: 0.26211125 | AV72: -0.069000998 | AW72: 368.0377 | AX72: 0.046430479 | AY72: -0.020469039 | AZ72: 269.1881 | BA72: 0.15002068 | BB72: 1.3973391 | BC72: 0.033959924 | BD72: 7.46 | BR72: 22.64 | BS72: 4.06 | BT72: H1 FY23 | BU72: -316.2362 | BV72: 97.912 | BW72: -414.1482 | BX72: -0.89447202 | BY72: 0 | CN72: no option prices for this event
A73: Q3 FY23 | B73: Oct-Dec 2022 | C73: 44926 | D73: SOLARINDS | E73: Solar Industries India Limited | F73: Chemicals - Speciality | G73: Nifty Commodities | H73: 50 | I73: 44951 | J73: 14:21 | K73: During market | L73: NSE announcement | M73: 44950 | N73: 44951 | O73: 44953 | P73: 44951 | Q73: 0.0040639459 | R73: -0.0082778631 | S73: 0.009059953 | T73: 0.0048460359 | U73: -0.02858096 | V73: -0.047542633 | W73: 0.033426996 | X73: 0.052388669 | AA73: 0.0030478141 | AB73: -0.0082778631 | AC73: 0.0082778631 | AD73: 0.0475459 | AE73: 0.52487179 | AF73: 2.0385381 | AG73: 4084.7 | AH73: -0.047633481 | AI73: 0.011953573 | AJ73: 0.024568884 | AK73: 0.49886247 | AL73: 0.7856612 | AM73: 0.041762771 | AN73: -0.029809198 | AO73: -0.046964086 | AP73: -0.073376054 | AQ73: -0.06550584 | AR73: Consolidated | AS73: Company | AT73: 1811.75 | AU73: 0.77994243 | AV73: 0.15648538 | AW73: 349.51 | AX73: 0.19291293 | AY73: 0.018067419 | AZ73: 204.58 | BA73: 1 | BB73: 0.15988207 | BC73: 0.11291845 | BD73: 22.61 | BR73: 13.21 | BS73: 2.29 | BT73: H1 FY23 | BU73: 136.57 | BV73: 207.02 | BW73: -70.45 | BX73: 0.39403907 | BY73: 1 | CN73: no option prices for this event
A74: Q3 FY23 | B74: Oct-Dec 2022 | C74: 44926 | D74: TATAELXSI | E74: Tata Elxsi Limited | F74: Computers - Software | G74: Nifty IT | H74: 125 | I74: 44951 | J74: 16:53 | K74: After close | L74: NSE announcement | M74: 44950 | N74: 44951 | O74: 44953 | P74: 44953 | Q74: 0.0065209715 | R74: -0.015174246 | S74: 0.010178561 | T74: 0.0015252858 | U74: -0.02858096 | V74: -0.010565032 | W74: 0.030106246 | X74: 0.012090318 | Y74: 0.00047142478 | Z74: 0.001053861 | AA74: 0.015582368 | AB74: 0.010178561 | AC74: 0.010178561 | AD74: 0.041684351 | AE74: 0.68854545 | AF74: 1.9305038 | AG74: 6655.45 | AH74: 0.06438664 | AI74: 0.14010038 | AJ74: -0.089454531 | AK74: -0.18799336 | AL74: -0.10430055 | AM74: 0.065479574 | AN74: 0.07462081 | AO74: -0.01398486 | AP74: -0.0227329 | AQ74: -0.014862686 | AR74: Standalone | AS74: Company | AT74: 817.7431 | AU74: 0.28694698 | AV74: 0.071506901 | AW74: 246.8583 | AX74: 0.30187757 | AY74: -0.029943204 | AZ74: 194.6786 | BA74: 0.28968161 | BB74: 0.11706165 | BC74: 0.23806817 | BD74: 31.26 | BR74: 26.59 | BS74: 8.42 | BT74: H1 FY23 | BU74: 254.2873 | BV74: 32.4509 | BW74: 221.8364 | BX74: 0.70832413 | BY74: 9 | BZ74: 0.19564731 | CA74: 0.1102467 | CB74: 2 of 10 | CC74: 26.279137 | CN74: no option prices for this event
A75: Q3 FY23 | B75: Oct-Dec 2022 | C75: 44926 | D75: TMPV | E75: Tata Motors Passenger Vehicles Limited | G75: Nifty 500 | H75: 1600 | I75: 44951 | J75: 16:36 | K75: After close | L75: NSE announcement | M75: 44950 | N75: 44951 | O75: 44953 | P75: 44953 | AM75: 0.023740529 | AR75: Consolidated | AS75: Company | AT75: 88488.59 | AU75: 0.22510674 | AV75: 0.11150694 | AW75: 10819.84 | AX75: 0.12227384 | AY75: 0.023087212 | AZ75: 2957.71 | BC75: 0.033424761 | BD75: 7.71 | BR75: 22.64 | BS75: 4.06 | BT75: H1 FY23 | BU75: 650.25 | BV75: 3401.56 | BW75: -2751.31 | BY75: 0 | CN75: no option prices for this event
A76: Q3 FY23 | B76: Oct-Dec 2022 | C76: 44926 | D76: TORNTPHARM | E76: Torrent Pharmaceuticals Limited | F76: Pharmaceuticals | G76: Nifty Pharma | H76: 125 | I76: 44951 | J76: 16:37 | K76: After close | L76: NSE announcement | M76: 44950 | N76: 44951 | O76: 44953 | P76: 44953 | Q76: -0.0081059089 | R76: -0.017606412 | S76: -0.012429741 | T76: -0.038142062 | U76: -0.02858096 | V76: -0.016542956 | W76: -0.0095611018 | X76: -0.021599106 | Y76: -0.015730131 | Z76: -0.022411931 | AA76: -0.0024088646 | AB76: -0.012429741 | AC76: 0.012429741 | AD76: 0.029227557 | AE76: 0.65714286 | AF76: 1.4519693 | AG76: 1597.6 | AH76: 0.017417609 | AI76: 0.022464 | AJ76: 0.01933261 | AK76: 0.076006062 | AL76: -0.0029955067 | AM76: -0.0051625217 | AN76: 0.027626522 | AO76: -0.0035774685 | AP76: -0.03704306 | AQ76: -0.029172846 | AR76: Consolidated | AS76: Company | AT76: 2491 | AU76: 0.1816888 | AV76: 0.087298123 | AW76: 724 | AX76: 0.29064633 | AY76: 0.03542811 | AZ76: 283 | BA76: 0.13654618 | BB76: -0.092948718 | BC76: 0.11360899 | BD76: 8.36 | BL76: 54072.37 | BM76: 770 | BN76: 70.223857 | BO76: 8.8774207 | BP76: 0.12641602 | BQ76: 0.6596618 | BR76: 33.05 | BS76: 4.35 | BT76: H1 FY23 | BU76: 1039 | BV76: 305 | BW76: 734 | BX76: 1.5600601 | BY76: 8 | BZ76: 0.079492092 | CA76: -0.38068768 | CB76: 1 of 7 | CC76: 32.159 | CD76: 1.1836455 | CE76: 44980 | CG76: 0.30519992 | CH76: 0.28403436 | CI76: -0.069349817 | CJ76: 0.070912 | CK76: 0.17528403
A77: Q3 FY23 | B77: Oct-Dec 2022 | C77: 44926 | D77: BAJFINANCE | E77: Bajaj Finance Limited | F77: Finance | G77: Nifty Financial Services | H77: 750 | I77: 44953 | J77: 16:05 | K77: After close | L77: NSE announcement | M77: 44951 | N77: 44953 | O77: 44956 | P77: 44956 | Q77: -0.01010239 | R77: -0.0060732587 | S77: 0.045324353 | T77: 0.029148704 | U77: -0.026033697 | V77: -0.042658033 | W77: 0.055182401 | X77: 0.071806737 | Y77: 0.02151708 | Z77: 0.0076316235 | AA77: 0.0016230666 | AB77: 0.045324353 | AC77: 0.045324353 | AD77: 0.051408683 | AE77: 0.85007598 | AF77: 1.9142199 | AG77: 5855.05 | AH77: -0.021704442 | AI77: -0.08994047 | AJ77: -0.17568176 | AK77: -0.064426956 | AL77: -0.20596033 | AM77: -0.0020418783 | AN77: -0.087898591 | AO77: 0.013683616 | AP77: 0.028679132 | AQ77: 0.04319841 | AR77: Consolidated | AS77: NBFC / financial | AT77: 10784.3 | AU77: 0.26389673 | AV77: 0.081848642 | AZ77: 0 | BB77: -1 | BC77: 0 | BD77: 49.2 | BL77: 353703.57 | BM77: 7796.41 | BN77: 45.367492 | BO77: 7.3622321 | BP77: 0.1622799 | BQ77: 1.3396328 | BR77: 18.29 | BS77: 3.65 | BT77: H1 FY23 | BU77: -17435.42 | BV77: 219.79 | BW77: -17655.21 | BX77: -3.2426528 | BY77: 6 | BZ77: 0.10034488 | CA77: 0.14453129 | CC77: 12.827809 | CD77: 2.5366518 | CE77: 44980 | CF77: 0.27699549 | CG77: 0.36102525 | CH77: 0.28376521 | CI77: -0.21400175 | CJ77: 0.078988055 | CK77: 0.57381275 | CL77: 0.16721301 | CM77: No
A78: Q3 FY23 | B78: Oct-Dec 2022 | C78: 44926 | D78: GODFRYPHLP | E78: Godfrey Phillips India Limited | F78: Cigarettes | G78: Nifty FMCG | H78: 275 | I78: 44953 | J78: 16:58 | K78: After close | L78: NSE announcement | M78: 44951 | N78: 44953 | O78: 44956 | P78: 44956 | Q78: 0.02387323 | R78: -0.040569341 | S78: -0.029326987 | T78: -0.046023097 | U78: -0.026033697 | V78: -0.002320274 | W78: -0.0199894 | X78: -0.043702823 | AA78: 0.0091233637 | AB78: -0.029326987 | AC78: 0.029326987 | AD78: 0.065582441 | AE78: 0.1233871 | AF78: 0.70119619 | AG78: 1924.75 | AH78: -0.0023325126 | AI78: 0.06584157 | AJ78: 0.29151849 | AK78: 0.70158688 | AL78: 0.71508131 | AM78: -0.0093800181 | AN78: 0.075221589 | AO78: -0.01819866 | AP78: -0.07404784 | AQ78: -0.059528562 | AR78: Consolidated | AS78: Company | AT78: 1112.04 | AU78: 0.28228959 | AV78: -0.066736044 | AW78: 209.75 | AX78: 0.18861732 | AY78: -0.013243782 | AZ78: 199.25 | BA78: 0.7025549 | BB78: -0.01273412 | BC78: 0.17917521 | BD78: 38.32 | BL78: 10008.7 | BM78: 564.89 | BN78: 17.717963 | BO78: 3.1970651 | BP78: 0.18044203 | BQ78: 0.01176775 | BR78: 40.54 | BS78: 10.76 | BT78: H1 FY23 | BU78: 499.22 | BV78: 37.05 | BW78: 462.17 | BX78: 1.4507149 | BY78: 1 | CN78: no option prices for this event
A79: Q3 FY23 | B79: Oct-Dec 2022 | C79: 44926 | D79: VEDL | E79: Vedanta Limited | G79: Nifty 500 | H79: 1150 | I79: 44953 | J79: 15:59 | K79: After close | L79: NSE announcement | M79: 44951 | N79: 44953 | O79: 44956 | P79: 44956 | Q79: -0.010313969 | R79: -0.019923372 | S79: 0.0067240031 | T79: -0.023513338 | U79: -0.026033697 | V79: -0.035045717 | W79: 0.0025203593 | X79: 0.011532379 | AA79: 0.00078186083 | AB79: 0.0067240031 | AC79: 0.0067240031 | AD79: 0.026583268 | AE79: 0.65294118 | AF79: 1.0940406 | AG79: 329.65 | AH79: 0.036798239 | AI79: 0.11330632 | AJ79: 0.17732143 | AK79: 0.27598219 | AL79: 0.0196412 | AM79: 0.0058829105 | AN79: 0.1074234 | AO79: -0.048617583 | AP79: -0.10733147 | AQ79: -0.092812192 | AR79: Consolidated | AS79: Company | AT79: 33691 | AU79: -0.011907206 | AV79: -0.080837016 | AW79: 7559 | AX79: 0.22436259 | AY79: -0.08959465 | AZ79: 2464 | BA79: -0.40826129 | BB79: 0.36283186 | BC79: 0.073135259 | BD79: 6.64 | BL79: 122629.8 | BM79: 16192 | BN79: 7.5734807 | BO79: 2.2609156 | BP79: 0.29853058 | BQ79: 1.0803665 | BR79: 22.51 | BS79: 4.06 | BT79: H1 FY23 | BU79: 18068 | BV79: 8030 | BW79: 10038 | BX79: 2.9006261 | BY79: 0 | CE79: 44980 | CF79: 0.34335907 | CG79: 0.40672595 | CH79: 0.35888117 | CI79: -0.11763395 | CJ79: 0.088923557 | CK79: 0.075615544 | CL79: 0.018870654 | CM79: No
A80: Q3 FY23 | B80: Oct-Dec 2022 | C80: 44926 | D80: BEL | E80: Bharat Electronics Limited | F80: Electronics - Industrial | G80: Nifty India Manufacturing | H80: 1425 | I80: 44954 | J80: 13:18 | K80: Non-trading day | L80: NSE announcement | M80: 44953 | N80: 44956 | O80: 44957 | P80: 44956 | Q80: -0.048915784 | R80: -0.056733828 | S80: 0.067453626 | T80: -0.038195987 | U80: -0.012792883 | V80: 0.0045917124 | W80: -0.025403103 | X80: -0.042787699 | AA80: -0.014316013 | AB80: -0.056733828 | AC80: 0.056733828 | AD80: 0.063096501 | AE80: 0.32773109 | AF80: 5.8765562 | AG80: 99.15 | AH80: -0.034566699 | AI80: -0.010972569 | AJ80: -0.080667594 | AK80: 0.10146269 | AL80: 0.50760264 | AM80: 0.0028630826 | AN80: -0.013835651 | AO80: -0.0052659294 | AP80: -0.0036861506 | AQ80: 0.016594506 | AR80: Consolidated | AS80: Company | AT80: 4153.12 | AU80: 0.12196453 | AV80: 0.04834675 | AW80: 863.39 | AX80: 0.20788949 | AY80: -0.016148439 | AZ80: 613.01 | BA80: 0.028781929 | BB80: -0.017202681 | BC80: 0.14760228 | BD80: 0.83 | BL80: 72476.667 | BM80: 2739.45 | BN80: 26.456649 | BO80: 5.6050679 | BP80: 0.21185857 | BQ80: 0 | BR80: 22.19 | BS80: 3.9 | BT80: H1 FY23 | BU80: -2511.6 | BV80: 221.41 | BW80: -2733.01 | BX80: -2.5385338 | BY80: 0 | CE80: 44980 | CF80: 0.33662632 | CG80: 0.40117876 | CH80: 0.42802023 | CI80: 0.066906495 | CJ80: 0.087719298 | CK80: 0.64676564 | CL80: 0.13786584 | CM80: No
A81: Q3 FY23 | B81: Oct-Dec 2022 | C81: 44926 | D81: NTPC | E81: NTPC Limited | F81: Power | G81: Nifty Energy | H81: 1500 | I81: 44954 | J81: 15:26 | K81: Non-trading day | L81: NSE announcement | M81: 44953 | N81: 44956 | O81: 44957 | P81: 44956 | Q81: 0.002411091 | R81: 0.015333734 | S81: 0.013621558 | T81: 0.031366383 | U81: -0.012792883 | V81: -0.068830972 | W81: 0.044159266 | X81: 0.10019735 | Y81: -0.020671514 | Z81: 0.052037897 | AA81: 0.0078171978 | AB81: 0.015333734 | AC81: 0.015333734 | AD81: 0.03096813 | AE81: 0.33980583 | AF81: 3.2995905 | AG81: 165.9 | AH81: -0.020950133 | AI81: 0.0042372881 | AJ81: -0.027834749 | AK81: 0.10526316 | AL81: 0.25113122 | AM81: -0.0074644037 | AN81: 0.011701692 | AO81: -0.034472685 | AP81: -0.0037978382 | AQ81: 0.016482819 | AR81: Consolidated | AS81: Company | AT81: 44601.84 | AU81: 0.3396919 | AV81: 0.0096617931 | AW81: 14477.59 | AX81: 0.32459625 | AY81: -0.0061561303 | AZ81: 4776.61 | BA81: 0.061803947 | BB81: 0.43078674 | BC81: 0.10709446 | BD81: 4.93 | BL81: 160867.76 | BM81: 16981.3 | BN81: 9.4732297 | BO81: 1.1364109 | BP81: 0.11996024 | BQ81: 1.5677705 | BR81: 14.51 | BS81: 2.21 | BT81: H1 FY23 | BU81: 12396.74 | BV81: 13227.68 | BW81: -830.94 | BX81: 1.703956 | BY81: 5 | BZ81: 0.19754071 | CA81: -0.17405098 | CB81: 3 of 6 | CC81: 10.263687 | CD81: -0.077014975 | CE81: 44980 | CF81: 0.21875157 | CG81: 0.2425809 | CH81: 0.22954714 | CI81: -0.053729565 | CJ81: 0.053582179 | CK81: 0.28617228 | CL81: -0.0027838828 | CM81: No
A82: Q3 FY23 | B82: Oct-Dec 2022 | C82: 44926 | D82: BAJAJFINSV | E82: Bajaj Finserv Limited | F82: Finance | G82: Nifty Financial Services | H82: 300 | I82: 44956 | J82: 12:58 | K82: During market | L82: NSE announcement | M82: 44953 | N82: 44956 | O82: 44957 | P82: 44956 | Q82: -0.00011412485 | R82: 0.022561254 | S82: -0.0010417829 | T82: 0.021405346 | U82: -0.012792883 | V82: -0.021198766 | W82: 0.03419823 | X82: 0.042604112 | Y82: 0.023318667 | Z82: -0.0019133204 | AA82: 0.0050220667 | AB82: 0.022561254 | AC82: 0.022561254 | AD82: 0.032072744 | AE82: 0.6168446 | AF82: 1.6287215 | AG82: 1314.35 | AH82: -0.038725956 | AI82: -0.1452494 | AJ82: -0.19411999 | AK82: 0.041518913 | AL82: -0.16321548 | AM82: -0.027491689 | AN82: -0.11775771 | AO82: 0.0059220083 | AP82: -0.0056240456 | AQ82: 0.014656611 | AR82: Consolidated | AS82: NBFC / financial | AT82: 21755.15 | AU82: 0.23702005 | AV82: 0.045758782 | AZ82: 1782.022 | BA82: 0.41904459 | BB82: 0.14457426 | BC82: 0.081912651 | BD82: 11.2 | BL82: 209165.66 | BM82: 5468.18 | BN82: 38.251422 | BO82: 4.9259273 | BP82: 0.12877763 | BQ82: 1.5157002 | BR82: 17.9 | BS82: 3.57 | BT82: H1 FY23 | BU82: -16627.69 | BV82: 385.04 | BW82: -17012.73 | BX82: -5.8010787 | BY82: 6 | BZ82: 0.10034488 | CA82: 0.053050806 | CB82: 2 of 6 | CC82: 12.827809 | CD82: 1.9819139 | CE82: 44980 | CF82: 0.32033422 | CG82: 0.37816531 | CH82: 0.33767432 | CI82: -0.1070722 | CJ82: 0.082702498 | CK82: 0.27280015 | CL82: 0.0276048 | CM82: No
A83: Q3 FY23 | B83: Oct-Dec 2022 | C83: 44926 | D83: BAJAJHLDNG | E83: Bajaj Holdings & Investment Limited | F83: Finance | G83: Nifty Financial Services | H83: 75 | I83: 44956 | J83: 16:06 | K83: After close | L83: NSE announcement | M83: 44953 | N83: 44956 | O83: 44957 | P83: 44957 | Q83: 0.02827092 | R83: 0.015834039 | S83: -0.019096441 | T83: 0.025008518 | U83: -0.012792883 | V83: -0.021198766 | W83: 0.037801402 | X83: 0.046207284 | Y83: 0.02151708 | Z83: 0.0034914379 | AA83: -0.0078853047 | AB83: -0.019096441 | AC83: 0.019096441 | AD83: 0.025748104 | AE83: 0.34800906 | AF83: 1.0082841 | AG83: 5742.65 | AH83: 0.017893543 | AI83: -0.020969543 | AJ83: -0.12726347 | AK83: 0.1823329 | AL83: 0.13084361 | AM83: -0.027491689 | AN83: 0.0065221461 | AO83: 0.033056025 | AP83: 0.062916918 | AQ83: 0.083197575 | AR83: Consolidated | AS83: NBFC / financial | AT83: 98.41 | AU83: 0.029716438 | AV83: -0.47542644 | AZ83: 1285.65 | BA83: 0.23601177 | BB83: 0.034486921 | BC83: 13.064221 | BD83: 115.52 | BL83: 63909.952 | BM83: 4357.67 | BN83: 14.666083 | BO83: 1.4867807 | BP83: 0.10137544 | BQ83: 0 | BR83: 17.9 | BS83: 3.57 | BT83: H1 FY23 | BU83: 1452.55 | BV83: 1.05 | BW83: 1451.5 | BX83: 0.65663255 | BY83: 6 | BZ83: 0.19586864 | CA83: 0.053050806 | CB83: 3 of 6 | CC83: 21.89809 | CD83: -0.33025743 | CN83: no option prices for this event
A84: Q3 FY23 | B84: Oct-Dec 2022 | C84: 44926 | D84: BPCL | E84: Bharat Petroleum Corporation Limited | F84: Refineries | G84: Nifty Oil & Gas | H84: 1975 | I84: 44956 | J84: 17:38 | K84: After close | L84: NSE announcement | M84: 44953 | N84: 44956 | O84: 44957 | P84: 44957 | Q84: -0.029416006 | R84: -0.0043084237 | S84: 0.024321098 | T84: -0.0094033313 | U84: -0.012792883 | V84: -0.10289538 | W84: 0.0033895521 | X84: 0.093492048 | Y84: -0.014593952 | Z84: 0.0051906205 | AA84: 0.023425843 | AB84: 0.024321098 | AC84: 0.024321098 | AD84: 0.030587884 | AE84: 0.19512195 | AF84: 3.2880637 | AG84: 346.75 | AH84: 0.0020228291 | AI84: 0.063650307 | AJ84: 0.13465314 | AK84: 0.093331231 | AL84: -0.070624497 | AM84: 0.024051517 | AN84: 0.039598789 | AO84: -0.032337946 | AP84: -0.075455208 | AQ84: -0.055174551 | AR84: Consolidated | AS84: Company | AT84: 133347.51 | AU84: 0.13291908 | AV84: 0.038890281 | AW84: 4023.73 | AX84: 0.030174767 | AY84: -0.010198432 | AZ84: 1747.01 | BA84: -0.37720002 | BC84: 0.013101182 | BD84: 8.2 | BR84: 15.3 | BS84: 2.06 | BT84: H1 FY23 | BU84: -9151.21 | BV84: 4294.5 | BW84: -13445.71 | BY84: 3 | BZ84: 0.15329559 | CA84: -0.51138163 | CB84: 2 of 3 | CC84: 27.335064 | CE84: 44980 | CF84: 0.24212883 | CG84: 0.29351214 | CH84: 0.26536877 | CI84: -0.095884866 | CJ84: 0.06285206 | CK84: 0.38695785 | CL84: 0.14386668 | CM84: No
A85: Q3 FY23 | B85: Oct-Dec 2022 | C85: 44926 | D85: GAIL | E85: GAIL (India) Limited | F85: Gas | G85: Nifty Oil & Gas | H85: 3550 | I85: 44956 | J85: 13:55 | K85: During market | L85: NSE announcement | M85: 44953 | N85: 44956 | O85: 44957 | P85: 44956 | Q85: -0.017343905 | R85: -0.042360061 | S85: 0.0021063718 | T85: -0.057597594 | U85: -0.012792883 | V85: -0.10289538 | W85: -0.04480471 | X85: 0.045297786 | AA85: 0.0010085729 | AB85: -0.042360061 | AC85: 0.042360061 | AD85: 0.081190116 | AE85: 0.38509317 | AF85: 2.8438997 | AG85: 100.9 | AH85: 0.037532134 | AI85: 0.062105263 | AJ85: 0.14593981 | AK85: 0.029591837 | AL85: 0.074547391 | AM85: 0.024051517 | AN85: 0.038053746 | AO85: 0.0089332633 | AP85: 0.078822911 | AQ85: 0.099103568 | AR85: Consolidated | AS85: Company | AT85: 35939.96 | AU85: 0.3730329 | AV85: -0.072010898 | AW85: 481.91 | AX85: 0.013408752 | AY85: -0.16335052 | AZ85: 413.76 | BA85: -0.89056226 | BC85: 0.011512534 | BD85: 0.63 | BL85: 66342.759 | BM85: 10487.97 | BN85: 6.3256053 | BO85: 1.0081984 | BP85: 0.1593837 | BQ85: 0.19756097 | BR85: 15.3 | BS85: 2.06 | BT85: H1 FY23 | BU85: -392.25 | BV85: 3952.36 | BW85: -4344.61 | BY85: 1 | CE85: 44980 | CF85: 0.27097805 | CG85: 0.33478676 | CH85: 0.33799616 | CI85: 0.009586412 | CJ85: 0.073366834 | CK85: 0.57737343 | CL85: 0.00051713265 | CM85: No
A86: Q3 FY23 | B86: Oct-Dec 2022 | C86: 44926 | D86: LAURUSLABS | E86: Laurus Labs Limited | G86: Nifty 500 | H86: 850 | I86: 44956 | J86: 11:54 | K86: During market | L86: NSE announcement | M86: 44953 | N86: 44956 | O86: 44957 | P86: 44956 | Q86: -0.0010227937 | R86: -0.00014626298 | S86: -0.033645407 | T86: -0.034814463 | U86: -0.012792883 | V86: -0.015497117 | W86: -0.02202158 | X86: -0.019317346 | AA86: 0.0019014188 | AB86: -0.00014626298 | AC86: 0.00014626298 | AD86: 0.064355712 | AE86: 0.17272727 | AF86: 2.8232224 | AG86: 342.2 | AH86: -0.035105033 | AI86: -0.086736056 | AJ86: -0.25422251 | AK86: -0.31153807 | AL86: -0.27121712 | AM86: -0.015980958 | AN86: -0.070755098 | AO86: 0.00015137754 | AP86: -0.048289434 | AQ86: -0.028008777 | AR86: Consolidated | AS86: Company | AT86: 1544.82 | AU86: 0.50163303 | AV86: -0.019715843 | AW86: 403.57 | AX86: 0.26124079 | AY86: -0.016073645 | AZ86: 230.04 | BA86: 0.49638977 | BB86: -0.011898114 | BC86: 0.14891055 | BD86: 3.78 | BL86: 18388.117 | BM86: 868.316 | BN86: 21.176757 | BO86: 4.8859216 | BP86: 0.23072095 | BQ86: 0.54539802 | BR86: 22.19 | BS86: 4 | BT86: H1 FY23 | BU86: 243.27 | BV86: 416.22 | BW86: -172.95 | BX86: 0.50253052 | BY86: 0 | CE86: 44980 | CF86: 0.3607466 | CG86: 0.37777432 | CH86: 0.40330758 | CI86: 0.067588666 | CJ86: 0.08272435 | CK86: 0.0017680765 | CL86: -0.10112557 | CM86: No
A87: Q3 FY23 | B87: Oct-Dec 2022 | C87: 44926 | D87: LT | E87: Larsen & Toubro Limited | F87: Engineering | G87: Nifty India Manufacturing | H87: 175 | I87: 44956 | J87: 16:04 | K87: After close | L87: NSE announcement | M87: 44953 | N87: 44956 | O87: 44957 | P87: 44957 | Q87: -0.0068285281 | R87: -0.021737621 | S87: 0.0054427564 | T87: -0.023123392 | U87: -0.012792883 | V87: 0.0045917124 | W87: -0.010330509 | X87: -0.027715105 | AA87: 0.0033366463 | AB87: 0.0054427564 | AC87: 0.0054427564 | AD87: 0.028444318 | AE87: 0.86106489 | AF87: 2.2533495 | AG87: 2174.7 | AH87: -0.040502978 | AI87: 0.023821854 | AJ87: 0.10725287 | AK87: 0.22006227 | AL87: 0.14463919 | AM87: 0.0028630826 | AN87: 0.020958771 | AO87: 0.019252495 | AP87: -0.0071784975 | AQ87: 0.013102159 | AR87: Consolidated | AS87: Company | AT87: 46389.72 | AU87: 0.17255551 | AV87: 0.084819659 | AW87: 5209.03 | AX87: 0.11228846 | AY87: -0.0022233148 | AZ87: 2552.92 | BA87: 0.24245403 | BB87: 0.14533619 | BC87: 0.05503202 | BD87: 18.17 | BL87: 305588.84 | BM87: 9606.47 | BN87: 31.810732 | BO87: 3.7342108 | BP87: 0.1173884 | BQ87: 1.5524761 | BR87: 22.19 | BS87: 3.9 | BT87: H1 FY23 | BU87: 629.281 | BV87: 1666.88 | BW87: -1037.599 | BX87: 0.16008003 | BY87: 1 | CE87: 44980 | CF87: 0.22100206 | CG87: 0.28565227 | CH87: 0.24047601 | CI87: -0.15815124 | CJ87: 0.060906915 | CK87: 0.08936188 | CL87: 0.36224141 | CM87: No
A88: Q3 FY23 | B88: Oct-Dec 2022 | C88: 44926 | D88: MAZDOCK | E88: Mazagon Dock Shipbuilders Limited | G88: Nifty 500 | H88: 225 | I88: 44956 | J88: 15:19 | K88: During market | L88: NSE announcement | M88: 44953 | N88: 44956 | O88: 44957 | P88: 44956 | Q88: -0.022898178 | R88: 0.058378978 | S88: 0.039305601 | T88: 0.074786401 | U88: -0.012792883 | V88: -0.015497117 | W88: 0.087579285 | X88: 0.090283518 | AA88: 0.0036053526 | AB88: 0.058378978 | AC88: 0.058378978 | AD88: 0.083755113 | AE88: 0.68211921 | AF88: 0.79058403 | AG88: 738.05 | AH88: -0.031366888 | AI88: -0.1018558 | AJ88: 0.17383698 | AK88: 1.7239343 | AL88: 1.8667702 | AM88: -0.015980958 | AN88: -0.085874838 | AO88: -0.066624645 | AP88: -0.092908919 | AQ88: -0.072628262 | AR88: Consolidated | AS88: Company | AT88: 1815.91 | AU88: 0.16966828 | AV88: 0.06670152 | AW88: 295.73 | AX88: 0.16285499 | AY88: 0.032768031 | AZ88: 0 | BC88: 0 | BD88: 17.56 | BL88: 14885.73 | BM88: 159.01 | BN88: 93.615058 | BO88: 3.4584359 | BP88: 0.036943158 | BQ88: 0 | BR88: 22.19 | BS88: 4 | BT88: H1 FY23 | BU88: 229.63 | BV88: 18.07 | BW88: 211.56 | BY88: 0 | CN88: no option prices for this event
A89: Q3 FY23 | B89: Oct-Dec 2022 | C89: 44926 | D89: NAM-INDIA | E89: Nippon Life India Asset Management Limited | G89: Nifty 500 | H89: 625 | I89: 44956 | J89: 16:03 | K89: After close | L89: NSE announcement | M89: 44953 | N89: 44956 | O89: 44957 | P89: 44957 | Q89: -0.002688728 | R89: -0.023641642 | S89: 0.057561597 | T89: 0.031231227 | U89: -0.012792883 | V89: -0.015497117 | W89: 0.04402411 | X89: 0.046728344 | AA89: 0.019541206 | AB89: 0.057561597 | AC89: 0.057561597 | AD89: 0.07306712 | AE89: 0.70639535 | AF89: 2.0760161 | AG89: 241.75 | AH89: -0.032419452 | AI89: -0.052889324 | AJ89: -0.098116023 | AK89: -0.15011426 | AL89: -0.27543833 | AM89: -0.015980958 | AN89: -0.036908366 | AO89: -0.11648925 | AP89: -0.11086564 | AQ89: -0.090584979 | AR89: Consolidated | AS89: NBFC / financial | AT89: 353.81 | AU89: 0.045136325 | AZ89: 0 | BC89: 0 | BD89: 3.29 | BR89: 22.19 | BS89: 4 | BY89: 0 | CN89: no option prices for this event
A90: Q3 FY23 | B90: Oct-Dec 2022 | C90: 44926 | D90: PNB | E90: Punjab National Bank | F90: Banks | G90: Nifty Bank | H90: 8000 | I90: 44956 | J90: 14:33 | K90: During market | L90: NSE announcement | M90: 44953 | N90: 44956 | O90: 44957 | P90: 44956 | Q90: -0.054003724 | R90: -0.0019685039 | S90: 0.056213018 | T90: 0.00024078942 | U90: -0.012792883 | V90: -0.02360012 | W90: 0.013033673 | X90: 0.023840909 | Y90: 0.0016124488 | Z90: -0.0013716594 | AA90: 0.0059055118 | AB90: -0.0019685039 | AC90: 0.0019685039 | AD90: 0.081692913 | AE90: 0.38554217 | AF90: 1.7732293 | AG90: 53.7 | AH90: -0.053744493 | AI90: -0.0092250923 | AJ90: 0.24883721 | AK90: 0.69936709 | AL90: 0.41315789 | AM90: -0.028274945 | AN90: 0.019049853 | AO90: -0.042016807 | AP90: -0.097105509 | AQ90: -0.076824852 | AR90: Standalone | AS90: Bank | AT90: 22384.44 | AU90: 0.15828936 | AV90: 0.11066874 | AZ90: 628.88 | BA90: -0.44187863 | BB90: 0.52911713 | BC90: 0.028094516 | BD90: 0.57 | BE90: 9179.36 | BF90: 0.17635239 | BG90: 0.12599506 | BH90: 0.40547778 | BI90: 0.0976 | BJ90: 0.033 | BK90: 0.0017 | BL90: 59129.07 | BM90: 2048.06 | BN90: 28.87077 | BO90: 0.59873422 | BP90: 0.020738422 | BR90: 16.58 | BS90: 2.75 | BY90: 14 | BZ90: 0.28932048 | CA90: 0.61249873 | CB90: 12 of 13 | CC90: 21.800207 | CD90: 0.32433472 | CE90: 44980 | CF90: 0.48097558 | CG90: 0.57272468 | CH90: 0.52966423 | CI90: -0.075185252 | CJ90: 0.125 | CK90: 0.015748031 | CL90: 0.1762963 | CM90: No
A91: Q3 FY23 | B91: Oct-Dec 2022 | C91: 44926 | D91: RECLTD | E91: REC Limited | F91: Financial Institution | G91: Nifty 500 | H91: 1575 | I91: 44956 | J91: 18:36 | K91: After close | L91: NSE announcement | M91: 44953 | N91: 44956 | O91: 44957 | P91: 44957 | Q91: -0.04439834 | R91: 0.0069474598 | S91: 0.050021561 | T91: 0.012570681 | U91: -0.012792883 | V91: -0.015497117 | W91: 0.025363564 | X91: 0.028067798 | AA91: 0.0017248814 | AB91: 0.050021561 | AC91: 0.050021561 | AD91: 0.069857697 | AE91: 0.95679012 | AF91: 1.3623266 | AG91: 120.5 | AH91: -0.025869038 | AI91: 0.062141913 | AJ91: 0.24870466 | AK91: 0.25422847 | AL91: 0.24306899 | AM91: -0.015980958 | AN91: 0.07812287 | AO91: -0.0094455852 | AP91: -0.061190965 | AQ91: -0.040910308 | AR91: Consolidated | AS91: Company | AT91: 9781.76 | AU91: -0.025434764 | AV91: -0.017500018 | AW91: 9736.59 | AX91: 0.99538222 | AY91: 0.1015698 | AZ91: 0 | BC91: 0 | BD91: 11.07 | BL91: 31730.349 | BM91: 0 | BO91: 0.58982642 | BP91: 0 | BQ91: 2.164506 | BR91: 22.19 | BS91: 4 | BT91: H1 FY23 | BU91: -5875.69 | BV91: -0.05 | BW91: -5875.64 | BY91: 1 | CE91: 44980 | CF91: 0.25912204 | CG91: 0.2930359 | CH91: 0.25208999 | CI91: -0.13973 | CJ91: 0.062446167 | CK91: 0.80103493 | CL91: 0.24428469 | CM91: No
A92: Q3 FY23 | B92: Oct-Dec 2022 | C92: 44926 | D92: SRF | E92: SRF Limited | F92: Textiles - Synthetic | G92: Nifty India Consumption | H92: 200 | I92: 44956 | J92: 15:10 | K92: During market | L92: NSE announcement | M92: 44953 | N92: 44956 | O92: 44957 | P92: 44956 | Q92: 0.0012920807 | R92: 0.0095255971 | S92: 0.014432463 | T92: 0.02525014 | U92: -0.012792883 | V92: -0.0056790158 | W92: 0.038043024 | X92: 0.030929156 | AA92: 0.0083994181 | AB92: 0.0095255971 | AC92: 0.0095255971 | AD92: 0.052508094 | AE92: 0.61930295 | AF92: 1.4639748 | AG92: 2128.35 | AH92: -0.018967504 | AI92: -0.084580645 | AJ92: -0.14847266 | AK92: -0.10702973 | AL92: -0.10184834 | AM92: -0.023171763 | AN92: -0.061408882 | AO92: 0.010057504 | AP92: -0.006368989 | AQ92: 0.013911668 | AR92: Consolidated | AS92: Company | AT92: 3469.66 | AU92: 0.036997851 | AV92: -0.069242284 | AW92: 833.52 | AX92: 0.24023103 | AY92: -0.0232012 | AZ92: 0 | BC92: 0 | BD92: 17.24 | BR92: 37.9 | BS92: 8.14 | BT92: H1 FY23 | BU92: 1220.1 | BV92: 1267.12 | BW92: -47.02 | BY92: 0 | CE92: 44980 | CF92: 0.30165591 | CG92: 0.34041068 | CH92: 0.34471234 | CI92: 0.012636692 | CJ92: 0.074483275 | CK92: 0.12788907 | CL92: -0.030496855 | CM92: No
A93: Q3 FY23 | B93: Oct-Dec 2022 | C93: 44926 | D93: TECHM | E93: Tech Mahindra Limited | F93: Computers - Software | G93: Nifty IT | H93: 600 | I93: 44956 | J93: 15:45 | K93: After close | L93: NSE announcement | M93: 44953 | N93: 44956 | O93: 44957 | P93: 44957 | Q93: -0.020025686 | R93: 0.0058246772 | S93: -0.02036483 | T93: -0.034565839 | U93: -0.012792883 | V93: -0.0099816887 | W93: -0.021772955 | X93: -0.02458415 | Y93: 0.0015252858 | Z93: -0.036091124 | AA93: -0.010713252 | AB93: -0.02036483 | AC93: 0.02036483 | AD93: 0.031657176 | AE93: 0.5777439 | AF93: 3.1343305 | AG93: 1051.15 | AH93: 0.0026708637 | AI93: 0.041206478 | AJ93: -0.022958591 | AK93: 0.033325141 | AL93: -0.30532333 | AM93: 0.049156227 | AN93: -0.0079497487 | AO93: -0.012364532 | AP93: 0.083990148 | AQ93: 0.1042708 | AR93: Consolidated | AS93: Company | AT93: 13734.56 | AU93: 0.19944373 | AV93: 0.046087776 | AW93: 2134.9704 | AX93: 0.15544512 | AY93: -0.024392067 | AZ93: 1296.5704 | BA93: -0.052543736 | BB93: 0.0086753035 | BC93: 0.094402031 | BD93: 14.7 | BR93: 26.56 | BS93: 8.4 | BT93: H1 FY23 | BU93: 3170.9304 | BV93: 430.5 | BW93: 2740.4304 | BX93: 1.3119419 | BY93: 9 | BZ93: 0.19564731 | CA93: 0.13375796 | CB93: 9 of 10 | CC93: 26.279137 | CE93: 44980 | CF93: 0.23827356 | CG93: 0.32679171 | CH93: 0.25331243 | CI93: -0.22485049 | CJ93: 0.069666044 | CK93: 0.29232074 | CL93: 0.15557586 | CM93: No
A94: Q3 FY23 | B94: Oct-Dec 2022 | C94: 44926 | D94: BLUESTARCO | E94: Blue Star Limited | F94: Airconditioners | G94: Nifty Consumer Durables | H94: 325 | I94: 44957 | J94: 16:31 | K94: After close | L94: NSE announcement | M94: 44956 | N94: 44957 | O94: 44958 | P94: 44958 | Q94: -0.013035909 | R94: 0.0082037819 | S94: 0.030920705 | T94: 0.026088577 | U94: 0.00068543789 | V94: 0.014471843 | W94: 0.025403139 | X94: 0.011616734 | AA94: 0.0070385288 | AB94: 0.030920705 | AC94: 0.030920705 | AD94: 0.036453883 | AE94: 0.65513393 | AF94: 2.9653514 | AG94: 1235.05 | AH94: -0.0037910869 | AI94: 0.036768101 | AJ94: 0.011134308 | AK94: 0.24144343 | AL94: 0.34091526 | AM94: -0.05961732 | AN94: 0.096385421 | AO94: 0.084652117 | AP94: 0.13402265 | AQ94: 0.14341168 | AR94: Consolidated | AS94: Company | AT94: 1788.2 | AU94: 0.18721037 | AV94: 0.13447191 | AW94: 104.71 | AX94: 0.05855609 | AY94: -0.0015878466 | AZ94: 58.41 | BA94: 0.22968421 | BB94: 0.37273796 | BC94: 0.032664132 | BD94: 6.06 | BL94: 11893.531 | BM94: 240.46 | BN94: 49.46158 | BO94: 11.377124 | BP94: 0.23001942 | BQ94: 0.69309062 | BR94: 53.18 | BS94: 10.19 | BT94: H1 FY23 | BU94: -5.52 | BV94: 176.29 | BW94: -181.81 | BX94: -0.047260274 | BY94: 0 | CN94: no option prices for this event
A95: Q3 FY23 | B95: Oct-Dec 2022 | C95: 44926 | D95: CHOLAFIN | E95: Cholamandalam Investment and Finance Company Limited | F95: Finance | G95: Nifty Financial Services | H95: 625 | I95: 44957 | J95: 18:08 | K95: After close | L95: NSE announcement | M95: 44956 | N95: 44957 | O95: 44958 | P95: 44958 | Q95: 0.0011973517 | R95: -0.005346465 | S95: 0.06061249 | T95: 0.056463377 | U95: 0.00068543789 | V95: 0.0029934052 | W95: 0.055777939 | X95: 0.053469972 | Y95: 0.02151708 | Z95: 0.034946297 | AA95: 0.034160832 | AB95: 0.06061249 | AC95: 0.06061249 | AD95: 0.061107575 | AE95: 0.43287037 | AF95: 5.3123577 | AG95: 709.9 | AH95: 0.012335116 | AI95: -0.021906861 | AJ95: -0.0092805806 | AK95: 0.04743637 | AL95: 0.10301429 | AM95: -0.050150531 | AN95: 0.028243669 | AO95: 0.061683115 | AP95: 0.022606028 | AQ95: 0.03199506 | AR95: Consolidated | AS95: NBFC / financial | AT95: 3356.13 | AU95: 0.31238269 | AV95: 0.11246536 | AZ95: 684.82 | BA95: 0.053050806 | BB95: 0.20933107 | BC95: 0.2040505 | BD95: 8.34 | BL95: 58350.23 | BM95: 1778.61 | BN95: 32.806647 | BO95: 4.5231475 | BP95: 0.1378729 | BQ95: 4.4872275 | BR95: 17.45 | BS95: 3.48 | BT95: H1 FY23 | BU95: -9885.26 | BV95: 49.32 | BW95: -9934.58 | BX95: -8.7205441 | BY95: 6 | BZ95: 0.10034488 | CA95: 0.23601177 | CB95: 4 of 6 | CC95: 12.827809 | CD95: 1.5574631 | CE95: 44980 | CF95: 0.26923488 | CG95: 0.35813947 | CH95: 0.32413621 | CI95: -0.094944177 | CJ95: 0.074183144 | CK95: 0.81706554 | CL95: 0.030255319 | CM95: No
A96: Q3 FY23 | B96: Oct-Dec 2022 | C96: 44926 | D96: COALINDIA | E96: Coal India Limited | F96: Mining | G96: Nifty Metal | H96: 1350 | I96: 44957 | J96: 18:01 | K96: After close | L96: NSE announcement | M96: 44956 | N96: 44957 | O96: 44958 | P96: 44958 | Q96: 0.01551259 | R96: -0.0044277175 | S96: -0.018679119 | T96: -0.007594247 | U96: 0.00068543789 | V96: -0.032612228 | W96: -0.0082796849 | X96: 0.025017981 | AA96: 0.01400934 | AB96: -0.018679119 | AC96: 0.018679119 | AD96: 0.06159662 | AE96: 0.46931408 | AF96: 3.3256569 | AG96: 222.4 | AH96: -0.0069211878 | AI96: -0.0035842294 | AJ96: -0.090016367 | AK96: 0.09935739 | AL96: 0.38008067 | AM96: -0.034236481 | AN96: 0.030652252 | AO96: -0.023340131 | AP96: -0.0086109223 | AQ96: 0.00077810947 | AR96: Consolidated | AS96: Company | AT96: 35169.33 | AU96: 0.23689767 | AV96: 0.17867308 | AW96: 10388.72 | AX96: 0.29539147 | AY96: 0.055340823 | AZ96: 7755.55 | BA96: 0.70137922 | BB96: 0.28327721 | BC96: 0.22052027 | BD96: 12.58 | BL96: 137059.12 | BM96: 26127.74 | BN96: 5.2457317 | BO96: 2.431727 | BP96: 0.46356298 | BQ96: 0.06589888 | BR96: 10.23 | BS96: 2.08 | BT96: H1 FY23 | BU96: 15522.1 | BV96: 5731.66 | BW96: 9790.44 | BX96: 1.0434036 | BY96: 1 | CE96: 44980 | CF96: 0.20947494 | CG96: 0.27344433 | CH96: 0.2719476 | CI96: -0.005473606 | CJ96: 0.056641493 | CK96: 0.32977802 | CL96: 0.18358949 | CM96: No
A97: Q3 FY23 | B97: Oct-Dec 2022 | C97: 44926 | D97: GODREJCP | E97: Godrej Consumer Products Limited | F97: Personal Care | G97: Nifty FMCG | H97: 500 | I97: 44957 | J97: 13:21 | K97: During market | L97: NSE announcement | M97: 44956 | N97: 44957 | O97: 44958 | P97: 44957 | Q97: -0.0036379671 | R97: 0.010455853 | S97: 0.018012592 | T97: 0.024830478 | U97: 0.00068543789 | V97: 0.010641621 | W97: 0.02414504 | X97: 0.014188857 | Y97: -0.032847129 | Z97: 0.057677607 | AA97: 0.0018256251 | AB97: 0.010455853 | AC97: 0.010455853 | AD97: 0.020413808 | AE97: 0.63414634 | AF97: 2.4232539 | AG97: 907.1 | AH97: -0.023836427 | AI97: 0.012275416 | AJ97: 0.093089112 | AK97: 0.076421028 | AL97: 0.014142769 | AM97: -0.0022987655 | AN97: 0.014574181 | AO97: 0.011831774 | AP97: -0.018984619 | AQ97: -0.0095955869 | AR97: Consolidated | AS97: Company | AT97: 3598.92 | AU97: 0.089729848 | AV97: 0.061027383 | AW97: 719.2 | AX97: 0.19983773 | AY97: -0.0065917896 | AZ97: 546.34 | BA97: 0.035519333 | BB97: 0.52243215 | BC97: 0.15180665 | BD97: 5.34 | BL97: 92760.046 | BM97: 1569.23 | BN97: 59.111823 | BO97: 7.3164823 | BP97: 0.12377359 | BQ97: 0.083727776 | BR97: 40.77 | BS97: 10.8 | BT97: H1 FY23 | BU97: 786.58 | BV97: 133.19 | BW97: 653.39 | BX97: 1.1173329 | BY97: 3 | BZ97: 0.02617366 | CA97: 0.058064516 | CB97: 3 of 4 | CC97: 52.871168 | CD97: 0.11803513 | CE97: 44980 | CF97: 0.23380267 | CG97: 0.33995657 | CH97: 0.2653973 | CI97: -0.21931999 | CJ97: 0.072419275 | CK97: 0.14437942 | CL97: 0.21030189 | CM97: No
A98: Q3 FY23 | B98: Oct-Dec 2022 | C98: 44926 | D98: INDHOTEL | E98: The Indian Hotels Company Limited | F98: Hotels | G98: Nifty 500 | H98: 1000 | I98: 44957 | J98: 16:43 | K98: After close | L98: NSE announcement | M98: 44956 | N98: 44957 | O98: 44958 | P98: 44958 | Q98: 0.016931402 | R98: 0.033299004 | S98: 0.08538206 | T98: 0.13561247 | U98: 0.00068543789 | V98: -0.0017902954 | W98: 0.13492703 | X98: 0.13740276 | AA98: 0.056478405 | AB98: 0.08538206 | AC98: 0.08538206 | AD98: 0.067275748 | AE98: 0.81481481 | AF98: 8.4755541 | AG98: 286.45 | AH98: -0.044210878 | AI98: -0.093799431 | AJ98: -0.11109387 | AK98: 0.1079095 | AL98: 0.447814 | AM98: -0.036159997 | AN98: -0.057639434 | AO98: -0.025252525 | AP98: -0.035812672 | AQ98: -0.02642364 | AR98: Consolidated | AS98: Company | AT98: 1685.8 | AU98: 0.51707133 | AV98: 0.36766698 | AW98: 597.31 | AX98: 0.35431842 | AY98: 0.073986897 | AZ98: 382.71 | BA98: 4.0349954 | BB98: 2.1483218 | BC98: 0.22701981 | BD98: 2.69 | BL98: 40687.358 | BM98: 441.81 | BN98: 92.092433 | BO98: 5.6604718 | BP98: 0.061465113 | BQ98: 0.10693547 | BR98: 21.63 | BS98: 3.92 | BT98: H1 FY23 | BU98: 654.57 | BV98: 192.09 | BW98: 462.48 | BX98: 2.2446761 | BY98: 0 | CE98: 44980 | CF98: 0.25435041 | CG98: 0.31139178 | CH98: 0.30965672 | CI98: -0.0055719407 | CJ98: 0.064505513 | CK98: 1.3236397 | CL98: 0.029441341 | CM98: No
