Workbook

Sheet Summary
A1: Summary by quarter
A2: Every number is a formula over the Events sheet. 'Rule pass' = front expiry within 14 sessions of the last close before results (the playbook's run-up rule).
A3: Quarter | B3: Period | C3: Results events | D3: After close | E3: During market | F3: Weekend / holiday | G3: Avg three-day sum % | H3: % three-day positive | I3: Avg excess vs Nifty % | J3: Avg size of reaction move % | K3: % sales up YoY | L3: % profit up YoY | M3: Avg EBITDA margin chg YoY (pts) | N3: Avg expected move % (options) | O3: Avg actual / expected move (x) | P3: Avg IV drop % | Q3: Run-up trades (rule pass) | R3: Run-up avg return % (rule pass) | S3: Run-up win rate (rule pass)
A4: Q4 FY21 | B4: Jan-Mar 2021 | C4: =COUNTIFS(Events!$A$6:$A$4467,$A4) -> 189 | D4: =COUNTIFS(Events!$A$6:$A$4467,$A4,Events!$L$6:$L$4467,"After close") -> 119 | E4: =COUNTIFS(Events!$A$6:$A$4467,$A4,Events!$L$6:$L$4467,"During market") -> 47 | F4: =COUNTIFS(Events!$A$6:$A$4467,$A4,Events!$L$6:$L$4467,"Non-trading day") -> 21 | G4: =IFERROR(AVERAGEIFS(Events!$U$6:$U$4467,Events!$A$6:$A$4467,$A4),"") -> 0.010705195 | H4: =IFERROR(COUNTIFS(Events!$A$6:$A$4467,$A4,Events!$U$6:$U$4467,">0")/COUNTIFS(Events!$A$6:$A$4467,$A4,Events!$U$6:$U$4467,"<>"),"") -> 0.53439153 | I4: =IFERROR(AVERAGEIFS(Events!$X$6:$X$4467,Events!$A$6:$A$4467,$A4),"") -> 0.0039018948 | J4: =IFERROR(AVERAGEIFS(Events!$AD$6:$AD$4467,Events!$A$6:$A$4467,$A4),"") -> 0.032426424 | K4: =IFERROR(COUNTIFS(Events!$A$6:$A$4467,$A4,Events!$AV$6:$AV$4467,">0")/COUNTIFS(Events!$A$6:$A$4467,$A4,Events!$AV$6:$AV$4467,"<>"),"") -> 0.8 | L4: =IFERROR(COUNTIFS(Events!$A$6:$A$4467,$A4,Events!$BB$6:$BB$4467,">0")/COUNTIFS(Events!$A$6:$A$4467,$A4,Events!$BB$6:$BB$4467,"<>"),"") -> 0.82142857 | M4: =IFERROR(AVERAGEIFS(Events!$AZ$6:$AZ$4467,Events!$A$6:$A$4467,$A4),"") -> 0.088731298 | N4: =IFERROR(AVERAGEIFS(Events!$CK$6:$CK$4467,Events!$A$6:$A$4467,$A4),"") -> 0.085260837 | O4: =IFERROR(AVERAGEIFS(Events!$CL$6:$CL$4467,Events!$A$6:$A$4467,$A4),"") -> 0.41877944 | P4: =IFERROR(AVERAGEIFS(Events!$CJ$6:$CJ$4467,Events!$A$6:$A$4467,$A4),"") -> -0.10430849 | Q4: =COUNTIFS(Events!$A$6:$A$4467,$A4,Events!$CN$6:$CN$4467,"Yes",Events!$CM$6:$CM$4467,"<>") -> 40 | R4: =IFERROR(AVERAGEIFS(Events!$CM$6:$CM$4467,Events!$A$6:$A$4467,$A4,Events!$CN$6:$CN$4467,"Yes"),"") -> -0.067049031 | S4: =IFERROR(COUNTIFS(Events!$A$6:$A$4467,$A4,Events!$CM$6:$CM$4467,">0",Events!$CN$6:$CN$4467,"Yes")/COUNTIFS(Events!$A$6:$A$4467,$A4,Events!$CM$6:$CM$4467,"<>",Events!$CN$6:$CN$4467,"Yes"),"") -> 0.3
A5: Q1 FY22 | B5: Apr-Jun 2021 | C5: =COUNTIFS(Events!$A$6:$A$4467,$A5) -> 191 | D5: =COUNTIFS(Events!$A$6:$A$4467,$A5,Events!$L$6:$L$4467,"After close") -> 98 | E5: =COUNTIFS(Events!$A$6:$A$4467,$A5,Events!$L$6:$L$4467,"During market") -> 71 | F5: =COUNTIFS(Events!$A$6:$A$4467,$A5,Events!$L$6:$L$4467,"Non-trading day") -> 21 | G5: =IFERROR(AVERAGEIFS(Events!$U$6:$U$4467,Events!$A$6:$A$4467,$A5),"") -> 0.0058594489 | H5: =IFERROR(COUNTIFS(Events!$A$6:$A$4467,$A5,Events!$U$6:$U$4467,">0")/COUNTIFS(Events!$A$6:$A$4467,$A5,Events!$U$6:$U$4467,"<>"),"") -> 0.57591623 | I5: =IFERROR(AVERAGEIFS(Events!$X$6:$X$4467,Events!$A$6:$A$4467,$A5),"") -> -0.0017520956 | J5: =IFERROR(AVERAGEIFS(Events!$AD$6:$AD$4467,Events!$A$6:$A$4467,$A5),"") -> 0.028354234 | K5: =IFERROR(COUNTIFS(Events!$A$6:$A$4467,$A5,Events!$AV$6:$AV$4467,">0")/COUNTIFS(Events!$A$6:$A$4467,$A5,Events!$AV$6:$AV$4467,"<>"),"") -> 0.87134503 | L5: =IFERROR(COUNTIFS(Events!$A$6:$A$4467,$A5,Events!$BB$6:$BB$4467,">0")/COUNTIFS(Events!$A$6:$A$4467,$A5,Events!$BB$6:$BB$4467,"<>"),"") -> 0.81538462 | M5: =IFERROR(AVERAGEIFS(Events!$AZ$6:$AZ$4467,Events!$A$6:$A$4467,$A5),"") -> 0.13180538 | N5: =IFERROR(AVERAGEIFS(Events!$CK$6:$CK$4467,Events!$A$6:$A$4467,$A5),"") -> 0.065773861 | O5: =IFERROR(AVERAGEIFS(Events!$CL$6:$CL$4467,Events!$A$6:$A$4467,$A5),"") -> 0.41804914 | P5: =IFERROR(AVERAGEIFS(Events!$CJ$6:$CJ$4467,Events!$A$6:$A$4467,$A5),"") -> -0.11812389 | Q5: =COUNTIFS(Events!$A$6:$A$4467,$A5,Events!$CN$6:$CN$4467,"Yes",Events!$CM$6:$CM$4467,"<>") -> 72 | R5: =IFERROR(AVERAGEIFS(Events!$CM$6:$CM$4467,Events!$A$6:$A$4467,$A5,Events!$CN$6:$CN$4467,"Yes"),"") -> -0.0046021713 | S5: =IFERROR(COUNTIFS(Events!$A$6:$A$4467,$A5,Events!$CM$6:$CM$4467,">0",Events!$CN$6:$CN$4467,"Yes")/COUNTIFS(Events!$A$6:$A$4467,$A5,Events!$CM$6:$CM$4467,"<>",Events!$CN$6:$CN$4467,"Yes"),"") -> 0.38888889
A6: Q2 FY22 | B6: Jul-Sep 2021 | C6: =COUNTIFS(Events!$A$6:$A$4467,$A6) -> 193 | D6: =COUNTIFS(Events!$A$6:$A$4467,$A6,Events!$L$6:$L$4467,"After close") -> 112 | E6: =COUNTIFS(Events!$A$6:$A$4467,$A6,Events!$L$6:$L$4467,"During market") -> 64 | F6: =COUNTIFS(Events!$A$6:$A$4467,$A6,Events!$L$6:$L$4467,"Non-trading day") -> 16 | G6: =IFERROR(AVERAGEIFS(Events!$U$6:$U$4467,Events!$A$6:$A$4467,$A6),"") -> -0.0066521881 | H6: =IFERROR(COUNTIFS(Events!$A$6:$A$4467,$A6,Events!$U$6:$U$4467,">0")/COUNTIFS(Events!$A$6:$A$4467,$A6,Events!$U$6:$U$4467,"<>"),"") -> 0.43005181 | I6: =IFERROR(AVERAGEIFS(Events!$X$6:$X$4467,Events!$A$6:$A$4467,$A6),"") -> -0.0015216204 | J6: =IFERROR(AVERAGEIFS(Events!$AD$6:$AD$4467,Events!$A$6:$A$4467,$A6),"") -> 0.032970392 | K6: =IFERROR(COUNTIFS(Events!$A$6:$A$4467,$A6,Events!$AV$6:$AV$4467,">0")/COUNTIFS(Events!$A$6:$A$4467,$A6,Events!$AV$6:$AV$4467,"<>"),"") -> 0.85142857 | L6: =IFERROR(COUNTIFS(Events!$A$6:$A$4467,$A6,Events!$BB$6:$BB$4467,">0")/COUNTIFS(Events!$A$6:$A$4467,$A6,Events!$BB$6:$BB$4467,"<>"),"") -> 0.80745342 | M6: =IFERROR(AVERAGEIFS(Events!$AZ$6:$AZ$4467,Events!$A$6:$A$4467,$A6),"") -> 0.15237023 | N6: =IFERROR(AVERAGEIFS(Events!$CK$6:$CK$4467,Events!$A$6:$A$4467,$A6),"") -> 0.087063293 | O6: =IFERROR(AVERAGEIFS(Events!$CL$6:$CL$4467,Events!$A$6:$A$4467,$A6),"") -> 0.41284431 | P6: =IFERROR(AVERAGEIFS(Events!$CJ$6:$CJ$4467,Events!$A$6:$A$4467,$A6),"") -> -0.12755009 | Q6: =COUNTIFS(Events!$A$6:$A$4467,$A6,Events!$CN$6:$CN$4467,"Yes",Events!$CM$6:$CM$4467,"<>") -> 61 | R6: =IFERROR(AVERAGEIFS(Events!$CM$6:$CM$4467,Events!$A$6:$A$4467,$A6,Events!$CN$6:$CN$4467,"Yes"),"") -> -0.035104556 | S6: =IFERROR(COUNTIFS(Events!$A$6:$A$4467,$A6,Events!$CM$6:$CM$4467,">0",Events!$CN$6:$CN$4467,"Yes")/COUNTIFS(Events!$A$6:$A$4467,$A6,Events!$CM$6:$CM$4467,"<>",Events!$CN$6:$CN$4467,"Yes"),"") -> 0.3442623
A7: Q3 FY22 | B7: Oct-Dec 2021 | C7: =COUNTIFS(Events!$A$6:$A$4467,$A7) -> 195 | D7: =COUNTIFS(Events!$A$6:$A$4467,$A7,Events!$L$6:$L$4467,"After close") -> 116 | E7: =COUNTIFS(Events!$A$6:$A$4467,$A7,Events!$L$6:$L$4467,"During market") -> 63 | F7: =COUNTIFS(Events!$A$6:$A$4467,$A7,Events!$L$6:$L$4467,"Non-trading day") -> 16 | G7: =IFERROR(AVERAGEIFS(Events!$U$6:$U$4467,Events!$A$6:$A$4467,$A7),"") -> -0.0075208755 | H7: =IFERROR(COUNTIFS(Events!$A$6:$A$4467,$A7,Events!$U$6:$U$4467,">0")/COUNTIFS(Events!$A$6:$A$4467,$A7,Events!$U$6:$U$4467,"<>"),"") -> 0.44102564 | I7: =IFERROR(AVERAGEIFS(Events!$X$6:$X$4467,Events!$A$6:$A$4467,$A7),"") -> 6.5916685e-05 | J7: =IFERROR(AVERAGEIFS(Events!$AD$6:$AD$4467,Events!$A$6:$A$4467,$A7),"") -> 0.02976176 | K7: =IFERROR(COUNTIFS(Events!$A$6:$A$4467,$A7,Events!$AV$6:$AV$4467,">0")/COUNTIFS(Events!$A$6:$A$4467,$A7,Events!$AV$6:$AV$4467,"<>"),"") -> 0.84023669 | L7: =IFERROR(COUNTIFS(Events!$A$6:$A$4467,$A7,Events!$BB$6:$BB$4467,">0")/COUNTIFS(Events!$A$6:$A$4467,$A7,Events!$BB$6:$BB$4467,"<>"),"") -> 0.63522013 | M7: =IFERROR(AVERAGEIFS(Events!$AZ$6:$AZ$4467,Events!$A$6:$A$4467,$A7),"") -> 0.029874892 | N7: =IFERROR(AVERAGEIFS(Events!$CK$6:$CK$4467,Events!$A$6:$A$4467,$A7),"") -> 0.074243253 | O7: =IFERROR(AVERAGEIFS(Events!$CL$6:$CL$4467,Events!$A$6:$A$4467,$A7),"") -> 0.39626993 | P7: =IFERROR(AVERAGEIFS(Events!$CJ$6:$CJ$4467,Events!$A$6:$A$4467,$A7),"") -> -0.071629841 | Q7: =COUNTIFS(Events!$A$6:$A$4467,$A7,Events!$CN$6:$CN$4467,"Yes",Events!$CM$6:$CM$4467,"<>") -> 64 | R7: =IFERROR(AVERAGEIFS(Events!$CM$6:$CM$4467,Events!$A$6:$A$4467,$A7,Events!$CN$6:$CN$4467,"Yes"),"") -> -0.08038067 | S7: =IFERROR(COUNTIFS(Events!$A$6:$A$4467,$A7,Events!$CM$6:$CM$4467,">0",Events!$CN$6:$CN$4467,"Yes")/COUNTIFS(Events!$A$6:$A$4467,$A7,Events!$CM$6:$CM$4467,"<>",Events!$CN$6:$CN$4467,"Yes"),"") -> 0.21875
A8: Q4 FY22 | B8: Jan-Mar 2022 | C8: =COUNTIFS(Events!$A$6:$A$4467,$A8) -> 197 | D8: =COUNTIFS(Events!$A$6:$A$4467,$A8,Events!$L$6:$L$4467,"After close") -> 132 | E8: =COUNTIFS(Events!$A$6:$A$4467,$A8,Events!$L$6:$L$4467,"During market") -> 45 | F8: =COUNTIFS(Events!$A$6:$A$4467,$A8,Events!$L$6:$L$4467,"Non-trading day") -> 19 | G8: =IFERROR(AVERAGEIFS(Events!$U$6:$U$4467,Events!$A$6:$A$4467,$A8),"") -> -0.0019315281 | H8: =IFERROR(COUNTIFS(Events!$A$6:$A$4467,$A8,Events!$U$6:$U$4467,">0")/COUNTIFS(Events!$A$6:$A$4467,$A8,Events!$U$6:$U$4467,"<>"),"") -> 0.46192893 | I8: =IFERROR(AVERAGEIFS(Events!$X$6:$X$4467,Events!$A$6:$A$4467,$A8),"") -> 0.00083488031 | J8: =IFERROR(AVERAGEIFS(Events!$AD$6:$AD$4467,Events!$A$6:$A$4467,$A8),"") -> 0.036187332 | K8: =IFERROR(COUNTIFS(Events!$A$6:$A$4467,$A8,Events!$AV$6:$AV$4467,">0")/COUNTIFS(Events!$A$6:$A$4467,$A8,Events!$AV$6:$AV$4467,"<>"),"") -> 0.87777778 | L8: =IFERROR(COUNTIFS(Events!$A$6:$A$4467,$A8,Events!$BB$6:$BB$4467,">0")/COUNTIFS(Events!$A$6:$A$4467,$A8,Events!$BB$6:$BB$4467,"<>"),"") -> 0.62130178 | M8: =IFERROR(AVERAGEIFS(Events!$AZ$6:$AZ$4467,Events!$A$6:$A$4467,$A8),"") -> -0.023466717 | N8: =IFERROR(AVERAGEIFS(Events!$CK$6:$CK$4467,Events!$A$6:$A$4467,$A8),"") -> 0.07953462 | O8: =IFERROR(AVERAGEIFS(Events!$CL$6:$CL$4467,Events!$A$6:$A$4467,$A8),"") -> 0.4518504 | P8: =IFERROR(AVERAGEIFS(Events!$CJ$6:$CJ$4467,Events!$A$6:$A$4467,$A8),"") -> -0.061597619 | Q8: =COUNTIFS(Events!$A$6:$A$4467,$A8,Events!$CN$6:$CN$4467,"Yes",Events!$CM$6:$CM$4467,"<>") -> 50 | R8: =IFERROR(AVERAGEIFS(Events!$CM$6:$CM$4467,Events!$A$6:$A$4467,$A8,Events!$CN$6:$CN$4467,"Yes"),"") -> 0.083495076 | S8: =IFERROR(COUNTIFS(Events!$A$6:$A$4467,$A8,Events!$CM$6:$CM$4467,">0",Events!$CN$6:$CN$4467,"Yes")/COUNTIFS(Events!$A$6:$A$4467,$A8,Events!$CM$6:$CM$4467,"<>",Events!$CN$6:$CN$4467,"Yes"),"") -> 0.54
A9: Q1 FY23 | B9: Apr-Jun 2022 | C9: =COUNTIFS(Events!$A$6:$A$4467,$A9) -> 197 | D9: =COUNTIFS(Events!$A$6:$A$4467,$A9,Events!$L$6:$L$4467,"After close") -> 104 | E9: =COUNTIFS(Events!$A$6:$A$4467,$A9,Events!$L$6:$L$4467,"During market") -> 72 | F9: =COUNTIFS(Events!$A$6:$A$4467,$A9,Events!$L$6:$L$4467,"Non-trading day") -> 21 | G9: =IFERROR(AVERAGEIFS(Events!$U$6:$U$4467,Events!$A$6:$A$4467,$A9),"") -> 0.0090473029 | H9: =IFERROR(COUNTIFS(Events!$A$6:$A$4467,$A9,Events!$U$6:$U$4467,">0")/COUNTIFS(Events!$A$6:$A$4467,$A9,Events!$U$6:$U$4467,"<>"),"") -> 0.55837563 | I9: =IFERROR(AVERAGEIFS(Events!$X$6:$X$4467,Events!$A$6:$A$4467,$A9),"") -> -0.0053427416 | J9: =IFERROR(AVERAGEIFS(Events!$AD$6:$AD$4467,Events!$A$6:$A$4467,$A9),"") -> 0.026505183 | K9: =IFERROR(COUNTIFS(Events!$A$6:$A$4467,$A9,Events!$AV$6:$AV$4467,">0")/COUNTIFS(Events!$A$6:$A$4467,$A9,Events!$AV$6:$AV$4467,"<>"),"") -> 0.86896552 | L9: =IFERROR(COUNTIFS(Events!$A$6:$A$4467,$A9,Events!$BB$6:$BB$4467,">0")/COUNTIFS(Events!$A$6:$A$4467,$A9,Events!$BB$6:$BB$4467,"<>"),"") -> 0.70769231 | M9: =IFERROR(AVERAGEIFS(Events!$AZ$6:$AZ$4467,Events!$A$6:$A$4467,$A9),"") -> 0.017465402 | N9: =IFERROR(AVERAGEIFS(Events!$CK$6:$CK$4467,Events!$A$6:$A$4467,$A9),"") -> 0.067476234 | O9: =IFERROR(AVERAGEIFS(Events!$CL$6:$CL$4467,Events!$A$6:$A$4467,$A9),"") -> 0.38709844 | P9: =IFERROR(AVERAGEIFS(Events!$CJ$6:$CJ$4467,Events!$A$6:$A$4467,$A9),"") -> -0.065711374 | Q9: =COUNTIFS(Events!$A$6:$A$4467,$A9,Events!$CN$6:$CN$4467,"Yes",Events!$CM$6:$CM$4467,"<>") -> 82 | R9: =IFERROR(AVERAGEIFS(Events!$CM$6:$CM$4467,Events!$A$6:$A$4467,$A9,Events!$CN$6:$CN$4467,"Yes"),"") -> -0.0088894086 | S9: =IFERROR(COUNTIFS(Events!$A$6:$A$4467,$A9,Events!$CM$6:$CM$4467,">0",Events!$CN$6:$CN$4467,"Yes")/COUNTIFS(Events!$A$6:$A$4467,$A9,Events!$CM$6:$CM$4467,"<>",Events!$CN$6:$CN$4467,"Yes"),"") -> 0.30487805
A10: Q2 FY23 | B10: Jul-Sep 2022 | C10: =COUNTIFS(Events!$A$6:$A$4467,$A10) -> 197 | D10: =COUNTIFS(Events!$A$6:$A$4467,$A10,Events!$L$6:$L$4467,"After close") -> 101 | E10: =COUNTIFS(Events!$A$6:$A$4467,$A10,Events!$L$6:$L$4467,"During market") -> 69 | F10: =COUNTIFS(Events!$A$6:$A$4467,$A10,Events!$L$6:$L$4467,"Non-trading day") -> 27 | G10: =IFERROR(AVERAGEIFS(Events!$U$6:$U$4467,Events!$A$6:$A$4467,$A10),"") -> 0.0059134515 | H10: =IFERROR(COUNTIFS(Events!$A$6:$A$4467,$A10,Events!$U$6:$U$4467,">0")/COUNTIFS(Events!$A$6:$A$4467,$A10,Events!$U$6:$U$4467,"<>"),"") -> 0.52284264 | I10: =IFERROR(AVERAGEIFS(Events!$X$6:$X$4467,Events!$A$6:$A$4467,$A10),"") -> -0.0034610825 | J10: =IFERROR(AVERAGEIFS(Events!$AD$6:$AD$4467,Events!$A$6:$A$4467,$A10),"") -> 0.027237163 | K10: =IFERROR(COUNTIFS(Events!$A$6:$A$4467,$A10,Events!$AV$6:$AV$4467,">0")/COUNTIFS(Events!$A$6:$A$4467,$A10,Events!$AV$6:$AV$4467,"<>"),"") -> 0.89142857 | L10: =IFERROR(COUNTIFS(Events!$A$6:$A$4467,$A10,Events!$BB$6:$BB$4467,">0")/COUNTIFS(Events!$A$6:$A$4467,$A10,Events!$BB$6:$BB$4467,"<>"),"") -> 0.62111801 | M10: =IFERROR(AVERAGEIFS(Events!$AZ$6:$AZ$4467,Events!$A$6:$A$4467,$A10),"") -> -0.17847309 | N10: =IFERROR(AVERAGEIFS(Events!$CK$6:$CK$4467,Events!$A$6:$A$4467,$A10),"") -> 0.060571876 | O10: =IFERROR(AVERAGEIFS(Events!$CL$6:$CL$4467,Events!$A$6:$A$4467,$A10),"") -> 0.47580877 | P10: =IFERROR(AVERAGEIFS(Events!$CJ$6:$CJ$4467,Events!$A$6:$A$4467,$A10),"") -> -0.10255836 | Q10: =COUNTIFS(Events!$A$6:$A$4467,$A10,Events!$CN$6:$CN$4467,"Yes",Events!$CM$6:$CM$4467,"<>") -> 94 | R10: =IFERROR(AVERAGEIFS(Events!$CM$6:$CM$4467,Events!$A$6:$A$4467,$A10,Events!$CN$6:$CN$4467,"Yes"),"") -> -0.074778859 | S10: =IFERROR(COUNTIFS(Events!$A$6:$A$4467,$A10,Events!$CM$6:$CM$4467,">0",Events!$CN$6:$CN$4467,"Yes")/COUNTIFS(Events!$A$6:$A$4467,$A10,Events!$CM$6:$CM$4467,"<>",Events!$CN$6:$CN$4467,"Yes"),"") -> 0.21276596
A11: Q3 FY23 | B11: Oct-Dec 2022 | C11: =COUNTIFS(Events!$A$6:$A$4467,$A11) -> 199 | D11: =COUNTIFS(Events!$A$6:$A$4467,$A11,Events!$L$6:$L$4467,"After close") -> 123 | E11: =COUNTIFS(Events!$A$6:$A$4467,$A11,Events!$L$6:$L$4467,"During market") -> 64 | F11: =COUNTIFS(Events!$A$6:$A$4467,$A11,Events!$L$6:$L$4467,"Non-trading day") -> 11 | G11: =IFERROR(AVERAGEIFS(Events!$U$6:$U$4467,Events!$A$6:$A$4467,$A11),"") -> -0.00015474327 | H11: =IFERROR(COUNTIFS(Events!$A$6:$A$4467,$A11,Events!$U$6:$U$4467,">0")/COUNTIFS(Events!$A$6:$A$4467,$A11,Events!$U$6:$U$4467,"<>"),"") -> 0.46733668 | I11: =IFERROR(AVERAGEIFS(Events!$X$6:$X$4467,Events!$A$6:$A$4467,$A11),"") -> 0.00046620672 | J11: =IFERROR(AVERAGEIFS(Events!$AD$6:$AD$4467,Events!$A$6:$A$4467,$A11),"") -> 0.027399293 | K11: =IFERROR(COUNTIFS(Events!$A$6:$A$4467,$A11,Events!$AV$6:$AV$4467,">0")/COUNTIFS(Events!$A$6:$A$4467,$A11,Events!$AV$6:$AV$4467,"<>"),"") -> 0.85795455 | L11: =IFERROR(COUNTIFS(Events!$A$6:$A$4467,$A11,Events!$BB$6:$BB$4467,">0")/COUNTIFS(Events!$A$6:$A$4467,$A11,Events!$BB$6:$BB$4467,"<>"),"") -> 0.6686747 | M11: =IFERROR(AVERAGEIFS(Events!$AZ$6:$AZ$4467,Events!$A$6:$A$4467,$A11),"") -> -0.061465212 | N11: =IFERROR(AVERAGEIFS(Events!$CK$6:$CK$4467,Events!$A$6:$A$4467,$A11),"") -> 0.063115118 | O11: =IFERROR(AVERAGEIFS(Events!$CL$6:$CL$4467,Events!$A$6:$A$4467,$A11),"") -> 0.45728979 | P11: =IFERROR(AVERAGEIFS(Events!$CJ$6:$CJ$4467,Events!$A$6:$A$4467,$A11),"") -> -0.097020331 | Q11: =COUNTIFS(Events!$A$6:$A$4467,$A11,Events!$CN$6:$CN$4467,"Yes",Events!$CM$6:$CM$4467,"<>") -> 66 | R11: =IFERROR(AVERAGEIFS(Events!$CM$6:$CM$4467,Events!$A$6:$A$4467,$A11,Events!$CN$6:$CN$4467,"Yes"),"") -> -0.082838321 | S11: =IFERROR(COUNTIFS(Events!$A$6:$A$4467,$A11,Events!$CM$6:$CM$4467,">0",Events!$CN$6:$CN$4467,"Yes")/COUNTIFS(Events!$A$6:$A$4467,$A11,Events!$CM$6:$CM$4467,"<>",Events!$CN$6:$CN$4467,"Yes"),"") -> 0.28787879
A12: Q4 FY23 | B12: Jan-Mar 2023 | C12: =COUNTIFS(Events!$A$6:$A$4467,$A12) -> 200 | D12: =COUNTIFS(Events!$A$6:$A$4467,$A12,Events!$L$6:$L$4467,"After close") -> 120 | E12: =COUNTIFS(Events!$A$6:$A$4467,$A12,Events!$L$6:$L$4467,"During market") -> 57 | F12: =COUNTIFS(Events!$A$6:$A$4467,$A12,Events!$L$6:$L$4467,"Non-trading day") -> 21 | G12: =IFERROR(AVERAGEIFS(Events!$U$6:$U$4467,Events!$A$6:$A$4467,$A12),"") -> 0.0060714588 | H12: =IFERROR(COUNTIFS(Events!$A$6:$A$4467,$A12,Events!$U$6:$U$4467,">0")/COUNTIFS(Events!$A$6:$A$4467,$A12,Events!$U$6:$U$4467,"<>"),"") -> 0.55 | I12: =IFERROR(AVERAGEIFS(Events!$X$6:$X$4467,Events!$A$6:$A$4467,$A12),"") -> 7.5573827e-05 | J12: =IFERROR(AVERAGEIFS(Events!$AD$6:$AD$4467,Events!$A$6:$A$4467,$A12),"") -> 0.02852567 | K12: =IFERROR(COUNTIFS(Events!$A$6:$A$4467,$A12,Events!$AV$6:$AV$4467,">0")/COUNTIFS(Events!$A$6:$A$4467,$A12,Events!$AV$6:$AV$4467,"<>"),"") -> 0.86170213 | L12: =IFERROR(COUNTIFS(Events!$A$6:$A$4467,$A12,Events!$BB$6:$BB$4467,">0")/COUNTIFS(Events!$A$6:$A$4467,$A12,Events!$BB$6:$BB$4467,"<>"),"") -> 0.67630058 | M12: =IFERROR(AVERAGEIFS(Events!$AZ$6:$AZ$4467,Events!$A$6:$A$4467,$A12),"") -> 0.010168081 | N12: =IFERROR(AVERAGEIFS(Events!$CK$6:$CK$4467,Events!$A$6:$A$4467,$A12),"") -> 0.057593671 | O12: =IFERROR(AVERAGEIFS(Events!$CL$6:$CL$4467,Events!$A$6:$A$4467,$A12),"") -> 0.48159234 | P12: =IFERROR(AVERAGEIFS(Events!$CJ$6:$CJ$4467,Events!$A$6:$A$4467,$A12),"") -> -0.16593494 | Q12: =COUNTIFS(Events!$A$6:$A$4467,$A12,Events!$CN$6:$CN$4467,"Yes",Events!$CM$6:$CM$4467,"<>") -> 62 | R12: =IFERROR(AVERAGEIFS(Events!$CM$6:$CM$4467,Events!$A$6:$A$4467,$A12,Events!$CN$6:$CN$4467,"Yes"),"") -> 0.043146095 | S12: =IFERROR(COUNTIFS(Events!$A$6:$A$4467,$A12,Events!$CM$6:$CM$4467,">0",Events!$CN$6:$CN$4467,"Yes")/COUNTIFS(Events!$A$6:$A$4467,$A12,Events!$CM$6:$CM$4467,"<>",Events!$CN$6:$CN$4467,"Yes"),"") -> 0.51612903
A13: Q1 FY24 | B13: Apr-Jun 2023 | C13: =COUNTIFS(Events!$A$6:$A$4467,$A13) -> 200 | D13: =COUNTIFS(Events!$A$6:$A$4467,$A13,Events!$L$6:$L$4467,"After close") -> 112 | E13: =COUNTIFS(Events!$A$6:$A$4467,$A13,Events!$L$6:$L$4467,"During market") -> 72 | F13: =COUNTIFS(Events!$A$6:$A$4467,$A13,Events!$L$6:$L$4467,"Non-trading day") -> 15 | G13: =IFERROR(AVERAGEIFS(Events!$U$6:$U$4467,Events!$A$6:$A$4467,$A13),"") -> 0.00070859285 | H13: =IFERROR(COUNTIFS(Events!$A$6:$A$4467,$A13,Events!$U$6:$U$4467,">0")/COUNTIFS(Events!$A$6:$A$4467,$A13,Events!$U$6:$U$4467,"<>"),"") -> 0.48241206 | I13: =IFERROR(AVERAGEIFS(Events!$X$6:$X$4467,Events!$A$6:$A$4467,$A13),"") -> 0.0031089281 | J13: =IFERROR(AVERAGEIFS(Events!$AD$6:$AD$4467,Events!$A$6:$A$4467,$A13),"") -> 0.025281975 | K13: =IFERROR(COUNTIFS(Events!$A$6:$A$4467,$A13,Events!$AV$6:$AV$4467,">0")/COUNTIFS(Events!$A$6:$A$4467,$A13,Events!$AV$6:$AV$4467,"<>"),"") -> 0.81456954 | L13: =IFERROR(COUNTIFS(Events!$A$6:$A$4467,$A13,Events!$BB$6:$BB$4467,">0")/COUNTIFS(Events!$A$6:$A$4467,$A13,Events!$BB$6:$BB$4467,"<>"),"") -> 0.75539568 | M13: =IFERROR(AVERAGEIFS(Events!$AZ$6:$AZ$4467,Events!$A$6:$A$4467,$A13),"") -> 0.024801064 | N13: =IFERROR(AVERAGEIFS(Events!$CK$6:$CK$4467,Events!$A$6:$A$4467,$A13),"") -> 0.063094073 | O13: =IFERROR(AVERAGEIFS(Events!$CL$6:$CL$4467,Events!$A$6:$A$4467,$A13),"") -> 0.39778691 | P13: =IFERROR(AVERAGEIFS(Events!$CJ$6:$CJ$4467,Events!$A$6:$A$4467,$A13),"") -> -0.12208439 | Q13: =COUNTIFS(Events!$A$6:$A$4467,$A13,Events!$CN$6:$CN$4467,"Yes",Events!$CM$6:$CM$4467,"<>") -> 57 | R13: =IFERROR(AVERAGEIFS(Events!$CM$6:$CM$4467,Events!$A$6:$A$4467,$A13,Events!$CN$6:$CN$4467,"Yes"),"") -> 0.06443682 | S13: =IFERROR(COUNTIFS(Events!$A$6:$A$4467,$A13,Events!$CM$6:$CM$4467,">0",Events!$CN$6:$CN$4467,"Yes")/COUNTIFS(Events!$A$6:$A$4467,$A13,Events!$CM$6:$CM$4467,"<>",Events!$CN$6:$CN$4467,"Yes"),"") -> 0.31578947
A14: Q2 FY24 | B14: Jul-Sep 2023 | C14: =COUNTIFS(Events!$A$6:$A$4467,$A14) -> 202 | D14: =COUNTIFS(Events!$A$6:$A$4467,$A14,Events!$L$6:$L$4467,"After close") -> 109 | E14: =COUNTIFS(Events!$A$6:$A$4467,$A14,Events!$L$6:$L$4467,"During market") -> 71 | F14: =COUNTIFS(Events!$A$6:$A$4467,$A14,Events!$L$6:$L$4467,"Non-trading day") -> 20 | G14: =IFERROR(AVERAGEIFS(Events!$U$6:$U$4467,Events!$A$6:$A$4467,$A14),"") -> 0.0093807369 | H14: =IFERROR(COUNTIFS(Events!$A$6:$A$4467,$A14,Events!$U$6:$U$4467,">0")/COUNTIFS(Events!$A$6:$A$4467,$A14,Events!$U$6:$U$4467,"<>"),"") -> 0.55940594 | I14: =IFERROR(AVERAGEIFS(Events!$X$6:$X$4467,Events!$A$6:$A$4467,$A14),"") -> 0.0085039222 | J14: =IFERROR(AVERAGEIFS(Events!$AD$6:$AD$4467,Events!$A$6:$A$4467,$A14),"") -> 0.023915659 | K14: =IFERROR(COUNTIFS(Events!$A$6:$A$4467,$A14,Events!$AV$6:$AV$4467,">0")/COUNTIFS(Events!$A$6:$A$4467,$A14,Events!$AV$6:$AV$4467,"<>"),"") -> 0.81967213 | L14: =IFERROR(COUNTIFS(Events!$A$6:$A$4467,$A14,Events!$BB$6:$BB$4467,">0")/COUNTIFS(Events!$A$6:$A$4467,$A14,Events!$BB$6:$BB$4467,"<>"),"") -> 0.80952381 | M14: =IFERROR(AVERAGEIFS(Events!$AZ$6:$AZ$4467,Events!$A$6:$A$4467,$A14),"") -> 0.03496705 | N14: =IFERROR(AVERAGEIFS(Events!$CK$6:$CK$4467,Events!$A$6:$A$4467,$A14),"") -> 0.054551271 | O14: =IFERROR(AVERAGEIFS(Events!$CL$6:$CL$4467,Events!$A$6:$A$4467,$A14),"") -> 0.45015937 | P14: =IFERROR(AVERAGEIFS(Events!$CJ$6:$CJ$4467,Events!$A$6:$A$4467,$A14),"") -> -0.10259982 | Q14: =COUNTIFS(Events!$A$6:$A$4467,$A14,Events!$CN$6:$CN$4467,"Yes",Events!$CM$6:$CM$4467,"<>") -> 40 | R14: =IFERROR(AVERAGEIFS(Events!$CM$6:$CM$4467,Events!$A$6:$A$4467,$A14,Events!$CN$6:$CN$4467,"Yes"),"") -> -0.015778531 | S14: =IFERROR(COUNTIFS(Events!$A$6:$A$4467,$A14,Events!$CM$6:$CM$4467,">0",Events!$CN$6:$CN$4467,"Yes")/COUNTIFS(Events!$A$6:$A$4467,$A14,Events!$CM$6:$CM$4467,"<>",Events!$CN$6:$CN$4467,"Yes"),"") -> 0.325
A15: Q3 FY24 | B15: Oct-Dec 2023 | C15: =COUNTIFS(Events!$A$6:$A$4467,$A15) -> 203 | D15: =COUNTIFS(Events!$A$6:$A$4467,$A15,Events!$L$6:$L$4467,"After close") -> 115 | E15: =COUNTIFS(Events!$A$6:$A$4467,$A15,Events!$L$6:$L$4467,"During market") -> 74 | F15: =COUNTIFS(Events!$A$6:$A$4467,$A15,Events!$L$6:$L$4467,"Non-trading day") -> 14 | G15: =IFERROR(AVERAGEIFS(Events!$U$6:$U$4467,Events!$A$6:$A$4467,$A15),"") -> 0.0017522894 | H15: =IFERROR(COUNTIFS(Events!$A$6:$A$4467,$A15,Events!$U$6:$U$4467,">0")/COUNTIFS(Events!$A$6:$A$4467,$A15,Events!$U$6:$U$4467,"<>"),"") -> 0.51231527 | I15: =IFERROR(AVERAGEIFS(Events!$X$6:$X$4467,Events!$A$6:$A$4467,$A15),"") -> 0.00037605658 | J15: =IFERROR(AVERAGEIFS(Events!$AD$6:$AD$4467,Events!$A$6:$A$4467,$A15),"") -> 0.038196439 | K15: =IFERROR(COUNTIFS(Events!$A$6:$A$4467,$A15,Events!$AV$6:$AV$4467,">0")/COUNTIFS(Events!$A$6:$A$4467,$A15,Events!$AV$6:$AV$4467,"<>"),"") -> 0.84375 | L15: =IFERROR(COUNTIFS(Events!$A$6:$A$4467,$A15,Events!$BB$6:$BB$4467,">0")/COUNTIFS(Events!$A$6:$A$4467,$A15,Events!$BB$6:$BB$4467,"<>"),"") -> 0.80110497 | M15: =IFERROR(AVERAGEIFS(Events!$AZ$6:$AZ$4467,Events!$A$6:$A$4467,$A15),"") -> 0.028238754 | N15: =IFERROR(AVERAGEIFS(Events!$CK$6:$CK$4467,Events!$A$6:$A$4467,$A15),"") -> 0.078875288 | O15: =IFERROR(AVERAGEIFS(Events!$CL$6:$CL$4467,Events!$A$6:$A$4467,$A15),"") -> 0.49375029 | P15: =IFERROR(AVERAGEIFS(Events!$CJ$6:$CJ$4467,Events!$A$6:$A$4467,$A15),"") -> -0.10010828 | Q15: =COUNTIFS(Events!$A$6:$A$4467,$A15,Events!$CN$6:$CN$4467,"Yes",Events!$CM$6:$CM$4467,"<>") -> 44 | R15: =IFERROR(AVERAGEIFS(Events!$CM$6:$CM$4467,Events!$A$6:$A$4467,$A15,Events!$CN$6:$CN$4467,"Yes"),"") -> 0.19417718 | S15: =IFERROR(COUNTIFS(Events!$A$6:$A$4467,$A15,Events!$CM$6:$CM$4467,">0",Events!$CN$6:$CN$4467,"Yes")/COUNTIFS(Events!$A$6:$A$4467,$A15,Events!$CM$6:$CM$4467,"<>",Events!$CN$6:$CN$4467,"Yes"),"") -> 0.77272727
... A25: Q1 FY27 | B25: Apr-Jun 2026 | C25: =COUNTIFS(Events!$A$6:$A$4467,$A25) -> 212 | D25: =COUNTIFS(Events!$A$6:$A$4467,$A25,Events!$L$6:$L$4467,"After close") -> 114 | E25: =COUNTIFS(Events!$A$6:$A$4467,$A25,Events!$L$6:$L$4467,"During market") -> 80 | F25: =COUNTIFS(Events!$A$6:$A$4467,$A25,Events!$L$6:$L$4467,"Non-trading day") -> 16 | G25: =IFERROR(AVERAGEIFS(Events!$U$6:$U$4467,Events!$A$6:$A$4467,$A25),"") -> 0.0035881287 | H25: =IFERROR(COUNTIFS(Events!$A$6:$A$4467,$A25,Events!$U$6:$U$4467,">0")/COUNTIFS(Events!$A$6:$A$4467,$A25,Events!$U$6:$U$4467,"<>"),"") -> 0.51415094 | I25: =IFERROR(AVERAGEIFS(Events!$X$6:$X$4467,Events!$A$6:$A$4467,$A25),"") -> 0.0011012401 | J25: =IFERROR(AVERAGEIFS(Events!$AD$6:$AD$4467,Events!$A$6:$A$4467,$A25),"") -> 0.030007701 | K25: =IFERROR(COUNTIFS(Events!$A$6:$A$4467,$A25,Events!$AV$6:$AV$4467,">0")/COUNTIFS(Events!$A$6:$A$4467,$A25,Events!$AV$6:$AV$4467,"<>"),"") -> 0.92270531 | L25: =IFERROR(COUNTIFS(Events!$A$6:$A$4467,$A25,Events!$BB$6:$BB$4467,">0")/COUNTIFS(Events!$A$6:$A$4467,$A25,Events!$BB$6:$BB$4467,"<>"),"") -> 0.78606965 | M25: =IFERROR(AVERAGEIFS(Events!$AZ$6:$AZ$4467,Events!$A$6:$A$4467,$A25),"") -> 0.004594922 | N25: =IFERROR(AVERAGEIFS(Events!$CK$6:$CK$4467,Events!$A$6:$A$4467,$A25),"") -> 0.064907961 | O25: =IFERROR(AVERAGEIFS(Events!$CL$6:$CL$4467,Events!$A$6:$A$4467,$A25),"") -> 0.46502498 | P25: =IFERROR(AVERAGEIFS(Events!$CJ$6:$CJ$4467,Events!$A$6:$A$4467,$A25),"") -> -0.14724885 | Q25: =COUNTIFS(Events!$A$6:$A$4467,$A25,Events!$CN$6:$CN$4467,"Yes",Events!$CM$6:$CM$4467,"<>") -> 111 | R25: =IFERROR(AVERAGEIFS(Events!$CM$6:$CM$4467,Events!$A$6:$A$4467,$A25,Events!$CN$6:$CN$4467,"Yes"),"") -> -0.0061018844 | S25: =IFERROR(COUNTIFS(Events!$A$6:$A$4467,$A25,Events!$CM$6:$CM$4467,">0",Events!$CN$6:$CN$4467,"Yes")/COUNTIFS(Events!$A$6:$A$4467,$A25,Events!$CM$6:$CM$4467,"<>",Events!$CN$6:$CN$4467,"Yes"),"") -> 0.33333333
A26: All quarters | C26: =COUNTIFS(Events!$A$6:$A$4467,"<>") -> 4462 | D26: =COUNTIFS(Events!$A$6:$A$4467,"<>",Events!$L$6:$L$4467,"After close") -> 2623 | E26: =COUNTIFS(Events!$A$6:$A$4467,"<>",Events!$L$6:$L$4467,"During market") -> 1419 | F26: =COUNTIFS(Events!$A$6:$A$4467,"<>",Events!$L$6:$L$4467,"Non-trading day") -> 393 | G26: =IFERROR(AVERAGEIFS(Events!$U$6:$U$4467,Events!$A$6:$A$4467,"<>"),"") -> 0.0028108158 | H26: =IFERROR(COUNTIFS(Events!$A$6:$A$4467,"<>",Events!$U$6:$U$4467,">0")/COUNTIFS(Events!$A$6:$A$4467,"<>",Events!$U$6:$U$4467,"<>"),"") -> 0.50381166 | I26: =IFERROR(AVERAGEIFS(Events!$X$6:$X$4467,Events!$A$6:$A$4467,"<>"),"") -> 0.0016344564 | J26: =IFERROR(AVERAGEIFS(Events!$AD$6:$AD$4467,Events!$A$6:$A$4467,"<>"),"") -> 0.030647861 | K26: =IFERROR(COUNTIFS(Events!$A$6:$A$4467,"<>",Events!$AV$6:$AV$4467,">0")/COUNTIFS(Events!$A$6:$A$4467,"<>",Events!$AV$6:$AV$4467,"<>"),"") -> 0.86166299 | L26: =IFERROR(COUNTIFS(Events!$A$6:$A$4467,"<>",Events!$BB$6:$BB$4467,">0")/COUNTIFS(Events!$A$6:$A$4467,"<>",Events!$BB$6:$BB$4467,"<>"),"") -> 0.72437418 | M26: =IFERROR(AVERAGEIFS(Events!$AZ$6:$AZ$4467,Events!$A$6:$A$4467,"<>"),"") -> 0.014142264 | N26: =IFERROR(AVERAGEIFS(Events!$CK$6:$CK$4467,Events!$A$6:$A$4467,"<>"),"") -> 0.067968055 | O26: =IFERROR(AVERAGEIFS(Events!$CL$6:$CL$4467,Events!$A$6:$A$4467,"<>"),"") -> 0.4615053 | P26: =IFERROR(AVERAGEIFS(Events!$CJ$6:$CJ$4467,Events!$A$6:$A$4467,"<>"),"") -> -0.11842411 | Q26: =COUNTIFS(Events!$A$6:$A$4467,"<>",Events!$CN$6:$CN$4467,"Yes",Events!$CM$6:$CM$4467,"<>") -> 1685 | R26: =IFERROR(AVERAGEIFS(Events!$CM$6:$CM$4467,Events!$A$6:$A$4467,"<>",Events!$CN$6:$CN$4467,"Yes"),"") -> 0.018684818 | S26: =IFERROR(COUNTIFS(Events!$A$6:$A$4467,"<>",Events!$CM$6:$CM$4467,">0",Events!$CN$6:$CN$4467,"Yes")/COUNTIFS(Events!$A$6:$A$4467,"<>",Events!$CM$6:$CM$4467,"<>",Events!$CN$6:$CN$4467,"Yes"),"") -> 0.39762611

Sheet By industry
A1: By industry (NSE industry labels)
A2: Formulas over the Events sheet, all 22 quarters.
A3: Industry | B3: Results events | C3: After close | D3: During market | E3: Weekend / holiday | F3: Avg three-day sum % | G3: % three-day positive | H3: Avg excess vs Nifty % | I3: Avg size of reaction move % | J3: % sales up YoY | K3: % profit up YoY | L3: Avg EBITDA margin chg YoY (pts) | M3: Avg expected move % (options) | N3: Avg actual / expected move (x) | O3: Avg IV drop % | P3: Run-up trades (rule pass) | Q3: Run-up avg return % (rule pass) | R3: Run-up win rate (rule pass)
A4: Banks | B4: =COUNTIFS(Events!$F$6:$F$4467,$A4) -> 440 | C4: =COUNTIFS(Events!$F$6:$F$4467,$A4,Events!$L$6:$L$4467,"After close") -> 137 | D4: =COUNTIFS(Events!$F$6:$F$4467,$A4,Events!$L$6:$L$4467,"During market") -> 163 | E4: =COUNTIFS(Events!$F$6:$F$4467,$A4,Events!$L$6:$L$4467,"Non-trading day") -> 140 | F4: =IFERROR(AVERAGEIFS(Events!$U$6:$U$4467,Events!$F$6:$F$4467,$A4),"") -> 0.00090985432 | G4: =IFERROR(COUNTIFS(Events!$F$6:$F$4467,$A4,Events!$U$6:$U$4467,">0")/COUNTIFS(Events!$F$6:$F$4467,$A4,Events!$U$6:$U$4467,"<>"),"") -> 0.49318182 | H4: =IFERROR(AVERAGEIFS(Events!$X$6:$X$4467,Events!$F$6:$F$4467,$A4),"") -> 0.0019649222 | I4: =IFERROR(AVERAGEIFS(Events!$AD$6:$AD$4467,Events!$F$6:$F$4467,$A4),"") -> 0.033672508 | J4: =IFERROR(COUNTIFS(Events!$F$6:$F$4467,$A4,Events!$AV$6:$AV$4467,">0")/COUNTIFS(Events!$F$6:$F$4467,$A4,Events!$AV$6:$AV$4467,"<>"),"") -> 0.85866667 | K4: =IFERROR(COUNTIFS(Events!$F$6:$F$4467,$A4,Events!$BB$6:$BB$4467,">0")/COUNTIFS(Events!$F$6:$F$4467,$A4,Events!$BB$6:$BB$4467,"<>"),"") -> 0.8021978 | L4: =IFERROR(AVERAGEIFS(Events!$AZ$6:$AZ$4467,Events!$F$6:$F$4467,$A4),"") | M4: =IFERROR(AVERAGEIFS(Events!$CK$6:$CK$4467,Events!$F$6:$F$4467,$A4),"") -> 0.069221866 | N4: =IFERROR(AVERAGEIFS(Events!$CL$6:$CL$4467,Events!$F$6:$F$4467,$A4),"") -> 0.53476369 | O4: =IFERROR(AVERAGEIFS(Events!$CJ$6:$CJ$4467,Events!$F$6:$F$4467,$A4),"") -> -0.14621293 | P4: =COUNTIFS(Events!$F$6:$F$4467,$A4,Events!$CN$6:$CN$4467,"Yes",Events!$CM$6:$CM$4467,"<>") -> 167 | Q4: =IFERROR(AVERAGEIFS(Events!$CM$6:$CM$4467,Events!$F$6:$F$4467,$A4,Events!$CN$6:$CN$4467,"Yes"),"") -> 0.065146288 | R4: =IFERROR(COUNTIFS(Events!$F$6:$F$4467,$A4,Events!$CM$6:$CM$4467,">0",Events!$CN$6:$CN$4467,"Yes")/COUNTIFS(Events!$F$6:$F$4467,$A4,Events!$CM$6:$CM$4467,"<>",Events!$CN$6:$CN$4467,"Yes"),"") -> 0.4251497
A5: Computers - Software | B5: =COUNTIFS(Events!$F$6:$F$4467,$A5) -> 294 | C5: =COUNTIFS(Events!$F$6:$F$4467,$A5,Events!$L$6:$L$4467,"After close") -> 226 | D5: =COUNTIFS(Events!$F$6:$F$4467,$A5,Events!$L$6:$L$4467,"During market") -> 43 | E5: =COUNTIFS(Events!$F$6:$F$4467,$A5,Events!$L$6:$L$4467,"Non-trading day") -> 11 | F5: =IFERROR(AVERAGEIFS(Events!$U$6:$U$4467,Events!$F$6:$F$4467,$A5),"") -> 0.0071002116 | G5: =IFERROR(COUNTIFS(Events!$F$6:$F$4467,$A5,Events!$U$6:$U$4467,">0")/COUNTIFS(Events!$F$6:$F$4467,$A5,Events!$U$6:$U$4467,"<>"),"") -> 0.53061224 | H5: =IFERROR(AVERAGEIFS(Events!$X$6:$X$4467,Events!$F$6:$F$4467,$A5),"") -> 0.0052043494 | I5: =IFERROR(AVERAGEIFS(Events!$AD$6:$AD$4467,Events!$F$6:$F$4467,$A5),"") -> 0.036030915 | J5: =IFERROR(COUNTIFS(Events!$F$6:$F$4467,$A5,Events!$AV$6:$AV$4467,">0")/COUNTIFS(Events!$F$6:$F$4467,$A5,Events!$AV$6:$AV$4467,"<>"),"") -> 0.9352518 | K5: =IFERROR(COUNTIFS(Events!$F$6:$F$4467,$A5,Events!$BB$6:$BB$4467,">0")/COUNTIFS(Events!$F$6:$F$4467,$A5,Events!$BB$6:$BB$4467,"<>"),"") -> 0.78623188 | L5: =IFERROR(AVERAGEIFS(Events!$AZ$6:$AZ$4467,Events!$F$6:$F$4467,$A5),"") -> -0.016846436 | M5: =IFERROR(AVERAGEIFS(Events!$CK$6:$CK$4467,Events!$F$6:$F$4467,$A5),"") -> 0.066751726 | N5: =IFERROR(AVERAGEIFS(Events!$CL$6:$CL$4467,Events!$F$6:$F$4467,$A5),"") -> 0.56583902 | O5: =IFERROR(AVERAGEIFS(Events!$CJ$6:$CJ$4467,Events!$F$6:$F$4467,$A5),"") -> -0.19711359 | P5: =COUNTIFS(Events!$F$6:$F$4467,$A5,Events!$CN$6:$CN$4467,"Yes",Events!$CM$6:$CM$4467,"<>") -> 159 | Q5: =IFERROR(AVERAGEIFS(Events!$CM$6:$CM$4467,Events!$F$6:$F$4467,$A5,Events!$CN$6:$CN$4467,"Yes"),"") -> 0.039035197 | R5: =IFERROR(COUNTIFS(Events!$F$6:$F$4467,$A5,Events!$CM$6:$CM$4467,">0",Events!$CN$6:$CN$4467,"Yes")/COUNTIFS(Events!$F$6:$F$4467,$A5,Events!$CM$6:$CM$4467,"<>",Events!$CN$6:$CN$4467,"Yes"),"") -> 0.45283019
A6: Pharmaceuticals | B6: =COUNTIFS(Events!$F$6:$F$4467,$A6) -> 278 | C6: =COUNTIFS(Events!$F$6:$F$4467,$A6,Events!$L$6:$L$4467,"After close") -> 138 | D6: =COUNTIFS(Events!$F$6:$F$4467,$A6,Events!$L$6:$L$4467,"During market") -> 114 | E6: =COUNTIFS(Events!$F$6:$F$4467,$A6,Events!$L$6:$L$4467,"Non-trading day") -> 25 | F6: =IFERROR(AVERAGEIFS(Events!$U$6:$U$4467,Events!$F$6:$F$4467,$A6),"") -> 0.00090850504 | G6: =IFERROR(COUNTIFS(Events!$F$6:$F$4467,$A6,Events!$U$6:$U$4467,">0")/COUNTIFS(Events!$F$6:$F$4467,$A6,Events!$U$6:$U$4467,"<>"),"") -> 0.48561151 | H6: =IFERROR(AVERAGEIFS(Events!$X$6:$X$4467,Events!$F$6:$F$4467,$A6),"") -> -6.0053869e-05 | I6: =IFERROR(AVERAGEIFS(Events!$AD$6:$AD$4467,Events!$F$6:$F$4467,$A6),"") -> 0.026632639 | J6: =IFERROR(COUNTIFS(Events!$F$6:$F$4467,$A6,Events!$AV$6:$AV$4467,">0")/COUNTIFS(Events!$F$6:$F$4467,$A6,Events!$AV$6:$AV$4467,"<>"),"") -> 0.875 | K6: =IFERROR(COUNTIFS(Events!$F$6:$F$4467,$A6,Events!$BB$6:$BB$4467,">0")/COUNTIFS(Events!$F$6:$F$4467,$A6,Events!$BB$6:$BB$4467,"<>"),"") -> 0.65 | L6: =IFERROR(AVERAGEIFS(Events!$AZ$6:$AZ$4467,Events!$F$6:$F$4467,$A6),"") -> 0.00036369514 | M6: =IFERROR(AVERAGEIFS(Events!$CK$6:$CK$4467,Events!$F$6:$F$4467,$A6),"") -> 0.065561806 | N6: =IFERROR(AVERAGEIFS(Events!$CL$6:$CL$4467,Events!$F$6:$F$4467,$A6),"") -> 0.42726417 | O6: =IFERROR(AVERAGEIFS(Events!$CJ$6:$CJ$4467,Events!$F$6:$F$4467,$A6),"") -> -0.10448922 | P6: =COUNTIFS(Events!$F$6:$F$4467,$A6,Events!$CN$6:$CN$4467,"Yes",Events!$CM$6:$CM$4467,"<>") -> 135 | Q6: =IFERROR(AVERAGEIFS(Events!$CM$6:$CM$4467,Events!$F$6:$F$4467,$A6,Events!$CN$6:$CN$4467,"Yes"),"") -> -0.00061289839 | R6: =IFERROR(COUNTIFS(Events!$F$6:$F$4467,$A6,Events!$CM$6:$CM$4467,">0",Events!$CN$6:$CN$4467,"Yes")/COUNTIFS(Events!$F$6:$F$4467,$A6,Events!$CM$6:$CM$4467,"<>",Events!$CN$6:$CN$4467,"Yes"),"") -> 0.35555556
A7: Finance | B7: =COUNTIFS(Events!$F$6:$F$4467,$A7) -> 254 | C7: =COUNTIFS(Events!$F$6:$F$4467,$A7,Events!$L$6:$L$4467,"After close") -> 164 | D7: =COUNTIFS(Events!$F$6:$F$4467,$A7,Events!$L$6:$L$4467,"During market") -> 79 | E7: =COUNTIFS(Events!$F$6:$F$4467,$A7,Events!$L$6:$L$4467,"Non-trading day") -> 9 | F7: =IFERROR(AVERAGEIFS(Events!$U$6:$U$4467,Events!$F$6:$F$4467,$A7),"") -> -0.0025566199 | G7: =IFERROR(COUNTIFS(Events!$F$6:$F$4467,$A7,Events!$U$6:$U$4467,">0")/COUNTIFS(Events!$F$6:$F$4467,$A7,Events!$U$6:$U$4467,"<>"),"") -> 0.44488189 | H7: =IFERROR(AVERAGEIFS(Events!$X$6:$X$4467,Events!$F$6:$F$4467,$A7),"") -> -0.0054202227 | I7: =IFERROR(AVERAGEIFS(Events!$AD$6:$AD$4467,Events!$F$6:$F$4467,$A7),"") -> 0.031920099 | J7: =IFERROR(COUNTIFS(Events!$F$6:$F$4467,$A7,Events!$AV$6:$AV$4467,">0")/COUNTIFS(Events!$F$6:$F$4467,$A7,Events!$AV$6:$AV$4467,"<>"),"") -> 0.86585366 | K7: =IFERROR(COUNTIFS(Events!$F$6:$F$4467,$A7,Events!$BB$6:$BB$4467,">0")/COUNTIFS(Events!$F$6:$F$4467,$A7,Events!$BB$6:$BB$4467,"<>"),"") -> 0.78423237 | L7: =IFERROR(AVERAGEIFS(Events!$AZ$6:$AZ$4467,Events!$F$6:$F$4467,$A7),"") -> 0.011105987 | M7: =IFERROR(AVERAGEIFS(Events!$CK$6:$CK$4467,Events!$F$6:$F$4467,$A7),"") -> 0.074041519 | N7: =IFERROR(AVERAGEIFS(Events!$CL$6:$CL$4467,Events!$F$6:$F$4467,$A7),"") -> 0.46707607 | O7: =IFERROR(AVERAGEIFS(Events!$CJ$6:$CJ$4467,Events!$F$6:$F$4467,$A7),"") -> -0.097511957 | P7: =COUNTIFS(Events!$F$6:$F$4467,$A7,Events!$CN$6:$CN$4467,"Yes",Events!$CM$6:$CM$4467,"<>") -> 79 | Q7: =IFERROR(AVERAGEIFS(Events!$CM$6:$CM$4467,Events!$F$6:$F$4467,$A7,Events!$CN$6:$CN$4467,"Yes"),"") -> -0.0068793716 | R7: =IFERROR(COUNTIFS(Events!$F$6:$F$4467,$A7,Events!$CM$6:$CM$4467,">0",Events!$CN$6:$CN$4467,"Yes")/COUNTIFS(Events!$F$6:$F$4467,$A7,Events!$CM$6:$CM$4467,"<>",Events!$CN$6:$CN$4467,"Yes"),"") -> 0.40506329
A8: Electrical Equipment | B8: =COUNTIFS(Events!$F$6:$F$4467,$A8) -> 242 | C8: =COUNTIFS(Events!$F$6:$F$4467,$A8,Events!$L$6:$L$4467,"After close") -> 157 | D8: =COUNTIFS(Events!$F$6:$F$4467,$A8,Events!$L$6:$L$4467,"During market") -> 75 | E8: =COUNTIFS(Events!$F$6:$F$4467,$A8,Events!$L$6:$L$4467,"Non-trading day") -> 10 | F8: =IFERROR(AVERAGEIFS(Events!$U$6:$U$4467,Events!$F$6:$F$4467,$A8),"") -> 0.006105328 | G8: =IFERROR(COUNTIFS(Events!$F$6:$F$4467,$A8,Events!$U$6:$U$4467,">0")/COUNTIFS(Events!$F$6:$F$4467,$A8,Events!$U$6:$U$4467,"<>"),"") -> 0.53305785 | H8: =IFERROR(AVERAGEIFS(Events!$X$6:$X$4467,Events!$F$6:$F$4467,$A8),"") -> 0.0040622124 | I8: =IFERROR(AVERAGEIFS(Events!$AD$6:$AD$4467,Events!$F$6:$F$4467,$A8),"") -> 0.037754795 | J8: =IFERROR(COUNTIFS(Events!$F$6:$F$4467,$A8,Events!$AV$6:$AV$4467,">0")/COUNTIFS(Events!$F$6:$F$4467,$A8,Events!$AV$6:$AV$4467,"<>"),"") -> 0.88940092 | K8: =IFERROR(COUNTIFS(Events!$F$6:$F$4467,$A8,Events!$BB$6:$BB$4467,">0")/COUNTIFS(Events!$F$6:$F$4467,$A8,Events!$BB$6:$BB$4467,"<>"),"") -> 0.76023392 | L8: =IFERROR(AVERAGEIFS(Events!$AZ$6:$AZ$4467,Events!$F$6:$F$4467,$A8),"") -> 0.035037571 | M8: =IFERROR(AVERAGEIFS(Events!$CK$6:$CK$4467,Events!$F$6:$F$4467,$A8),"") -> 0.075419324 | N8: =IFERROR(AVERAGEIFS(Events!$CL$6:$CL$4467,Events!$F$6:$F$4467,$A8),"") -> 0.48971367 | O8: =IFERROR(AVERAGEIFS(Events!$CJ$6:$CJ$4467,Events!$F$6:$F$4467,$A8),"") -> -0.14088574 | P8: =COUNTIFS(Events!$F$6:$F$4467,$A8,Events!$CN$6:$CN$4467,"Yes",Events!$CM$6:$CM$4467,"<>") -> 82 | Q8: =IFERROR(AVERAGEIFS(Events!$CM$6:$CM$4467,Events!$F$6:$F$4467,$A8,Events!$CN$6:$CN$4467,"Yes"),"") -> 0.061848599 | R8: =IFERROR(COUNTIFS(Events!$F$6:$F$4467,$A8,Events!$CM$6:$CM$4467,">0",Events!$CN$6:$CN$4467,"Yes")/COUNTIFS(Events!$F$6:$F$4467,$A8,Events!$CM$6:$CM$4467,"<>",Events!$CN$6:$CN$4467,"Yes"),"") -> 0.46341463
A9: Capital Markets | B9: =COUNTIFS(Events!$F$6:$F$4467,$A9) -> 210 | C9: =COUNTIFS(Events!$F$6:$F$4467,$A9,Events!$L$6:$L$4467,"After close") -> 136 | D9: =COUNTIFS(Events!$F$6:$F$4467,$A9,Events!$L$6:$L$4467,"During market") -> 45 | E9: =COUNTIFS(Events!$F$6:$F$4467,$A9,Events!$L$6:$L$4467,"Non-trading day") -> 28 | F9: =IFERROR(AVERAGEIFS(Events!$U$6:$U$4467,Events!$F$6:$F$4467,$A9),"") -> 0.0050144602 | G9: =IFERROR(COUNTIFS(Events!$F$6:$F$4467,$A9,Events!$U$6:$U$4467,">0")/COUNTIFS(Events!$F$6:$F$4467,$A9,Events!$U$6:$U$4467,"<>"),"") -> 0.52857143 | H9: =IFERROR(AVERAGEIFS(Events!$X$6:$X$4467,Events!$F$6:$F$4467,$A9),"") -> 0.0036161339 | I9: =IFERROR(AVERAGEIFS(Events!$AD$6:$AD$4467,Events!$F$6:$F$4467,$A9),"") -> 0.032579734 | J9: =IFERROR(COUNTIFS(Events!$F$6:$F$4467,$A9,Events!$AV$6:$AV$4467,">0")/COUNTIFS(Events!$F$6:$F$4467,$A9,Events!$AV$6:$AV$4467,"<>"),"") -> 0.93048128 | K9: =IFERROR(COUNTIFS(Events!$F$6:$F$4467,$A9,Events!$BB$6:$BB$4467,">0")/COUNTIFS(Events!$F$6:$F$4467,$A9,Events!$BB$6:$BB$4467,"<>"),"") -> 0.83243243 | L9: =IFERROR(AVERAGEIFS(Events!$AZ$6:$AZ$4467,Events!$F$6:$F$4467,$A9),"") -> 0.022268676 | M9: =IFERROR(AVERAGEIFS(Events!$CK$6:$CK$4467,Events!$F$6:$F$4467,$A9),"") -> 0.074476857 | N9: =IFERROR(AVERAGEIFS(Events!$CL$6:$CL$4467,Events!$F$6:$F$4467,$A9),"") -> 0.42838692 | O9: =IFERROR(AVERAGEIFS(Events!$CJ$6:$CJ$4467,Events!$F$6:$F$4467,$A9),"") -> -0.090326304 | P9: =COUNTIFS(Events!$F$6:$F$4467,$A9,Events!$CN$6:$CN$4467,"Yes",Events!$CM$6:$CM$4467,"<>") -> 45 | Q9: =IFERROR(AVERAGEIFS(Events!$CM$6:$CM$4467,Events!$F$6:$F$4467,$A9,Events!$CN$6:$CN$4467,"Yes"),"") -> 0.17714685 | R9: =IFERROR(COUNTIFS(Events!$F$6:$F$4467,$A9,Events!$CM$6:$CM$4467,">0",Events!$CN$6:$CN$4467,"Yes")/COUNTIFS(Events!$F$6:$F$4467,$A9,Events!$CM$6:$CM$4467,"<>",Events!$CN$6:$CN$4467,"Yes"),"") -> 0.48888889
A10: Construction | B10: =COUNTIFS(Events!$F$6:$F$4467,$A10) -> 176 | C10: =COUNTIFS(Events!$F$6:$F$4467,$A10,Events!$L$6:$L$4467,"After close") -> 134 | D10: =COUNTIFS(Events!$F$6:$F$4467,$A10,Events!$L$6:$L$4467,"During market") -> 32 | E10: =COUNTIFS(Events!$F$6:$F$4467,$A10,Events!$L$6:$L$4467,"Non-trading day") -> 10 | F10: =IFERROR(AVERAGEIFS(Events!$U$6:$U$4467,Events!$F$6:$F$4467,$A10),"") -> -0.0073478961 | G10: =IFERROR(COUNTIFS(Events!$F$6:$F$4467,$A10,Events!$U$6:$U$4467,">0")/COUNTIFS(Events!$F$6:$F$4467,$A10,Events!$U$6:$U$4467,"<>"),"") -> 0.42045455 | H10: =IFERROR(AVERAGEIFS(Events!$X$6:$X$4467,Events!$F$6:$F$4467,$A10),"") -> -0.008931228 | I10: =IFERROR(AVERAGEIFS(Events!$AD$6:$AD$4467,Events!$F$6:$F$4467,$A10),"") -> 0.026135308 | J10: =IFERROR(COUNTIFS(Events!$F$6:$F$4467,$A10,Events!$AV$6:$AV$4467,">0")/COUNTIFS(Events!$F$6:$F$4467,$A10,Events!$AV$6:$AV$4467,"<>"),"") -> 0.71856287 | K10: =IFERROR(COUNTIFS(Events!$F$6:$F$4467,$A10,Events!$BB$6:$BB$4467,">0")/COUNTIFS(Events!$F$6:$F$4467,$A10,Events!$BB$6:$BB$4467,"<>"),"") -> 0.73584906 | L10: =IFERROR(AVERAGEIFS(Events!$AZ$6:$AZ$4467,Events!$F$6:$F$4467,$A10),"") -> 0.0080839402 | M10: =IFERROR(AVERAGEIFS(Events!$CK$6:$CK$4467,Events!$F$6:$F$4467,$A10),"") -> 0.077784044 | N10: =IFERROR(AVERAGEIFS(Events!$CL$6:$CL$4467,Events!$F$6:$F$4467,$A10),"") -> 0.38304596 | O10: =IFERROR(AVERAGEIFS(Events!$CJ$6:$CJ$4467,Events!$F$6:$F$4467,$A10),"") -> -0.11011185 | P10: =COUNTIFS(Events!$F$6:$F$4467,$A10,Events!$CN$6:$CN$4467,"Yes",Events!$CM$6:$CM$4467,"<>") -> 38 | Q10: =IFERROR(AVERAGEIFS(Events!$CM$6:$CM$4467,Events!$F$6:$F$4467,$A10,Events!$CN$6:$CN$4467,"Yes"),"") -> 0.087890514 | R10: =IFERROR(COUNTIFS(Events!$F$6:$F$4467,$A10,Events!$CM$6:$CM$4467,">0",Events!$CN$6:$CN$4467,"Yes")/COUNTIFS(Events!$F$6:$F$4467,$A10,Events!$CM$6:$CM$4467,"<>",Events!$CN$6:$CN$4467,"Yes"),"") -> 0.42105263
A11: Power | B11: =COUNTIFS(Events!$F$6:$F$4467,$A11) -> 176 | C11: =COUNTIFS(Events!$F$6:$F$4467,$A11,Events!$L$6:$L$4467,"After close") -> 111 | D11: =COUNTIFS(Events!$F$6:$F$4467,$A11,Events!$L$6:$L$4467,"During market") -> 47 | E11: =COUNTIFS(Events!$F$6:$F$4467,$A11,Events!$L$6:$L$4467,"Non-trading day") -> 18 | F11: =IFERROR(AVERAGEIFS(Events!$U$6:$U$4467,Events!$F$6:$F$4467,$A11),"") -> -0.008446011 | G11: =IFERROR(COUNTIFS(Events!$F$6:$F$4467,$A11,Events!$U$6:$U$4467,">0")/COUNTIFS(Events!$F$6:$F$4467,$A11,Events!$U$6:$U$4467,"<>"),"") -> 0.44318182 | H11: =IFERROR(AVERAGEIFS(Events!$X$6:$X$4467,Events!$F$6:$F$4467,$A11),"") -> -0.0092370897 | I11: =IFERROR(AVERAGEIFS(Events!$AD$6:$AD$4467,Events!$F$6:$F$4467,$A11),"") -> 0.023050454 | J11: =IFERROR(COUNTIFS(Events!$F$6:$F$4467,$A11,Events!$AV$6:$AV$4467,">0")/COUNTIFS(Events!$F$6:$F$4467,$A11,Events!$AV$6:$AV$4467,"<>"),"") -> 0.77906977 | K11: =IFERROR(COUNTIFS(Events!$F$6:$F$4467,$A11,Events!$BB$6:$BB$4467,">0")/COUNTIFS(Events!$F$6:$F$4467,$A11,Events!$BB$6:$BB$4467,"<>"),"") -> 0.65060241 | L11: =IFERROR(AVERAGEIFS(Events!$AZ$6:$AZ$4467,Events!$F$6:$F$4467,$A11),"") -> 0.0065885768 | M11: =IFERROR(AVERAGEIFS(Events!$CK$6:$CK$4467,Events!$F$6:$F$4467,$A11),"") -> 0.064375127 | N11: =IFERROR(AVERAGEIFS(Events!$CL$6:$CL$4467,Events!$F$6:$F$4467,$A11),"") -> 0.36100018 | O11: =IFERROR(AVERAGEIFS(Events!$CJ$6:$CJ$4467,Events!$F$6:$F$4467,$A11),"") -> -0.10175107 | P11: =COUNTIFS(Events!$F$6:$F$4467,$A11,Events!$CN$6:$CN$4467,"Yes",Events!$CM$6:$CM$4467,"<>") -> 45 | Q11: =IFERROR(AVERAGEIFS(Events!$CM$6:$CM$4467,Events!$F$6:$F$4467,$A11,Events!$CN$6:$CN$4467,"Yes"),"") -> -0.064932197 | R11: =IFERROR(COUNTIFS(Events!$F$6:$F$4467,$A11,Events!$CM$6:$CM$4467,">0",Events!$CN$6:$CN$4467,"Yes")/COUNTIFS(Events!$F$6:$F$4467,$A11,Events!$CM$6:$CM$4467,"<>",Events!$CN$6:$CN$4467,"Yes"),"") -> 0.31111111
A12: Insurance | B12: =COUNTIFS(Events!$F$6:$F$4467,$A12) -> 128 | C12: =COUNTIFS(Events!$F$6:$F$4467,$A12,Events!$L$6:$L$4467,"After close") -> 89 | D12: =COUNTIFS(Events!$F$6:$F$4467,$A12,Events!$L$6:$L$4467,"During market") -> 31 | E12: =COUNTIFS(Events!$F$6:$F$4467,$A12,Events!$L$6:$L$4467,"Non-trading day") -> 8 | F12: =IFERROR(AVERAGEIFS(Events!$U$6:$U$4467,Events!$F$6:$F$4467,$A12),"") -> 0.0056480383 | G12: =IFERROR(COUNTIFS(Events!$F$6:$F$4467,$A12,Events!$U$6:$U$4467,">0")/COUNTIFS(Events!$F$6:$F$4467,$A12,Events!$U$6:$U$4467,"<>"),"") -> 0.53125 | H12: =IFERROR(AVERAGEIFS(Events!$X$6:$X$4467,Events!$F$6:$F$4467,$A12),"") -> 0.0051971859 | I12: =IFERROR(AVERAGEIFS(Events!$AD$6:$AD$4467,Events!$F$6:$F$4467,$A12),"") -> 0.027146426 | J12: =IFERROR(COUNTIFS(Events!$F$6:$F$4467,$A12,Events!$AV$6:$AV$4467,">0")/COUNTIFS(Events!$F$6:$F$4467,$A12,Events!$AV$6:$AV$4467,"<>"),"") -> 0.66666667 | K12: =IFERROR(COUNTIFS(Events!$F$6:$F$4467,$A12,Events!$BB$6:$BB$4467,">0")/COUNTIFS(Events!$F$6:$F$4467,$A12,Events!$BB$6:$BB$4467,"<>"),"") -> 0.25 | L12: =IFERROR(AVERAGEIFS(Events!$AZ$6:$AZ$4467,Events!$F$6:$F$4467,$A12),"") | M12: =IFERROR(AVERAGEIFS(Events!$CK$6:$CK$4467,Events!$F$6:$F$4467,$A12),"") -> 0.054830466 | N12: =IFERROR(AVERAGEIFS(Events!$CL$6:$CL$4467,Events!$F$6:$F$4467,$A12),"") -> 0.52077536 | O12: =IFERROR(AVERAGEIFS(Events!$CJ$6:$CJ$4467,Events!$F$6:$F$4467,$A12),"") -> -0.13086352 | P12: =COUNTIFS(Events!$F$6:$F$4467,$A12,Events!$CN$6:$CN$4467,"Yes",Events!$CM$6:$CM$4467,"<>") -> 81 | Q12: =IFERROR(AVERAGEIFS(Events!$CM$6:$CM$4467,Events!$F$6:$F$4467,$A12,Events!$CN$6:$CN$4467,"Yes"),"") -> -0.0085236312 | R12: =IFERROR(COUNTIFS(Events!$F$6:$F$4467,$A12,Events!$CM$6:$CM$4467,">0",Events!$CN$6:$CN$4467,"Yes")/COUNTIFS(Events!$F$6:$F$4467,$A12,Events!$CM$6:$CM$4467,"<>",Events!$CN$6:$CN$4467,"Yes"),"") -> 0.41975309
A13: Automobiles - 4 Wheelers | B13: =COUNTIFS(Events!$F$6:$F$4467,$A13) -> 128 | C13: =COUNTIFS(Events!$F$6:$F$4467,$A13,Events!$L$6:$L$4467,"After close") -> 63 | D13: =COUNTIFS(Events!$F$6:$F$4467,$A13,Events!$L$6:$L$4467,"During market") -> 62 | E13: =COUNTIFS(Events!$F$6:$F$4467,$A13,Events!$L$6:$L$4467,"Non-trading day") -> 3 | F13: =IFERROR(AVERAGEIFS(Events!$U$6:$U$4467,Events!$F$6:$F$4467,$A13),"") -> 0.017023852 | G13: =IFERROR(COUNTIFS(Events!$F$6:$F$4467,$A13,Events!$U$6:$U$4467,">0")/COUNTIFS(Events!$F$6:$F$4467,$A13,Events!$U$6:$U$4467,"<>"),"") -> 0.625 | H13: =IFERROR(AVERAGEIFS(Events!$X$6:$X$4467,Events!$F$6:$F$4467,$A13),"") -> 0.013774852 | I13: =IFERROR(AVERAGEIFS(Events!$AD$6:$AD$4467,Events!$F$6:$F$4467,$A13),"") -> 0.027633885 | J13: =IFERROR(COUNTIFS(Events!$F$6:$F$4467,$A13,Events!$AV$6:$AV$4467,">0")/COUNTIFS(Events!$F$6:$F$4467,$A13,Events!$AV$6:$AV$4467,"<>"),"") -> 0.88695652 | K13: =IFERROR(COUNTIFS(Events!$F$6:$F$4467,$A13,Events!$BB$6:$BB$4467,">0")/COUNTIFS(Events!$F$6:$F$4467,$A13,Events!$BB$6:$BB$4467,"<>"),"") -> 0.74489796 | L13: =IFERROR(AVERAGEIFS(Events!$AZ$6:$AZ$4467,Events!$F$6:$F$4467,$A13),"") -> 0.0088972097 | M13: =IFERROR(AVERAGEIFS(Events!$CK$6:$CK$4467,Events!$F$6:$F$4467,$A13),"") -> 0.066550007 | N13: =IFERROR(AVERAGEIFS(Events!$CL$6:$CL$4467,Events!$F$6:$F$4467,$A13),"") -> 0.40131556 | O13: =IFERROR(AVERAGEIFS(Events!$CJ$6:$CJ$4467,Events!$F$6:$F$4467,$A13),"") -> -0.11234639 | P13: =COUNTIFS(Events!$F$6:$F$4467,$A13,Events!$CN$6:$CN$4467,"Yes",Events!$CM$6:$CM$4467,"<>") -> 52 | Q13: =IFERROR(AVERAGEIFS(Events!$CM$6:$CM$4467,Events!$F$6:$F$4467,$A13,Events!$CN$6:$CN$4467,"Yes"),"") -> -0.025384798 | R13: =IFERROR(COUNTIFS(Events!$F$6:$F$4467,$A13,Events!$CM$6:$CM$4467,">0",Events!$CN$6:$CN$4467,"Yes")/COUNTIFS(Events!$F$6:$F$4467,$A13,Events!$CM$6:$CM$4467,"<>",Events!$CN$6:$CN$4467,"Yes"),"") -> 0.38461538
A14: Food And Food Processing | B14: =COUNTIFS(Events!$F$6:$F$4467,$A14) -> 122 | C14: =COUNTIFS(Events!$F$6:$F$4467,$A14,Events!$L$6:$L$4467,"After close") -> 67 | D14: =COUNTIFS(Events!$F$6:$F$4467,$A14,Events!$L$6:$L$4467,"During market") -> 47 | E14: =COUNTIFS(Events!$F$6:$F$4467,$A14,Events!$L$6:$L$4467,"Non-trading day") -> 8 | F14: =IFERROR(AVERAGEIFS(Events!$U$6:$U$4467,Events!$F$6:$F$4467,$A14),"") -> 0.0056010326 | G14: =IFERROR(COUNTIFS(Events!$F$6:$F$4467,$A14,Events!$U$6:$U$4467,">0")/COUNTIFS(Events!$F$6:$F$4467,$A14,Events!$U$6:$U$4467,"<>"),"") -> 0.52459016 | H14: =IFERROR(AVERAGEIFS(Events!$X$6:$X$4467,Events!$F$6:$F$4467,$A14),"") -> 0.0044538192 | I14: =IFERROR(AVERAGEIFS(Events!$AD$6:$AD$4467,Events!$F$6:$F$4467,$A14),"") -> 0.03162427 | J14: =IFERROR(COUNTIFS(Events!$F$6:$F$4467,$A14,Events!$AV$6:$AV$4467,">0")/COUNTIFS(Events!$F$6:$F$4467,$A14,Events!$AV$6:$AV$4467,"<>"),"") -> 0.95762712 | K14: =IFERROR(COUNTIFS(Events!$F$6:$F$4467,$A14,Events!$BB$6:$BB$4467,">0")/COUNTIFS(Events!$F$6:$F$4467,$A14,Events!$BB$6:$BB$4467,"<>"),"") -> 0.72807018 | L14: =IFERROR(AVERAGEIFS(Events!$AZ$6:$AZ$4467,Events!$F$6:$F$4467,$A14),"") -> 0.0019971448 | M14: =IFERROR(AVERAGEIFS(Events!$CK$6:$CK$4467,Events!$F$6:$F$4467,$A14),"") -> 0.061219948 | N14: =IFERROR(AVERAGEIFS(Events!$CL$6:$CL$4467,Events!$F$6:$F$4467,$A14),"") -> 0.57343076 | O14: =IFERROR(AVERAGEIFS(Events!$CJ$6:$CJ$4467,Events!$F$6:$F$4467,$A14),"") -> -0.1308149 | P14: =COUNTIFS(Events!$F$6:$F$4467,$A14,Events!$CN$6:$CN$4467,"Yes",Events!$CM$6:$CM$4467,"<>") -> 41 | Q14: =IFERROR(AVERAGEIFS(Events!$CM$6:$CM$4467,Events!$F$6:$F$4467,$A14,Events!$CN$6:$CN$4467,"Yes"),"") -> -0.012842883 | R14: =IFERROR(COUNTIFS(Events!$F$6:$F$4467,$A14,Events!$CM$6:$CM$4467,">0",Events!$CN$6:$CN$4467,"Yes")/COUNTIFS(Events!$F$6:$F$4467,$A14,Events!$CM$6:$CM$4467,"<>",Events!$CN$6:$CN$4467,"Yes"),"") -> 0.34146341
A15: Miscellaneous | B15: =COUNTIFS(Events!$F$6:$F$4467,$A15) -> 110 | C15: =COUNTIFS(Events!$F$6:$F$4467,$A15,Events!$L$6:$L$4467,"After close") -> 76 | D15: =COUNTIFS(Events!$F$6:$F$4467,$A15,Events!$L$6:$L$4467,"During market") -> 30 | E15: =COUNTIFS(Events!$F$6:$F$4467,$A15,Events!$L$6:$L$4467,"Non-trading day") -> 4 | F15: =IFERROR(AVERAGEIFS(Events!$U$6:$U$4467,Events!$F$6:$F$4467,$A15),"") -> 0.012454502 | G15: =IFERROR(COUNTIFS(Events!$F$6:$F$4467,$A15,Events!$U$6:$U$4467,">0")/COUNTIFS(Events!$F$6:$F$4467,$A15,Events!$U$6:$U$4467,"<>"),"") -> 0.55454545 | H15: =IFERROR(AVERAGEIFS(Events!$X$6:$X$4467,Events!$F$6:$F$4467,$A15),"") -> 0.010943248 | I15: =IFERROR(AVERAGEIFS(Events!$AD$6:$AD$4467,Events!$F$6:$F$4467,$A15),"") -> 0.032079051 | J15: =IFERROR(COUNTIFS(Events!$F$6:$F$4467,$A15,Events!$AV$6:$AV$4467,">0")/COUNTIFS(Events!$F$6:$F$4467,$A15,Events!$AV$6:$AV$4467,"<>"),"") -> 0.97222222 | K15: =IFERROR(COUNTIFS(Events!$F$6:$F$4467,$A15,Events!$BB$6:$BB$4467,">0")/COUNTIFS(Events!$F$6:$F$4467,$A15,Events!$BB$6:$BB$4467,"<>"),"") -> 0.84 | L15: =IFERROR(AVERAGEIFS(Events!$AZ$6:$AZ$4467,Events!$F$6:$F$4467,$A15),"") -> 0.018598858 | M15: =IFERROR(AVERAGEIFS(Events!$CK$6:$CK$4467,Events!$F$6:$F$4467,$A15),"") -> 0.071302869 | N15: =IFERROR(AVERAGEIFS(Events!$CL$6:$CL$4467,Events!$F$6:$F$4467,$A15),"") -> 0.52670961 | O15: =IFERROR(AVERAGEIFS(Events!$CJ$6:$CJ$4467,Events!$F$6:$F$4467,$A15),"") -> -0.13632786 | P15: =COUNTIFS(Events!$F$6:$F$4467,$A15,Events!$CN$6:$CN$4467,"Yes",Events!$CM$6:$CM$4467,"<>") -> 39 | Q15: =IFERROR(AVERAGEIFS(Events!$CM$6:$CM$4467,Events!$F$6:$F$4467,$A15,Events!$CN$6:$CN$4467,"Yes"),"") -> -0.00028071286 | R15: =IFERROR(COUNTIFS(Events!$F$6:$F$4467,$A15,Events!$CM$6:$CM$4467,">0",Events!$CN$6:$CN$4467,"Yes")/COUNTIFS(Events!$F$6:$F$4467,$A15,Events!$CM$6:$CM$4467,"<>",Events!$CN$6:$CN$4467,"Yes"),"") -> 0.35897436
... A52: Electronics - Industrial | B52: =COUNTIFS(Events!$F$6:$F$4467,$A52) -> 22 | C52: =COUNTIFS(Events!$F$6:$F$4467,$A52,Events!$L$6:$L$4467,"After close") -> 8 | D52: =COUNTIFS(Events!$F$6:$F$4467,$A52,Events!$L$6:$L$4467,"During market") -> 9 | E52: =COUNTIFS(Events!$F$6:$F$4467,$A52,Events!$L$6:$L$4467,"Non-trading day") -> 5 | F52: =IFERROR(AVERAGEIFS(Events!$U$6:$U$4467,Events!$F$6:$F$4467,$A52),"") -> 0.028458548 | G52: =IFERROR(COUNTIFS(Events!$F$6:$F$4467,$A52,Events!$U$6:$U$4467,">0")/COUNTIFS(Events!$F$6:$F$4467,$A52,Events!$U$6:$U$4467,"<>"),"") -> 0.68181818 | H52: =IFERROR(AVERAGEIFS(Events!$X$6:$X$4467,Events!$F$6:$F$4467,$A52),"") -> 0.024893692 | I52: =IFERROR(AVERAGEIFS(Events!$AD$6:$AD$4467,Events!$F$6:$F$4467,$A52),"") -> 0.031555097 | J52: =IFERROR(COUNTIFS(Events!$F$6:$F$4467,$A52,Events!$AV$6:$AV$4467,">0")/COUNTIFS(Events!$F$6:$F$4467,$A52,Events!$AV$6:$AV$4467,"<>"),"") -> 0.90909091 | K52: =IFERROR(COUNTIFS(Events!$F$6:$F$4467,$A52,Events!$BB$6:$BB$4467,">0")/COUNTIFS(Events!$F$6:$F$4467,$A52,Events!$BB$6:$BB$4467,"<>"),"") -> 0.86363636 | L52: =IFERROR(AVERAGEIFS(Events!$AZ$6:$AZ$4467,Events!$F$6:$F$4467,$A52),"") -> 0.018008865 | M52: =IFERROR(AVERAGEIFS(Events!$CK$6:$CK$4467,Events!$F$6:$F$4467,$A52),"") -> 0.076136924 | N52: =IFERROR(AVERAGEIFS(Events!$CL$6:$CL$4467,Events!$F$6:$F$4467,$A52),"") -> 0.38292172 | O52: =IFERROR(AVERAGEIFS(Events!$CJ$6:$CJ$4467,Events!$F$6:$F$4467,$A52),"") -> -0.058656332 | P52: =COUNTIFS(Events!$F$6:$F$4467,$A52,Events!$CN$6:$CN$4467,"Yes",Events!$CM$6:$CM$4467,"<>") -> 7 | Q52: =IFERROR(AVERAGEIFS(Events!$CM$6:$CM$4467,Events!$F$6:$F$4467,$A52,Events!$CN$6:$CN$4467,"Yes"),"") -> 0.21042063 | R52: =IFERROR(COUNTIFS(Events!$F$6:$F$4467,$A52,Events!$CM$6:$CM$4467,">0",Events!$CN$6:$CN$4467,"Yes")/COUNTIFS(Events!$F$6:$F$4467,$A52,Events!$CM$6:$CM$4467,"<>",Events!$CN$6:$CN$4467,"Yes"),"") -> 0.42857143
A53: All industries | B53: =COUNTIFS(Events!$F$6:$F$4467,"<>") -> 4462 | C53: =COUNTIFS(Events!$F$6:$F$4467,"<>",Events!$L$6:$L$4467,"After close") -> 2623 | D53: =COUNTIFS(Events!$F$6:$F$4467,"<>",Events!$L$6:$L$4467,"During market") -> 1419 | E53: =COUNTIFS(Events!$F$6:$F$4467,"<>",Events!$L$6:$L$4467,"Non-trading day") -> 393 | F53: =IFERROR(AVERAGEIFS(Events!$U$6:$U$4467,Events!$F$6:$F$4467,"<>"),"") -> 0.0028108158 | G53: =IFERROR(COUNTIFS(Events!$F$6:$F$4467,"<>",Events!$U$6:$U$4467,">0")/COUNTIFS(Events!$F$6:$F$4467,"<>",Events!$U$6:$U$4467,"<>"),"") -> 0.50381166 | H53: =IFERROR(AVERAGEIFS(Events!$X$6:$X$4467,Events!$F$6:$F$4467,"<>"),"") -> 0.0016344564 | I53: =IFERROR(AVERAGEIFS(Events!$AD$6:$AD$4467,Events!$F$6:$F$4467,"<>"),"") -> 0.030647861 | J53: =IFERROR(COUNTIFS(Events!$F$6:$F$4467,"<>",Events!$AV$6:$AV$4467,">0")/COUNTIFS(Events!$F$6:$F$4467,"<>",Events!$AV$6:$AV$4467,"<>"),"") -> 0.86166299 | K53: =IFERROR(COUNTIFS(Events!$F$6:$F$4467,"<>",Events!$BB$6:$BB$4467,">0")/COUNTIFS(Events!$F$6:$F$4467,"<>",Events!$BB$6:$BB$4467,"<>"),"") -> 0.72437418 | L53: =IFERROR(AVERAGEIFS(Events!$AZ$6:$AZ$4467,Events!$F$6:$F$4467,"<>"),"") -> 0.014142264 | M53: =IFERROR(AVERAGEIFS(Events!$CK$6:$CK$4467,Events!$F$6:$F$4467,"<>"),"") -> 0.067968055 | N53: =IFERROR(AVERAGEIFS(Events!$CL$6:$CL$4467,Events!$F$6:$F$4467,"<>"),"") -> 0.4615053 | O53: =IFERROR(AVERAGEIFS(Events!$CJ$6:$CJ$4467,Events!$F$6:$F$4467,"<>"),"") -> -0.11842411 | P53: =COUNTIFS(Events!$F$6:$F$4467,"<>",Events!$CN$6:$CN$4467,"Yes",Events!$CM$6:$CM$4467,"<>") -> 1685 | Q53: =IFERROR(AVERAGEIFS(Events!$CM$6:$CM$4467,Events!$F$6:$F$4467,"<>",Events!$CN$6:$CN$4467,"Yes"),"") -> 0.018684818 | R53: =IFERROR(COUNTIFS(Events!$F$6:$F$4467,"<>",Events!$CM$6:$CM$4467,">0",Events!$CN$6:$CN$4467,"Yes")/COUNTIFS(Events!$F$6:$F$4467,"<>",Events!$CM$6:$CM$4467,"<>",Events!$CN$6:$CN$4467,"Yes"),"") -> 0.39762611

Sheet By stock
A1: By stock
A2: Formulas over the Events sheet, all 22 quarters.
A3: Symbol | B3: Company | C3: Industry | D3: Results events | E3: After close | F3: Avg three-day sum % | G3: % three-day positive | H3: Avg excess vs Nifty % | I3: Avg size of reaction move % | J3: % sales up YoY | K3: % profit up YoY | L3: Avg EBITDA margin chg YoY (pts) | M3: Avg expected move % (options) | N3: Avg actual / expected move (x) | O3: Avg IV drop % | P3: Run-up trades (rule pass) | Q3: Run-up avg return % (rule pass) | R3: Run-up win rate (rule pass)
A4: 360ONE | B4: =INDEX(Events!$E$6:$E$4467,MATCH($A4,Events!$D$6:$D$4467,0)) -> 360 ONE WAM LIMITED | C4: =INDEX(Events!$F$6:$F$4467,MATCH($A4,Events!$D$6:$D$4467,0))&"" -> Capital Markets | D4: =COUNTIFS(Events!$D$6:$D$4467,$A4) -> 22 | E4: =COUNTIFS(Events!$D$6:$D$4467,$A4,Events!$L$6:$L$4467,"After close") -> 18 | F4: =IFERROR(AVERAGEIFS(Events!$U$6:$U$4467,Events!$D$6:$D$4467,$A4),"") -> 0.0090797633 | G4: =IFERROR(COUNTIFS(Events!$D$6:$D$4467,$A4,Events!$U$6:$U$4467,">0")/COUNTIFS(Events!$D$6:$D$4467,$A4,Events!$U$6:$U$4467,"<>"),"") -> 0.68181818 | H4: =IFERROR(AVERAGEIFS(Events!$X$6:$X$4467,Events!$D$6:$D$4467,$A4),"") -> 0.0087506089 | I4: =IFERROR(AVERAGEIFS(Events!$AD$6:$AD$4467,Events!$D$6:$D$4467,$A4),"") -> 0.035290339 | J4: =IFERROR(COUNTIFS(Events!$D$6:$D$4467,$A4,Events!$AV$6:$AV$4467,">0")/COUNTIFS(Events!$D$6:$D$4467,$A4,Events!$AV$6:$AV$4467,"<>"),"") -> 0.9 | K4: =IFERROR(COUNTIFS(Events!$D$6:$D$4467,$A4,Events!$BB$6:$BB$4467,">0")/COUNTIFS(Events!$D$6:$D$4467,$A4,Events!$BB$6:$BB$4467,"<>"),"") -> 0.94736842 | L4: =IFERROR(AVERAGEIFS(Events!$AZ$6:$AZ$4467,Events!$D$6:$D$4467,$A4),"") -> 0.016615718 | M4: =IFERROR(AVERAGEIFS(Events!$CK$6:$CK$4467,Events!$D$6:$D$4467,$A4),"") -> 0.058463763 | N4: =IFERROR(AVERAGEIFS(Events!$CL$6:$CL$4467,Events!$D$6:$D$4467,$A4),"") -> 0.44387782 | O4: =IFERROR(AVERAGEIFS(Events!$CJ$6:$CJ$4467,Events!$D$6:$D$4467,$A4),"") -> -0.15649243 | P4: =COUNTIFS(Events!$D$6:$D$4467,$A4,Events!$CN$6:$CN$4467,"Yes",Events!$CM$6:$CM$4467,"<>") -> 5 | Q4: =IFERROR(AVERAGEIFS(Events!$CM$6:$CM$4467,Events!$D$6:$D$4467,$A4,Events!$CN$6:$CN$4467,"Yes"),"") -> 0.069709918 | R4: =IFERROR(COUNTIFS(Events!$D$6:$D$4467,$A4,Events!$CM$6:$CM$4467,">0",Events!$CN$6:$CN$4467,"Yes")/COUNTIFS(Events!$D$6:$D$4467,$A4,Events!$CM$6:$CM$4467,"<>",Events!$CN$6:$CN$4467,"Yes"),"") -> 0.4
A5: ABB | B5: =INDEX(Events!$E$6:$E$4467,MATCH($A5,Events!$D$6:$D$4467,0)) -> ABB India Limited | C5: =INDEX(Events!$F$6:$F$4467,MATCH($A5,Events!$D$6:$D$4467,0))&"" -> Electrical Equipment | D5: =COUNTIFS(Events!$D$6:$D$4467,$A5) -> 22 | E5: =COUNTIFS(Events!$D$6:$D$4467,$A5,Events!$L$6:$L$4467,"After close") -> 18 | F5: =IFERROR(AVERAGEIFS(Events!$U$6:$U$4467,Events!$D$6:$D$4467,$A5),"") -> 0.0055872373 | G5: =IFERROR(COUNTIFS(Events!$D$6:$D$4467,$A5,Events!$U$6:$U$4467,">0")/COUNTIFS(Events!$D$6:$D$4467,$A5,Events!$U$6:$U$4467,"<>"),"") -> 0.54545455 | H5: =IFERROR(AVERAGEIFS(Events!$X$6:$X$4467,Events!$D$6:$D$4467,$A5),"") -> 0.0035192286 | I5: =IFERROR(AVERAGEIFS(Events!$AD$6:$AD$4467,Events!$D$6:$D$4467,$A5),"") -> 0.040461622 | J5: =IFERROR(COUNTIFS(Events!$D$6:$D$4467,$A5,Events!$AV$6:$AV$4467,">0")/COUNTIFS(Events!$D$6:$D$4467,$A5,Events!$AV$6:$AV$4467,"<>"),"") -> 1 | K5: =IFERROR(COUNTIFS(Events!$D$6:$D$4467,$A5,Events!$BB$6:$BB$4467,">0")/COUNTIFS(Events!$D$6:$D$4467,$A5,Events!$BB$6:$BB$4467,"<>"),"") -> 0.81818182 | L5: =IFERROR(AVERAGEIFS(Events!$AZ$6:$AZ$4467,Events!$D$6:$D$4467,$A5),"") -> 0.015923713 | M5: =IFERROR(AVERAGEIFS(Events!$CK$6:$CK$4467,Events!$D$6:$D$4467,$A5),"") -> 0.072857118 | N5: =IFERROR(AVERAGEIFS(Events!$CL$6:$CL$4467,Events!$D$6:$D$4467,$A5),"") -> 0.61289742 | O5: =IFERROR(AVERAGEIFS(Events!$CJ$6:$CJ$4467,Events!$D$6:$D$4467,$A5),"") -> -0.13833043 | P5: =COUNTIFS(Events!$D$6:$D$4467,$A5,Events!$CN$6:$CN$4467,"Yes",Events!$CM$6:$CM$4467,"<>") -> 10 | Q5: =IFERROR(AVERAGEIFS(Events!$CM$6:$CM$4467,Events!$D$6:$D$4467,$A5,Events!$CN$6:$CN$4467,"Yes"),"") -> 0.1083875 | R5: =IFERROR(COUNTIFS(Events!$D$6:$D$4467,$A5,Events!$CM$6:$CM$4467,">0",Events!$CN$6:$CN$4467,"Yes")/COUNTIFS(Events!$D$6:$D$4467,$A5,Events!$CM$6:$CM$4467,"<>",Events!$CN$6:$CN$4467,"Yes"),"") -> 0.6
A6: ABCAPITAL | B6: =INDEX(Events!$E$6:$E$4467,MATCH($A6,Events!$D$6:$D$4467,0)) -> Aditya Birla Capital Limited | C6: =INDEX(Events!$F$6:$F$4467,MATCH($A6,Events!$D$6:$D$4467,0))&"" -> Finance | D6: =COUNTIFS(Events!$D$6:$D$4467,$A6) -> 22 | E6: =COUNTIFS(Events!$D$6:$D$4467,$A6,Events!$L$6:$L$4467,"After close") -> 7 | F6: =IFERROR(AVERAGEIFS(Events!$U$6:$U$4467,Events!$D$6:$D$4467,$A6),"") -> 0.026211941 | G6: =IFERROR(COUNTIFS(Events!$D$6:$D$4467,$A6,Events!$U$6:$U$4467,">0")/COUNTIFS(Events!$D$6:$D$4467,$A6,Events!$U$6:$U$4467,"<>"),"") -> 0.72727273 | H6: =IFERROR(AVERAGEIFS(Events!$X$6:$X$4467,Events!$D$6:$D$4467,$A6),"") -> 0.021366968 | I6: =IFERROR(AVERAGEIFS(Events!$AD$6:$AD$4467,Events!$D$6:$D$4467,$A6),"") -> 0.027840454 | J6: =IFERROR(COUNTIFS(Events!$D$6:$D$4467,$A6,Events!$AV$6:$AV$4467,">0")/COUNTIFS(Events!$D$6:$D$4467,$A6,Events!$AV$6:$AV$4467,"<>"),"") -> 1 | K6: =IFERROR(COUNTIFS(Events!$D$6:$D$4467,$A6,Events!$BB$6:$BB$4467,">0")/COUNTIFS(Events!$D$6:$D$4467,$A6,Events!$BB$6:$BB$4467,"<>"),"") -> 0.8 | L6: =IFERROR(AVERAGEIFS(Events!$AZ$6:$AZ$4467,Events!$D$6:$D$4467,$A6),"") | M6: =IFERROR(AVERAGEIFS(Events!$CK$6:$CK$4467,Events!$D$6:$D$4467,$A6),"") -> 0.076935985 | N6: =IFERROR(AVERAGEIFS(Events!$CL$6:$CL$4467,Events!$D$6:$D$4467,$A6),"") -> 0.34060094 | O6: =IFERROR(AVERAGEIFS(Events!$CJ$6:$CJ$4467,Events!$D$6:$D$4467,$A6),"") -> -0.068224079 | P6: =COUNTIFS(Events!$D$6:$D$4467,$A6,Events!$CN$6:$CN$4467,"Yes",Events!$CM$6:$CM$4467,"<>") -> 5 | Q6: =IFERROR(AVERAGEIFS(Events!$CM$6:$CM$4467,Events!$D$6:$D$4467,$A6,Events!$CN$6:$CN$4467,"Yes"),"") -> 0.099351373 | R6: =IFERROR(COUNTIFS(Events!$D$6:$D$4467,$A6,Events!$CM$6:$CM$4467,">0",Events!$CN$6:$CN$4467,"Yes")/COUNTIFS(Events!$D$6:$D$4467,$A6,Events!$CM$6:$CM$4467,"<>",Events!$CN$6:$CN$4467,"Yes"),"") -> 0.6
A7: ADANIENSOL | B7: =INDEX(Events!$E$6:$E$4467,MATCH($A7,Events!$D$6:$D$4467,0)) -> Adani Energy Solutions Limited | C7: =INDEX(Events!$F$6:$F$4467,MATCH($A7,Events!$D$6:$D$4467,0))&"" -> Power | D7: =COUNTIFS(Events!$D$6:$D$4467,$A7) -> 22 | E7: =COUNTIFS(Events!$D$6:$D$4467,$A7,Events!$L$6:$L$4467,"After close") -> 11 | F7: =IFERROR(AVERAGEIFS(Events!$U$6:$U$4467,Events!$D$6:$D$4467,$A7),"") -> -0.0029780705 | G7: =IFERROR(COUNTIFS(Events!$D$6:$D$4467,$A7,Events!$U$6:$U$4467,">0")/COUNTIFS(Events!$D$6:$D$4467,$A7,Events!$U$6:$U$4467,"<>"),"") -> 0.45454545 | H7: =IFERROR(AVERAGEIFS(Events!$X$6:$X$4467,Events!$D$6:$D$4467,$A7),"") -> -0.0019174925 | I7: =IFERROR(AVERAGEIFS(Events!$AD$6:$AD$4467,Events!$D$6:$D$4467,$A7),"") -> 0.016595101 | J7: =IFERROR(COUNTIFS(Events!$D$6:$D$4467,$A7,Events!$AV$6:$AV$4467,">0")/COUNTIFS(Events!$D$6:$D$4467,$A7,Events!$AV$6:$AV$4467,"<>"),"") -> 0.95454545 | K7: =IFERROR(COUNTIFS(Events!$D$6:$D$4467,$A7,Events!$BB$6:$BB$4467,">0")/COUNTIFS(Events!$D$6:$D$4467,$A7,Events!$BB$6:$BB$4467,"<>"),"") -> 0.55 | L7: =IFERROR(AVERAGEIFS(Events!$AZ$6:$AZ$4467,Events!$D$6:$D$4467,$A7),"") -> -0.0021137085 | M7: =IFERROR(AVERAGEIFS(Events!$CK$6:$CK$4467,Events!$D$6:$D$4467,$A7),"") -> 0.080326302 | N7: =IFERROR(AVERAGEIFS(Events!$CL$6:$CL$4467,Events!$D$6:$D$4467,$A7),"") -> 0.26987123 | O7: =IFERROR(AVERAGEIFS(Events!$CJ$6:$CJ$4467,Events!$D$6:$D$4467,$A7),"") -> -0.026866126 | P7: =COUNTIFS(Events!$D$6:$D$4467,$A7,Events!$CN$6:$CN$4467,"Yes",Events!$CM$6:$CM$4467,"<>") -> 3 | Q7: =IFERROR(AVERAGEIFS(Events!$CM$6:$CM$4467,Events!$D$6:$D$4467,$A7,Events!$CN$6:$CN$4467,"Yes"),"") -> -0.15664483 | R7: =IFERROR(COUNTIFS(Events!$D$6:$D$4467,$A7,Events!$CM$6:$CM$4467,">0",Events!$CN$6:$CN$4467,"Yes")/COUNTIFS(Events!$D$6:$D$4467,$A7,Events!$CM$6:$CM$4467,"<>",Events!$CN$6:$CN$4467,"Yes"),"") -> 0
A8: ADANIENT | B8: =INDEX(Events!$E$6:$E$4467,MATCH($A8,Events!$D$6:$D$4467,0)) -> Adani Enterprises Limited | C8: =INDEX(Events!$F$6:$F$4467,MATCH($A8,Events!$D$6:$D$4467,0))&"" -> Trading | D8: =COUNTIFS(Events!$D$6:$D$4467,$A8) -> 22 | E8: =COUNTIFS(Events!$D$6:$D$4467,$A8,Events!$L$6:$L$4467,"After close") -> 6 | F8: =IFERROR(AVERAGEIFS(Events!$U$6:$U$4467,Events!$D$6:$D$4467,$A8),"") -> 0.0055583675 | G8: =IFERROR(COUNTIFS(Events!$D$6:$D$4467,$A8,Events!$U$6:$U$4467,">0")/COUNTIFS(Events!$D$6:$D$4467,$A8,Events!$U$6:$U$4467,"<>"),"") -> 0.63636364 | H8: =IFERROR(AVERAGEIFS(Events!$X$6:$X$4467,Events!$D$6:$D$4467,$A8),"") -> 0.0026573714 | I8: =IFERROR(AVERAGEIFS(Events!$AD$6:$AD$4467,Events!$D$6:$D$4467,$A8),"") -> 0.029127229 | J8: =IFERROR(COUNTIFS(Events!$D$6:$D$4467,$A8,Events!$AV$6:$AV$4467,">0")/COUNTIFS(Events!$D$6:$D$4467,$A8,Events!$AV$6:$AV$4467,"<>"),"") -> 0.72727273 | K8: =IFERROR(COUNTIFS(Events!$D$6:$D$4467,$A8,Events!$BB$6:$BB$4467,">0")/COUNTIFS(Events!$D$6:$D$4467,$A8,Events!$BB$6:$BB$4467,"<>"),"") -> 0.57142857 | L8: =IFERROR(AVERAGEIFS(Events!$AZ$6:$AZ$4467,Events!$D$6:$D$4467,$A8),"") -> 0.031877316 | M8: =IFERROR(AVERAGEIFS(Events!$CK$6:$CK$4467,Events!$D$6:$D$4467,$A8),"") -> 0.094882444 | N8: =IFERROR(AVERAGEIFS(Events!$CL$6:$CL$4467,Events!$D$6:$D$4467,$A8),"") -> 0.34714871 | O8: =IFERROR(AVERAGEIFS(Events!$CJ$6:$CJ$4467,Events!$D$6:$D$4467,$A8),"") -> -0.035881558 | P8: =COUNTIFS(Events!$D$6:$D$4467,$A8,Events!$CN$6:$CN$4467,"Yes",Events!$CM$6:$CM$4467,"<>") -> 4 | Q8: =IFERROR(AVERAGEIFS(Events!$CM$6:$CM$4467,Events!$D$6:$D$4467,$A8,Events!$CN$6:$CN$4467,"Yes"),"") -> 0.086611906 | R8: =IFERROR(COUNTIFS(Events!$D$6:$D$4467,$A8,Events!$CM$6:$CM$4467,">0",Events!$CN$6:$CN$4467,"Yes")/COUNTIFS(Events!$D$6:$D$4467,$A8,Events!$CM$6:$CM$4467,"<>",Events!$CN$6:$CN$4467,"Yes"),"") -> 0.5
A9: ADANIGREEN | B9: =INDEX(Events!$E$6:$E$4467,MATCH($A9,Events!$D$6:$D$4467,0)) -> Adani Green Energy Limited | C9: =INDEX(Events!$F$6:$F$4467,MATCH($A9,Events!$D$6:$D$4467,0))&"" -> Power | D9: =COUNTIFS(Events!$D$6:$D$4467,$A9) -> 22 | E9: =COUNTIFS(Events!$D$6:$D$4467,$A9,Events!$L$6:$L$4467,"After close") -> 7 | F9: =IFERROR(AVERAGEIFS(Events!$U$6:$U$4467,Events!$D$6:$D$4467,$A9),"") -> -0.0047711245 | G9: =IFERROR(COUNTIFS(Events!$D$6:$D$4467,$A9,Events!$U$6:$U$4467,">0")/COUNTIFS(Events!$D$6:$D$4467,$A9,Events!$U$6:$U$4467,"<>"),"") -> 0.5 | H9: =IFERROR(AVERAGEIFS(Events!$X$6:$X$4467,Events!$D$6:$D$4467,$A9),"") -> -0.005228722 | I9: =IFERROR(AVERAGEIFS(Events!$AD$6:$AD$4467,Events!$D$6:$D$4467,$A9),"") -> 0.037266966 | J9: =IFERROR(COUNTIFS(Events!$D$6:$D$4467,$A9,Events!$AV$6:$AV$4467,">0")/COUNTIFS(Events!$D$6:$D$4467,$A9,Events!$AV$6:$AV$4467,"<>"),"") -> 0.90909091 | K9: =IFERROR(COUNTIFS(Events!$D$6:$D$4467,$A9,Events!$BB$6:$BB$4467,">0")/COUNTIFS(Events!$D$6:$D$4467,$A9,Events!$BB$6:$BB$4467,"<>"),"") -> 0.81818182 | L9: =IFERROR(AVERAGEIFS(Events!$AZ$6:$AZ$4467,Events!$D$6:$D$4467,$A9),"") -> 0.036274952 | M9: =IFERROR(AVERAGEIFS(Events!$CK$6:$CK$4467,Events!$D$6:$D$4467,$A9),"") -> 0.087514166 | N9: =IFERROR(AVERAGEIFS(Events!$CL$6:$CL$4467,Events!$D$6:$D$4467,$A9),"") -> 0.68843693 | O9: =IFERROR(AVERAGEIFS(Events!$CJ$6:$CJ$4467,Events!$D$6:$D$4467,$A9),"") -> 0.053175881 | P9: =COUNTIFS(Events!$D$6:$D$4467,$A9,Events!$CN$6:$CN$4467,"Yes",Events!$CM$6:$CM$4467,"<>") -> 3 | Q9: =IFERROR(AVERAGEIFS(Events!$CM$6:$CM$4467,Events!$D$6:$D$4467,$A9,Events!$CN$6:$CN$4467,"Yes"),"") -> 0.0031240639 | R9: =IFERROR(COUNTIFS(Events!$D$6:$D$4467,$A9,Events!$CM$6:$CM$4467,">0",Events!$CN$6:$CN$4467,"Yes")/COUNTIFS(Events!$D$6:$D$4467,$A9,Events!$CM$6:$CM$4467,"<>",Events!$CN$6:$CN$4467,"Yes"),"") -> 0.33333333
A10: ADANIPORTS | B10: =INDEX(Events!$E$6:$E$4467,MATCH($A10,Events!$D$6:$D$4467,0)) -> Adani Ports and Special Economic Zone Limited | C10: =INDEX(Events!$F$6:$F$4467,MATCH($A10,Events!$D$6:$D$4467,0))&"" -> Shipping | D10: =COUNTIFS(Events!$D$6:$D$4467,$A10) -> 22 | E10: =COUNTIFS(Events!$D$6:$D$4467,$A10,Events!$L$6:$L$4467,"After close") -> 6 | F10: =IFERROR(AVERAGEIFS(Events!$U$6:$U$4467,Events!$D$6:$D$4467,$A10),"") -> 0.027351832 | G10: =IFERROR(COUNTIFS(Events!$D$6:$D$4467,$A10,Events!$U$6:$U$4467,">0")/COUNTIFS(Events!$D$6:$D$4467,$A10,Events!$U$6:$U$4467,"<>"),"") -> 0.77272727 | H10: =IFERROR(AVERAGEIFS(Events!$X$6:$X$4467,Events!$D$6:$D$4467,$A10),"") -> 0.019994651 | I10: =IFERROR(AVERAGEIFS(Events!$AD$6:$AD$4467,Events!$D$6:$D$4467,$A10),"") -> 0.023798608 | J10: =IFERROR(COUNTIFS(Events!$D$6:$D$4467,$A10,Events!$AV$6:$AV$4467,">0")/COUNTIFS(Events!$D$6:$D$4467,$A10,Events!$AV$6:$AV$4467,"<>"),"") -> 1 | K10: =IFERROR(COUNTIFS(Events!$D$6:$D$4467,$A10,Events!$BB$6:$BB$4467,">0")/COUNTIFS(Events!$D$6:$D$4467,$A10,Events!$BB$6:$BB$4467,"<>"),"") -> 0.72727273 | L10: =IFERROR(AVERAGEIFS(Events!$AZ$6:$AZ$4467,Events!$D$6:$D$4467,$A10),"") -> 0.020888307 | M10: =IFERROR(AVERAGEIFS(Events!$CK$6:$CK$4467,Events!$D$6:$D$4467,$A10),"") -> 0.083374326 | N10: =IFERROR(AVERAGEIFS(Events!$CL$6:$CL$4467,Events!$D$6:$D$4467,$A10),"") -> 0.29593808 | O10: =IFERROR(AVERAGEIFS(Events!$CJ$6:$CJ$4467,Events!$D$6:$D$4467,$A10),"") -> -0.059160412 | P10: =COUNTIFS(Events!$D$6:$D$4467,$A10,Events!$CN$6:$CN$4467,"Yes",Events!$CM$6:$CM$4467,"<>") -> 2 | Q10: =IFERROR(AVERAGEIFS(Events!$CM$6:$CM$4467,Events!$D$6:$D$4467,$A10,Events!$CN$6:$CN$4467,"Yes"),"") -> -0.039406918 | R10: =IFERROR(COUNTIFS(Events!$D$6:$D$4467,$A10,Events!$CM$6:$CM$4467,">0",Events!$CN$6:$CN$4467,"Yes")/COUNTIFS(Events!$D$6:$D$4467,$A10,Events!$CM$6:$CM$4467,"<>",Events!$CN$6:$CN$4467,"Yes"),"") -> 0.5
A11: ADANIPOWER | B11: =INDEX(Events!$E$6:$E$4467,MATCH($A11,Events!$D$6:$D$4467,0)) -> Adani Power Limited | C11: =INDEX(Events!$F$6:$F$4467,MATCH($A11,Events!$D$6:$D$4467,0))&"" -> Power | D11: =COUNTIFS(Events!$D$6:$D$4467,$A11) -> 22 | E11: =COUNTIFS(Events!$D$6:$D$4467,$A11,Events!$L$6:$L$4467,"After close") -> 9 | F11: =IFERROR(AVERAGEIFS(Events!$U$6:$U$4467,Events!$D$6:$D$4467,$A11),"") -> 0.0076563333 | G11: =IFERROR(COUNTIFS(Events!$D$6:$D$4467,$A11,Events!$U$6:$U$4467,">0")/COUNTIFS(Events!$D$6:$D$4467,$A11,Events!$U$6:$U$4467,"<>"),"") -> 0.63636364 | H11: =IFERROR(AVERAGEIFS(Events!$X$6:$X$4467,Events!$D$6:$D$4467,$A11),"") -> 0.0073539365 | I11: =IFERROR(AVERAGEIFS(Events!$AD$6:$AD$4467,Events!$D$6:$D$4467,$A11),"") -> 0.022711194 | J11: =IFERROR(COUNTIFS(Events!$D$6:$D$4467,$A11,Events!$AV$6:$AV$4467,">0")/COUNTIFS(Events!$D$6:$D$4467,$A11,Events!$AV$6:$AV$4467,"<>"),"") -> 0.68181818 | K11: =IFERROR(COUNTIFS(Events!$D$6:$D$4467,$A11,Events!$BB$6:$BB$4467,">0")/COUNTIFS(Events!$D$6:$D$4467,$A11,Events!$BB$6:$BB$4467,"<>"),"") -> 0.5 | L11: =IFERROR(AVERAGEIFS(Events!$AZ$6:$AZ$4467,Events!$D$6:$D$4467,$A11),"") -> 0.019059252 | M11: =IFERROR(AVERAGEIFS(Events!$CK$6:$CK$4467,Events!$D$6:$D$4467,$A11),"") -> 0.089872865 | N11: =IFERROR(AVERAGEIFS(Events!$CL$6:$CL$4467,Events!$D$6:$D$4467,$A11),"") -> 0.19520299 | O11: =IFERROR(AVERAGEIFS(Events!$CJ$6:$CJ$4467,Events!$D$6:$D$4467,$A11),"") -> -0.055152584 | P11: =COUNTIFS(Events!$D$6:$D$4467,$A11,Events!$CN$6:$CN$4467,"Yes",Events!$CM$6:$CM$4467,"<>") -> 1 | Q11: =IFERROR(AVERAGEIFS(Events!$CM$6:$CM$4467,Events!$D$6:$D$4467,$A11,Events!$CN$6:$CN$4467,"Yes"),"") -> -0.32681942 | R11: =IFERROR(COUNTIFS(Events!$D$6:$D$4467,$A11,Events!$CM$6:$CM$4467,">0",Events!$CN$6:$CN$4467,"Yes")/COUNTIFS(Events!$D$6:$D$4467,$A11,Events!$CM$6:$CM$4467,"<>",Events!$CN$6:$CN$4467,"Yes"),"") -> 0
A12: ALKEM | B12: =INDEX(Events!$E$6:$E$4467,MATCH($A12,Events!$D$6:$D$4467,0)) -> Alkem Laboratories Limited | C12: =INDEX(Events!$F$6:$F$4467,MATCH($A12,Events!$D$6:$D$4467,0))&"" -> Pharmaceuticals | D12: =COUNTIFS(Events!$D$6:$D$4467,$A12) -> 22 | E12: =COUNTIFS(Events!$D$6:$D$4467,$A12,Events!$L$6:$L$4467,"After close") -> 1 | F12: =IFERROR(AVERAGEIFS(Events!$U$6:$U$4467,Events!$D$6:$D$4467,$A12),"") -> -0.0068119126 | G12: =IFERROR(COUNTIFS(Events!$D$6:$D$4467,$A12,Events!$U$6:$U$4467,">0")/COUNTIFS(Events!$D$6:$D$4467,$A12,Events!$U$6:$U$4467,"<>"),"") -> 0.36363636 | H12: =IFERROR(AVERAGEIFS(Events!$X$6:$X$4467,Events!$D$6:$D$4467,$A12),"") -> -0.001853203 | I12: =IFERROR(AVERAGEIFS(Events!$AD$6:$AD$4467,Events!$D$6:$D$4467,$A12),"") -> 0.019239297 | J12: =IFERROR(COUNTIFS(Events!$D$6:$D$4467,$A12,Events!$AV$6:$AV$4467,">0")/COUNTIFS(Events!$D$6:$D$4467,$A12,Events!$AV$6:$AV$4467,"<>"),"") -> 0.86363636 | K12: =IFERROR(COUNTIFS(Events!$D$6:$D$4467,$A12,Events!$BB$6:$BB$4467,">0")/COUNTIFS(Events!$D$6:$D$4467,$A12,Events!$BB$6:$BB$4467,"<>"),"") -> 0.68181818 | L12: =IFERROR(AVERAGEIFS(Events!$AZ$6:$AZ$4467,Events!$D$6:$D$4467,$A12),"") -> -0.0067219392 | M12: =IFERROR(AVERAGEIFS(Events!$CK$6:$CK$4467,Events!$D$6:$D$4467,$A12),"") -> 0.065644254 | N12: =IFERROR(AVERAGEIFS(Events!$CL$6:$CL$4467,Events!$D$6:$D$4467,$A12),"") -> 0.32917548 | O12: =IFERROR(AVERAGEIFS(Events!$CJ$6:$CJ$4467,Events!$D$6:$D$4467,$A12),"") -> -0.086151809 | P12: =COUNTIFS(Events!$D$6:$D$4467,$A12,Events!$CN$6:$CN$4467,"Yes",Events!$CM$6:$CM$4467,"<>") -> 9 | Q12: =IFERROR(AVERAGEIFS(Events!$CM$6:$CM$4467,Events!$D$6:$D$4467,$A12,Events!$CN$6:$CN$4467,"Yes"),"") -> 0.02108569 | R12: =IFERROR(COUNTIFS(Events!$D$6:$D$4467,$A12,Events!$CM$6:$CM$4467,">0",Events!$CN$6:$CN$4467,"Yes")/COUNTIFS(Events!$D$6:$D$4467,$A12,Events!$CM$6:$CM$4467,"<>",Events!$CN$6:$CN$4467,"Yes"),"") -> 0.33333333
A13: AMBER | B13: =INDEX(Events!$E$6:$E$4467,MATCH($A13,Events!$D$6:$D$4467,0)) -> Amber Enterprises India Limited | C13: =INDEX(Events!$F$6:$F$4467,MATCH($A13,Events!$D$6:$D$4467,0))&"" -> Consumer Durables | D13: =COUNTIFS(Events!$D$6:$D$4467,$A13) -> 22 | E13: =COUNTIFS(Events!$D$6:$D$4467,$A13,Events!$L$6:$L$4467,"After close") -> 8 | F13: =IFERROR(AVERAGEIFS(Events!$U$6:$U$4467,Events!$D$6:$D$4467,$A13),"") -> 0.01603554 | G13: =IFERROR(COUNTIFS(Events!$D$6:$D$4467,$A13,Events!$U$6:$U$4467,">0")/COUNTIFS(Events!$D$6:$D$4467,$A13,Events!$U$6:$U$4467,"<>"),"") -> 0.63636364 | H13: =IFERROR(AVERAGEIFS(Events!$X$6:$X$4467,Events!$D$6:$D$4467,$A13),"") -> 0.015523667 | I13: =IFERROR(AVERAGEIFS(Events!$AD$6:$AD$4467,Events!$D$6:$D$4467,$A13),"") -> 0.067218312 | J13: =IFERROR(COUNTIFS(Events!$D$6:$D$4467,$A13,Events!$AV$6:$AV$4467,">0")/COUNTIFS(Events!$D$6:$D$4467,$A13,Events!$AV$6:$AV$4467,"<>"),"") -> 0.81818182 | K13: =IFERROR(COUNTIFS(Events!$D$6:$D$4467,$A13,Events!$BB$6:$BB$4467,">0")/COUNTIFS(Events!$D$6:$D$4467,$A13,Events!$BB$6:$BB$4467,"<>"),"") -> 0.55555556 | L13: =IFERROR(AVERAGEIFS(Events!$AZ$6:$AZ$4467,Events!$D$6:$D$4467,$A13),"") -> 0.0028634851 | M13: =IFERROR(AVERAGEIFS(Events!$CK$6:$CK$4467,Events!$D$6:$D$4467,$A13),"") -> 0.080991597 | N13: =IFERROR(AVERAGEIFS(Events!$CL$6:$CL$4467,Events!$D$6:$D$4467,$A13),"") -> 0.84266153 | O13: =IFERROR(AVERAGEIFS(Events!$CJ$6:$CJ$4467,Events!$D$6:$D$4467,$A13),"") -> -0.19925 | P13: =COUNTIFS(Events!$D$6:$D$4467,$A13,Events!$CN$6:$CN$4467,"Yes",Events!$CM$6:$CM$4467,"<>") -> 4 | Q13: =IFERROR(AVERAGEIFS(Events!$CM$6:$CM$4467,Events!$D$6:$D$4467,$A13,Events!$CN$6:$CN$4467,"Yes"),"") -> 0.30297012 | R13: =IFERROR(COUNTIFS(Events!$D$6:$D$4467,$A13,Events!$CM$6:$CM$4467,">0",Events!$CN$6:$CN$4467,"Yes")/COUNTIFS(Events!$D$6:$D$4467,$A13,Events!$CM$6:$CM$4467,"<>",Events!$CN$6:$CN$4467,"Yes"),"") -> 0.5
A14: AMBUJACEM | B14: =INDEX(Events!$E$6:$E$4467,MATCH($A14,Events!$D$6:$D$4467,0)) -> Ambuja Cements Limited | C14: =INDEX(Events!$F$6:$F$4467,MATCH($A14,Events!$D$6:$D$4467,0))&"" -> Cement And Cement Products | D14: =COUNTIFS(Events!$D$6:$D$4467,$A14) -> 22 | E14: =COUNTIFS(Events!$D$6:$D$4467,$A14,Events!$L$6:$L$4467,"After close") -> 8 | F14: =IFERROR(AVERAGEIFS(Events!$U$6:$U$4467,Events!$D$6:$D$4467,$A14),"") -> -0.0093496194 | G14: =IFERROR(COUNTIFS(Events!$D$6:$D$4467,$A14,Events!$U$6:$U$4467,">0")/COUNTIFS(Events!$D$6:$D$4467,$A14,Events!$U$6:$U$4467,"<>"),"") -> 0.36363636 | H14: =IFERROR(AVERAGEIFS(Events!$X$6:$X$4467,Events!$D$6:$D$4467,$A14),"") -> -0.011325329 | I14: =IFERROR(AVERAGEIFS(Events!$AD$6:$AD$4467,Events!$D$6:$D$4467,$A14),"") -> 0.021031985 | J14: =IFERROR(COUNTIFS(Events!$D$6:$D$4467,$A14,Events!$AV$6:$AV$4467,">0")/COUNTIFS(Events!$D$6:$D$4467,$A14,Events!$AV$6:$AV$4467,"<>"),"") -> 0.9 | K14: =IFERROR(COUNTIFS(Events!$D$6:$D$4467,$A14,Events!$BB$6:$BB$4467,">0")/COUNTIFS(Events!$D$6:$D$4467,$A14,Events!$BB$6:$BB$4467,"<>"),"") -> 0.55 | L14: =IFERROR(AVERAGEIFS(Events!$AZ$6:$AZ$4467,Events!$D$6:$D$4467,$A14),"") -> -0.0074843104 | M14: =IFERROR(AVERAGEIFS(Events!$CK$6:$CK$4467,Events!$D$6:$D$4467,$A14),"") -> 0.071486612 | N14: =IFERROR(AVERAGEIFS(Events!$CL$6:$CL$4467,Events!$D$6:$D$4467,$A14),"") -> 0.35151951 | O14: =IFERROR(AVERAGEIFS(Events!$CJ$6:$CJ$4467,Events!$D$6:$D$4467,$A14),"") -> -0.074920093 | P14: =COUNTIFS(Events!$D$6:$D$4467,$A14,Events!$CN$6:$CN$4467,"Yes",Events!$CM$6:$CM$4467,"<>") -> 6 | Q14: =IFERROR(AVERAGEIFS(Events!$CM$6:$CM$4467,Events!$D$6:$D$4467,$A14,Events!$CN$6:$CN$4467,"Yes"),"") -> -0.06908887 | R14: =IFERROR(COUNTIFS(Events!$D$6:$D$4467,$A14,Events!$CM$6:$CM$4467,">0",Events!$CN$6:$CN$4467,"Yes")/COUNTIFS(Events!$D$6:$D$4467,$A14,Events!$CM$6:$CM$4467,"<>",Events!$CN$6:$CN$4467,"Yes"),"") -> 0.16666667
A15: ANANDRATHI | B15: =INDEX(Events!$E$6:$E$4467,MATCH($A15,Events!$D$6:$D$4467,0)) -> Anand Rathi Wealth Limited | C15: =INDEX(Events!$F$6:$F$4467,MATCH($A15,Events!$D$6:$D$4467,0))&"" -> Capital Markets | D15: =COUNTIFS(Events!$D$6:$D$4467,$A15) -> 19 | E15: =COUNTIFS(Events!$D$6:$D$4467,$A15,Events!$L$6:$L$4467,"After close") -> 17 | F15: =IFERROR(AVERAGEIFS(Events!$U$6:$U$4467,Events!$D$6:$D$4467,$A15),"") -> 0.025621134 | G15: =IFERROR(COUNTIFS(Events!$D$6:$D$4467,$A15,Events!$U$6:$U$4467,">0")/COUNTIFS(Events!$D$6:$D$4467,$A15,Events!$U$6:$U$4467,"<>"),"") -> 0.68421053 | H15: =IFERROR(AVERAGEIFS(Events!$X$6:$X$4467,Events!$D$6:$D$4467,$A15),"") -> 0.021537466 | I15: =IFERROR(AVERAGEIFS(Events!$AD$6:$AD$4467,Events!$D$6:$D$4467,$A15),"") -> 0.033376362 | J15: =IFERROR(COUNTIFS(Events!$D$6:$D$4467,$A15,Events!$AV$6:$AV$4467,">0")/COUNTIFS(Events!$D$6:$D$4467,$A15,Events!$AV$6:$AV$4467,"<>"),"") -> 1 | K15: =IFERROR(COUNTIFS(Events!$D$6:$D$4467,$A15,Events!$BB$6:$BB$4467,">0")/COUNTIFS(Events!$D$6:$D$4467,$A15,Events!$BB$6:$BB$4467,"<>"),"") -> 1 | L15: =IFERROR(AVERAGEIFS(Events!$AZ$6:$AZ$4467,Events!$D$6:$D$4467,$A15),"") -> -0.010104669 | M15: =IFERROR(AVERAGEIFS(Events!$CK$6:$CK$4467,Events!$D$6:$D$4467,$A15),"") | N15: =IFERROR(AVERAGEIFS(Events!$CL$6:$CL$4467,Events!$D$6:$D$4467,$A15),"") | O15: =IFERROR(AVERAGEIFS(Events!$CJ$6:$CJ$4467,Events!$D$6:$D$4467,$A15),"") | P15: =COUNTIFS(Events!$D$6:$D$4467,$A15,Events!$CN$6:$CN$4467,"Yes",Events!$CM$6:$CM$4467,"<>") -> 0 | Q15: =IFERROR(AVERAGEIFS(Events!$CM$6:$CM$4467,Events!$D$6:$D$4467,$A15,Events!$CN$6:$CN$4467,"Yes"),"") | R15: =IFERROR(COUNTIFS(Events!$D$6:$D$4467,$A15,Events!$CM$6:$CM$4467,">0",Events!$CN$6:$CN$4467,"Yes")/COUNTIFS(Events!$D$6:$D$4467,$A15,Events!$CM$6:$CM$4467,"<>",Events!$CN$6:$CN$4467,"Yes"),"")
... A215: ZYDUSLIFE | B215: =INDEX(Events!$E$6:$E$4467,MATCH($A215,Events!$D$6:$D$4467,0)) -> Zydus Lifesciences Limited | C215: =INDEX(Events!$F$6:$F$4467,MATCH($A215,Events!$D$6:$D$4467,0))&"" -> Pharmaceuticals | D215: =COUNTIFS(Events!$D$6:$D$4467,$A215) -> 22 | E215: =COUNTIFS(Events!$D$6:$D$4467,$A215,Events!$L$6:$L$4467,"After close") -> 1 | F215: =IFERROR(AVERAGEIFS(Events!$U$6:$U$4467,Events!$D$6:$D$4467,$A215),"") -> 0.015970044 | G215: =IFERROR(COUNTIFS(Events!$D$6:$D$4467,$A215,Events!$U$6:$U$4467,">0")/COUNTIFS(Events!$D$6:$D$4467,$A215,Events!$U$6:$U$4467,"<>"),"") -> 0.5 | H215: =IFERROR(AVERAGEIFS(Events!$X$6:$X$4467,Events!$D$6:$D$4467,$A215),"") -> 0.015194413 | I215: =IFERROR(AVERAGEIFS(Events!$AD$6:$AD$4467,Events!$D$6:$D$4467,$A215),"") -> 0.022042311 | J215: =IFERROR(COUNTIFS(Events!$D$6:$D$4467,$A215,Events!$AV$6:$AV$4467,">0")/COUNTIFS(Events!$D$6:$D$4467,$A215,Events!$AV$6:$AV$4467,"<>"),"") -> 0.90909091 | K215: =IFERROR(COUNTIFS(Events!$D$6:$D$4467,$A215,Events!$BB$6:$BB$4467,">0")/COUNTIFS(Events!$D$6:$D$4467,$A215,Events!$BB$6:$BB$4467,"<>"),"") -> 0.68181818 | L215: =IFERROR(AVERAGEIFS(Events!$AZ$6:$AZ$4467,Events!$D$6:$D$4467,$A215),"") -> 0.01243618 | M215: =IFERROR(AVERAGEIFS(Events!$CK$6:$CK$4467,Events!$D$6:$D$4467,$A215),"") -> 0.061672751 | N215: =IFERROR(AVERAGEIFS(Events!$CL$6:$CL$4467,Events!$D$6:$D$4467,$A215),"") -> 0.39731734 | O215: =IFERROR(AVERAGEIFS(Events!$CJ$6:$CJ$4467,Events!$D$6:$D$4467,$A215),"") -> -0.078176719 | P215: =COUNTIFS(Events!$D$6:$D$4467,$A215,Events!$CN$6:$CN$4467,"Yes",Events!$CM$6:$CM$4467,"<>") -> 15 | Q215: =IFERROR(AVERAGEIFS(Events!$CM$6:$CM$4467,Events!$D$6:$D$4467,$A215,Events!$CN$6:$CN$4467,"Yes"),"") -> -0.034015468 | R215: =IFERROR(COUNTIFS(Events!$D$6:$D$4467,$A215,Events!$CM$6:$CM$4467,">0",Events!$CN$6:$CN$4467,"Yes")/COUNTIFS(Events!$D$6:$D$4467,$A215,Events!$CM$6:$CM$4467,"<>",Events!$CN$6:$CN$4467,"Yes"),"") -> 0.33333333

Sheet Events
A1: F&O stocks - results report, last 22 quarters (no conditions applied)
A2: 4462 results events, 212 stocks. All data from NSE: results date/time (NSE filings), prices (equity bhavcopy), indices, financials (results XBRL), options (F&O bhavcopy). See Notes.
A4: Stock & quarter | J4: Results timing | R4: 3-day window (Day -1, Result day, Day +1) | AB4: Reaction day | AH4: Before results (2 sessions before result day) | AP4: After results | AS4: Results: this quarter (Rs crore) | BF4: Banks only | BM4: Valuation & ratios (before results) | BU4: Cash flow (latest half-year or year) | BZ4: Peers (same industry, same quarter) | CF4: Options (NSE F&O) | CO4: Notes
A5: Quarter | B5: Quarter period | C5: Quarter end | D5: Symbol | E5: Company | F5: Industry | G5: Industry source | H5: Sector index | I5: Lot size | J5: Results date | K5: Results time (IST) | L5: Timing | M5: Time source | N5: Day -1 | O5: Result day | P5: Day +1 | Q5: Reaction day | R5: Day -1 % | S5: Result day % | T5: Day +1 % | U5: Three-day sum % | V5: Nifty 50 3-day % | W5: Sector 3-day % | X5: Excess vs Nifty % | Y5: Excess vs sector % | Z5: Peer median 3-day % | AA5: Vs peers 3-day % | AB5: Gap at open % | AC5: Close move % | AD5: Size of move % | AE5: High-low range % | AF5: Close in range (0 low-1 high) | AG5: Volume vs 20D avg (x) | AH5: Price (Rs) | AI5: 1W % | AJ5: 1M % | AK5: 3M % | AL5: 6M % | AM5: 1Y % | AN5: Sector 1M % | AO5: 1M vs sector % | AP5: Next 5 sessions % | AQ5: Next 20 sessions % | AR5: Next 20 vs Nifty % | AS5: Basis | AT5: Type | AU5: Sales / Interest earned | AV5: Sales YoY % | AW5: Sales QoQ % | AX5: EBITDA | AY5: EBITDA margin % | AZ5: EBITDA margin chg YoY (pts) | BA5: Net profit | BB5: Net profit YoY % | BC5: Net profit QoQ % | BD5: Net margin % | BE5: EPS (Rs) | BF5: Net interest income | BG5: NII YoY % | BH5: Pre-provision profit YoY % | BI5: Provisions YoY % | BJ5: Gross NPA % | BK5: Net NPA % | BL5: ROA % (quarter) | BM5: Market cap (Rs cr) | BN5: TTM net profit | BO5: P/E | BP5: P/B | BQ5: ROE % | BR5: Debt / equity | BS5: Sector index P/E | BT5: Sector index P/B | BU5: Cash-flow period | BV5: Operating cash flow | BW5: Capex | BX5: Free cash flow | BY5: CFO / net profit (x) | BZ5: Peers (n) | CA5: Peer median sales YoY % | CB5: Peer median profit YoY % | CC5: Profit growth rank | CD5: Peer median P/E | CE5: P/E vs peers % | CF5: Expiry used | CG5: IV 5 sessions before | CH5: IV before results | CI5: IV after results | CJ5: IV drop % | CK5: Expected move % (straddle) | CL5: Actual / expected move (x) | CM5: Run-up straddle return % | CN5: Run-up rule pass | CO5: Data notes
A6: Q4 FY21 | B6: Jan-Mar 2021 | C6: 44286 | D6: TCS | E6: Tata Consultancy Services Limited | F6: Computers - Software | G6: NSE | H6: Nifty IT | I6: 225 | J6: 44298 | K6: 18:43 | L6: After close | M6: NSE announcement | N6: 44295 | O6: 44298 | P6: 44299 | Q6: 44299 | R6: 0.0014770826 | S6: -0.022785763 | T6: -0.043892748 | U6: -0.065201428 | V6: -0.024388105 | W6: -0.048098071 | X6: -0.040813323 | Y6: -0.017103357 | Z6: 0.0021188294 | AA6: -0.067320257 | AB6: -0.010026028 | AC6: -0.043892748 | AD6: 0.043892748 | AE6: 0.043415318 | AF6: 0.21993615 | AG6: 2.4275005 | AH6: 3317.35 | AI6: 0.043897604 | AJ6: 0.10282409 | AK6: 0.072534756 | AL6: 0.22217515 | AM6: 0.94514644 | AN6: 0.076053524 | AO6: 0.026770564 | AP6: 0.0047518564 | AQ6: -0.016929495 | AR6: -0.028856582 | AS6: Consolidated | AT6: Company | AU6: 43705 | AV6: 0.094102038 | AW6: 0.04022373 | AX6: 12801 | AY6: 0.29289555 | AZ6: 0.018124609 | BA6: 9246 | BB6: 0.14871413 | BC6: 0.062636479 | BD6: 0.21155474 | BE6: 24.97 | BM6: 1244006.2 | BN6: 31233 | BO6: 39.829867 | BS6: 30.09 | BT6: 8.73 | BZ6: 12 | CA6: 0.0567063 | CB6: 0.27771268 | CC6: 10 of 12 | CD6: 33.437503 | CE6: 0.19117348 | CF6: 44315 | CG6: 0.32674744 | CH6: 0.35235434 | CI6: 0.2940141 | CJ6: -0.16557265 | CK6: 0.058685916 | CL6: 0.74792643 | CM6: -0.14695953 | CN6: Yes
A7: Q4 FY21 | B7: Jan-Mar 2021 | C7: 44286 | D7: INFY | E7: Infosys Limited | F7: Computers - Software | G7: NSE | H7: Nifty IT | I7: 400 | J7: 44300 | K7: 16:09 | L7: Non-trading day | M7: NSE announcement | N7: 44299 | O7: 44301 | P7: 44302 | Q7: 44301 | R7: -0.020059618 | S7: -0.026053037 | T7: -0.0051442219 | U7: -0.051256876 | V7: 0.021336975 | W7: -0.014547926 | X7: -0.072593851 | Y7: -0.03670895 | Z7: 0.0021188294 | AA7: -0.053375706 | AB7: -0.046415918 | AC7: -0.026053037 | AD7: 0.026053037 | AE7: 0.033210464 | AF7: 0.87823276 | AG7: 2.9511967 | AH7: 1425.75 | AI7: 0.011241932 | AJ7: 0.059603879 | AK7: 0.12962009 | AL7: 0.30360245 | AM7: 1.2368215 | AN7: 0.044775011 | AO7: 0.014828869 | AP7: -0.007534626 | AQ7: -0.010156971 | AR7: -0.043694735 | AS7: Consolidated | AT7: Company | AU7: 26311 | AV7: 0.13082907 | AW7: 0.014810815 | AX7: 7271 | AY7: 0.2763483 | AZ7: 0.032397636 | BA7: 5076 | BB7: 0.17472807 | BC7: -0.023282663 | BD7: 0.19292311 | BE7: 11.96 | BM7: 605373.45 | BN7: 18596 | BO7: 32.553961 | BS7: 29.62 | BT7: 8.6 | BZ7: 12 | CA7: 0.0567063 | CB7: 0.27771268 | CC7: 8 of 12 | CD7: 35.888344 | CE7: -0.092909932 | CF7: 44315 | CG7: 0.36419299 | CH7: 0.39872287 | CI7: 0.31165834 | CJ7: -0.21835849 | CK7: 0.063307401 | CL7: 0.41153224 | CM7: -0.1243461 | CN7: Yes
A8: Q4 FY21 | B8: Jan-Mar 2021 | C8: 44286 | D8: WIPRO | E8: Wipro Limited | F8: Computers - Software | G8: NSE | H8: Nifty IT | I8: 3000 | J8: 44301 | K8: 15:45 | L8: After close | M8: NSE announcement | N8: 44299 | O8: 44301 | P8: 44302 | Q8: 44302 | R8: -0.031553398 | S8: 0.028046306 | T8: 0.089389366 | U8: 0.085882274 | V8: 0.021336975 | W8: -0.014547926 | X8: 0.064545299 | Y8: 0.1004302 | Z8: -0.0057262579 | AA8: 0.091608532 | AB8: 0.025539819 | AC8: 0.089389366 | AD8: 0.089389366 | AE8: 0.087415835 | AF8: 0.88180611 | AG8: 8.6323825 | AH8: 432.6 | AI8: 0.016805735 | AJ8: 0.031965649 | AK8: 0.063552551 | AL8: 0.20350536 | AM8: 1.2864693 | AN8: 0.044775011 | AO8: -0.012809362 | AP8: 0.023657289 | AQ8: 0.082800512 | AR8: 0.049262748 | AS8: Consolidated | AT8: Company | AU8: 16245.4 | AV8: 0.031421225 | AW8: 0.036719847 | AX8: 4027.6 | AY8: 0.24792249 | AZ8: 0.049871633 | BA8: 2972.3 | BB8: 0.27780405 | BC8: 0.0014487871 | BD8: 0.18296256 | BE8: 5.39 | BM8: 247252.53 | BN8: 10150.2 | BO8: 24.359375 | BS8: 29.62 | BT8: 8.6 | BZ8: 12 | CA8: 0.075925207 | CB8: 0.25896704 | CC8: 5 of 12 | CD8: 35.888344 | CE8: -0.3212455 | CF8: 44315 | CG8: 0.4202012 | CH8: 0.40680809 | CI8: 0.37180905 | CJ8: -0.086033305 | CK8: 0.061460259 | CL8: 1.4544255 | CM8: -0.25368825 | CN8: Yes
A9: Q4 FY21 | B9: Jan-Mar 2021 | C9: 44286 | D9: HDFCBANK | E9: HDFC Bank Limited | F9: Banks | G9: NSE | H9: Nifty Bank | I9: 650 | J9: 44303 | K9: 14:32 | L9: Non-trading day | M9: NSE announcement | N9: 44302 | O9: 44305 | P9: 44306 | Q9: 44305 | R9: -0.0010139151 | S9: -0.011374374 | T9: -0.014868309 | U9: -0.027256599 | V9: -0.019571532 | W9: -0.031332623 | X9: -0.0076850663 | Y9: 0.0040760241 | Z9: -0.010168456 | AA9: -0.017088143 | AB9: -0.027053512 | AC9: -0.011374374 | AD9: 0.011374374 | AE9: 0.031778252 | AF9: 0.88325991 | AG9: 1.1148687 | AH9: 1430.1 | AI9: -0.01181592 | AJ9: -0.078514127 | AK9: -0.014709429 | AL9: 0.17834631 | AM9: 0.62557545 | AN9: -0.095327306 | AO9: 0.016813178 | AP9: 0.06137703 | AQ9: 0.029754204 | AR9: -0.012889398 | AS9: Standalone | AT9: Bank | AU9: 30423.59 | AV9: 0.018020041 | AW9: 0.011432627 | BA9: 8186.51 | BB9: 0.18170848 | BC9: -0.065284433 | BD9: 0.26908429 | BE9: 14.9 | BF9: 17120.15 | BG9: 0.12602489 | BH9: 0.19862534 | BI9: 0.24024637 | BJ9: 0.0132 | BK9: 0.004 | BL9: 0.005 | BM9: 787656.18 | BN9: 29857.71 | BO9: 26.380328 | BS9: 24.94 | BT9: 2.92 | BZ9: 19 | CA9: 0.0068971806 | CB9: 0.48380133 | CC9: 9 of 13 | CD9: 29.632537 | CE9: -0.10975129 | CF9: 44315 | CG9: 0.36721832 | CH9: 0.34706209 | CI9: 0.32627965 | CJ9: -0.05988104 | CK9: 0.04951636 | CL9: 0.22970942 | CM9: -0.29713473 | CN9: Yes
A10: Q4 FY21 | B10: Jan-Mar 2021 | C10: 44286 | D10: ICICIGI | E10: ICICI Lombard General Insurance Company Limited | F10: Insurance | G10: Assigned | H10: Nifty Financial Services | I10: 325 | J10: 44303 | K10: 17:16 | L10: Non-trading day | M10: NSE announcement (no filing record) | N10: 44302 | O10: 44305 | P10: 44306 | Q10: 44305 | R10: 0.022032309 | S10: -0.039833469 | T10: 0.028147277 | U10: 0.010346118 | V10: -0.019571532 | W10: -0.030416157 | X10: 0.02991765 | Y10: 0.040762275 | Z10: 0.044991299 | AA10: -0.034645181 | AB10: -0.0050453375 | AC10: -0.039833469 | AD10: 0.039833469 | AE10: 0.053875737 | AF10: 0.35428946 | AG10: 2.2458503 | AH10: 1386.6 | AI10: -0.043394274 | AJ10: -0.057504078 | AK10: -0.13859725 | AL10: 0.14784768 | AM10: 0.19818535 | AN10: -0.067789063 | AO10: 0.010284985 | AP10: 0.018513224 | AQ10: 0.092101501 | AR10: 0.049457898 | BS10: 25.32 | BT10: 3.97 | BZ10: 4 | CA10: 1.2888397 | CD10: 101.10041 | CO10: no NSE XBRL results for this quarter; no option prices for this event
A11: Q4 FY21 | B11: Jan-Mar 2021 | C11: 44286 | D11: ICICIPRULI | E11: ICICI Prudential Life Insurance Company Limited | F11: Insurance | G11: Assigned | H11: Nifty Financial Services | I11: 925 | J11: 44305 | K11: 18:38 | L11: After close | M11: NSE announcement (no filing record) | N11: 44302 | O11: 44305 | P11: 44306 | Q11: 44306 | R11: -0.010855263 | S11: 0.0022170491 | T11: 0.057294547 | U11: 0.048656333 | V11: -0.019571532 | W11: -0.030416157 | X11: 0.068227865 | Y11: 0.07907249 | Z11: 0.025836191 | AA11: 0.022820142 | AB11: 0.029753346 | AC11: 0.057294547 | AD11: 0.057294547 | AE11: 0.10927995 | AF11: 0.25202429 | AG11: 10.517608 | AH11: 456 | AI11: 0.00032905561 | AJ11: -0.01255955 | AK11: -0.133327 | AL11: 0.088695237 | AM11: 0.36180379 | AN11: -0.067789063 | AO11: 0.055229513 | AP11: 0.089758343 | AQ11: 0.13380061 | AR11: 0.091157004 | BS11: 25.32 | BT11: 3.97 | BZ11: 4 | CA11: 1.2888397 | CD11: 101.10041 | CF11: 44315 | CG11: 0.38857242 | CH11: 0.46464013 | CI11: 0.40474766 | CJ11: -0.12890078 | CK11: 0.061759823 | CL11: 0.92769934 | CM11: -0.085467306 | CN11: Yes | CO11: no NSE XBRL results for this quarter
A12: Q4 FY21 | B12: Jan-Mar 2021 | C12: 44286 | D12: INDUSTOWER | E12: Indus Towers Limited | F12: Telecommunication - Services | G12: Assigned | H12: Nifty Services Sector | I12: 1700 | J12: 44308 | K12: 17:40 | L12: After close | M12: NSE announcement | N12: 44306 | O12: 44308 | P12: 44309 | Q12: 44309 | R12: 0.011460186 | S12: 0.017581559 | T12: -0.03148397 | U12: -0.0024422254 | V12: -0.0012121579 | W12: 0.0042922838 | X12: -0.0012300676 | Y12: -0.0067345093 | Z12: -0.092289858 | AA12: 0.089847633 | AB12: 0.013246304 | AC12: -0.03148397 | AD12: 0.03148397 | AE12: 0.067767326 | AF12: 0.053824363 | AG12: 2.6567316 | AH12: 253.05 | AI12: -0.014410906 | AJ12: -0.035816346 | AK12: -0.01956606 | AL12: 0.33500396 | AM12: 0.58851224 | AN12: -0.050359832 | AO12: 0.014543486 | AP12: 0.00099108028 | AQ12: -0.040237859 | AR12: -0.099949811 | AS12: Consolidated | AT12: Company | AU12: 6491.8 | AV12: 2.8593425 | AW12: 0.59868988 | AX12: 3412.3 | AY12: 0.52563234 | AZ12: 0.012345373 | BA12: 1363.7 | BB12: 1.0996151 | BC12: 0.39280972 | BD12: 0.21006501 | BE12: 5.06 | BM12: 68194.444 | BN12: 3064.8 | BO12: 22.250863 | BS12: 29.27 | BT12: 4.42 | BZ12: 2 | CA12: -0.048639833 | CF12: 44315 | CG12: 0.4830804 | CH12: 0.60487545 | CI12: 0.53725719 | CJ12: -0.11178874 | CK12: 0.067929583 | CL12: 0.46347951 | CM12: 0.16600751 | CN12: Yes
A13: Q4 FY21 | B13: Jan-Mar 2021 | C13: 44286 | D13: TATAELXSI | E13: Tata Elxsi Limited | F13: Computers - Software | G13: NSE | H13: Nifty IT | I13: 125 | J13: 44308 | K13: 18:30 | L13: After close | M13: NSE announcement | N13: 44306 | O13: 44308 | P13: 44309 | Q13: 44309 | R13: -0.016297219 | S13: 0.016067202 | T13: 0.045126472 | U13: 0.044896455 | V13: -0.0012121579 | W13: -0.024086795 | X13: 0.046108613 | Y13: 0.06898325 | Z13: -0.0057262579 | AA13: 0.050622713 | AB13: 0.033430662 | AC13: 0.045126472 | AD13: 0.045126472 | AE13: 0.069731964 | AF13: 0.27381793 | AG13: 3.8368946 | AH13: 3049.6 | AI13: -0.01676554 | AJ13: 0.10036263 | AK13: 0.28574741 | AL13: 1.0899839 | AM13: 3.1809707 | AN13: -0.0048153058 | AO13: 0.10517793 | AP13: 0.092430116 | AQ13: 0.124433 | AR13: 0.064721052 | BM13: 18991.811 | BN13: 335.0349 | BO13: 56.686067 | BS13: 28.27 | BT13: 8.44 | BZ13: 12 | CA13: 0.066315753 | CB13: 0.26833986 | CD13: 33.437503 | CE13: 0.69528409 | CO13: no NSE XBRL results for this quarter; no option prices for this event
A14: Q4 FY21 | B14: Jan-Mar 2021 | C14: 44286 | D14: HCLTECH | E14: HCL Technologies Limited | F14: Computers - Software | G14: NSE | H14: Nifty IT | I14: 400 | J14: 44309 | K14: 17:31 | L14: After close | M14: NSE announcement | N14: 44308 | O14: 44309 | P14: 44312 | Q14: 44312 | R14: 0.00062415479 | S14: -0.0064975569 | T14: -0.02809606 | U14: -0.033969462 | V14: 0.01319517 | W14: -0.0076120796 | X14: -0.047164632 | Y14: -0.026357383 | Z14: 0.0021188294 | AA14: -0.036088292 | AB14: -0.016376288 | AC14: -0.02809606 | AD14: 0.02809606 | AE14: 0.032909538 | AF14: 0.18282989 | AG14: 3.50259 | AH14: 961.3 | AI14: -0.047652071 | AJ14: -0.026482354 | AK14: -0.064610295 | AL14: 0.1177907 | AM14: 1.1095019 | AN14: -0.01168293 | AO14: -0.014799423 | AP14: -0.022717485 | AQ14: 0.012704565 | AR14: -0.037240205 | AS14: Consolidated | AT14: Company | AU14: 19641 | AV14: 0.0567063 | AW14: 0.017562947 | AX14: 4549 | AY14: 0.23160735 | AZ14: -0.029758119 | BA14: 1102 | BB14: -0.65258512 | BC14: -0.7223482 | BD14: 0.056107123 | BE14: 4.06 | BM14: 260863.17 | BN14: 13215 | BO14: 19.73993 | BS14: 27.88 | BT14: 8.32 | BZ14: 12 | CA14: 0.075925207 | CB14: 0.27771268 | CC14: 12 of 12 | CD14: 35.888344 | CE14: -0.44996264 | CF14: 44315 | CG14: 0.38409796 | CH14: 0.49724767 | CI14: 0.28225156 | CJ14: -0.43237228 | CK14: 0.049952676 | CL14: 0.56245355 | CM14: -0.013537118 | CN14: Yes
A15: Q4 FY21 | B15: Jan-Mar 2021 | C15: 44286 | D15: ICICIBANK | E15: ICICI Bank Limited | F15: Banks | G15: NSE | H15: Nifty Bank | I15: 700 | J15: 44310 | K15: 17:59 | L15: Non-trading day | M15: NSE announcement | N15: 44309 | O15: 44312 | P15: 44313 | Q15: 44312 | R15: -0.015970304 | S15: 0.037108518 | T15: 0.012941973 | U15: 0.034080187 | V15: 0.017120069 | W15: 0.029789187 | X15: 0.016960118 | Y15: 0.0042910005 | Z15: -0.012781967 | AA15: 0.046862154 | AB15: 0.056233003 | AC15: 0.037108518 | AD15: 0.037108518 | AE15: 0.030704448 | AF15: 0.17714286 | AG15: 2.4353753 | AH15: 579.2 | AI15: 0.033178737 | AJ15: 0.0010369858 | AK15: 0.066666667 | AL15: 0.46225701 | AM15: 0.72406608 | AN15: -0.061263912 | AO15: 0.062300897 | AP15: -0.012025052 | AQ15: 0.089770355 | AR15: 0.045520182 | AS15: Standalone | AT15: Bank | AU15: 19841.67 | AV15: 0.034029959 | AW15: 0.0056706128 | BA15: 4402.61 | BB15: 2.6046784 | BC15: -0.10870943 | BD15: 0.22188707 | BE15: 6.37 | BF15: 10431.13 | BG15: 0.16850661 | BH15: 0.15557862 | BI15: -0.5167995 | BJ15: 0.0533 | BK15: 0.0124 | BL15: 0.0151 | BM15: 399923.12 | BN15: 13011.43 | BO15: 30.736293 | BS15: 24.57 | BT15: 2.89 | BZ15: 19 | CA15: 0.0068971806 | CB15: 0.3548314 | CC15: 1 of 13 | CD15: 26.380328 | CE15: 0.16512171 | CF15: 44315 | CG15: 0.38560863 | CH15: 0.50351809 | CI15: 0.30711722 | CJ15: -0.39005722 | CK15: 0.050582975 | CL15: 0.73361676 | CM15: -0.14241562 | CN15: Yes
A16: Q4 FY21 | B16: Jan-Mar 2021 | C16: 44286 | D16: HDFCLIFE | E16: HDFC Life Insurance Company Limited | F16: Insurance | G16: Assigned | H16: Nifty Financial Services | I16: 1100 | J16: 44312 | K16: 17:59 | L16: After close | M16: NSE announcement (no filing record) | N16: 44309 | O16: 44312 | P16: 44313 | Q16: 44313 | R16: 0.010750313 | S16: 0.026371385 | T16: -0.036482362 | U16: 0.00063933567 | V16: 0.017120069 | W16: 0.02282346 | X16: -0.016480733 | Y16: -0.022184124 | Z16: 0.044991299 | AA16: -0.044351963 | AB16: 0.0093690113 | AC16: -0.036482362 | AD16: 0.036482362 | AE16: 0.059620981 | AF16: 0.041666667 | AG16: 3.7742574 | AH16: 679.05 | AI16: -0.038309021 | AJ16: -0.0026437541 | AK16: -0.036603533 | AL16: 0.21010425 | AM16: 0.34825772 | AN16: -0.038432417 | AO16: 0.035788663 | AP16: -0.016058932 | AQ16: -0.029834254 | AR16: -0.074084427 | BS16: 24.84 | BT16: 3.93 | BZ16: 4 | CA16: 1.2888397 | CD16: 101.10041 | CF16: 44343 | CH16: 0.35737728 | CI16: 0.30429679 | CJ16: -0.1485279 | CK16: 0.084377433 | CL16: 0.43237108 | CO16: no NSE XBRL results for this quarter
A17: Q4 FY21 | B17: Jan-Mar 2021 | C17: 44286 | D17: SBICARD | E17: SBI Cards and Payment Services Limited | F17: Finance | G17: Assigned | H17: Nifty Financial Services | I17: 800 | J17: 44312 | K17: 15:43 | L17: After close | M17: NSE announcement | N17: 44309 | O17: 44312 | P17: 44313 | Q17: 44313 | R17: -0.0070967059 | S17: -0.019255387 | T17: 0.038396693 | U17: 0.0120446 | V17: 0.017120069 | W17: 0.02282346 | X17: -0.0050754685 | Y17: -0.010778859 | Z17: 0.032646975 | AA17: -0.020602374 | AB17: 0.00070702127 | AC17: 0.038396693 | AD17: 0.038396693 | AE17: 0.058737151 | AF17: 0.82685185 | AG17: 2.3380259 | AH17: 944.1 | AI17: 0.051336303 | AJ17: -0.056277489 | AK17: -0.011879219 | AL17: 0.073328786 | AM17: 0.77329076 | AN17: -0.038432417 | AO17: -0.017845072 | AP17: 0.0011522548 | AQ17: 0.073796679 | AR17: 0.029546506 | AS17: Standalone | AT17: NBFC / financial | AU17: 2308.68 | AV17: -0.051192018 | AW17: -0.039329973 | BA17: 175.42 | BB17: 1.0997143 | BC17: -0.16330724 | BD17: 0.075982813 | BE17: 1.87 | BM17: 88795.012 | BN17: 892.6453 | BO17: 99.474016 | BS17: 24.84 | BT17: 3.93 | BZ17: 10 | CA17: 0.11153335 | CB17: 1.6257713 | CC17: 6 of 10 | CD17: 16.666663 | CE17: 4.9684422 | CO17: no option prices for this event
A18: Q4 FY21 | B18: Jan-Mar 2021 | C18: 44286 | D18: TECHM | E18: Tech Mahindra Limited | F18: Computers - Software | G18: NSE | H18: Nifty IT | I18: 600 | J18: 44312 | K18: 20:21 | L18: After close | M18: NSE announcement | N18: 44309 | O18: 44312 | P18: 44313 | Q18: 44313 | R18: -0.018185576 | S18: 0.01262892 | T18: 0.0073269591 | U18: 0.0017703037 | V18: 0.017120069 | W18: -0.00037065643 | X18: -0.015349765 | Y18: 0.0021409602 | Z18: -0.0053777322 | AA18: 0.007148036 | AB18: 0.00051964249 | AC18: 0.0073269591 | AD18: 0.0073269591 | AE18: 0.045156932 | AF18: 0.57767549 | AG18: 2.4328434 | AH18: 967.8 | AI18: -0.033987124 | AJ18: -0.028508332 | AK18: -0.03921374 | AL18: 0.176299 | AM18: 0.86725834 | AN18: 0.017867172 | AO18: -0.046375503 | AP18: -0.0091307712 | AQ18: 0.03977302 | AR18: -0.0044771528 | AS18: Consolidated | AT18: Company | AU18: 9729.9 | AV18: 0.025259579 | AW18: 0.0085874799 | AX18: 1897.6 | AY18: 0.1950277 | AZ18: 0.075769501 | BA18: 1081.4 | BB18: 0.34522231 | BC18: -0.17434663 | BD18: 0.11114194 | BE18: 12.37 | BM18: 84500.747 | BN18: 4150.6152 | BO18: 20.358608 | BS18: 27.82 | BT18: 8.31 | BZ18: 12 | CA18: 0.075925207 | CB18: 0.25896704 | CC18: 4 of 12 | CD18: 35.888344 | CE18: -0.43272368 | CF18: 44343 | CH18: 0.35159746 | CI18: 0.37219026 | CJ18: 0.058569243 | CK18: 0.08363561 | CL18: 0.087605735
A19: Q4 FY21 | B19: Jan-Mar 2021 | C19: 44286 | D19: ABB | E19: ABB India Limited | F19: Electrical Equipment | G19: NSE | H19: Nifty 500 | I19: 125 | J19: 44313 | K19: 16:01 | L19: After close | M19: NSE announcement | N19: 44312 | O19: 44313 | P19: 44314 | Q19: 44314 | R19: -0.0084015355 | S19: 0.011138704 | T19: 0.0025643804 | U19: 0.0053015492 | V19: 0.036052003 | W19: 0.033686335 | X19: -0.030750454 | Y19: -0.028384786 | Z19: -0.0046784497 | AA19: 0.0099799989 | AB19: 0.017156066 | AC19: 0.0025643804 | AD19: 0.0025643804 | AE19: 0.05363528 | AF19: 0.34882155 | AG19: 3.0994736 | AH19: 1380.7 | AI19: 0.023157583 | AJ19: -0.023446617 | AK19: 0.026924507 | AL19: 0.54018629 | AM19: 0.53104901 | AN19: -0.016963742 | AO19: -0.0064828755 | AP19: -0.012428849 | AQ19: 0.13787016 | AR19: 0.10602931 | AS19: Standalone | AT19: Company | AU19: 1629.15 | AV19: 0.070232026 | AW19: -0.042104706 | AX19: 206.78 | AY19: 0.12692508 | AZ19: 0.080092784 | BA19: 141.33 | BB19: 1.1864171 | BC19: 1.4553509 | BD19: 0.08675076 | BE19: 6.67 | BM19: 29257.033 | BN19: 219.22 | BO19: 133.45969 | BS19: 34.92 | BT19: 3.9 | BZ19: 9 | CA19: 0.41994847 | CB19: 0.53055694 | CC19: 1 of 5 | CD19: 75.274196 | CE19: 0.7729806 | CO19: no option prices for this event
A20: Q4 FY21 | B20: Jan-Mar 2021 | C20: 44286 | D20: AXISBANK | E20: Axis Bank Limited | F20: Banks | G20: NSE | H20: Nifty Bank | I20: 625 | J20: 44313 | K20: 16:47 | L20: After close | M20: NSE announcement | N20: 44312 | O20: 44313 | P20: 44314 | Q20: 44314 | R20: 0.043345498 | S20: -0.0012848883 | T20: 0.012293617 | U20: 0.054354227 | V20: 0.036052003 | W20: 0.06185109 | X20: 0.018302224 | Y20: -0.0074968627 | Z20: -0.012781967 | AA20: 0.067136194 | AB20: 0.012079194 | AC20: 0.012293617 | AD20: 0.012293617 | AE20: 0.034808091 | AF20: 0.82135524 | AG20: 3.1453721 | AH20: 671.35 | AI20: 0.0037377588 | AJ20: -0.075593804 | AK20: 0.021841705 | AL20: 0.36190283 | AM20: 0.56109755 | AN20: -0.071404735 | AO20: -0.0041890686 | AP20: 0.012779778 | AQ20: 0.059591894 | AR20: 0.027751038 | AS20: Standalone | AT20: Bank | AU20: 15545.16 | AV20: -0.042438421 | AW20: 0.0030203215 | BA20: 2677.06 | BC20: 1.3975103 | BD20: 0.1722118 | BE20: 8.74 | BF20: 7554.98 | BG20: 0.1097633 | BH20: 0.17322183 | BI20: -0.57374237 | BJ20: 0.037 | BK20: 0.0105 | BL20: 0.0111 | BM20: 205530.45 | BN20: 2523.66 | BO20: 81.441417 | BS20: 24.52 | BT20: 2.88 | BZ20: 19 | CA20: 0.013687632 | CB20: 0.38140606 | CD20: 26.380328 | CE20: 2.0872026 | CF20: 44343 | CG20: 0.41439739 | CH20: 0.42668648 | CI20: 0.37342292 | CJ20: -0.12483068 | CK20: 0.098032226 | CL20: 0.12540384 | CM20: 0.16212518 | CN20: No
A21: Q4 FY21 | B21: Jan-Mar 2021 | C21: 44286 | D21: BAJFINANCE | E21: Bajaj Finance Limited | F21: Finance | G21: NSE | H21: Nifty Financial Services | I21: 750 | J21: 44313 | K21: 17:39 | L21: After close | M21: NSE announcement | N21: 44312 | O21: 44313 | P21: 44314 | Q21: 44314 | R21: 0.014728566 | S21: 0.027129451 | T21: 0.085477025 | U21: 0.12733504 | V21: 0.036052003 | W21: 0.051803602 | X21: 0.091283039 | Y21: 0.075531439 | Z21: 0.015075048 | AA21: 0.11225999 | AB21: 0.010267109 | AC21: 0.085477025 | AD21: 0.085477025 | AE21: 0.081191355 | AF21: 0.92632911 | AG21: 3.2102147 | AH21: 4667.8 | AI21: 0.0016093385 | AJ21: -0.14403337 | AK21: -0.011027893 | AL21: 0.42868511 | AM21: 1.148634 | AN21: -0.046736543 | AO21: -0.097296831 | AP21: 0.044357969 | AQ21: 0.075990835 | AR21: 0.044149979 | AS21: Consolidated | AT21: NBFC / financial | AU21: 6850.62 | AV21: -0.052024609 | AW21: 0.029221228 | BA21: 1346.64 | BB21: 0.4203565 | BC21: 0.17509904 | BD21: 0.19657199 | BE21: 22.4 | BM21: 280488.1 | BN21: 4021.28 | BO21: 69.75095 | BS21: 24.84 | BT21: 3.93 | BZ21: 10 | CA21: 0.11153335 | CB21: 1.6257713 | CC21: 7 of 10 | CD21: 16.666663 | CE21: 3.1850579 | CF21: 44343 | CG21: 0.43814808 | CH21: 0.41648364 | CI21: 0.41204537 | CJ21: -0.010656548 | CK21: 0.096082003 | CL21: 0.88962576 | CM21: 0.09199947 | CN21: No
A22: Q4 FY21 | B22: Jan-Mar 2021 | C22: 44286 | D22: BRITANNIA | E22: Britannia Industries Limited | F22: Food And Food Processing | G22: NSE | H22: Nifty FMCG | I22: 125 | J22: 44313 | K22: 17:43 | L22: After close | M22: NSE announcement | N22: 44312 | O22: 44313 | P22: 44314 | Q22: 44314 | R22: -0.030435855 | S22: 0.00056509946 | T22: -0.017635265 | U22: -0.04750602 | V22: 0.036052003 | W22: 0.011903543 | X22: -0.083558023 | Y22: -0.059409563 | Z22: 0.036085948 | AA22: -0.083591968 | AB22: -0.015023156 | AC22: -0.017635265 | AD22: 0.017635265 | AE22: 0.016378629 | AF22: 0.16810345 | AG22: 2.6769016 | AH22: 3650.3 | AI22: -0.011482113 | AJ22: 0.052991404 | AK22: 0.01176601 | AL22: -0.032379488 | AM22: 0.23848137 | AN22: -0.0088822996 | AO22: 0.061873703 | AP22: -0.0078045275 | AQ22: -0.018426159 | AR22: -0.050267015 | AS22: Standalone | AT22: Company | AU22: 2952.64 | AV22: 0.029619556 | AW22: -0.067276133 | AX22: 487.82 | AY22: 0.16521486 | AZ22: 0.0068998326 | BA22: 353.46 | BB22: -0.056811207 | BC22: -0.22444323 | BD22: 0.11970982 | BE22: 14.67 | BM22: 87935.727 | BN22: 1874.33 | BO22: 46.915819 | BS22: 41.38 | BT22: 10.15 | BZ22: 4 | CA22: 0.29933713 | CB22: 1.7678704 | CC22: 3 of 3 | CD22: 90.328409 | CE22: -0.48060838 | CF22: 44343 | CH22: 0.26519895 | CI22: 0.24885152 | CJ22: -0.061642135 | CK22: 0.061026176 | CL22: 0.2889787
A23: Q4 FY21 | B23: Jan-Mar 2021 | C23: 44286 | D23: HDFCAMC | E23: HDFC Asset Management Company Limited | F23: Capital Markets | G23: Assigned | H23: Nifty Financial Services | I23: 300 | J23: 44313 | K23: 16:00 | L23: After close | M23: NSE announcement | N23: 44312 | O23: 44313 | P23: 44314 | Q23: 44314 | R23: 0.0035430839 | S23: 0.011562632 | T23: -0.020644643 | U23: -0.0055389271 | V23: 0.036052003 | W23: 0.051803602 | X23: -0.04159093 | Y23: -0.057342529 | Z23: -0.033087986 | AA23: 0.027549059 | AB23: -0.0042755179 | AC23: -0.020644643 | AD23: 0.020644643 | AE23: 0.026769977 | AF23: 0.36245111 | AG23: 2.6301459 | AH23: 2822.4 | AI23: -0.043092049 | AJ23: -0.0169279 | AK23: -0.11408258 | AL23: 0.2118766 | AM23: 0.089225069 | AN23: -0.046736543 | AO23: 0.029808643 | AP23: -0.027102637 | AQ23: 0.012045617 | AR23: -0.01979524 | AS23: Standalone | AT23: NBFC / financial | AU23: 502.93 | AV23: 0.056287148 | AW23: 0.043726394 | BA23: 316.08 | BB23: 0.26518032 | BC23: -0.14401777 | BD23: 0.62847712 | BE23: 14.84 | BM23: 60100.186 | BN23: 1259.51 | BO23: 47.717117 | BS23: 24.84 | BT23: 3.93 | BZ23: 7 | CA23: 0.27283372 | CB23: 0.80928352 | CC23: 4 of 4 | CD23: 39.637453 | CE23: 0.20383911 | CF23: 44343 | CH23: 0.35154918 | CI23: 0.28543916 | CJ23: -0.18805342 | CK23: 0.081213767 | CL23: 0.25420128
A24: Q4 FY21 | B24: Jan-Mar 2021 | C24: 44286 | D24: HINDZINC | E24: Hindustan Zinc Limited | F24: Metals | G24: NSE | H24: Nifty Metal | I24: 1225 | J24: 44313 | K24: 14:40 | L24: During market | M24: NSE announcement | N24: 44312 | O24: 44313 | P24: 44314 | Q24: 44313 | R24: 0.015356368 | S24: 0.04800263 | T24: -0.033098039 | U24: 0.030260959 | V24: 0.036052003 | W24: 0.044171248 | X24: -0.0057910438 | Y24: -0.013910289 | AB24: 0.012658228 | AC24: 0.04800263 | AD24: 0.04800263 | AE24: 0.052112445 | AF24: 0.76971609 | AG24: 4.2717525 | AH24: 299.55 | AI24: 0.026735219 | AJ24: 0.057173107 | AK24: 0.1152271 | AL24: 0.35604346 | AM24: 0.74715661 | AN24: 0.16030007 | AO24: -0.10312696 | AP24: -0.065379624 | AQ24: 0.066677482 | AR24: 0.034836626 | AS24: Standalone | AT24: Company | AU24: 6947 | AV24: 0.58209975 | AW24: 0.15150008 | AX24: 3875 | AY24: 0.55779473 | AZ24: 0.11051621 | BA24: 2481 | BB24: 0.85287528 | BC24: 0.12772727 | BD24: 0.35713258 | BE24: 5.87 | BM24: 126559.88 | BN24: 6838 | BO24: 18.508317 | BS24: 30.64 | BT24: 2.02 | BZ24: 1 | CO24: no option prices for this event
A25: Q4 FY21 | B25: Jan-Mar 2021 | C25: 44286 | D25: MARUTI | E25: Maruti Suzuki India Limited | F25: Automobiles - 4 Wheelers | G25: NSE | H25: Nifty Auto | I25: 50 | J25: 44313 | K25: 14:07 | L25: During market | M25: NSE announcement | N25: 44312 | O25: 44313 | P25: 44314 | Q25: 44313 | R25: -0.0055721155 | S25: -0.01056651 | T25: 0.00076879163 | U25: -0.015369833 | V25: 0.036052003 | W25: 0.028380954 | X25: -0.051421836 | Y25: -0.043750788 | Z25: 0.0073963897 | AA25: -0.022766223 | AB25: 0.0046769796 | AC25: -0.01056651 | AD25: 0.01056651 | AE25: 0.02515477 | AF25: 0.16017964 | AG25: 1.9384726 | AH25: 6676.1 | AI25: 0.0047936185 | AJ25: -0.061495315 | AK25: -0.14743987 | AL25: -0.025664227 | AM25: 0.29473368 | AN25: -0.05787562 | AO25: -0.0036196956 | AP25: 0.00247954 | AQ25: 0.060102224 | AR25: 0.028261368 | AS25: Consolidated | AT25: Company | AU25: 24034.5 | AV25: 0.32001845 | AW25: 0.023995262 | AX25: 1994.7 | AY25: 0.082993197 | AZ25: -0.0020257782 | BA25: 1241.1 | BB25: -0.061337165 | BC25: -0.3784244 | BD25: 0.05163827 | BE25: 41.09 | BM25: 201618.22 | BN25: 4471.6 | BO25: 45.088608 | BS25: 694.02 | BT25: 4.37 | BZ25: 4 | CA25: 0.3748844 | CB25: 9.6199612 | CC25: 3 of 3 | CD25: 63.746181 | CE25: -0.29268534 | CF25: 44343 | CG25: 0.31998455 | CH25: 0.33612571 | CI25: 0.32004454 | CJ25: -0.047842725 | CK25: 0.079213445 | CL25: 0.13339288 | CM25: -0.068428508 | CN25: No
A26: Q4 FY21 | B26: Jan-Mar 2021 | C26: 44286 | D26: NAM-INDIA | E26: Nippon Life India Asset Management Limited | F26: Capital Markets | G26: Assigned | H26: Nifty Financial Services | I26: 625 | J26: 44313 | K26: 16:15 | L26: After close | M26: NSE announcement | N26: 44312 | O26: 44313 | P26: 44314 | Q26: 44314 | R26: 0.015351551 | S26: 0.030087693 | T26: 0.0022016733 | U26: 0.047640917 | V26: 0.036052003 | W26: 0.051803602 | X26: 0.011588914 | Y26: -0.0041626857 | Z26: -0.033087986 | AA26: 0.080728902 | AB26: 0.015411713 | AC26: 0.0022016733 | AD26: 0.0022016733 | AE26: 0.043593131 | AF26: 0.42087542 | AG26: 1.4681584 | AH26: 325.7 | AI26: -0.021039976 | AJ26: -0.0033659731 | AK26: -0.027616062 | AL26: 0.19347746 | AM26: 0.2365224 | AN26: -0.046736543 | AO26: 0.04337057 | AP26: -0.0067369654 | AQ26: 0.018892794 | AR26: -0.012948062 | AS26: Consolidated | AT26: NBFC / financial | AU26: 301.9 | AV26: 0.099817851 | AW26: 0.12456232 | BA26: 166.77 | BB26: 43.830645 | BC26: -0.21316348 | BD26: 0.55240146 | BE26: 2.71 | BM26: 19963.782 | BN26: 517.28 | BO26: 38.593763 | BS26: 24.84 | BT26: 3.93 | BZ26: 7 | CA26: 0.27283372 | CB26: 0.34862222 | CC26: 1 of 4 | CD26: 47.382455 | CE26: -0.1854841 | CF26: 44343
A27: Q4 FY21 | B27: Jan-Mar 2021 | C27: 44286 | D27: PNBHOUSING | E27: PNB Housing Finance Limited | F27: Finance - Housing | G27: Assigned | H27: Nifty Financial Services | I27: 650 | J27: 44313 | K27: 20:33 | L27: After close | M27: NSE announcement | N27: 44312 | O27: 44313 | P27: 44314 | Q27: 44314 | R27: 0.02740109 | S27: 0.026262076 | T27: 0.0014584991 | U27: 0.055121666 | V27: 0.036052003 | W27: 0.051803602 | X27: 0.019069663 | Y27: 0.0033180638 | AB27: -0.0031821798 | AC27: 0.0014584991 | AD27: 0.0014584991 | AE27: 0.04176611 | AF27: 0.46984127 | AG27: 2.2553708 | AH27: 357.65 | AI27: -0.028125 | AJ27: -0.087394744 | AK27: 0.01923625 | AL27: -0.017175048 | AM27: 0.66503724 | AN27: -0.046736543 | AO27: -0.0406582 | AP27: -0.050178737 | AQ27: 0.13716404 | AR27: 0.10532318 | AS27: Consolidated | AT27: NBFC / financial | AU27: 1831.68 | AV27: -0.05895892 | AW27: -0.029146592 | BA27: 127.03 | BC27: -0.45339931 | BD27: 0.069351633 | BE27: 7.55 | BM27: 6015.3153 | BN27: 560.81 | BO27: 10.72612 | BS27: 24.84 | BT27: 3.93 | BZ27: 1 | CO27: no option prices for this event
A28: Q4 FY21 | B28: Jan-Mar 2021 | C28: 44286 | D28: TVSMOTOR | E28: TVS Motor Company Limited | F28: Automobiles - 2 And 3 Wheelers | G28: NSE | H28: Nifty Auto | I28: 175 | J28: 44313 | K28: 18:43 | L28: After close | M28: NSE announcement | N28: 44312 | O28: 44313 | P28: 44314 | Q28: 44314 | R28: 0.03734985 | S28: 0.024606477 | T28: 0.14038495 | U28: 0.20234128 | V28: 0.036052003 | W28: 0.028380954 | X28: 0.16628928 | Y28: 0.17396033 | Z28: 0.02205161 | AA28: 0.18028967 | AB28: 0.068338337 | AC28: 0.14038495 | AD28: 0.14038495 | AE28: 0.11831185 | AF28: 0.72835821 | AG28: 25.596323 | AH28: 532.8 | AI28: -0.018061187 | AJ28: -0.087749337 | AK28: 0.066239744 | AL28: 0.17137518 | AM28: 0.7828342 | AN28: -0.05787562 | AO28: -0.029873717 | AP28: -0.064958191 | AQ28: 0.0070455249 | AR28: -0.024795331 | AS28: Consolidated | AT28: Company | AU28: 6131.9 | AV28: 0.49386924 | AW28: 0.0060689986 | AX28: 771.5 | AY28: 0.12581745 | AZ28: 0.0083867388 | BA28: 310.05 | BB28: 3.1876013 | BC28: 0.093072448 | BD28: 0.050563447 | BE28: 6.53 | BM28: 25313.328 | BN28: 359.73 | BO28: 70.367576 | BS28: 694.02 | BT28: 4.37 | BZ28: 2 | CA28: 0.31656814 | CB28: 0.30135016 | CC28: 1 of 3 | CD28: 22.253127 | CE28: 2.1621433 | CF28: 44343 | CH28: 0.43929375 | CI28: 0.46125818 | CJ28: 0.049999395 | CK28: 0.10111072 | CL28: 1.388428
A29: Q4 FY21 | B29: Jan-Mar 2021 | C29: 44286 | D29: BAJAJFINSV | E29: Bajaj Finserv Limited | F29: Finance | G29: NSE | H29: Nifty Financial Services | I29: 300 | J29: 44314 | K29: 12:28 | L29: During market | M29: NSE announcement | N29: 44313 | O29: 44314 | P29: 44315 | Q29: 44314 | R29: 0.0089584323 | S29: 0.039434763 | T29: 0.065519148 | U29: 0.11391234 | V29: 0.028077282 | W29: 0.039222448 | X29: 0.085835061 | Y29: 0.074689896 | Z29: 0.015075048 | AA29: 0.098837296 | AB29: 0.010766647 | AC29: 0.039434763 | AD29: 0.039434763 | AE29: 0.046059249 | AF29: 0.72751721 | AG29: 2.2402573 | AH29: 10001.75 | AI29: 0.018015726 | AJ29: 0.063354189 | AK29: 0.120751 | AL29: 0.6804439 | AM29: 1.2784068 | AN29: -0.023120125 | AO29: 0.086474314 | AP29: -0.013295695 | AQ29: 0.048015711 | AR29: 0.011711339 | AS29: Consolidated | AT29: NBFC / financial | AU29: 15386.88 | AV29: 0.15740865 | AW29: -0.035820968 | BA29: 979.06 | BB29: 4.0355398 | BC29: -0.24101523 | BD29: 0.063629534 | BE29: 61.5 | BM29: 159167.85 | BN29: 3685.83 | BO29: 43.18372 | BS29: 25.16 | BT29: 3.98 | BZ29: 10 | CA29: 0.047978884 | CB29: 1.0997143 | CC29: 2 of 10 | CD29: 16.666663 | CE29: 1.5910237 | CF29: 44343 | CH29: 0.40423803 | CI29: 0.4167024 | CJ29: 0.030834227 | CK29: 0.093146157 | CL29: 0.42336436
A30: Q4 FY21 | B30: Jan-Mar 2021 | C30: 44286 | D30: BIOCON | E30: Biocon Limited | F30: Pharmaceuticals | G30: NSE | H30: Nifty Pharma | I30: 2500 | J30: 44314 | K30: 23:50 | L30: After close | M30: NSE announcement | N30: 44313 | O30: 44314 | P30: 44315 | Q30: 44315 | R30: 0.006573957 | S30: -0.018211505 | T30: 0.0078035052 | U30: -0.0038340424 | V30: 0.028077282 | W30: 0.0071900775 | X30: -0.031911325 | Y30: -0.01102412 | Z30: -0.010567215 | AA30: 0.0067331729 | AB30: -0.0072917999 | AC30: 0.0078035052 | AD30: 0.0078035052 | AE30: 0.041703979 | AF30: 0.48773006 | AG30: 3.6446567 | AH30: 395.5 | AI30: -0.042024949 | AJ30: -0.016780609 | AK30: -0.12422498 | AL30: -0.1007276 | AM30: 0.10660325 | AN30: 0.11417843 | AO30: -0.13095904 | AP30: -0.036049759 | AQ30: -0.029829906 | AR30: -0.066134279 | AS30: Consolidated | AT30: Company | AU30: 1838.7 | AV30: 0.1629981 | AW30: -0.0066450567 | AX30: 448.4 | AY30: 0.24386795 | AZ30: 0.042349924 | BA30: 253.2 | BB30: 1.0518639 | BC30: 0.50177936 | BD30: 0.13770599 | BE30: 2.13 | BM30: 47460 | BN30: 629.1 | BO30: 75.441106 | BS30: 34.8 | BT30: 5.43 | BZ30: 11 | CA30: 0.03339128 | CB30: 0.48692379 | CC30: 3 of 11 | CD30: 34.5243 | CE30: 1.1851596 | CF30: 44343 | CH30: 0.47810213 | CI30: 0.42333605 | CJ30: -0.11454892 | CK30: 0.10725755 | CL30: 0.072754836
A31: Q4 FY21 | B31: Jan-Mar 2021 | C31: 44286 | D31: KPITTECH | E31: KPIT Technologies Limited | F31: Computers - Software | G31: Assigned | H31: Nifty IT | I31: 775 | J31: 44314 | K31: 16:45 | L31: After close | M31: NSE announcement | N31: 44313 | O31: 44314 | P31: 44315 | Q31: 44315 | R31: -0.0020166373 | S31: -0.019449356 | T31: 0.0082431736 | U31: -0.01322282 | V31: 0.028077282 | W31: 0.0075616382 | X31: -0.041300102 | Y31: -0.020784458 | Z31: 0.0021188294 | AA31: -0.015341649 | AB31: 0.05615662 | AC31: 0.0082431736 | AD31: 0.0082431736 | AE31: 0.072127769 | AF31: 0.05 | AG31: 1.7809843 | AH31: 198.35 | AI31: 0.035499869 | AJ31: 0.22476073 | AK31: 0.41830533 | AL31: 0.75608676 | AM31: 3.1108808 | AN31: -0.013637228 | AO31: 0.23839796 | AP31: 0.043178334 | AQ31: 0.23965253 | AR31: 0.20334816 | AS31: Consolidated | AT31: Company | AU31: 540.327 | AV31: -0.028587198 | AW31: 0.044624888 | AX31: 87.559 | AY31: 0.16204817 | AZ31: 0.038498112 | BA31: 46.753 | BB31: 0.25896704 | BC31: 0.11921576 | BD31: 0.086527233 | BE31: 1.74 | BM31: 5335.3373 | BN31: 130.814 | BO31: 40.785675 | BS31: 27.67 | BT31: 8.26 | BZ31: 12 | CA31: 0.075925207 | CB31: 0.27771268 | CC31: 7 of 12 | CD31: 33.437503 | CE31: 0.21975839 | CO31: no option prices for this event
A32: Q4 FY21 | B32: Jan-Mar 2021 | C32: 44286 | D32: AMBUJACEM | E32: Ambuja Cements Limited | F32: Cement And Cement Products | G32: NSE | H32: Nifty Commodities | I32: 1200 | J32: 44315 | K32: 17:09 | L32: After close | M32: NSE announcement | N32: 44314 | O32: 44315 | P32: 44316 | Q32: 44316 | R32: 0.0075028543 | S32: 0.016836652 | T32: -0.015921032 | U32: 0.0084184748 | V32: -0.0012351345 | W32: 0.017182236 | X32: 0.0096536092 | Y32: -0.0087637613 | Z32: -0.00024657504 | AA32: 0.0086650498 | AB32: -0.00015921032 | AC32: -0.015921032 | AD32: 0.015921032 | AE32: 0.041713103 | AF32: 0.17557252 | AG32: 2.8704683 | AH32: 306.55 | AI32: 0.018607742 | AJ32: 0.0068976843 | AK32: 0.16959176 | AL32: 0.20998619 | AM32: 0.77916425 | AN32: 0.025000832 | AO32: -0.018103148 | AP32: 0.010354312 | AQ32: 0.057434072 | AR32: -0.0076123017 | AS32: Consolidated | AT32: Company | AU32: 7714.81 | AV32: 0.23443675 | AW32: 0.035146192 | AX32: 1838.49 | AY32: 0.23830658 | AZ32: 0.047683412 | BA32: 947.21 | BB32: 0.70899414 | BC32: 0.29357861 | BD32: 0.12277814 | BE32: 4.77 | BM32: 60870.101 | BN32: 2365.44 | BO32: 25.733099 | BS32: 23.5 | BT32: 2.25 | BZ32: 3 | CA32: 0.23124674 | CB32: 0.13920192 | CC32: 1 of 4 | CD32: 26.850061 | CE32: -0.041600005 | CF32: 44343 | CH32: 0.48937276 | CI32: 0.43233308 | CJ32: -0.11655672 | CK32: 0.10734283 | CL32: 0.14831948
A33: Q4 FY21 | B33: Jan-Mar 2021 | C33: 44286 | D33: AUBANK | E33: AU Small Finance Bank Limited | F33: Banks | G33: Assigned | H33: Nifty Bank | I33: 1000 | J33: 44315 | K33: 20:31 | L33: After close | M33: NSE announcement | N33: 44314 | O33: 44315 | P33: 44316 | Q33: 44316 | R33: 0.058021735 | S33: -0.021152507 | T33: -0.10689195 | U33: -0.070022724 | V33: -0.0012351345 | W33: 0.0022538596 | X33: -0.068787589 | Y33: -0.072276583 | Z33: -0.010168456 | AA33: -0.059854268 | AB33: -0.046687417 | AC33: -0.10689195 | AD33: 0.10689195 | AE33: 0.079101823 | AF33: 0.10399101 | AG33: 3.4466906 | AH33: 1085.8 | AI33: 0.068858591 | AJ33: -0.12808159 | AK33: 0.17976857 | AL33: 0.40365846 | AM33: 1.1034483 | AN33: -0.042389218 | AO33: -0.085692368 | AP33: -0.075126954 | AQ33: -0.015682565 | AR33: -0.080728939 | AS33: Standalone | AT33: Bank | AU33: 1292.369 | AV33: 0.092034506 | AW33: 0.024784131 | BA33: 168.9787 | BB33: 0.38140606 | BC33: -0.64724141 | BD33: 0.13075112 | BE33: 5.49 | BF33: 655.8305 | BG33: 0.18180157 | BH33: 0.18375606 | BI33: 0.18070001 | BJ33: 0.0425 | BK33: 0.0218 | BL33: 0.0034 | BM33: 33307.849 | BN33: 1124.0296 | BO33: 29.632537 | BS33: 24.15 | BT33: 2.98 | BZ33: 19 | CA33: 0.0068971806 | CB33: 0.45722667 | CC33: 7 of 13 | CD33: 26.380328 | CE33: 0.12328161 | CF33: 44343 | CH33: 0.56836241 | CI33: 0.54656307 | CJ33: -0.038354662 | CK33: 0.12483388 | CL33: 0.85627357
A34: Q4 FY21 | B34: Jan-Mar 2021 | C34: 44286 | D34: BAJAJ-AUTO | E34: Bajaj Auto Limited | F34: Automobiles - 2 And 3 Wheelers | G34: NSE | H34: Nifty Auto | I34: 75 | J34: 44315 | K34: 17:16 | L34: After close | M34: NSE announcement | N34: 44314 | O34: 44315 | P34: 44316 | Q34: 44316 | R34: 0.027539295 | S34: -0.01370268 | T34: -0.00070377563 | U34: 0.013132839 | V34: -0.0012351345 | W34: -0.0066790776 | X34: 0.014367973 | Y34: 0.019811917 | Z34: 0.11665583 | AA34: -0.10352299 | AB34: -0.0081976828 | AC34: -0.00070377563 | AD34: 0.00070377563 | AE34: 0.043360398 | AF34: 0.20288548 | AG34: 1.9772833 | AH34: 3785.5 | AI34: 0.076787416 | AJ34: 0.029129909 | AK34: 0.038845209 | AL34: 0.25430749 | AM34: 0.51072533 | AN34: -0.047061884 | AO34: 0.076191793 | AP34: 0.00860776 | AQ34: 0.093655037 | AR34: 0.028608664 | AS34: Consolidated | AT34: Company | AU34: 8596.1 | AV34: 0.26119266 | AW34: -0.035217085 | AX34: 1521.88 | AY34: 0.17704308 | AZ34: -0.0067315066 | BA34: 1551.28 | BB34: 0.14571009 | BC34: -0.096127626 | BD34: 0.18046323 | BE34: 53.6 | BM34: 109541.01 | BN34: 4659.73 | BO34: 23.508017 | BS34: 702.07 | BT34: 4.42 | BZ34: 2 | CA34: 0.43290643 | CB34: 1.8222958 | CC34: 3 of 3 | CD34: 45.682906 | CE34: -0.48540889 | CF34: 44343 | CG34: 0.3175408 | CH34: 0.38373449 | CI34: 0.35541451 | CJ34: -0.073800964 | CK34: 0.084060362 | CL34: 0.008372265 | CM34: 0.30427275 | CN34: No
A35: Q4 FY21 | B35: Jan-Mar 2021 | C35: 44286 | D35: BAJAJHLDNG | E35: Bajaj Holdings & Investment Limited | F35: Finance | G35: NSE | H35: Nifty Financial Services | I35: 75 | J35: 44315 | K35: 16:46 | L35: After close | M35: NSE announcement | N35: 44314 | O35: 44315 | P35: 44316 | Q35: 44316 | R35: 0.019232753 | S35: 0.015298302 | T35: -0.025521249 | U35: 0.0090098069 | V35: -0.0012351345 | W35: -0.00099190311 | X35: 0.010244941 | Y35: 0.01000171 | Z35: 0.032646975 | AA35: -0.023637168 | AB35: 0.025407315 | AC35: -0.025521249 | AD35: 0.025521249 | AE35: 0.068075652 | AF35: 0.046861925 | AG35: 1.8879106 | AH35: 3392.65 | AI35: 0.017408385 | AJ35: -0.016551924 | AK35: 0.044792437 | AL35: 0.44432619 | AM35: 0.78800495 | AN35: -0.022274278 | AO35: 0.0057223541 | AP35: 0.030252543 | AQ35: 0.037779142 | AR35: -0.027267232 | AS35: Consolidated | AT35: NBFC / financial | AU35: 92.49 | AV35: -0.16268332 | AW35: -0.078142131 | BA35: 948.98 | BB35: 1.6257713 | BC35: -0.17449851 | BD35: 10.260352 | BE35: 85.3 | BM35: 37756.802 | BN35: 3062.26 | BO35: 12.329718 | BS35: 24.5 | BT35: 4.02 | BZ35: 10 | CA35: 0.11153335 | CB35: 1.0997143 | CC35: 5 of 10 | CD35: 25.005002 | CE35: -0.50690995 | CO35: no option prices for this event
A36: Q4 FY21 | B36: Jan-Mar 2021 | C36: 44286 | D36: HINDUNILVR | E36: Hindustan Unilever Limited | F36: Diversified | G36: NSE | H36: Nifty 500 | I36: 300 | J36: 44315 | K36: 13:32 | L36: During market | M36: NSE announcement | N36: 44314 | O36: 44315 | P36: 44316 | Q36: 44315 | R36: 0.011219194 | S36: 0.00043630924 | T36: -0.022366672 | U36: -0.010711168 | V36: -0.0012351345 | W36: 0.00031578712 | X36: -0.009476034 | Y36: -0.011026956 | AB36: 0.010990838 | AC36: 0.00043630924 | AD36: 0.00043630924 | AE36: 0.026926513 | AF36: 0.36188272 | AG36: 1.4627195 | AH36: 2379.85 | AI36: -0.023310693 | AJ36: 0.018204766 | AK36: 0.010144528 | AL36: 0.10017798 | AM36: 0.025598483 | AN36: -0.0044091711 | AO36: 0.022613937 | AP36: 0.02440786 | AQ36: -0.0058204992 | AR36: -0.070866873 | AS36: Consolidated | AT36: Company | AU36: 12433 | AV36: 0.34979915 | AW36: 0.020687957 | AX36: 3057 | AY36: 0.24587791 | AZ36: 0.024295016 | BA36: 2186 | BB36: 0.44290429 | BC36: 0.1285493 | BD36: 0.17582241 | BE36: 9.31 | BM36: 559264.75 | BN36: 7324 | BO36: 76.360561 | BS36: 35.22 | BT36: 3.98 | BZ36: 0 | CF36: 44343 | CG36: 0.28213435 | CH36: 0.28417845 | CI36: 0.27963588 | CJ36: -0.015984937 | CK36: 0.063832435 | CL36: 0.0068352279 | CM36: -0.15826914 | CN36: No
A37: Q4 FY21 | B37: Jan-Mar 2021 | C37: 44286 | D37: LAURUSLABS | E37: Laurus Labs Limited | F37: Pharmaceuticals | G37: Assigned | H37: Nifty Pharma | I37: 850 | J37: 44315 | K37: 14:44 | L37: During market | M37: NSE announcement | N37: 44314 | O37: 44315 | P37: 44316 | Q37: 44315 | R37: 0.015944355 | S37: -0.034969454 | T37: -0.011678673 | U37: -0.030703772 | V37: -0.0012351345 | W37: 0.012982621 | X37: -0.029468637 | Y37: -0.043686393 | Z37: -0.0084068451 | AA37: -0.022296927 | AB37: 0.010954287 | AC37: -0.034969454 | AD37: 0.034969454 | AE37: 0.067305667 | AF37: 0.22065728 | AG37: 2.1499346 | AH37: 467.25 | AI37: 0.060846861 | AJ37: 0.29360465 | AK37: 0.25638613 | AL37: 0.39958065 | AM37: 3.5105705 | AN37: 0.1166983 | AO37: 0.17690635 | AP37: 0.076532303 | AQ37: 0.15681944 | AR37: 0.091773063 | AS37: Consolidated | AT37: Company | AU37: 1411.93 | AV37: 0.68258769 | AW37: 0.095861598 | AX37: 472.19 | AY37: 0.33442876 | AZ37: 0.10589771 | BA37: 296.92 | BB37: 1.6955969 | BC37: 0.088216969 | BD37: 0.21029371 | BE37: 5.53 | BM37: 25072.635 | BN37: 797.05 | BO37: 31.456791 | BS37: 35.04 | BT37: 5.47 | BZ37: 11 | CA37: 0.03339128 | CB37: 0.48692379 | CC37: 1 of 11 | CD37: 37.095173 | CE37: -0.15199774 | CO37: no option prices for this event
A38: Q4 FY21 | B38: Jan-Mar 2021 | C38: 44286 | D38: LTF | E38: L&T Finance Limited | F38: Finance | G38: Assigned | H38: Nifty Financial Services | I38: 2250 | J38: 44315 | K38: 17:50 | L38: After close | M38: NSE announcement | N38: 44314 | O38: 44315 | P38: 44316 | Q38: 44316 | R38: 0.038439796 | S38: -0.021230267 | T38: -0.031701891 | U38: -0.014492361 | V38: -0.0012351345 | W38: -0.00099190311 | X38: -0.013257227 | Y38: -0.013500458 | Z38: 0.032646975 | AA38: -0.047139336 | AB38: -0.021134594 | AC38: -0.031701891 | AD38: 0.031701891 | AE38: 0.032814238 | AF38: 0.18644068 | AG38: 1.6882137 | AH38: 88.45 | AI38: -0.0011293055 | AJ38: -0.12077535 | AK38: -0.1482908 | AL38: 0.40174326 | AM38: 0.44172779 | AN38: -0.022274278 | AO38: -0.09850107 | AP38: -0.0034462952 | AQ38: 0.076392878 | AR38: 0.011346504 | AS38: Consolidated | AT38: NBFC / financial | AU38: 3415.16 | AV38: 0.017858633 | AW38: -0.025195309 | BA38: 243.66 | BB38: -0.36900168 | BC38: -0.16170096 | BD38: 0.071346584 | BE38: 1.18 | BM38: 17751.738 | BN38: 1090.24 | BO38: 16.282413 | BS38: 24.5 | BT38: 4.02 | BZ38: 10 | CA38: 0.11153335 | CB38: 1.6257713 | CC38: 10 of 10 | CD38: 25.005002 | CE38: -0.34883376 | CF38: 44343 | CG38: 0.48336215 | CH38: 0.56042867 | CI38: 0.50704802 | CJ38: -0.095249689 | CK38: 0.12256267 | CL38: 0.25865861 | CM38: -0.020516796 | CN38: No
A39: Q4 FY21 | B39: Jan-Mar 2021 | C39: 44286 | D39: MAHABANK | E39: Bank of Maharashtra | F39: Banks | G39: NSE | H39: Nifty Bank | I39: 6500 | J39: 44315 | K39: 15:09 | L39: During market | M39: NSE announcement (no filing record) | N39: 44314 | O39: 44315 | P39: 44316 | Q39: 44315 | R39: 0.01059322 | S39: 0.037735849 | T39: -0.028282828 | U39: 0.020046241 | V39: -0.0012351345 | W39: 0.0022538596 | X39: 0.021281376 | Y39: 0.017792382 | Z39: -0.012781967 | AA39: 0.032828208 | AB39: 0.018867925 | AC39: 0.037735849 | AD39: 0.037735849 | AE39: 0.073375262 | AF39: 0.71428571 | AG39: 1.2545738 | AH39: 23.6 | AI39: 0.0063965885 | AJ39: 0.12649165 | AK39: 0.475 | AL39: 1.0257511 | AM39: 1.4712042 | AN39: -0.042389218 | AO39: 0.16888087 | AP39: 0.012474012 | AQ39: 0.01039501 | AR39: -0.054651363 | BM39: 15481.978 | BN39: 442.73 | BO39: 34.969344 | BS39: 24.15 | BT39: 2.98 | BZ39: 19 | CA39: 0.0093552237 | CB39: 0.38140606 | CD39: 26.380328 | CE39: 0.32558413 | CO39: no NSE XBRL results for this quarter; no option prices for this event
A40: Q4 FY21 | B40: Jan-Mar 2021 | C40: 44286 | D40: MOTILALOFS | E40: Motilal Oswal Financial Services Limited | F40: Finance | G40: NSE | H40: Nifty Financial Services | I40: 775 | J40: 44315 | K40: 18:34 | L40: After close | M40: NSE announcement | N40: 44314 | O40: 44315 | P40: 44316 | Q40: 44316 | R40: 0.0097071269 | S40: 0.034182416 | T40: 0.013348165 | U40: 0.057237707 | V40: -0.0012351345 | W40: -0.00099190311 | X40: 0.058472842 | Y40: 0.05822961 | Z40: 0.015075048 | AA40: 0.042162659 | AB40: 0.048784364 | AC40: 0.013348165 | AD40: 0.013348165 | AE40: 0.043699348 | AF40: 0.18909091 | AG40: 7.2995237 | AH40: 602.65 | AI40: 0.032288455 | AJ40: -0.10032097 | AK40: -0.036222613 | AL40: 0.052204278 | AM40: 0.269004 | AN40: -0.022274278 | AO40: -0.078046689 | AP40: 0.12341226 | AQ40: 0.27191469 | AR40: 0.20686832 | AS40: Consolidated | AT40: Company | AU40: 1140.95 | AV40: 0.86670702 | AW40: 0.20401638 | AX40: 665.45 | AY40: 0.58324204 | AZ40: 0.73211067 | BA40: 448.14 | BC40: 0.34225896 | BD40: 0.39277795 | BE40: 30.58 | BM40: 8828.8225 | BN40: 543.57 | BO40: 16.242292 | BS40: 24.5 | BT40: 4.02 | BZ40: 10 | CA40: 0.047978884 | CB40: 1.3627428 | CD40: 25.005002 | CE40: -0.3504383 | CO40: no option prices for this event
A41: Q4 FY21 | B41: Jan-Mar 2021 | C41: 44286 | D41: PERSISTENT | E41: Persistent Systems Limited | F41: Computers - Software | G41: NSE | H41: Nifty IT | I41: 125 | J41: 44315 | K41: 19:15 | L41: After close | M41: NSE announcement | N41: 44314 | O41: 44315 | P41: 44316 | Q41: 44316 | R41: 0.0047397008 | S41: 0.021240788 | T41: 0.017877653 | U41: 0.043858142 | V41: -0.0012351345 | W41: -0.0058231972 | X41: 0.045093277 | Y41: 0.049681339 | Z41: -0.0057262579 | AA41: 0.0495844 | AB41: 0.02372035 | AC41: 0.017877653 | AD41: 0.017877653 | AE41: 0.081048689 | AF41: 0.096734442 | AG41: 6.7146503 | AH41: 1951.6 | AI41: 0.010668048 | AJ41: 0.008318264 | AK41: 0.19473523 | AL41: 0.61609805 | AM41: 3.1616377 | AN41: -0.01110677 | AO41: 0.019425034 | AP41: 0.10812932 | AQ41: 0.24758377 | AR41: 0.1825374 | AS41: Consolidated | AT41: Company | AU41: 1113.358 | AV41: 0.20185672 | AW41: 0.035298559 | AX41: 188.33 | AY41: 0.16915493 | AZ41: 0.032150622 | BA41: 137.759 | BB41: 0.64349029 | BC41: -0.1322869 | BD41: 0.12373289 | BE41: 18.03 | BM41: 14915.103 | BN41: 434.576 | BO41: 34.321046 | BS41: 28.42 | BT41: 8.3 | BZ41: 12 | CA41: 0.0567063 | CB41: 0.25896704 | CC41: 3 of 12 | CD41: 35.004801 | CE41: -0.019533178 | CO41: no option prices for this event
A42: Q4 FY21 | B42: Jan-Mar 2021 | C42: 44286 | D42: SHRIRAMFIN | E42: Shriram Finance Limited | F42: Finance | G42: Assigned | H42: Nifty Financial Services | I42: 825 | J42: 44315 | K42: 17:57 | L42: After close | M42: NSE announcement | N42: 44314 | O42: 44315 | P42: 44316 | Q42: 44316 | R42: 0.060226415 | S42: 0.0081862187 | T42: -0.050307138 | U42: 0.018105495 | V42: -0.0012351345 | W42: -0.00099190311 | X42: 0.01934063 | Y42: 0.019097399 | Z42: 0.029616527 | AA42: -0.011511032 | AB42: 0.0096730919 | AC42: -0.050307138 | AD42: 0.050307138 | AE42: 0.077137612 | AF42: 0.085125858 | AG42: 1.4825995 | AH42: 1325 | AI42: -0.013145645 | AJ42: -0.057811278 | AK42: 0.061953995 | AL42: 0.98963886 | AM42: 1.0637022 | AN42: -0.022274278 | AO42: -0.035537 | AP42: -0.035240326 | AQ42: 0.06300881 | AR42: -0.0020375637 | AS42: Consolidated | AT42: Company | AU42: 4493.97 | AV42: 0.078099136 | AW42: 0.012527121 | AX42: 3254.45 | AY42: 0.72418151 | AZ42: 0.1163157 | BA42: 756.7 | BB42: 2.3728549 | BC42: 0.030968568 | BD42: 0.16838119 | BE42: 30.72 | BM42: 33530.45 | BN42: 1966.49 | BO42: 17.050913 | BS42: 24.5 | BT42: 4.02 | BZ42: 10 | CA42: 0.081413096 | CB42: 1.0997143 | CC42: 3 of 10 | CD42: 24.620752 | CE42: -0.30745767 | CF42: 44343 | CH42: 0.59509424 | CI42: 0.54433953 | CJ42: -0.085288518 | CK42: 0.13006066 | CL42: 0.38679751
A43: Q4 FY21 | B43: Jan-Mar 2021 | C43: 44286 | D43: TITAN | E43: Titan Company Limited | F43: Gems Jewellery And Watches | G43: NSE | H43: Nifty Consumer Durables | I43: 175 | J43: 44315 | K43: 18:01 | L43: After close | M43: NSE announcement | N43: 44314 | O43: 44315 | P43: 44316 | Q43: 44316 | R43: 0.0091967093 | S43: -0.0013586506 | T43: -0.01005442 | U43: -0.0022163613 | V43: -0.0012351345 | W43: -0.0047908162 | X43: -0.00098122687 | Y43: 0.0025744549 | AB43: -0.004512875 | AC43: -0.01005442 | AD43: 0.01005442 | AE43: 0.030229626 | AF43: 0.45334797 | AG43: 2.0429332 | AH43: 1495.1 | AI43: -0.015539606 | AJ43: -0.00016718494 | AK43: -0.023640044 | AL43: 0.20117297 | AM43: 0.61153328 | AN43: -0.011009553 | AO43: 0.010842368 | AP43: -0.030268495 | AQ43: 0.070123689 | AR43: 0.0050773147 | AS43: Consolidated | AT43: Company | AU43: 7494 | AV43: 0.59057625 | AW43: -0.016406353 | AX43: 817 | AY43: 0.10902055 | AZ43: -0.020969899 | BA43: 564.35 | BB43: 0.6298917 | BC43: 0.074583952 | BD43: 0.075306912 | BE43: 6.36 | BM43: 132734.98 | BN43: 755.55 | BO43: 175.67994 | BS43: 86.06 | BT43: 12.51 | BZ43: 1 | CF43: 44343 | CG43: 0.34590614 | CH43: 0.35576114 | CI43: 0.31148224 | CJ43: -0.12446242 | CK43: 0.078002914 | CL43: 0.12889801 | CM43: -0.098092609 | CN43: No
A44: Q4 FY21 | B44: Jan-Mar 2021 | C44: 44286 | D44: INDHOTEL | E44: The Indian Hotels Company Limited | F44: Hotels | G44: NSE | H44: Nifty 500 | I44: 1000 | J44: 44316 | K44: 19:41 | L44: After close | M44: NSE announcement | N44: 44315 | O44: 44316 | P44: 44319 | Q44: 44319 | R44: -0.027276727 | S44: 0.0085933967 | T44: -0.0035874439 | U44: -0.022270774 | V44: -0.015460529 | W44: -0.0097553146 | X44: -0.0068102446 | Y44: -0.012515459 | AB44: -0.013452915 | AC44: -0.0035874439 | AD44: 0.0035874439 | AE44: 0.05470852 | AF44: 0.67213115 | AG44: 1.0942488 | AH44: 113.65 | AI44: 0.18447108 | AJ44: 0.047948363 | AK44: -0.06422396 | AL44: 0.13197211 | AM44: 0.51331558 | AN44: 0.026297019 | AO44: 0.021651344 | AP44: 0.0180018 | AQ44: 0.22367237 | AR44: 0.15939122 | AS44: Consolidated | AT44: Company | AU44: 615.02 | AV44: -0.42141903 | AW44: 0.098524631 | AX44: 96.66 | AY44: 0.15716562 | AZ44: -0.07615956 | BA44: -91.3 | BB44: -2.2284715 | BD44: -0.14845046 | BE44: -0.77 | BM44: 13516.395 | BN44: -554.49 | BS44: 35.62 | BT44: 4.03 | BZ44: 0 | CO44: no option prices for this event
A45: Q4 FY21 | B45: Jan-Mar 2021 | C45: 44286 | D45: INDUSINDBK | E45: IndusInd Bank Limited | F45: Banks | G45: NSE | H45: Nifty Bank | I45: 700 | J45: 44316 | K45: 18:35 | L45: After close | M45: NSE announcement | N45: 44315 | O45: 44316 | P45: 44319 | Q45: 44319 | R45: 0.013539756 | S45: -0.0047900367 | T45: -0.022835446 | U45: -0.014085726 | V45: -0.015460529 | W45: -0.037551799 | X45: 0.0013748032 | Y45: 0.023466073 | Z45: -0.010168456 | AA45: -0.0039172704 | AB45: -0.0063639767 | AC45: -0.022835446 | AD45: 0.022835446 | AE45: 0.073479865 | AF45: 0.2125182 | AG45: 2.2690732 | AH45: 926.9 | AI45: 0.096923077 | AJ45: -0.033169918 | AK45: 0.001134093 | AL45: 0.52262834 | AM45: 0.98034398 | AN45: 0.012902015 | AO45: -0.046071932 | AP45: 0.034807356 | AQ45: 0.10557137 | AR45: 0.041290215 | AS45: Standalone | AT45: Bank | AU45: 7419.36 | AV45: 0.0044391375 | AW45: 0.02456121 | BA45: 875.95 | BB45: 1.9020342 | BC45: 0.027194052 | BD45: 0.11806274 | BE45: 11.45 | BF45: 3534.61 | BG45: 0.093903484 | BH45: 0.079459271 | BI45: -0.23547322 | BJ45: 0.0267 | BK45: 0.0069 | BL45: 0.0103 | BM45: 70176.526 | BN45: 2262.28 | BO45: 31.020265 | BS45: 24.88 | BT45: 3.07 | BZ45: 19 | CA45: 0.013687632 | CB45: 0.3548314 | CC45: 2 of 13 | CD45: 26.380328 | CE45: 0.17588627 | CF45: 44343 | CG45: 0.57027821 | CH45: 0.56780218 | CI45: 0.53658789 | CJ45: -0.054973884 | CK45: 0.12084866 | CL45: 0.18895903 | CM45: 0.060706356 | CN45: No
A46: Q4 FY21 | B46: Jan-Mar 2021 | C46: 44286 | D46: MARICO | E46: Marico Limited | F46: Personal Care | G46: NSE | H46: Nifty FMCG | I46: 1200 | J46: 44316 | K46: 13:34 | L46: During market | M46: NSE announcement | N46: 44315 | O46: 44316 | P46: 44319 | Q46: 44316 | R46: -0.0037676228 | S46: 0.0039038673 | T46: 0.081905456 | U46: 0.082041701 | V46: -0.015460529 | W46: -0.0038306254 | X46: 0.09750223 | Y46: 0.085872326 | Z46: 0.033672142 | AA46: 0.048369558 | AB46: 0 | AC46: 0.0039038673 | AD46: 0.0039038673 | AE46: 0.050018299 | AF46: 0.47560976 | AG46: 4.4036044 | AH46: 411.4 | AI46: 0.0029254022 | AJ46: 0.026703269 | AK46: -0.012363462 | AL46: 0.15335015 | AM46: 0.41813168 | AN46: 0.0041795269 | AO46: 0.022523742 | AP46: 0.057508705 | AQ46: 0.079860721 | AR46: 0.015579571 | AS46: Consolidated | AT46: Company | AU46: 2012 | AV46: 0.34491979 | AW46: -0.051837889 | AX46: 300 | AY46: 0.14910537 | AZ46: -0.032712814 | BA46: 219 | BB46: 0.10050251 | BC46: -0.28664495 | BD46: 0.10884692 | BE46: 1.7 | BM46: 53070.6 | BN46: 1160 | BO46: 45.750517 | BS46: 41.88 | BT46: 10.27 | BZ46: 3 | CA46: 0.2527287 | CB46: 0.54131766 | CC46: 4 of 4 | CD46: 45.296631 | CE46: 0.010020303 | CF46: 44343 | CH46: 0.29074376 | CI46: 0.28705872 | CJ46: -0.012674526 | CK46: 0.063643014 | CL46: 0.061340075
A47: Q4 FY21 | B47: Jan-Mar 2021 | C47: 44286 | D47: RELIANCE | E47: Reliance Industries Limited | F47: Refineries | G47: NSE | H47: Nifty Oil & Gas | I47: 500 | J47: 44316 | K47: 19:34 | L47: After close | M47: NSE announcement | N47: 44315 | O47: 44316 | P47: 44319 | Q47: 44319 | R47: 0.013393081 | S47: -0.014599442 | T47: -0.017773878 | U47: -0.018980239 | V47: -0.015460529 | W47: 0.0083035684 | X47: -0.0035197097 | Y47: -0.027283808 | Z47: 0.027115428 | AA47: -0.046095667 | AB47: -0.014289296 | AC47: -0.017773878 | AD47: 0.017773878 | AE47: 0.017999499 | AF47: 0.44428969 | AG47: 1.3767083 | AH47: 1997.3 | AI47: 0.050574652 | AJ47: -0.02442241 | AK47: -0.048632943 | AL47: -0.052042051 | AM47: 0.39852256 | AN47: 0.0066929887 | AO47: -0.031115399 | AP47: -0.016768332 | AQ47: 0.10711825 | AR47: 0.042837095 | AS47: Consolidated | AT47: Company | AU47: 154896 | AV47: 0.11209552 | AW47: 0.24919151 | AX47: 24148 | AY47: 0.15589815 | AZ47: 0.030146983 | BA47: 13227 | BB47: 1.0836484 | BC47: 0.0096175864 | BD47: 0.08539278 | BE47: 20.52 | BM47: 1287259.9 | BN47: 42249 | BO47: 30.46841 | BS47: 17.38 | BT47: 1.93 | BZ47: 3 | CA47: 0.18994598 | CD47: 19.885281 | CE47: 0.53220916 | CF47: 44343 | CG47: 0.3221125 | CH47: 0.35438538 | CI47: 0.30869341 | CJ47: -0.128933 | CK47: 0.075505069 | CL47: 0.2353998 | CM47: 0.12352184 | CN47: No
A48: Q4 FY21 | B48: Jan-Mar 2021 | C48: 44286 | D48: TRENT | E48: Trent Limited | F48: Miscellaneous | G48: NSE | H48: Nifty 500 | I48: 225 | J48: 44316 | K48: 18:44 | L48: After close | M48: NSE announcement | N48: 44315 | O48: 44316 | P48: 44319 | Q48: 44319 | R48: 0.0050521407 | S48: 0.0010955726 | T48: 0.0081756148 | U48: 0.014323328 | V48: -0.015460529 | W48: -0.0097553146 | X48: 0.029783858 | Y48: 0.024078643 | Z48: -0.0051124795 | AA48: 0.019435808 | AB48: -0.02407622 | AC48: 0.0081756148 | AD48: 0.0081756148 | AE48: 0.065533668 | AF48: 0.92239686 | AG48: 0.89747519 | AH48: 771.95 | AI48: 0.048133062 | AJ48: -0.016686835 | AK48: 0.1580408 | AL48: 0.20335152 | AM48: 0.56980173 | AN48: 0.026297019 | AO48: -0.042983854 | AP48: -0.045080135 | AQ48: 0.072983845 | AR48: 0.0087026946 | AS48: Consolidated | AT48: Company | AU48: 905.5491 | AV48: 0.074282201 | AW48: 0.060826024 | AX48: 123.7787 | AY48: 0.13668911 | AZ48: 0.037511012 | BA48: 29.0181 | BB48: 1.2801858 | BC48: -0.60752354 | BD48: 0.032044756 | BE48: 0.82 | BM48: 27441.819 | BN48: -162.4643 | BS48: 35.62 | BT48: 4.03 | BZ48: 4 | CA48: -0.0097113608 | CB48: 0.10273019 | CC48: 1 of 3 | CD48: 122.96354 | CO48: no option prices for this event
A49: Q4 FY21 | B49: Jan-Mar 2021 | C49: 44286 | D49: YESBANK | E49: Yes Bank Limited | F49: Banks | G49: NSE | H49: Nifty Bank | I49: 31100 | J49: 44316 | K49: 16:55 | L49: After close | M49: NSE announcement | N49: 44315 | O49: 44316 | P49: 44319 | Q49: 44319 | R49: -0.02027027 | S49: 0.0034482759 | T49: -0.04467354 | U49: -0.061495534 | V49: -0.015460529 | W49: -0.037551799 | X49: -0.046035004 | Y49: -0.023943735 | Z49: -0.010168456 | AA49: -0.051327078 | AB49: -0.11683849 | AC49: -0.04467354 | AD49: 0.04467354 | AE49: 0.079037801 | AF49: 0.91304348 | AG49: 2.8735395 | AH49: 14.8 | AI49: 0.053380783 | AJ49: 0.010238908 | AK49: -0.14202899 | AL49: 0.16535433 | AM49: -0.45688073 | AN49: 0.012902015 | AO49: -0.0026631068 | AP49: -0.057553957 | AQ49: -0.039568345 | AR49: -0.1038495 | AS49: Standalone | AT49: Bank | AU49: 3989.2514 | AV49: -0.23597319 | AW49: -0.25029762 | BA49: -3787.7506 | BB49: -2.4409654 | BC49: -26.131875 | BD49: -0.94948907 | BE49: -1.51 | BF49: 986.6686 | BG49: -0.22535852 | BH49: 0.73731347 | BI49: 0.075374645 | BJ49: 0.0015 | BK49: 0.0006 | BL49: -0.0006 | BM49: 37081.261 | BN49: 2954.1535 | BO49: 12.552246 | BS49: 24.88 | BT49: 3.07 | BZ49: 19 | CA49: 0.013687632 | CB49: 0.48380133 | CC49: 12 of 13 | CD49: 29.632537 | CE49: -0.57640327 | CO49: no option prices for this event
A50: Q4 FY21 | B50: Jan-Mar 2021 | C50: 44286 | D50: CDSL | E50: Central Depository Services (India) Limited | F50: Capital Markets | G50: Assigned | H50: Nifty Financial Services | I50: 475 | J50: 44317 | K50: 14:54 | L50: Non-trading day | M50: NSE announcement | N50: 44316 | O50: 44319 | P50: 44320 | Q50: 44319 | R50: 0.0041695189 | S50: -0.013572137 | T50: -0.023685368 | U50: -0.033087986 | V50: -0.026908381 | W50: -0.040547768 | X50: -0.0061796048 | Y50: 0.0074597827 | Z50: -0.0055389271 | AA50: -0.027549059 | AB50: 0.00018591968 | AC50: -0.013572137 | AD50: 0.013572137 | AE50: 0.038299455 | AF50: 0.22168285 | AG50: 0.63563906 | AH50: 803.45 | AI50: 0.11420053 | AJ50: 0.28039841 | AK50: 0.58973091 | AL50: 0.74530249 | AM50: 2.4721262 | AN50: 0.036982827 | AO50: 0.24341558 | AP50: 0.027027027 | AQ50: 0.2501287 | AR50: 0.17564865 | AS50: Consolidated | AT50: Company | AU50: 103.0881 | AV50: 0.72145166 | AW50: 0.19683539 | AX50: 63.3885 | AY50: 0.61489638 | AZ50: 0.18418488 | BA50: 51.7399 | BB50: 0.80928352 | BC50: -0.036285576 | BD50: 0.50189983 | BE50: 4.95 | BM50: 8396.0525 | BN50: 177.1975 | BO50: 47.382455 | BS50: 25.22 | BT50: 4.14 | BZ50: 7 | CA50: 0.099817851 | CB50: 0.34862222 | CC50: 2 of 4 | CD50: 39.637453 | CE50: 0.19539603 | CO50: no option prices for this event
A51: Q4 FY21 | B51: Jan-Mar 2021 | C51: 44286 | D51: GODREJPROP | E51: Godrej Properties Limited | F51: Construction | G51: NSE | H51: Nifty Infrastructure | I51: 325 | J51: 44319 | K51: 09:50 | L51: During market | M51: NSE announcement | N51: 44316 | O51: 44319 | P51: 44320 | Q51: 44319 | R51: -0.0082623664 | S51: -0.042861841 | T51: -0.019737344 | U51: -0.070861552 | V51: -0.026908381 | W51: -0.0054222202 | X51: -0.043953171 | Y51: -0.065439331 | Z51: -0.0045989016 | AA51: -0.06626265 | AB51: -0.023970475 | AC51: -0.042861841 | AD51: 0.042861841 | AE51: 0.041656009 | AF51: 0.17017544 | AG51: 1.4486341 | AH51: 1379.75 | AI51: 0.037211051 | AJ51: 0.035770588 | AK51: 0.021772133 | AL51: 0.31705804 | AM51: 1.0827987 | AN51: 0.018365048 | AO51: 0.01740554 | AP51: -0.019316898 | AQ51: 0.083187288 | AR51: 0.0087072413 | AS51: Consolidated | AT51: Company | AU51: 432.64 | AV51: -0.62801255 | AW51: 1.5376268 | AX51: -154.12 | AY51: -0.35623151 | AZ51: -0.4661236 | BA51: -191.62 | BB51: -2.8957262 | BC51: -14.35331 | BD51: -0.44290865 | BE51: -7.47 | BM51: 34780.738 | BN51: 102.3 | BO51: 339.98766 | BS51: 33.76 | BT51: 2.57 | BZ51: 7 | CA51: 0.14417596 | CB51: 0.26396096 | CC51: 6 of 6 | CD51: 43.902887 | CE51: 6.7440845 | CF51: 44343 | CG51: 0.43789244 | CH51: 0.48974333 | CI51: 0.44387435 | CJ51: -0.09365921 | CK51: 0.10469156 | CL51: 0.40941068 | CM51: 0.078426018 | CN51: No
A52: Q4 FY21 | B52: Jan-Mar 2021 | C52: 44286 | D52: KOTAKBANK | E52: Kotak Mahindra Bank Limited | F52: Banks | G52: NSE | H52: Nifty Bank | I52: 2000 | J52: 44319 | K52: 13:16 | L52: During market | M52: NSE announcement | N52: 44316 | O52: 44319 | P52: 44320 | Q52: 44319 | R52: -0.031135734 | S52: -0.013352013 | T52: 0.0041728245 | U52: -0.040314922 | V52: -0.026908381 | W52: -0.043324325 | X52: -0.013406541 | Y52: 0.003009403 | Z52: -0.010168456 | AA52: -0.030146467 | AB52: -0.0078911253 | AC52: -0.013352013 | AD52: 0.013352013 | AE52: 0.04231473 | AF52: 0.54662162 | AG52: 1.6893373 | AH52: 1805 | AI52: 0.039716598 | AJ52: 0.023881105 | AK52: -0.012582057 | AL52: 0.30508658 | AM52: 0.35934029 | AN52: 0.021451868 | AO52: 0.0024292373 | AP52: 0.013159034 | AQ52: 0.029117248 | AR52: -0.045362799 | AS52: Standalone | AT52: Bank | AU52: 6448.86 | AV52: -0.052290482 | AW52: -0.050317059 | BA52: 1682.37 | BB52: 0.32825675 | BC52: -0.092347616 | BD52: 0.26087867 | BE52: 8.29 | BF52: 3842.81 | BG52: 0.079547146 | BH52: 0.25032657 | BI52: 0.12596065 | BJ52: 0.0325 | BK52: 0.0121 | BL52: 0.0043 | BM52: 357476.64 | BN52: 6549.07 | BO52: 54.584336 | BS52: 24.87 | BT52: 3.07 | BZ52: 19 | CA52: 0.013687632 | CB52: 0.48380133 | CC52: 8 of 13 | CD52: 26.380328 | CE52: 1.0691303 | CF52: 44343 | CG52: 0.38626828 | CH52: 0.3719493 | CI52: 0.3436166 | CJ52: -0.076173569 | CK52: 0.079211021 | CL52: 0.16856256 | CM52: -0.1818383 | CN52: No
A53: Q4 FY21 | B53: Jan-Mar 2021 | C53: 44286 | D53: SBILIFE | E53: SBI Life Insurance Company Limited | F53: Insurance | G53: Assigned | H53: Nifty Financial Services | I53: 375 | J53: 44319 | K53: 14:53 | L53: During market | M53: NSE announcement (no filing record) | N53: 44316 | O53: 44319 | P53: 44320 | Q53: 44319 | R53: 0.00053867701 | S53: 0.032195542 | T53: 0.025349468 | U53: 0.058083687 | V53: -0.026908381 | W53: -0.040547768 | X53: 0.084992068 | Y53: 0.098631456 | Z53: 0.025836191 | AA53: 0.032247496 | AB53: -0.0072682244 | AC53: 0.032195542 | AD53: 0.032195542 | AE53: 0.068859696 | AF53: 0.66536357 | AG53: 2.9281054 | AH53: 928.2 | AI53: 0.015091864 | AJ53: 0.074181229 | AK53: 0.07611153 | AL53: 0.20435967 | AM53: 0.30118455 | AN53: 0.036982827 | AO53: 0.037198402 | AP53: 0.018364025 | AQ53: 0.0015260962 | AR53: -0.072953951 | BS53: 25.22 | BT53: 4.14 | BZ53: 4 | CA53: 1.2888397 | CD53: 101.10041 | CF53: 44343 | CG53: 0.29581484 | CH53: 0.34346448 | CI53: 0.33664255 | CJ53: -0.019862117 | CK53: 0.073254197 | CL53: 0.4395044 | CM53: 0.0020555556 | CN53: No | CO53: no NSE XBRL results for this quarter
A54: Q4 FY21 | B54: Jan-Mar 2021 | C54: 44286 | D54: SUPREMEIND | E54: Supreme Industries Limited | F54: Plastic And Plastic Products | G54: NSE | H54: Nifty 500 | I54: 175 | J54: 44319 | K54: 13:35 | L54: During market | M54: NSE announcement | N54: 44316 | O54: 44319 | P54: 44320 | Q54: 44319 | R54: 0.00017079836 | S54: 0.029152741 | T54: 0.011141137 | U54: 0.040464676 | V54: -0.026908381 | W54: -0.018589702 | X54: 0.067373057 | Y54: 0.059054378 | AB54: 0.0033178015 | AC54: 0.029152741 | AD54: 0.029152741 | AE54: 0.059208119 | AF54: 0.45859085 | AG54: 5.3107444 | AH54: 2049.2 | AI54: 0.036493766 | AJ54: 0.026113517 | AK54: 0.18742576 | AL54: 0.4436069 | AM54: 0.87948271 | AN54: 0.044983449 | AO54: -0.018869932 | AP54: 0.035798012 | AQ54: 0.061304389 | AR54: -0.013175658 | AS54: Consolidated | AT54: Company | AU54: 2084.59 | AV54: 0.45725591 | AW54: 0.13059442 | AX54: 509.74 | AY54: 0.2445277 | AZ54: 0.053383408 | BA54: 450.38 | BB54: 2.8402115 | BC54: 0.44223133 | BD54: 0.21605208 | BE54: 35.46 | BM54: 26035.086 | BN54: 645.04 | BO54: 40.361971 | BS54: 35.86 | BT54: 4.04 | BZ54: 1 | CO54: no option prices for this event
A55: Q4 FY21 | B55: Jan-Mar 2021 | C55: 44286 | D55: VBL | E55: Varun Beverages Limited | F55: Food And Food Processing | G55: Assigned | H55: Nifty FMCG | I55: 1275 | J55: 44319 | K55: 11:35 | L55: During market | M55: NSE announcement | N55: 44316 | O55: 44319 | P55: 44320 | Q55: 44319 | R55: 0.014406915 | S55: 0.0560728 | T55: -0.0029884943 | U55: 0.067491221 | V55: -0.026908381 | W55: -0.0053536818 | X55: 0.094399602 | Y55: 0.072844903 | Z55: -0.01004559 | AA55: 0.077536811 | AB55: 0.020461838 | AC55: 0.0560728 | AD55: 0.0560728 | AE55: 0.05933407 | AF55: 0.75443262 | AG55: 5.8550052 | AH55: 937.05 | AI55: 0.052037723 | AJ55: -0.061683272 | AK55: 0.036559735 | AL55: 0.39858209 | AM55: 0.42279077 | AN55: 0.023961895 | AO55: -0.085645167 | AP55: -0.0080431633 | AQ55: 0.018034671 | AR55: -0.056445376 | AS55: Consolidated | AT55: Company | AU55: 2269.877 | AV55: 0.33581267 | AW55: 0.67972433 | AX55: 381.622 | AY55: 0.16812453 | AZ55: 0.047702436 | BA55: 129.255 | BB55: 1.3535571 | BD55: 0.056943614 | BE55: 4.48 | BM55: 27051.603 | BN55: 328.995 | BO55: 82.224966 | BS55: 41.73 | BT55: 10.24 | BZ55: 4 | CA55: 0.20246546 | CB55: 1.0626863 | CC55: 2 of 3 | CD55: 90.15372 | CE55: -0.087947054 | CO55: no option prices for this event
A56: Q4 FY21 | B56: Jan-Mar 2021 | C56: 44286 | D56: ADANIPORTS | E56: Adani Ports and Special Economic Zone Limited | F56: Shipping | G56: NSE | H56: Nifty Services Sector | I56: 475 | J56: 44320 | K56: 16:14 | L56: After close | M56: NSE announcement | N56: 44319 | O56: 44320 | P56: 44321 | Q56: 44321 | R56: 0.042942264 | S56: 0.0096532703 | T56: -0.039869919 | U56: 0.012725616 | V56: -0.00082663482 | W56: 0.0026060232 | X56: 0.013552251 | Y56: 0.010119593 | AB56: 0.0042276423 | AC56: -0.039869919 | AD56: 0.039869919 | AE56: 0.054764228 | AF56: 0.12826603 | AG56: 0.98581947 | AH56: 730.05 | AI56: 0.0064796305 | AJ56: 0.038404096 | AK56: 0.3941564 | AL56: 1.0072862 | AM56: 1.516546 | AN56: -0.0016917947 | AO56: 0.040095891 | AP56: 0.018290205 | AQ56: 0.11814117 | AR56: 0.044771971 | AS56: Consolidated | AT56: Company | AU56: 3607.9 | AV56: 2.0445129 | AW56: -0.036991958 | AX56: 2310.96 | AY56: 0.64052773 | AZ56: 0.87362338 | BA56: 1287.81 | BB56: 1.574127 | BC56: -0.17525793 | BD56: 0.35694171 | BE56: 6.34 | BM56: 148327.91 | BN56: 4206.78 | BO56: 35.25925 | BS56: 29.2 | BT56: 4.51 | BZ56: 0 | CF56: 44343 | CG56: 0.5208698 | CH56: 0.61087976 | CI56: 0.55405623 | CJ56: -0.093019186 | CK56: 0.12245427 | CL56: 0.32559026 | CM56: 0.0045301275 | CN56: No
A57: Q4 FY21 | B57: Jan-Mar 2021 | C57: 44286 | D57: LTM | E57: LTM Limited | F57: Computers - Software | G57: Assigned | H57: Nifty IT | I57: 150 | J57: 44320 | K57: 18:40 | L57: After close | M57: NSE announcement | N57: 44319 | O57: 44320 | P57: 44321 | Q57: 44321 | R57: 0.0085727138 | S57: -0.019675808 | T57: 0.017873856 | U57: 0.006770762 | V57: -0.00082663482 | W57: 0.0048563442 | X57: 0.0075973968 | Y57: 0.0019144178 | Z57: -0.0057262579 | AA57: 0.01249702 | AB57: 0.014806052 | AC57: 0.017873856 | AD57: 0.017873856 | AE57: 0.040206427 | AF57: 0.67798254 | AG57: 1.4748448 | AH57: 3890.25 | AI57: -0.0027684854 | AJ57: -0.014440433 | AK57: -0.00092453484 | AL57: 0.29709589 | AM57: 1.442167 | AN57: 0.011004487 | AO57: -0.02544492 | AP57: -0.064659081 | AQ57: -0.019833212 | AR57: -0.093202415 | AS57: Consolidated | AT57: Company | AU57: 3269.4 | AV57: 0.085494206 | AW57: 0.036982999 | AX57: 715.5 | AY57: 0.21884749 | AZ57: 0.026942053 | BA57: 545.2 | BB57: 0.27771268 | BC57: 0.051089262 | BD57: 0.16675843 | BE57: 31.22 | BM57: 68079.375 | BN57: 1817.6 | BO57: 37.455642 | BS57: 27.99 | BT57: 8.26 | BZ57: 12 | CA57: 0.0567063 | CB57: 0.25896704 | CC57: 6 of 12 | CD57: 33.437503 | CE57: 0.12016862 | CO57: no option prices for this event
A58: Q4 FY21 | B58: Jan-Mar 2021 | C58: 44286 | D58: RBLBANK | E58: RBL Bank Limited | F58: Banks | G58: Assigned | H58: Nifty Bank | I58: 3175 | J58: 44320 | K58: 16:17 | L58: After close | M58: NSE announcement | N58: 44319 | O58: 44320 | P58: 44321 | Q58: 44321 | R58: -0.024495289 | S58: 0.0030353201 | T58: 0.013480055 | U58: -0.0079799143 | V58: -0.00082663482 | W58: 0.00024812077 | X58: -0.0071532794 | Y58: -0.008228035 | Z58: -0.012781967 | AA58: 0.004802053 | AB58: -0.0082530949 | AC58: 0.013480055 | AD58: 0.013480055 | AE58: 0.036588721 | AF58: 0.59398496 | AG58: 1.1348098 | AH58: 185.75 | AI58: 0.042368126 | AJ58: -0.12008527 | AK58: -0.1661055 | AL58: 0.058404558 | AM58: 0.4055997 | AN58: -0.016099309 | AO58: -0.10398596 | AP58: 0.019815418 | AQ58: 0.18811075 | AR58: 0.11474155 | AS58: Standalone | AT58: Bank | AU58: 1922.4 | AV58: -0.12943851 | AW58: -0.029036967 | BA58: 75.34 | BB58: -0.34120322 | BC58: -0.4876921 | BD58: 0.039190595 | BE58: 1.26 | BF58: 906.04 | BG58: -0.11257811 | BH58: 0.14603054 | BI58: 0.24780159 | BJ58: 0.0434 | BK58: 0.0212 | BL58: 0.0032 | BM58: 11103.206 | BN58: 546.8 | BO58: 20.305791 | BS58: 24.18 | BT58: 2.98 | BZ58: 19 | CA58: 0.013687632 | CB58: 0.48380133 | CC58: 10 of 13 | CD58: 29.632537 | CE58: -0.31474681 | CF58: 44343 | CG58: 0.53930349 | CH58: 0.65897968 | CI58: 0.56684762 | CJ58: -0.13981016 | CK58: 0.13188326 | CL58: 0.10221202 | CM58: 0.022545591 | CN58: No
A59: Q4 FY21 | B59: Jan-Mar 2021 | C59: 44286 | D59: ADANIENT | E59: Adani Enterprises Limited | F59: Trading | G59: NSE | H59: Nifty 500 | I59: 309 | J59: 44321 | K59: 14:01 | L59: During market | M59: NSE announcement | N59: 44320 | O59: 44321 | P59: 44322 | Q59: 44321 | R59: 0.0055354227 | S59: 0.003960396 | T59: 0.015187377 | U59: 0.024683195 | V59: 0.0062813025 | W59: 0.0086638272 | X59: 0.018401893 | Y59: 0.016019368 | AB59: 0.0094257426 | AC59: 0.003960396 | AD59: 0.003960396 | AE59: 0.038019802 | AF59: 0.56770833 | AG59: 0.74162489 | AH59: 1255.55 | AI59: 0.070055823 | AJ59: 0.21714895 | AK59: 1.4484204 | AL59: 2.9979303 | AM59: 8.5442797 | AN59: 0.0005933209 | AO59: 0.21655563 | AP59: -0.051602875 | AQ59: 0.32189625 | AR59: 0.25768825 | AS59: Consolidated | AT59: Company | AU59: 13525.07 | AV59: 0.0071666705 | AW59: 0.16390243 | AX59: 724.24 | AY59: 0.053547967 | AZ59: 0.025418934 | BA59: 332.53 | BB59: 4.4324315 | BC59: 0.12034635 | BD59: 0.024586194 | BE59: 2.13 | BM59: 138086.64 | BN59: 750.181 | BO59: 184.0711 | BS59: 34.65 | BT59: 3.99 | BZ59: 0 | CF59: 44343 | CG59: 0.59219878 | CH59: 0.6664144 | CI59: 0.58045418 | CJ59: -0.12898914 | CK59: 0.13339644 | CL59: 0.029688918 | CM59: 0.020148127 | CN59: No
A60: Q4 FY21 | B60: Jan-Mar 2021 | C60: 44286 | D60: ADANIGREEN | E60: Adani Green Energy Limited | F60: Power | G60: Assigned | H60: Nifty Energy | I60: 600 | J60: 44321 | K60: 18:17 | L60: After close | M60: NSE announcement | N60: 44320 | O60: 44321 | P60: 44322 | Q60: 44322 | R60: 0.0082971539 | S60: 0.018610659 | T60: 0.03292471 | U60: 0.059832523 | V60: 0.0062813025 | W60: 0.010816711 | X60: 0.053551221 | Y60: 0.049015812 | Z60: -0.001572476 | AA60: 0.061404999 | AB60: 0.018223663 | AC60: 0.03292471 | AD60: 0.03292471 | AE60: 0.033817106 | AF60: 0.76666667 | AG60: 1.7171861 | AH60: 1036.5 | AI60: -0.012151537 | AJ60: -0.10465167 | AK60: 0.0077293277 | AL60: 0.40086498 | AM60: 3.9463135 | AN60: -0.023644192 | AO60: -0.081007473 | AP60: -0.01050382 | AQ60: 0.16155875 | AR60: 0.097350746 | AS60: Consolidated | AT60: Company | AU60: 986 | AV60: 0.41720484 | AW60: 0.31703962 | AX60: 613 | AY60: 0.62170385 | AZ60: 0.32720639 | BA60: 105 | BB60: 0.089052327 | BC60: 1.3991939 | BD60: 0.10649087 | BE60: 0.48 | BM60: 162110.08 | BN60: 178.2952 | BO60: 909.22292 | BS60: 15.51 | BT60: 1.69 | BZ60: 7 | CA60: 0.032591702 | CB60: 0.98428248 | CC60: 4 of 7 | CD60: 20.928347 | CE60: 42.444563 | CO60: no option prices for this event
A61: Q4 FY21 | B61: Jan-Mar 2021 | C61: 44286 | D61: ANGELONE | E61: Angel One Limited | F61: Capital Markets | G61: Assigned | H61: Nifty Financial Services | I61: 2500 | J61: 44321 | K61: 19:27 | L61: After close | M61: NSE announcement | N61: 44320 | O61: 44321 | P61: 44322 | Q61: 44322 | R61: 0.12363827 | S61: -0.0028034108 | T61: 0.19995315 | U61: 0.32078801 | V61: 0.0062813025 | W61: 0.0081531888 | X61: 0.3145067 | Y61: 0.31263482 | Z61: -0.033087986 | AA61: 0.35387599 | AB61: 0.030807075 | AC61: 0.19995315 | AD61: 0.19995315 | AE61: 0.18741947 | AF61: 1 | AG61: 5.7138655 | AH61: 380.95 | AI61: 0.039710699 | AJ61: 0.28786342 | AK61: 0.038010899 | AL61: 0.27621441 | AN61: -0.031715598 | AO61: 0.31957902 | AP61: 0.28650918 | AQ61: 0.58600156 | AR61: 0.52179356 | AS61: Consolidated | AT61: NBFC / financial | AU61: 408.612 | AW61: 0.33188176 | BA61: 101.912 | BC61: 0.39284933 | BD61: 0.2494102 | BE61: 12.45 | BS61: 23.38 | BT61: 4 | BZ61: 7 | CA61: 0.18632579 | CB61: 0.57895287 | CD61: 43.509954 | CO61: no option prices for this event
A62: Q4 FY21 | B62: Jan-Mar 2021 | C62: 44286 | D62: OFSS | E62: Oracle Financial Services Software Limited | F62: Computers - Software | G62: NSE | H62: Nifty IT | I62: 100 | J62: 44321 | K62: 20:59 | L62: After close | M62: NSE announcement | N62: 44320 | O62: 44321 | P62: 44322 | Q62: 44322 | R62: -0.0019396273 | S62: 0.02058561 | T62: -0.016178628 | U62: 0.0024673551 | V62: 0.0062813025 | W62: 0.022698494 | X62: -0.0038139475 | Y62: -0.020231139 | Z62: -0.0057262579 | AA62: 0.008193613 | AB62: 0.0054163846 | AC62: -0.016178628 | AD62: 0.016178628 | AE62: 0.034134507 | AF62: 0.11115702 | AG62: 1.755756 | AH62: 3480.05 | AI62: 0.052153407 | AJ62: 0.036731958 | AK62: 0.069517648 | AL62: 0.08123097 | AM62: 0.5057981 | AN62: -0.01703795 | AO62: 0.053769908 | AP62: 0.059341353 | AQ62: 0.0078854177 | AR62: -0.056322585 | AS62: Consolidated | AT62: Company | AU62: 1210.864 | AV62: -0.04169529 | AW62: -0.022253301 | AX62: 589.514 | AY62: 0.48685401 | AZ62: 0.039516834 | BA62: 460.314 | BB62: 0.70976165 | BC62: 0.07129741 | BD62: 0.38015335 | BE62: 53.49 | BM62: 29942.35 | BN62: 1570.768 | BO62: 19.062236 | BS62: 28 | BT62: 8.26 | BZ62: 12 | CA62: 0.075925207 | CB62: 0.25896704 | CC62: 2 of 12 | CD62: 35.888344 | CE62: -0.46884605 | CO62: no option prices for this event
A63: Q4 FY21 | B63: Jan-Mar 2021 | C63: 44286 | D63: POWERINDIA | E63: Hitachi Energy India Limited | F63: Electrical Equipment | G63: Assigned | H63: Nifty 500 | I63: 25 | J63: 44321 | K63: 15:17 | L63: During market | M63: NSE announcement | N63: 44320 | O63: 44321 | P63: 44322 | Q63: 44321 | R63: -0.0162537 | S63: -0.021230949 | T63: -0.01989809 | U63: -0.057382739 | V63: 0.0062813025 | W63: 0.0086638272 | X63: -0.063664042 | Y63: -0.066046567 | Z63: 0.0053015492 | AA63: -0.062684289 | AB63: 0.014153966 | AC63: -0.021230949 | AD63: 0.021230949 | AE63: 0.081106684 | AF63: 0.391618 | AG63: 0.65416307 | AH63: 1824.2 | AI63: 0.19961858 | AJ63: 0.33592091 | AK63: 0.5041847 | AL63: 0.89635636 | AM63: 1.3063405 | AN63: 0.0005933209 | AO63: 0.33532759 | AP63: -0.0074644206 | AQ63: 0.10121987 | AR63: 0.037011864 | AS63: Standalone | AT63: Company | AU63: 1015.53 | AV63: 0.25134619 | AW63: -0.026906603 | AX63: 73.74 | AY63: 0.072612331 | AZ63: -0.0057069351 | BA63: 39.44 | BB63: 0.35161069 | BC63: -0.28238719 | BD63: 0.038836864 | BE63: 9.31 | BM63: 7734.608 | BN63: 99.8 | BO63: 77.501082 | BS63: 34.65 | BT63: 3.99 | BZ63: 9 | CA63: 0.41994847 | CB63: 0.80637367 | CC63: 4 of 5 | CD63: 78.002441 | CE63: -0.0064274821 | CO63: no option prices for this event
A64: Q4 FY21 | B64: Jan-Mar 2021 | C64: 44286 | D64: SRF | E64: SRF Limited | F64: Textiles - Synthetic | G64: NSE | H64: Nifty India Consumption | I64: 200 | J64: 44321 | K64: 13:51 | L64: During market | M64: NSE announcement | N64: 44320 | O64: 44321 | P64: 44322 | Q64: 44321 | R64: 0.027319643 | S64: 0.019102631 | T64: 0.0038761674 | U64: 0.050298441 | V64: 0.0062813025 | W64: 0.0038944466 | X64: 0.044017139 | Y64: 0.046403995 | AB64: 0.01483193 | AC64: 0.019102631 | AD64: 0.019102631 | AE64: 0.05148692 | AF64: 0.52996526 | AG64: 2.7297178 | AH64: 6530.1 | AI64: 0.052698607 | AJ64: 0.20877412 | AK64: 0.21791596 | AL64: 0.49048206 | AM64: 0.79371249 | AN64: -0.0089246661 | AO64: 0.21769879 | AP64: -0.087955239 | AQ64: -0.034925654 | AR64: -0.099133656 | AS64: Consolidated | AT64: Company | AU64: 2607.65 | AV64: 0.4035999 | AW64: 0.21488905 | AX64: 643.33 | AY64: 0.24670872 | AZ64: 0.052229141 | BA64: 380.92 | BB64: 1.0507133 | BC64: 0.17303606 | BD64: 0.14607789 | BE64: 64.3 | BM64: 38690.842 | BN64: 1002.77 | BO64: 38.583965 | BS64: 151.3 | BT64: 7.08 | BZ64: 0 | CF64: 44343 | CH64: 0.45872235 | CI64: 0.40336353 | CJ64: -0.12068045 | CK64: 0.092374921 | CL64: 0.20679456
A65: Q4 FY21 | B65: Jan-Mar 2021 | C65: 44286 | D65: TATASTEEL | E65: Tata Steel Limited | F65: Steel And Steel Products | G65: NSE | H65: Nifty Metal | I65: 2750 | J65: 44321 | K65: 19:23 | L65: After close | M65: NSE announcement | N65: 44320 | O65: 44321 | P65: 44322 | Q65: 44322 | R65: -0.00084526884 | S65: 0.0059218875 | T65: 0.02873429 | U65: 0.033810908 | V65: 0.0062813025 | W65: 0.028755241 | X65: 0.027529606 | Y65: 0.0050556673 | Z65: -0.0070329134 | AA65: 0.040843822 | AB65: -0.014156894 | AC65: 0.02873429 | AD65: 0.02873429 | AE65: 0.08082979 | AF65: 0.67514451 | AG65: 1.8288442 | AH65: 1064.75 | AI65: 0.13180973 | AJ65: 0.3309375 | AK65: 0.70087859 | AL65: 1.5906326 | AM65: 2.8916301 | AN65: 0.24967197 | AO65: 0.081265534 | AP65: 0.028340449 | AQ65: 0.017985285 | AR65: -0.046222718 | AS65: Consolidated | AT65: Company | AU65: 49977.4 | AV65: 0.47993704 | AW65: 0.26224394 | AX65: 13192.95 | AY65: 0.26397832 | AZ65: 0.22722937 | BA65: 6644.15 | BC65: 0.79706644 | BD65: 0.13294309 | BE65: 57.53 | BM65: 121908.55 | BN65: -635.27 | BS65: 33.92 | BT65: 2.25 | BZ65: 4 | CA65: 0.4048485 | CB65: 2.4717902 | CD65: 29.293853 | CF65: 44343 | CG65: 0.48850287 | CH65: 0.51394847 | CI65: 0.46227066 | CJ65: -0.10055056 | CK65: 0.099785907 | CL65: 0.2879594 | CM65: 0.20426606 | CN65: No
A66: Q4 FY21 | B66: Jan-Mar 2021 | C66: 44286 | D66: ADANIENSOL | E66: Adani Energy Solutions Limited | F66: Power | G66: Assigned | H66: Nifty Energy | I66: 675 | J66: 44322 | K66: 17:47 | L66: After close | M66: NSE announcement | N66: 44321 | O66: 44322 | P66: 44323 | Q66: 44323 | R66: 0.02144835 | S66: 0.035195736 | T66: 0.044296494 | U66: 0.10094058 | V66: 0.022366591 | W66: 0.019251819 | X66: 0.078573989 | Y66: 0.081688761 | Z66: -0.001572476 | AA66: 0.10251306 | AB66: 0.032401243 | AC66: 0.044296494 | AD66: 0.044296494 | AE66: 0.044207723 | AF66: 0.87148594 | AG66: 1.38121 | AH66: 1065.35 | AI66: 0.020352457 | AJ66: 0.17277631 | AK66: 1.3195079 | AL66: 2.7243489 | AM66: 4.3819146 | AN66: -0.013046395 | AO66: 0.18582271 | AP66: 0.020358722 | AQ66: 0.35111357 | AR66: 0.28847506 | AS66: Consolidated | AT66: Company | AU66: 2726.61 | AV66: 3.0983782 | AW66: 0.0498995 | AX66: 1027.18 | AY66: 0.37672421 | AZ66: 0.39921065 | BA66: 238.42 | BB66: 9.7251462 | BC66: -0.3968784 | BD66: 0.087441915 | BE66: 1.67 | BM66: 117168.26 | BN66: 1007.85 | BO66: 116.25565 | BS66: 14.96 | BT66: 1.68 | BZ66: 7 | CA66: 0.032591702 | CB66: 0.076631479 | CC66: 1 of 7 | CD66: 20.928347 | CE66: 4.554937 | CO66: no option prices for this event
A67: Q4 FY21 | B67: Jan-Mar 2021 | C67: 44286 | D67: ADANIPOWER | E67: Adani Power Limited | F67: Power | G67: NSE | H67: Nifty Energy | I67: 3550 | J67: 44322 | K67: 15:39 | L67: After close | M67: NSE announcement | N67: 44321 | O67: 44322 | P67: 44323 | Q67: 44323 | R67: 0.014106583 | S67: -0.0020607934 | T67: 0.002065049 | U67: 0.014110839 | V67: 0.022366591 | W67: 0.019251819 | X67: -0.0082557527 | Y67: -0.0051409804 | Z67: -0.001572476 | AA67: 0.015683315 | AB67: 0.022199277 | AC67: 0.002065049 | AD67: 0.002065049 | AE67: 0.034073309 | AF67: 0.10606061 | AG67: 0.67840542 | AH67: 95.7 | AI67: 0.063333333 | AJ67: 0.12522046 | AK67: 0.95306122 | AL67: 1.7110482 | AM67: 2.1428571 | AN67: -0.013046395 | AO67: 0.13826685 | AP67: -2.220446e-16 | AQ67: 0.30757342 | AR67: 0.24493491 | AS67: Consolidated | AT67: Company | AU67: 6373.6 | AV67: 0.032591702 | AW67: -0.075598564 | AX67: 1614.34 | AY67: 0.25328543 | AZ67: 0.22014451 | BA67: 13.13 | BD67: 0.0020600602 | BE67: -0.83 | BM67: 36910.916 | BN67: -56.05 | BS67: 14.96 | BT67: 1.68 | BZ67: 7 | CA67: 0.035668184 | CB67: 0.089052327 | CD67: 30.901227 | CO67: no option prices for this event
A68: Q4 FY21 | B68: Jan-Mar 2021 | C68: 44286 | D68: BLUESTARCO | E68: Blue Star Limited | F68: Airconditioners | G68: NSE | H68: Nifty Consumer Durables | I68: 325 | J68: 44322 | K68: 16:15 | L68: After close | M68: NSE announcement | N68: 44321 | O68: 44322 | P68: 44323 | Q68: 44323 | R68: 0.0026965484 | S68: -0.0094424192 | T68: 0.016832579 | U68: 0.010086708 | V68: 0.022366591 | W68: 0.0089964097 | X68: -0.012279883 | Y68: 0.0010902987 | AB68: 0.032880845 | AC68: 0.016832579 | AD68: 0.016832579 | AE68: 0.049411765 | AF68: 0.21611722 | AG68: 2.7761172 | AH68: 834.4 | AI68: -0.034706155 | AJ68: -0.10682937 | AK68: 0.13377267 | AL68: 0.29104131 | AM68: 0.65096953 | AN68: -0.049543895 | AO68: -0.057285477 | AP68: -0.030437878 | AQ68: -0.018037261 | AR68: -0.080675769 | AS68: Consolidated | AT68: Company | AU68: 1611.56 | AV68: 0.24027213 | AW68: 0.43391257 | AX68: 101.81 | AY68: 0.063174812 | AZ68: 0.035022491 | BA68: 68.09 | BB68: 6.6078212 | BC68: 0.85178134 | BD68: 0.042250987 | BE68: 7.06 | BM68: 8035.272 | BN68: 41.52 | BO68: 193.52775 | BS68: 79.97 | BT68: 12.15 | BZ68: 0 | CO68: no option prices for this event
A69: Q4 FY21 | B69: Jan-Mar 2021 | C69: 44286 | D69: COFORGE | E69: Coforge Limited | F69: Computers - Software | G69: Assigned | H69: Nifty IT | I69: 475 | J69: 44322 | K69: 09:58 | L69: During market | M69: NSE announcement | N69: 44321 | O69: 44322 | P69: 44323 | Q69: 44322 | R69: 0.014893169 | S69: 0.17402126 | T69: -0.0045345465 | U69: 0.18437988 | V69: 0.022366591 | W69: 0.030392881 | X69: 0.16201329 | Y69: 0.153987 | Z69: -0.0057262579 | AA69: 0.19010614 | AB69: 0.0042347247 | AC69: 0.17402126 | AD69: 0.17402126 | AE69: 0.21680062 | AF69: 0.91572989 | AG69: 10.751288 | AH69: 2850.3 | AI69: 0.0042986505 | AJ69: -0.02618767 | AK69: 0.17776125 | AL69: 0.27115016 | AM69: 1.3957134 | AN69: -0.014155869 | AO69: -0.0120318 | AP69: -0.0039340383 | AQ69: 0.098395326 | AR69: 0.035756818 | AS69: Consolidated | AT69: Company | AU69: 1261.5 | AV69: 0.13720364 | AW69: 0.059549807 | AX69: 209.8 | AY69: 0.16630995 | AZ69: -0.0010027713 | BA69: 133 | BB69: 0.17077465 | BC69: 0.090163934 | BD69: 0.10543004 | BE69: 21.95 | BM69: 17272.818 | BN69: 436.2 | BO69: 39.598391 | BS69: 27.8 | BT69: 8.2 | BZ69: 12 | CA69: 0.0567063 | CB69: 0.27771268 | CC69: 9 of 12 | CD69: 33.437503 | CE69: 0.18425081 | CO69: no option prices for this event
A70: Q4 FY21 | B70: Jan-Mar 2021 | C70: 44286 | D70: HEROMOTOCO | E70: Hero MotoCorp Limited | F70: Automobiles - 2 And 3 Wheelers | G70: NSE | H70: Nifty Auto | I70: 150 | J70: 44322 | K70: 20:41 | L70: After close | M70: NSE announcement | N70: 44321 | O70: 44322 | P70: 44323 | Q70: 44323 | R70: 0.0041235257 | S70: 0.044867657 | T70: -0.018020801 | U70: 0.030970381 | V70: 0.022366591 | W70: 0.025108201 | X70: 0.0086037897 | Y70: 0.0058621798 | Z70: 0.10773706 | AA70: -0.076766679 | AB70: 0.012236982 | AC70: -0.018020801 | AD70: 0.018020801 | AE70: 0.060069337 | AF70: 0.23314286 | AG70: 2.6345959 | AH70: 2776.75 | AI70: -0.044312511 | AJ70: -0.046969385 | AK70: -0.18268382 | AL70: -0.057514765 | AM70: 0.41285267 | AN70: -0.028872136 | AO70: -0.018097249 | AP70: -0.0021147931 | AQ70: 0.06692184 | AR70: 0.004283332 | AS70: Consolidated | AT70: Company | AU70: 8689.74 | AV70: 0.37194362 | AW70: -0.1157326 | AX70: 1226.64 | AY70: 0.14115957 | AZ70: 0.032867514 | BA70: 880.94 | BB70: 0.45699023 | BC70: -0.13563845 | BD70: 0.10137703 | BE70: 44.1 | BM70: 55465.581 | BN70: 2641.44 | BO70: 20.998236 | BS70: 532.02 | BT70: 4.36 | BZ70: 2 | CA70: 0.37753095 | CB70: 1.6666557 | CC70: 2 of 3 | CD70: 46.937796 | CE70: -0.55263694 | CF70: 44343 | CG70: 0.37453032 | CH70: 0.35324543 | CI70: 0.30869196 | CJ70: -0.1261261 | CK70: 0.066610902 | CL70: 0.27053832 | CM70: -0.2191938 | CN70: Yes
A71: Q4 FY21 | B71: Jan-Mar 2021 | C71: 44286 | D71: TATACONSUM | E71: TATA CONSUMER PRODUCTS LIMITED | F71: Food And Food Processing | G71: Assigned | H71: Nifty FMCG | I71: 550 | J71: 44322 | K71: 16:27 | L71: After close | M71: NSE announcement | N71: 44321 | O71: 44322 | P71: 44323 | Q71: 44323 | R71: 0.0058891902 | S71: 0.0062398891 | T71: -0.036900934 | U71: -0.024771855 | V71: 0.022366591 | W71: 0.008867364 | X71: -0.047138446 | Y71: -0.033639219 | Z71: 0.036085948 | AA71: -0.060857803 | AB71: -0.02618282 | AC71: -0.036900934 | AD71: 0.036900934 | AE71: 0.042872454 | AF71: 0.53571429 | AG71: 4.2635216 | AH71: 645.25 | AI71: -0.042229479 | AJ71: 0.0099389576 | AK71: 0.14284449 | AL71: 0.30922187 | AM71: 0.95827011 | AN71: -0.031746236 | AO71: 0.041685194 | AP71: 0.03863275 | AQ71: 0.11279809 | AR71: 0.050159584 | AS71: Consolidated | AT71: Company | AU71: 3037.22 | AV71: 0.26286159 | AW71: -0.010535712 | AX71: 236.27 | AY71: 0.077791533 | AZ71: 0.059509017 | BA71: 53.9 | BC71: -0.75294495 | BD71: 0.017746492 | BE71: 0.58 | BM71: 59466.24 | BN71: 726.3 | BO71: 81.875589 | BS71: 40.84 | BT71: 10.18 | BZ71: 4 | CA71: 0.238941 | CB71: 1.3535571 | CD71: 90.328409 | CE71: -0.09357876 | CF71: 44343 | CG71: 0.40576829 | CH71: 0.4135193 | CI71: 0.35486128 | CJ71: -0.14185074 | CK71: 0.077694427 | CL71: 0.47494956 | CM71: -0.13706893 | CN71: Yes
A72: Q4 FY21 | B72: Jan-Mar 2021 | C72: 44286 | D72: CHOLAFIN | E72: Cholamandalam Investment and Finance Company Limited | F72: Finance | G72: NSE | H72: Nifty Financial Services | I72: 625 | J72: 44323 | K72: 18:24 | L72: After close | M72: NSE announcement | N72: 44322 | O72: 44323 | P72: 44326 | Q72: 44326 | R72: 0.038847118 | S72: -0.019645011 | T72: -0.025927228 | U72: -0.0067251214 | V72: 0.022037081 | W72: 0.022196431 | X72: -0.028762202 | Y72: -0.028921552 | Z72: 0.032646975 | AA72: -0.039372096 | AB72: -0.015644226 | AC72: -0.025927228 | AD72: 0.025927228 | AE72: 0.055370012 | AF72: 0.81428571 | AG72: 2.1086571 | AH72: 558.6 | AI72: -0.043165468 | AJ72: -0.0069333333 | AK72: 0.40404675 | AL72: 1.2335066 | AM72: 2.7227591 | AN72: -0.022147493 | AO72: 0.015214159 | AP72: -0.014075611 | AQ72: 0.030226473 | AR72: -0.02316205 | AS72: Consolidated | AT72: NBFC / financial | AU72: 2479.37 | AV72: 0.14496756 | AW72: -0.016310385 | BA72: 245.13 | BB72: 4.7745583 | BC72: -0.40181556 | BD72: 0.098867858 | BE72: 2.99 | BM72: 45805.2 | BN72: 1318.18 | BO72: 34.74882 | BS72: 23.32 | BT72: 4.01 | BZ72: 10 | CA72: 0.047978884 | CB72: 1.0997143 | CC72: 1 of 10 | CD72: 16.666663 | CE72: 1.0849297 | CF72: 44343 | CG72: 0.55071629 | CH72: 0.55098393 | CI72: 0.51614534 | CJ72: -0.063229776 | CK72: 0.099788807 | CL72: 0.259821 | CM72: -0.1751663 | CN72: Yes
A73: Q4 FY21 | B73: Jan-Mar 2021 | C73: 44286 | D73: DABUR | E73: Dabur India Limited | F73: Personal Care | G73: NSE | H73: Nifty FMCG | I73: 1250 | J73: 44323 | K73: 14:17 | L73: During market | M73: NSE announcement | N73: 44322 | O73: 44323 | P73: 44326 | Q73: 44323 | R73: 0.0079489786 | S73: -0.019532325 | T73: -0.022166105 | U73: -0.033749451 | V73: 0.022037081 | W73: 0.0090089346 | X73: -0.055786532 | Y73: -0.042758386 | Z73: 0.082041701 | AA73: -0.11579115 | AB73: 0.005043558 | AC73: -0.019532325 | AD73: 0.019532325 | AE73: 0.028794131 | AF73: 0.14649682 | AG73: 3.5487729 | AH73: 540.95 | AI73: -0.00055427252 | AJ73: 0.0042699341 | AK73: 0.051306967 | AL73: 0.040788841 | AM73: 0.18707483 | AN73: -0.028001795 | AO73: 0.032271729 | AP73: 0.015973219 | AQ73: 0.064275466 | AR73: 0.010886943 | AS73: Consolidated | AT73: Company | AU73: 2336.79 | AV73: 0.2527287 | AW73: -0.1436691 | AX73: 442.47 | AY73: 0.18934949 | AZ73: 0.011228379 | BA73: 377.82 | BB73: 0.34374222 | BC73: -0.23210439 | BD73: 0.16168333 | BE73: 2.14 | BM73: 95607.503 | BN73: 1596.65 | BO73: 59.880063 | BS73: 40.87 | BT73: 10.2 | BZ73: 3 | CA73: 0.26787074 | CB73: 0.54131766 | CC73: 3 of 4 | CD73: 45.296631 | CE73: 0.32195401 | CF73: 44343 | CG73: 0.28066064 | CH73: 0.308109 | CI73: 0.29582451 | CJ73: -0.039870585 | CK73: 0.057912581 | CL73: 0.33727256 | CM73: -0.071210762 | CN73: Yes
A74: Q4 FY21 | B74: Jan-Mar 2021 | C74: 44286 | D74: ULTRACEMCO | E74: UltraTech Cement Limited | F74: Cement And Cement Products | G74: NSE | H74: Nifty Commodities | I74: 50 | J74: 44323 | K74: 20:19 | L74: After close | M74: NSE announcement | N74: 44322 | O74: 44323 | P74: 44326 | Q74: 44326 | R74: 0.0039339535 | S74: 0.011935149 | T74: -0.012156929 | U74: 0.0037121731 | V74: 0.022037081 | W74: 0.051803626 | X74: -0.018324908 | Y74: -0.048091453 | Z74: -0.00024657504 | AA74: 0.0039587482 | AB74: 0.016677209 | AC74: -0.012156929 | AD74: 0.012156929 | AE74: 0.042425832 | AF74: 0.26581818 | AG74: 1.3911655 | AH74: 6380.35 | AI74: 0.0030735128 | AJ74: -0.075157454 | AK74: 0.19768173 | AL74: 0.39406354 | AM74: 0.91924859 | AN74: 0.037808398 | AO74: -0.11296585 | AP74: 0.039027971 | AQ74: 0.061111024 | AR74: 0.0077225011 | AS74: Consolidated | AT74: Company | AU74: 14405.61 | AV74: 0.34060296 | AW74: 0.17557279 | AX74: 3651.58 | AY74: 0.25348319 | AZ74: 0.026165457 | BA74: 1775.23 | BB74: -0.45255754 | BC74: 0.1204855 | BD74: 0.12323185 | BE74: 61.54 | BM74: 184162.42 | BN74: 6858.92 | BO74: 26.850061 | BS74: 23.57 | BT74: 2.32 | BZ74: 3 | CA74: 0.23124674 | CB74: 0.48980277 | CC74: 4 of 4 | CD74: 25.733099 | CE74: 0.043405682 | CF74: 44343 | CG74: 0.37772227 | CH74: 0.37929376 | CI74: 0.32313931 | CJ74: -0.14805003 | CK74: 0.068669199 | CL74: 0.17703613 | CM74: -0.075901429 | CN74: Yes
A75: Q4 FY21 | B75: Jan-Mar 2021 | C75: 44286 | D75: BANDHANBNK | E75: Bandhan Bank Limited | F75: Banks | G75: Assigned | H75: Nifty Bank | I75: 3600 | J75: 44324 | K75: 15:49 | L75: Non-trading day | M75: NSE announcement | N75: 44323 | O75: 44326 | P75: 44327 | Q75: 44326 | R75: 0.0088210348 | S75: -0.0047082563 | T75: -0.016894746 | U75: -0.012781967 | V75: 0.0085904564 | W75: 0.0014137498 | X75: -0.021372424 | Y75: -0.014195717 | Z75: -0.010168456 | AA75: -0.0026135113 | AB75: -0.041533546 | AC75: -0.0047082563 | AD75: 0.0047082563 | AE75: 0.0669245 | AF75: 0.55025126 | AG75: 3.6014432 | AH75: 294.75 | AI75: -0.11246612 | AJ75: -0.12132956 | AK75: -0.088167053 | AL75: 0.018310589 | AM75: 0.16871531 | AN75: 0.0045579939 | AO75: -0.12588755 | AP75: -0.0048118233 | AQ75: 0.091252793 | AR75: 0.038420444 | AS75: Standalone | AT75: Bank | AU75: 3000.6575 | AV75: 0.054234746 | AW75: -0.092864323 | BA75: 103.0325 | BB75: -0.80082075 | BC75: -0.83712635 | BD75: 0.034336641 | BE75: 0.64 | BF75: 1757.0033 | BG75: 0.045812452 | BH75: 0.1372983 | BI75: 0.92696811 | BJ75: 0.0681 | BK75: 0.0351 | BL75: 0.0009 | BM75: 47465.948 | BN75: 2619.7099 | BO75: 18.11878 | BS75: 22.38 | BT75: 2.99 | BZ75: 19 | CA75: 0.0068971806 | CB75: 0.48380133 | CC75: 11 of 13 | CD75: 29.632537 | CE75: -0.38855117 | CF75: 44343 | CG75: 0.51148099 | CH75: 0.62693083 | CI75: 0.54031586 | CJ75: -0.13815713 | CK75: 0.11375839 | CL75: 0.041388211 | CM75: 0.14695639 | CN75: Yes
A76: Q4 FY21 | B76: Jan-Mar 2021 | C76: 44286 | D76: DMART | E76: Avenue Supermarts Limited | F76: Retail | G76: Assigned | H76: Nifty India Consumption | I76: 150 | J76: 44324 | K76: 14:50 | L76: Non-trading day | M76: NSE announcement | N76: 44323 | O76: 44326 | P76: 44327 | Q76: 44326 | R76: 0.0060281778 | S76: -0.014867898 | T76: -0.00066609406 | U76: -0.0095058147 | V76: 0.0085904564 | W76: 0.0022622083 | X76: -0.018096271 | Y76: -0.011768023 | AB76: 0.010188223 | AC76: -0.014867898 | AD76: 0.014867898 | AE76: 0.041443619 | AF76: 0.10375 | AG76: 1.9331022 | AH76: 2878.15 | AI76: -0.0097028919 | AJ76: 0.010959097 | AK76: 0.023524182 | AL76: 0.28494576 | AM76: 0.31898171 | AN76: 0.0046036761 | AO76: 0.0063554204 | AP76: 0.062216064 | AQ76: 0.12073109 | AR76: 0.067898738 | AS76: Consolidated | AT76: Company | AU76: 7411.68 | AV76: 0.18474471 | AW76: -0.017279236 | AX76: 612.66 | AY76: 0.082661421 | AZ76: 0.015951915 | BA76: 413.88 | BB76: 0.52559991 | BC76: -0.074031814 | BD76: 0.055841591 | BE76: 6.39 | BM76: 186439.07 | BN76: 956.9 | BO76: 194.83653 | BS76: 147.39 | BT76: 7.11 | BZ76: 0 | CO76: no option prices for this event
A77: Q4 FY21 | B77: Jan-Mar 2021 | C77: 44286 | D77: IDFCFIRSTB | E77: IDFC First Bank Limited | F77: Banks | G77: Assigned | H77: Nifty Bank | I77: 9275 | J77: 44324 | K77: 22:19 | L77: Non-trading day | M77: NSE announcement | N77: 44323 | O77: 44326 | P77: 44327 | Q77: 44326 | R77: -0.001759015 | S77: -0.024669604 | T77: 0.016260163 | U77: -0.010168456 | V77: 0.0085904564 | W77: 0.0014137498 | X77: -0.018758912 | Y77: -0.011582206 | Z77: -0.012781967 | AA77: 0.0026135113 | AB77: -0.013215859 | AC77: -0.024669604 | AD77: 0.024669604 | AE77: 0.024669604 | AF77: 0.10714286 | AG77: 1.0748164 | AH77: 56.85 | AI77: 0.037408759 | AJ77: 0.046961326 | AK77: 0.21995708 | AL77: 0.85784314 | AM77: 1.739759 | AN77: 0.0045579939 | AO77: 0.042403332 | AP77: -0.012444444 | AQ77: 0.061333333 | AR77: 0.0085009848 | AS77: Standalone | AT77: Bank | AU77: 3992.8728 | AV77: 0.0093552237 | AW77: 0.010224746 | BA77: 127.811 | BB77: 0.78655946 | BC77: -0.01314611 | BD77: 0.032009785 | BE77: 0.23 | BF77: 1960.2669 | BG77: 0.25376985 | BH77: 0.24256147 | BI77: 0.4615778 | BJ77: 0.0415 | BK77: 0.0186 | BL77: 0.0033 | BM77: 32250.493 | BN77: 396.0096 | BO77: 81.438666 | BS77: 22.38 | BT77: 2.99 | BZ77: 19 | CA77: 0.011229589 | CB77: 0.3548314 | CC77: 5 of 13 | CD77: 26.380328 | CE77: 2.0870983 | CF77: 44343 | CG77: 0.50287249 | CH77: 0.50944577 | CI77: 0.49442691 | CJ77: -0.029480781 | CK77: 0.092186128 | CL77: 0.26760646 | CM77: -0.058383679 | CN77: Yes
A78: Q4 FY21 | B78: Jan-Mar 2021 | C78: 44286 | D78: GODREJCP | E78: Godrej Consumer Products Limited | F78: Personal Care | G78: NSE | H78: Nifty FMCG | I78: 500 | J78: 44327 | K78: 15:41 | L78: After close | M78: NSE announcement | N78: 44326 | O78: 44327 | P78: 44328 | Q78: 44328 | R78: 0.010183735 | S78: 0.0097990835 | T78: 0.21872382 | U78: 0.23870664 | V78: -0.0084754323 | W78: -0.001931538 | X78: 0.24718207 | Y78: 0.24063818 | Z78: 0.033672142 | AA78: 0.2050345 | AB78: 0.082099972 | AC78: 0.21872382 | AD78: 0.21872382 | AE78: 0.16594527 | AF78: 0.83887253 | AG78: 30.527727 | AH78: 702.1 | AI78: 0.014962053 | AJ78: -0.03524562 | AK78: -0.061175369 | AL78: 0.070192821 | AM78: 0.40546492 | AN78: -0.014337151 | AO78: -0.02090847 | AP78: -0.065704302 | AQ78: 0.014779172 | AR78: -0.056071031 | AS78: Consolidated | AT78: Company | AU78: 2730.74 | AV78: 0.26787074 | AW78: -0.10626362 | AX78: 485.18 | AY78: 0.17767345 | AZ78: -0.0094887738 | BA78: 365.84 | BB78: 0.59130057 | BC78: -0.27135118 | BD78: 0.13397101 | BE78: 3.58 | BM78: 71789.725 | BN78: 1584.88 | BO78: 45.296631 | BS78: 41.13 | BT78: 10.27 | BZ78: 3 | CA78: 0.2527287 | CB78: 0.34374222 | CC78: 1 of 4 | CD78: 45.750517 | CE78: -0.0099208922 | CF78: 44343 | CH78: 0.38434186 | CI78: 0.55547673 | CJ78: 0.44526732 | CK78: 0.064049011 | CL78: 3.4149445
A79: Q4 FY21 | B79: Jan-Mar 2021 | C79: 44286 | D79: SIEMENS | E79: Siemens Limited | F79: Electrical Equipment | G79: NSE | H79: Nifty 500 | I79: 175 | J79: 44327 | K79: 16:22 | L79: After close | M79: NSE announcement | N79: 44326 | O79: 44327 | P79: 44328 | Q79: 44328 | R79: 0.010708247 | S79: 0.034864578 | T79: 0.028301645 | U79: 0.07387447 | V79: -0.0084754323 | W79: -0.0019313649 | X79: 0.082349902 | Y79: 0.075805835 | Z79: -0.0046784497 | AA79: 0.078552919 | AB79: 0.044825905 | AC79: 0.028301645 | AD79: 0.028301645 | AE79: 0.082364714 | AF79: 0.12959502 | AG79: 15.868285 | AH79: 1863.05 | AI79: -0.0097796912 | AJ79: 0.043170302 | AK79: 0.024301069 | AL79: 0.45170842 | AM79: 0.7856424 | AN79: 0.016588311 | AO79: 0.026581991 | AP79: -0.0016967761 | AQ79: 0.044141132 | AR79: -0.026709071 | AS79: Consolidated | AT79: Company | AU79: 3483.7 | AV79: 0.22756263 | AW79: 0.19092712 | AX79: 457.8 | AY79: 0.131412 | AZ79: 0.047723361 | BA79: 334.4 | BB79: 0.90324417 | BC79: 0.13164129 | BD79: 0.095989896 | BE79: 9.39 | BM79: 66324.58 | BN79: 799.5 | BO79: 82.957573 | BS79: 33.6 | BT79: 4.05 | BZ79: 9 | CA79: 0.41994847 | CB79: 0.53055694 | CC79: 2 of 5 | CD79: 75.274196 | CE79: 0.10207187 | CF79: 44343 | CH79: 0.46411083 | CI79: 0.4018139 | CJ79: -0.13422855 | CK79: 0.077509886 | CL79: 0.36513593
A80: Q4 FY21 | B80: Jan-Mar 2021 | C80: 44286 | D80: ASIANPAINT | E80: Asian Paints Limited | F80: Paints | G80: NSE | H80: Nifty Consumer Durables | I80: 250 | J80: 44328 | K80: 15:05 | L80: During market | M80: NSE announcement | N80: 44327 | O80: 44328 | P80: 44330 | Q80: 44328 | R80: -0.00027376366 | S80: -1.9559902e-05 | T80: 0.085400203 | U80: 0.08510688 | V80: -0.01778932 | W80: -0.0004194454 | X80: 0.1028962 | Y80: 0.085526325 | AB80: 0.0081173594 | AC80: -1.9559902e-05 | AD80: 1.9559902e-05 | AE80: 0.023061125 | AF80: 0.44444444 | AG80: 1.5111167 | AH80: 2556.95 | AI80: -0.0097593091 | AJ80: -0.027257856 | AK80: 0.042100544 | AL80: 0.18671246 | AM80: 0.62904562 | AN80: -0.031536514 | AO80: 0.0042786584 | AP80: 0.020904668 | AQ80: 0.065507299 | AR80: -0.010904016 | AS80: Consolidated | AT80: Company | AU80: 6651.43 | AV80: 0.43486158 | AW80: -0.02018717 | AX80: 1318.26 | AY80: 0.19819197 | AZ80: 0.01275279 | BA80: 852.13 | BB80: 0.84487649 | BC80: -0.31187719 | BD80: 0.1281123 | BE80: 8.88 | BM80: 245262.64 | BN80: 2749.05 | BO80: 89.217236 | BS80: 79.55 | BT80: 12.27 | BZ80: 0 | CF80: 44343 | CG80: 0.30416266 | CH80: 0.33231392 | CI80: 0.33770087 | CJ80: 0.016210428 | CK80: 0.055422531 | CL80: 0.00035292329 | CM80: -0.13797859 | CN80: Yes
A81: Q4 FY21 | B81: Jan-Mar 2021 | C81: 44286 | D81: JINDALSTEL | E81: JINDAL STEEL LIMITED | F81: Steel And Steel Products | G81: NSE | H81: Nifty Metal | I81: 625 | J81: 44328 | K81: 15:50 | L81: After close | M81: NSE announcement | N81: 44327 | O81: 44328 | P81: 44330 | Q81: 44330 | R81: -0.028559772 | S81: -0.041159177 | T81: -0.086070959 | U81: -0.15578991 | V81: -0.01778932 | W81: -0.076593424 | X81: -0.13800059 | Y81: -0.079196484 | Z81: 0.027243836 | AA81: -0.18303374 | AB81: 0.011826544 | AC81: -0.086070959 | AD81: 0.086070959 | AE81: 0.1608629 | AF81: 0.39142274 | AG81: 3.8196624 | AH81: 490.2 | AI81: 0.1008309 | AJ81: 0.26080247 | AK81: 0.71698774 | AL81: 1.4309447 | AM81: 4.4709821 | AN81: 0.27231849 | AO81: -0.011516018 | AP81: -0.033908459 | AQ81: 0.0091061586 | AR81: -0.067305156 | AS81: Consolidated | AT81: Company | AU81: 11880.61 | AV81: 0.34843281 | AW81: 0.1278871 | AX81: 4318.45 | AY81: 0.36348723 | AZ81: 0.12396088 | BA81: 1968.24 | BB81: 3.8453755 | BC81: -0.12703467 | BD81: 0.16566826 | BE81: 19.3 | BM81: 49877.85 | BN81: 3686.72 | BO81: 13.529058 | BS81: 24.09 | BT81: 2.55 | BZ81: 4 | CA81: 0.45988983 | CB81: 1.0982049 | CC81: 2 of 4 | CD81: 43.131301 | CE81: -0.68632853 | CF81: 44343 | CG81: 0.58318669 | CH81: 0.66487892 | CI81: 0.6197564 | CJ81: -0.067865762 | CK81: 0.10562459 | CL81: 0.81487614 | CM81: -0.097325349 | CN81: Yes | CO81: share count in the previous filing looked mis-scaled; used the stock's other quarters
A82: Q4 FY21 | B82: Jan-Mar 2021 | C82: 44286 | D82: PIDILITIND | E82: Pidilite Industries Limited | F82: Chemicals - Speciality | G82: NSE | H82: Nifty Commodities | I82: 500 | J82: 44328 | K82: 19:56 | L82: After close | M82: NSE announcement | N82: 44327 | O82: 44328 | P82: 44330 | Q82: 44330 | R82: 0.016433387 | S82: 0.0014383124 | T82: 0.0044417256 | U82: 0.022313425 | V82: -0.01778932 | W82: -0.024407097 | X82: 0.040102744 | Y82: 0.046720522 | AB82: -0.0079259535 | AC82: 0.0044417256 | AD82: 0.0044417256 | AE82: 0.051146338 | AF82: 0.74830993 | AG82: 4.8454587 | AH82: 1846.85 | AI82: 0.019739385 | AJ82: -0.022002754 | AK82: 0.061774175 | AL82: 0.17964359 | AM82: 0.34077462 | AN82: 0.082923037 | AO82: -0.10492579 | AP82: 0.047530782 | AQ82: 0.12111744 | AR82: 0.044706122 | AS82: Consolidated | AT82: Company | AU82: 2235.52 | AV82: 0.44723826 | AW82: -0.027620464 | AX82: 457.17 | AY82: 0.20450276 | AZ82: 0.031049354 | BA82: 306.19 | BB82: 0.94369326 | BC82: -0.31120509 | BD82: 0.1369659 | BE82: 6.03 | BM82: 93838.448 | BN82: 985.28 | BO82: 95.240387 | BS82: 21.51 | BT82: 2.46 | BZ82: 1 | CF82: 44343 | CH82: 0.33786684 | CI82: 0.30742012 | CJ82: -0.090114554 | CK82: 0.053663982 | CL82: 0.082769214
A83: Q4 FY21 | B83: Jan-Mar 2021 | C83: 44286 | D83: TATAPOWER | E83: Tata Power Company Limited | F83: Power | G83: NSE | H83: Nifty Energy | I83: 1450 | J83: 44328 | K83: 17:31 | L83: After close | M83: NSE announcement | N83: 44327 | O83: 44328 | P83: 44330 | Q83: 44330 | R83: -0.0054570259 | S83: -0.025148605 | T83: -0.047842402 | U83: -0.078448033 | V83: -0.01778932 | W83: 0.003593881 | X83: -0.060658713 | Y83: -0.082041914 | Z83: 0.00893829 | AA83: -0.087386323 | AB83: -0.0023452158 | AC83: -0.047842402 | AD83: 0.047842402 | AE83: 0.065666041 | AF83: 0.071428571 | AG83: 1.5454514 | AH83: 109.95 | AI83: 0.10115173 | AJ83: 0.052656774 | AK83: 0.30581948 | AL83: 1.051306 | AM83: 3.0274725 | AN83: 0.014001805 | AO83: 0.038654968 | AP83: 0.033497537 | AQ83: 0.23842365 | AR83: 0.16201233 | AS83: Consolidated | AT83: Company | AU83: 10127.39 | AV83: 0.52963237 | AW83: 0.33291787 | AX83: 1445.61 | AY83: 0.1427426 | AZ83: -0.14421517 | BA83: 392.94 | BB83: -0.023969796 | BC83: 0.58309496 | BD83: 0.03879973 | BE83: 1.1 | BM83: 35135.622 | BN83: 1137.03 | BO83: 30.901227 | BS83: 15.49 | BT83: 1.74 | BZ83: 7 | CA83: 0.032591702 | CB83: 0.99670333 | CC83: 7 of 7 | CD83: 22.099614 | CE83: 0.39826997 | CF83: 44343 | CG83: 0.48976777 | CH83: 0.63938524 | CI83: 0.54099946 | CJ83: -0.15387559 | CK83: 0.10148976 | CL83: 0.47140128 | CM83: 0.044802829 | CN83: Yes
A84: Q4 FY21 | B84: Jan-Mar 2021 | C84: 44286 | D84: UPL | E84: UPL Limited | F84: Pesticides And Agrochemicals | G84: Assigned | H84: Nifty Commodities | I84: 1355 | J84: 44328 | K84: 15:49 | L84: After close | M84: NSE announcement | N84: 44327 | O84: 44328 | P84: 44330 | Q84: 44330 | R84: 0.014453009 | S84: 0.010667056 | T84: 0.074676498 | U84: 0.099796564 | V84: -0.01778932 | W84: -0.024407097 | X84: 0.11758588 | Y84: 0.12420366 | AB84: 0.02653076 | AC84: 0.074676498 | AD84: 0.074676498 | AE84: 0.085809297 | AF84: 0.64448189 | AG84: 8.4570747 | AH84: 674.6 | AI84: 0.091939139 | AJ84: 0.030789212 | AK84: 0.20841917 | AL84: 0.61755185 | AM84: 0.83265417 | AN84: 0.082923037 | AO84: -0.052133825 | AP84: 0.049172609 | AQ84: 0.12357056 | AR84: 0.047159249 | AS84: Consolidated | AT84: Company | AU84: 12796 | AV84: 0.1485504 | AW84: 0.40214771 | AX84: 2571 | AY84: 0.20092216 | AZ84: 0.045370597 | BA84: 1063 | BB84: 0.72285251 | BC84: 0.33879093 | BD84: 0.083072835 | BE84: 12.75 | BM84: 51606.9 | BN84: 2425 | BO84: 21.281196 | BS84: 21.51 | BT84: 2.46 | BZ84: 1 | CF84: 44343 | CG84: 0.48894962 | CH84: 0.58565523 | CI84: 0.50809402 | CJ84: -0.13243493 | CK84: 0.09287881 | CL84: 0.80402084 | CM84: 0.16497072 | CN84: Yes
A85: Q4 FY21 | B85: Jan-Mar 2021 | C85: 44286 | D85: VOLTAS | E85: Voltas Limited | F85: Engineering | G85: NSE | H85: Nifty 500 | I85: 375 | J85: 44328 | K85: 14:24 | L85: During market | M85: NSE announcement | N85: 44327 | O85: 44328 | P85: 44330 | Q85: 44328 | R85: 0.04375452 | S85: -0.037861915 | T85: 0.02813786 | U85: 0.034030465 | V85: -0.01778932 | W85: -0.015680518 | X85: 0.051819785 | Y85: 0.049710983 | AB85: 0.013610492 | AC85: -0.037861915 | AD85: 0.037861915 | AE85: 0.061766889 | AF85: 0.16666667 | AG85: 3.6013528 | AH85: 967.9 | AI85: 0.0096489856 | AJ85: -0.031664249 | AK85: -0.036388073 | AL85: 0.36323944 | AM85: 1.0639727 | AN85: 0.015110605 | AO85: -0.046774854 | AP85: 0.00050032521 | AQ85: 0.04683044 | AR85: -0.029580875 | AS85: Consolidated | AT85: Company | AU85: 2627.84 | AV85: 0.25756234 | AW85: 0.31745077 | AX85: 306.91 | AY85: 0.11679174 | AZ85: 0.02586655 | BA85: 237.73 | BB85: 0.49836128 | BC85: 0.85857243 | BD85: 0.090465934 | BE85: 7.18 | BM85: 32018.132 | BN85: 446.07 | BO85: 71.778268 | BS85: 33.72 | BT85: 4.09 | BZ85: 1 | CF85: 44343 | CG85: 0.40723141 | CH85: 0.44214419 | CI85: 0.47058328 | CJ85: 0.064320848 | CK85: 0.073767666 | CL85: 0.51325896 | CM85: -0.03031375 | CN85: Yes
A86: Q4 FY21 | B86: Jan-Mar 2021 | C86: 44286 | D86: BSE | E86: BSE Limited | F86: Capital Markets | G86: Assigned | H86: Nifty Financial Services | I86: 200 | J86: 44329 | K86: 16:57 | L86: Non-trading day | M86: NSE announcement | N86: 44328 | O86: 44330 | P86: 44333 | Q86: 44330 | R86: 0.041177303 | S86: 0.022356619 | T86: -0.0036556996 | U86: 0.059878222 | V86: 0.0050566277 | W86: 0.013587066 | X86: 0.054821594 | Y86: 0.046291156 | Z86: -0.033087986 | AA86: 0.092966208 | AB86: 0.010736613 | AC86: 0.022356619 | AD86: 0.022356619 | AE86: 0.0638081 | AF86: 0.62193823 | AG86: 2.4123172 | AH86: 706.7 | AI86: 0.13809485 | AJ86: 0.16945226 | AK86: 0.15069608 | AL86: 0.49502856 | AM86: 0.85509909 | AN86: 0.01125593 | AO86: 0.15819633 | AP86: 0.051034023 | AQ86: 0.24162775 | AR86: 0.18207598 | AS86: Consolidated | AT86: Company | AU86: 152.18 | AV86: 0.27283372 | AW86: 0.26196202 | AX86: 37.25 | AY86: 0.24477592 | AZ86: 0.43003855 | BA86: 32.57 | BC86: 0.0061785604 | BD86: 0.21402287 | BE86: 6.93 | BM86: 3180.15 | BN86: 111.02 | BO86: 28.644839 | BS86: 23.22 | BT86: 4.05 | BZ86: 7 | CA86: 0.099817851 | CB86: 0.57895287 | CD86: 47.382455 | CE86: -0.39545473 | CO86: no option prices for this event
A87: Q4 FY21 | B87: Jan-Mar 2021 | C87: 44286 | D87: IEX | E87: Indian Energy Exchange Limited | F87: Capital Markets | G87: Assigned | H87: Nifty Financial Services | I87: 4350 | J87: 44329 | K87: 16:49 | L87: Non-trading day | M87: NSE announcement | N87: 44328 | O87: 44330 | P87: 44333 | Q87: 44330 | R87: -0.0090897771 | S87: -0.061698919 | T87: -0.0054908263 | U87: -0.076279523 | V87: 0.0050566277 | W87: 0.013587066 | X87: -0.08133615 | Y87: -0.089866589 | Z87: -0.0055389271 | AA87: -0.070740596 | AB87: 0.0077909022 | AC87: -0.061698919 | AD87: 0.061698919 | AE87: 0.077406384 | AF87: 0.076298701 | AG87: 1.9101442 | AH87: 401.55 | AI87: 0.05104044 | AJ87: 0.14222728 | AK87: 0.55972033 | AL87: 1.2154483 | AM87: 1.7788927 | AN87: 0.01125593 | AO87: 0.13097135 | AP87: -0.011042284 | AQ87: -0.014274172 | AR87: -0.073825942 | AS87: Consolidated | AT87: Company | AU87: 93.8162 | AV87: 0.35095804 | AW87: 0.10071828 | AX87: 77.4532 | AY87: 0.82558449 | AZ87: 0.069685513 | BA87: 61.5201 | BB87: 0.34862222 | BC87: 0.058064461 | BD87: 0.65575135 | BE87: 2.06 | BM87: 11984.541 | BN87: 190.1902 | BO87: 63.013451 | BS87: 23.22 | BT87: 4.05 | BZ87: 7 | CA87: 0.099817851 | CB87: 0.80928352 | CC87: 3 of 4 | CD87: 39.637453 | CE87: 0.58974519 | CO87: no option prices for this event
A88: Q4 FY21 | B88: Jan-Mar 2021 | C88: 44286 | D88: LUPIN | E88: Lupin Limited | F88: Pharmaceuticals | G88: NSE | H88: Nifty Pharma | I88: 425 | J88: 44329 | K88: 00:11 | L88: Non-trading day | M88: NSE announcement | N88: 44328 | O88: 44330 | P88: 44333 | Q88: 44330 | R88: 0.012444147 | S88: -0.027882038 | T88: 0.0090797234 | U88: -0.0063581667 | V88: 0.0050566277 | W88: -0.0148095 | X88: -0.011414794 | Y88: 0.0084513336 | Z88: -0.010567215 | AA88: 0.0042090487 | AB88: -0.0018560528 | AC88: -0.027882038 | AD88: 0.027882038 | AE88: 0.055929058 | AF88: 0.18362832 | AG88: 1.2483504 | AH88: 1197.35 | AI88: 0.13176426 | AJ88: 0.14109406 | AK88: 0.13892324 | AL88: 0.26750648 | AM88: 0.40558784 | AN88: 0.1153651 | AO88: 0.025728965 | AP88: 0.0081150402 | AQ88: 0.0029432788 | AR88: -0.056608491 | AS88: Consolidated | AT88: Company | AU88: 3783.1 | AV88: -0.016288153 | AW88: -0.058311926 | AX88: 707.55 | AY88: 0.18702916 | AZ88: 0.028825533 | BA88: 460.36 | BC88: 0.050450656 | BD88: 0.12168856 | BE88: 10.24 | BM88: 54299.823 | BN88: 214.4 | BO88: 253.2641 | BS88: 36.87 | BT88: 5.79 | BZ88: 11 | CA88: 0.041300242 | CB88: 0.68074812 | CD88: 34.5243 | CE88: 6.3358214 | CF88: 44343 | CG88: 0.53191107 | CH88: 0.50999443 | CI88: 0.42596442 | CJ88: -0.16476652 | CK88: 0.081097762 | CL88: 0.34380773 | CM88: -0.2541412 | CN88: Yes
A89: Q4 FY21 | B89: Jan-Mar 2021 | C89: 44286 | D89: MPHASIS | E89: MphasiS Limited | F89: Computers - Software | G89: NSE | H89: Nifty IT | I89: 275 | J89: 44329 | K89: 22:38 | L89: Non-trading day | M89: NSE announcement | N89: 44328 | O89: 44330 | P89: 44333 | Q89: 44330 | R89: -0.026694434 | S89: -0.0058354406 | T89: -0.014786036 | U89: -0.04731591 | V89: 0.0050566277 | W89: -0.015452341 | X89: -0.052372538 | Y89: -0.031863569 | Z89: 0.0021188294 | AA89: -0.04943474 | AB89: -0.012865757 | AC89: -0.0058354406 | AD89: 0.0058354406 | AE89: 0.023675216 | AF89: 0.63849765 | AG89: 1.367366 | AH89: 1848.7 | AI89: 0.053420325 | AJ89: 0.050188883 | AK89: 0.16307015 | AL89: 0.34656566 | AM89: 1.2925347 | AN89: -0.038370585 | AO89: 0.088559468 | AP89: 0.038328416 | AQ89: 0.13183727 | AR89: 0.072285497 | AS89: Consolidated | AT89: Company | AU89: 2524.283 | AV89: 0.075925207 | AW89: 0.020165819 | AX89: 467.126 | AY89: 0.18505294 | AZ89: -0.0041944662 | BA89: 316.935 | BB89: -0.10275175 | BC89: -0.026394124 | BD89: 0.12555446 | BE89: 16.96 | BM89: 34522.439 | BN89: 1253.1 | BO89: 27.549628 | BS89: 28.26 | BT89: 8.4 | BZ89: 12 | CA89: 0.0567063 | CB89: 0.27771268 | CC89: 11 of 12 | CD89: 35.888344 | CE89: -0.23235165 | CF89: 44343 | CH89: 0.40542521 | CI89: 0.32547767 | CJ89: -0.19719429 | CK89: 0.064374827 | CL89: 0.090647865
A90: Q4 FY21 | B90: Jan-Mar 2021 | C90: 44286 | D90: POLYCAB | E90: Polycab India Limited | F90: Electrical Equipment | G90: Assigned | H90: Nifty 500 | I90: 125 | J90: 44329 | K90: 19:11 | L90: Non-trading day | M90: NSE announcement | N90: 44328 | O90: 44330 | P90: 44333 | Q90: 44330 | R90: -0.0040323881 | S90: 0.035952581 | T90: 0.046898449 | U90: 0.078818643 | V90: 0.0050566277 | W90: 0.0025335381 | X90: 0.073762015 | Y90: 0.076285104 | Z90: -0.0046784497 | AA90: 0.083497092 | AB90: 0.033231846 | AC90: 0.035952581 | AD90: 0.035952581 | AE90: 0.059111226 | AF90: 0.38849315 | AG90: 5.2661598 | AH90: 1549.95 | AI90: 0.070333541 | AJ90: 0.10643538 | AK90: 0.17438248 | AL90: 0.6451202 | AM90: 1.3190693 | AN90: 0.0080212731 | AO90: 0.098414105 | AP90: 0.0021801457 | AQ90: 0.084637439 | AR90: 0.025085669 | AS90: Consolidated | AT90: Company | AU90: 3037.437 | AV90: 0.4264413 | AW90: 0.085254348 | AX90: 421.251 | AY90: 0.13868633 | AZ90: -0.0024683028 | BA90: 283.191 | BB90: 0.32371212 | BC90: 0.10830157 | BD90: 0.093233539 | BE90: 18.88 | BM90: 23105.57 | BN90: 812.784 | BO90: 28.427688 | BS90: 33.57 | BT90: 4.08 | BZ90: 9 | CA90: 0.36180496 | CB90: 0.80637367 | CC90: 5 of 5 | CD90: 80.229328 | CE90: -0.64566963 | CO90: no option prices for this event
A91: Q4 FY21 | B91: Jan-Mar 2021 | C91: 44286 | D91: VEDL | E91: Vedanta Limited | F91: Metals | G91: Assigned | H91: Nifty Metal | I91: 1150 | J91: 44329 | K91: 15:50 | L91: Non-trading day | M91: NSE announcement | N91: 44328 | O91: 44330 | P91: 44333 | Q91: 44330 | R91: -0.022522523 | S91: -0.03438497 | T91: 0.0229442 | U91: -0.033963293 | V91: 0.0050566277 | W91: -0.044518548 | X91: -0.03901992 | Y91: 0.010555255 | AB91: 0.0101028 | AC91: -0.03438497 | AD91: 0.03438497 | AE91: 0.06628855 | AF91: 0.21925134 | AG91: 1.8702122 | AH91: 288.6 | AI91: 0.1162251 | AJ91: 0.21388013 | AK91: 0.63605442 | AL91: 2.1369565 | AM91: 2.2408759 | AN91: 0.21306132 | AO91: 0.00081880181 | AP91: -0.013278306 | AQ91: -0.017046474 | AR91: -0.076598244 | AS91: Consolidated | AT91: Company | AU91: 27874 | AV91: 0.42848358 | AW91: 0.23895457 | AX91: 7932 | AY91: 0.28456626 | AZ91: 0.94166666 | BA91: 6432 | BC91: 0.94968172 | BD91: 0.23075267 | BE91: 17.37 | BM91: 107359.2 | BN91: -7365 | BS91: 23.87 | BT91: 2.52 | BZ91: 1 | CF91: 44343 | CG91: 0.55337843 | CH91: 0.69384158 | CI91: 0.60993091 | CJ91: -0.12093636 | CK91: 0.11032781 | CL91: 0.31166185 | CM91: 0.041518699 | CN91: Yes
A92: Q4 FY21 | B92: Jan-Mar 2021 | C92: 44286 | D92: ABCAPITAL | E92: Aditya Birla Capital Limited | F92: Finance | G92: Assigned | H92: Nifty Financial Services | I92: 3100 | J92: 44330 | K92: 16:17 | L92: After close | M92: NSE announcement | N92: 44328 | O92: 44330 | P92: 44333 | Q92: 44333 | R92: -0.0029227557 | S92: 0.016750419 | T92: 0.033360791 | U92: 0.047188454 | V92: 0.0050566277 | W92: 0.013587066 | X92: 0.042131826 | Y92: 0.033601388 | Z92: 0.015075048 | AA92: 0.032113406 | AB92: 0.046128501 | AC92: 0.033360791 | AD92: 0.033360791 | AE92: 0.049011532 | AF92: 0.34453782 | AG92: 3.1656633 | AH92: 119.75 | AI92: 0.049058257 | AJ92: -0.062989045 | AK92: 0.32466814 | AL92: 0.77407407 | AM92: 1.8242925 | AN92: 0.01125593 | AO92: -0.074244975 | AP92: 0.0039856517 | AQ92: -0.013949781 | AR92: -0.073501551 | AS92: Consolidated | AT92: NBFC / financial | AU92: 5586.83 | AV92: 0.15314343 | AW92: 0.11159018 | BA92: 375.15 | BB92: 1.9764361 | BC92: 0.29953582 | BD92: 0.067148991 | BE92: 1.55 | BM92: 28919.625 | BN92: 877.44 | BO92: 32.959091 | BS92: 23.22 | BT92: 4.05 | BZ92: 10 | CA92: 0.047978884 | CB92: 1.0997143 | CC92: 4 of 10 | CD92: 16.666663 | CE92: 0.9775459 | CO92: no option prices for this event
A93: Q4 FY21 | B93: Jan-Mar 2021 | C93: 44286 | D93: CIPLA | E93: Cipla Limited | F93: Pharmaceuticals | G93: NSE | H93: Nifty Pharma | I93: 425 | J93: 44330 | K93: 18:12 | L93: After close | M93: NSE announcement | N93: 44328 | O93: 44330 | P93: 44333 | Q93: 44333 | R93: 0.0086429453 | S93: 0.00606499 | T93: -0.025275151 | U93: -0.010567215 | V93: 0.0050566277 | W93: -0.0148095 | X93: -0.015623843 | Y93: 0.0042422849 | Z93: -0.0084068451 | AA93: -0.0021603703 | AB93: -0.010010508 | AC93: -0.025275151 | AD93: 0.025275151 | AE93: 0.038714673 | AF93: 0.32 | AG93: 1.4928482 | AH93: 890.9 | AI93: 0.014172691 | AJ93: 0.05807601 | AK93: 0.06764935 | AL93: 0.14049798 | AM93: 0.56257125 | AN93: 0.1153651 | AO93: -0.057289088 | AP93: 0.056797549 | AQ93: 0.10775079 | AR93: 0.048199024 | AS93: Consolidated | AT93: Company | AU93: 4606.45 | AV93: 0.052616545 | AW93: -0.10877805 | AX93: 796.24 | AY93: 0.17285328 | AZ93: 0.028088087 | BA93: 413.38 | BB93: 0.68074812 | BC93: -0.44746374 | BD93: 0.089739387 | BE93: 5.13 | BM93: 71846.63 | BN93: 2237.44 | BO93: 32.111087 | BS93: 36.87 | BT93: 5.79 | BZ93: 11 | CA93: 0.03339128 | CB93: 0.51284215 | CC93: 6 of 11 | CD93: 37.095173 | CE93: -0.13435943 | CF93: 44343 | CG93: 0.50077205 | CH93: 0.5289496 | CI93: 0.38590039 | CJ93: -0.27044016 | CK93: 0.07979046 | CL93: 0.31676908 | CM93: -0.19288559 | CN93: Yes
A94: Q4 FY21 | B94: Jan-Mar 2021 | C94: 44286 | D94: DRREDDY | E94: Dr. Reddy's Laboratories Limited | F94: Pharmaceuticals | G94: NSE | H94: Nifty Pharma | I94: 625 | J94: 44330 | K94: 12:26 | L94: During market | M94: NSE announcement | N94: 44328 | O94: 44330 | P94: 44333 | Q94: 44330 | R94: 0.0010385294 | S94: -0.019730451 | T94: 0.010285077 | U94: -0.0084068451 | V94: 0.0050566277 | W94: -0.0148095 | X94: -0.013463473 | Y94: 0.0064026552 | Z94: -0.010567215 | AA94: 0.0021603703 | AB94: 0.0069980854 | AC94: -0.019730451 | AD94: 0.019730451 | AE94: 0.044968829 | AF94: 0.15457215 | AG94: 1.9625077 | AH94: 5295.95 | AI94: 0.045132962 | AJ94: 0.1294292 | AK94: 0.13453443 | AL94: 0.073010374 | AM94: 0.40349552 | AN94: 0.1153651 | AO94: 0.014064105 | AP94: 0.004161667 | AQ94: 0.040197703 | AR94: -0.019354067 | AS94: Consolidated | AT94: Company | AU94: 4768.2 | AV94: 0.07177055 | AW94: -0.035148425 | AX94: 1053.2 | AY94: 0.22088 | AZ94: 0.0075238861 | BA94: 557.3 | BB94: -0.28651901 | BC94: 18.97491 | BD94: 0.11687849 | BE94: 33.61 | BM94: 88018.689 | BN94: 2167.7 | BO94: 40.604645 | BS94: 36.87 | BT94: 5.79 | BZ94: 11 | CA94: 0.03339128 | CB94: 0.70666648 | CC94: 11 of 11 | CD94: 34.5243 | CE94: 0.17611784 | CF94: 44343 | CG94: 0.42330008 | CH94: 0.48995011 | CI94: 0.46470663 | CJ94: -0.051522566 | CK94: 0.07776285 | CL94: 0.25372593 | CM94: -0.066764087 | CN94: Yes
A95: Q4 FY21 | B95: Jan-Mar 2021 | C95: 44286 | D95: LODHA | E95: Lodha Developers Limited | F95: Construction | G95: Assigned | H95: Nifty Infrastructure | I95: 625 | J95: 44330 | K95: 16:28 | L95: After close | M95: NSE announcement | N95: 44328 | O95: 44330 | P95: 44333 | Q95: 44333 | R95: -0.065129391 | S95: 0.0019330395 | T95: -0.00077172403 | U95: -0.063968076 | V95: 0.0050566277 | W95: -0.0088500425 | X95: -0.069024704 | Y95: -0.055118033 | Z95: -0.0045989016 | AA95: -0.059369174 | AB95: 0.00015434481 | AC95: -0.00077172403 | AD95: 0.00077172403 | AE95: 0.045377373 | AF95: 0.67346939 | AG95: 0.57865512 | AH95: 691.7 | AI95: 0.15726953 | AN95: 0.0020827099 | AP95: -0.0049428483 | AQ95: 0.058232932 | AR95: -0.0013188385 | AS95: Consolidated | AT95: Company | AU95: 2533.5634 | AX95: 808.3964 | AY95: 0.31907487 | BA95: 310.559 | BD95: 0.12257795 | BE95: 7.85 | BS95: 33.28 | BT95: 2.64 | BZ95: 7 | CA95: 0.084987017 | CB95: 0.20517796 | CD95: 59.674386 | CO95: no option prices for this event
A96: Q4 FY21 | B96: Jan-Mar 2021 | C96: 44286 | D96: LT | E96: Larsen & Toubro Limited | F96: Engineering | G96: NSE | H96: Nifty 500 | I96: 175 | J96: 44330 | K96: 17:43 | L96: After close | M96: NSE announcement | N96: 44328 | O96: 44330 | P96: 44333 | Q96: 44333 | R96: 0.0012286788 | S96: 0.021800332 | T96: -0.020310844 | U96: 0.0027181666 | V96: 0.0050566277 | W96: 0.0025335381 | X96: -0.0023384611 | Y96: 0.00018462855 | AB96: 0.012363123 | AC96: -0.020310844 | AD96: 0.020310844 | AE96: 0.05143059 | AF96: 0.25480769 | AG96: 3.4314532 | AH96: 1383.6 | AI96: 0.034389952 | AJ96: -0.025050206 | AK96: -0.095568048 | AL96: 0.47214981 | AM96: 0.69808542 | AN96: 0.0080212731 | AO96: -0.033071479 | AP96: 0.040742744 | AQ96: 0.093023256 | AR96: 0.033471486 | AS96: Consolidated | AT96: Company | AU96: 48087.9 | AV96: 0.086848134 | AW96: 0.35091956 | AX96: 6388.93 | AY96: 0.13285941 | AZ96: 0.017117346 | BA96: 3292.81 | BB96: 0.029946169 | BC96: 0.33489952 | BD96: 0.068474814 | BE96: 23.45 | BM96: 194292.03 | BN96: 11487.19 | BO96: 16.9138 | BS96: 33.57 | BT96: 4.08 | BZ96: 1 | CF96: 44343 | CG96: 0.29964049 | CH96: 0.37277842 | CI96: 0.2937646 | CJ96: -0.21195919 | CK96: 0.05616713 | CL96: 0.36161442 | CM96: 0.28280837 | CN96: Yes
A97: Q4 FY21 | B97: Jan-Mar 2021 | C97: 44286 | D97: BHARTIARTL | E97: Bharti Airtel Limited | F97: Telecommunication - Services | G97: NSE | H97: Nifty Services Sector | I97: 475 | J97: 44333 | K97: 16:01 | L97: After close | M97: NSE announcement | N97: 44330 | O97: 44333 | P97: 44334 | Q97: 44334 | R97: -0.0024032043 | S97: -0.019182727 | T97: -0.024197216 | U97: -0.045783147 | V97: 0.027836805 | W97: 0.028884139 | X97: -0.073619952 | Y97: -0.074667286 | Z97: -0.070619397 | AA97: 0.02483625 | AB97: -0.0039115801 | AC97: -0.024197216 | AD97: 0.024197216 | AE97: 0.033384881 | AF97: 0.098092643 | AG97: 3.7302224 | AH97: 561.75 | AI97: 0.0032145727 | AJ97: 0.030261348 | AK97: -0.033298916 | AL97: 0.22840586 | AM97: 0.010432593 | AN97: -0.014448577 | AO97: 0.044709925 | AP97: -0.019110655 | AQ97: 0.011466393 | AR97: -0.038913866 | AS97: Consolidated | AT97: Company | AU97: 25747.3 | AV97: 0.085344417 | AW97: -0.029055955 | AX97: 12772.3 | AY97: 0.49606366 | AZ97: 0.36280733 | BA97: 759.2 | BC97: -0.11059044 | BD97: 0.029486587 | BE97: 1.39 | BM97: 306468.33 | BN97: -21079.7 | BS97: 27.8 | BT97: 4.51 | BZ97: 2 | CA97: 1.3383592 | CB97: 1.0996151 | CD97: 22.250863 | CF97: 44343 | CG97: 0.3091068 | CH97: 0.42134808 | CI97: 0.34117631 | CJ97: -0.19027443 | CK97: 0.059843807 | CL97: 0.40433953 | CM97: 0.13569887 | CN97: Yes
